Workbook
Name COGS: LAMBDA((Snacks!$D$2 + Snacks!$K$2 - Snacks!$M$2) * Snacks!$E$2)

Sheet Transactions
B1: Anas | D1: Snacky
K2: Total income | L2: Revenue Income | M2: ads Income | N2: Total Spent | O2: Name
B3: =SUMIFS(C11:C501, B11:B501, "anas", D11:D501, "lyd", E11:E501, "money in") - SUMIFS(C11:C501, B11:B501, "anas", D11:D501, "lyd", E11:E501, "money out") -> -24360.5 | D3: =SUMIFS(C11:C566, B11:B566, "snacky", D11:D566, "lyd", E11:E566, "money in") - SUMIFS(C11:C566, B11:B566, "snacky", D11:D566, "lyd", E11:E566, "money out") -> 27469 | K3: =SUMIFS(C11:C501, B11:B501, "snacky", D11:D501, "lyd", E11:E501, "money in") -> 300808 | L3: =SUMIFS(C11:C501, B11:B501, "snacky", D11:D501, "lyd", E11:E501, "money in",F11:F501,"Revenue") -> 266258 | M3: =SUMIFS(C11:C501, B11:B501, "snacky", D11:D501, "lyd", E11:E501, "money in",F11:F501,"ads") -> 30000 | N3: =SUMIFS(C11:C501, B11:B501, "snacky", D11:D501, "lyd", E11:E501, "money out") -> 307626 | O3: Snacky
K4: =SUMIFS(C11:C501, B11:B501, "anas", D11:D501, "lyd", E11:E501, "money in") -> 11590 | N4: =SUMIFS(C11:C501, B11:B501, "anas", D11:D501, "lyd", E11:E501, "money out") -> 35950.5 | O4: Anas
B5: =SUMIFS(C11:C501, B11:B501, "anas", D11:D501, "$", E11:E501, "money in") - SUMIFS(C11:C501, B11:B501, "anas", D11:D501, "$", E11:E501, "money out") -> -418 | D5: =SUMIFS(C11:C501, B11:B501, "snacky", D11:D501, "$", E11:E501, "money in") - SUMIFS(C11:C501, B11:B501, "snakcy", D11:D501, "$", E11:E501, "money out") -> 0
B8: Transactions
K9: Average Monthly Net Revenue per Machine (including ad revenue)
A10: Date | B10: NameTransaction Amount | C10: Transaction | D10: Currency | E10: Money Flow | F10: Transaction Type | G10: Location | H10: Transaction Description
B11: Anas | C11: 1800 | D11: $ | E11: Money Out | H11: شراء اول مكينه | L11: =IFERROR(__xludf.DUMMYFUNCTION("VSTACK( {""Month"",""Total Revenue"",""HTMall"", ""HTLand"",""deplomacyMall"",""AlTahaddy"",""KhalijUniversity"",""AlmouasafatHospital"",""Istiklal"",""Ads (cash)"",""Total Rent"",""Net Revenue (excl Ads)""}, ARRAYFORMULA( LET( monthCol, TEX"&"T(DATEVALUE(A11:A666),""yyyy-mm""), amountCol, VALUE(SUBSTITUTE(C11:C666, "","","""")), placeCol, G11:G666, directionCol, E11:E666, typeCol, F11:F666, revOK, (directionCol=""Money In"")*(typeCol=""Revenue""), months, S"&"ORT(UNIQUE(FILTER(monthCol, revOK))), baseData, FILTER({monthCol, placeCol, amountCol}, revOK), HTMRev, IFERROR(VLOOKUP(months, QUERY(baseData, ""select Col1,sum(Col3) where Col2='HTMall' group by Col1"",0),2,false),0), "&" HTLRev, IFERROR(VLOOKUP(months, QUERY(baseData, ""select Col1,sum(Col3) where Col2='HTLand' group by Col1"",0),2,false),0), DPRev, IFERROR(VLOOKUP(months, QUERY(baseData, ""select Col1,sum(Col3) where Col2='deplomacyMall' group "&"by Col1"",0),2,false),0), ALTRev, IFERROR(VLOOKUP(months, QUERY(baseData, ""select Col1,sum(Col3) where Col2='AlTahaddy' group by Col1"",0),2,false),0), ALKRev, IFERROR(VLOOKUP(months, QU"&"ERY(baseData, ""select Col1,sum(Col3) where Col2='KhalijUniversity' group by Col1"",0),2,false),0), AHRev, IFERROR(VLOOKUP(months, QUERY(baseData, ""select Col1,sum(Col3) where Col2='AlmouasafatHospital' group by Col1"",0),2,false),0), "&" ISRev, IFERROR(VLOOKUP(months, QUERY(baseData, ""select Col1,sum(Col3) where Col2='Istiklal' group by Col1"",0),2,false),0), totalRev, HTMRev +HTLRev+ DPRev + ALTRev + ALKRev + AHRev +ISRev, adsBase, FILTER({monthCo"&"l, amountCol}, (directionCol=""Money In"")*(typeCol=""Ads"")), adsCash, IFERROR(VLOOKUP(months, QUERY(adsBase,""select Col1,sum(Col2) group by Col1"",0),2,false),0), rent, IF(HTMRev>0,1000,0)+IF(HTLRev>0,800,0)+IF(DPRev>0,500,0), netRev"&", totalRev - rent, HSTACK(months,totalRev,HTMRev,HTLRev,DPRev,ALTRev,ALKRev,AHRev,ISRev,adsCash,rent,netRev) ) ) ) "),"Month") -> Month | M11: =IFERROR(__xludf.DUMMYFUNCTION("""COMPUTED_VALUE"""),"Total Revenue") -> Total Revenue | N11: =IFERROR(__xludf.DUMMYFUNCTION("""COMPUTED_VALUE"""),"HTMall") -> HTMall | O11: =IFERROR(__xludf.DUMMYFUNCTION("""COMPUTED_VALUE"""),"HTLand") -> HTLand | P11: =IFERROR(__xludf.DUMMYFUNCTION("""COMPUTED_VALUE"""),"deplomacyMall") -> deplomacyMall | Q11: =IFERROR(__xludf.DUMMYFUNCTION("""COMPUTED_VALUE"""),"AlTahaddy") -> AlTahaddy | R11: =IFERROR(__xludf.DUMMYFUNCTION("""COMPUTED_VALUE"""),"KhalijUniversity") -> KhalijUniversity | S11: =IFERROR(__xludf.DUMMYFUNCTION("""COMPUTED_VALUE"""),"AlmouasafatHospital") -> AlmouasafatHospital | T11: =IFERROR(__xludf.DUMMYFUNCTION("""COMPUTED_VALUE"""),"Istiklal") -> Istiklal | U11: =IFERROR(__xludf.DUMMYFUNCTION("""COMPUTED_VALUE"""),"Ads (cash)") -> Ads (cash) | V11: =IFERROR(__xludf.DUMMYFUNCTION("""COMPUTED_VALUE"""),"Total Rent") -> Total Rent | W11: =IFERROR(__xludf.DUMMYFUNCTION("""COMPUTED_VALUE"""),"Net Revenue (excl Ads)") -> Net Revenue (excl Ads)
B12: Anas | C12: 363 | D12: $ | E12: Money Out | H12: سعر التوصيل من شاهين | L12: =IFERROR(__xludf.DUMMYFUNCTION("""COMPUTED_VALUE"""),"2024-08") -> 2024-08 | M12: =IFERROR(__xludf.DUMMYFUNCTION("""COMPUTED_VALUE"""),3283.0) -> 3283 | N12: =IFERROR(__xludf.DUMMYFUNCTION("""COMPUTED_VALUE"""),0.0) -> 0 | O12: =IFERROR(__xludf.DUMMYFUNCTION("""COMPUTED_VALUE"""),0.0) -> 0 | P12: =IFERROR(__xludf.DUMMYFUNCTION("""COMPUTED_VALUE"""),3283.0) -> 3283 | Q12: =IFERROR(__xludf.DUMMYFUNCTION("""COMPUTED_VALUE"""),0.0) -> 0 | R12: =IFERROR(__xludf.DUMMYFUNCTION("""COMPUTED_VALUE"""),0.0) -> 0 | S12: =IFERROR(__xludf.DUMMYFUNCTION("""COMPUTED_VALUE"""),0.0) -> 0 | T12: =IFERROR(__xludf.DUMMYFUNCTION("""COMPUTED_VALUE"""),0.0) -> 0 | U12: =IFERROR(__xludf.DUMMYFUNCTION("""COMPUTED_VALUE"""),2500.0) -> 2500 | V12: =IFERROR(__xludf.DUMMYFUNCTION("""COMPUTED_VALUE"""),500.0) -> 500 | W12: =IFERROR(__xludf.DUMMYFUNCTION("""COMPUTED_VALUE"""),2783.0) -> 2783
B13: Anas | C13: 10000 | D13: LYD | E13: Money Out | H13: توديع قيمه فالمصرف | L13: =IFERROR(__xludf.DUMMYFUNCTION("""COMPUTED_VALUE"""),"2024-09") -> 2024-09 | M13: =IFERROR(__xludf.DUMMYFUNCTION("""COMPUTED_VALUE"""),10159.0) -> 10159 | N13: =IFERROR(__xludf.DUMMYFUNCTION("""COMPUTED_VALUE"""),0.0) -> 0 | O13: =IFERROR(__xludf.DUMMYFUNCTION("""COMPUTED_VALUE"""),0.0) -> 0 | P13: =IFERROR(__xludf.DUMMYFUNCTION("""COMPUTED_VALUE"""),10159.0) -> 10159 | Q13: =IFERROR(__xludf.DUMMYFUNCTION("""COMPUTED_VALUE"""),0.0) -> 0 | R13: =IFERROR(__xludf.DUMMYFUNCTION("""COMPUTED_VALUE"""),0.0) -> 0 | S13: =IFERROR(__xludf.DUMMYFUNCTION("""COMPUTED_VALUE"""),0.0) -> 0 | T13: =IFERROR(__xludf.DUMMYFUNCTION("""COMPUTED_VALUE"""),0.0) -> 0 | U13: =IFERROR(__xludf.DUMMYFUNCTION("""COMPUTED_VALUE"""),0.0) -> 0 | V13: =IFERROR(__xludf.DUMMYFUNCTION("""COMPUTED_VALUE"""),500.0) -> 500 | W13: =IFERROR(__xludf.DUMMYFUNCTION("""COMPUTED_VALUE"""),9659.0) -> 9659
B14: Anas | C14: 1500 | D14: LYD | E14: Money Out | H14: فتح حساب في مصرف السراي | L14: =IFERROR(__xludf.DUMMYFUNCTION("""COMPUTED_VALUE"""),"2024-11") -> 2024-11 | M14: =IFERROR(__xludf.DUMMYFUNCTION("""COMPUTED_VALUE"""),836.0) -> 836 | N14: =IFERROR(__xludf.DUMMYFUNCTION("""COMPUTED_VALUE"""),0.0) -> 0 | O14: =IFERROR(__xludf.DUMMYFUNCTION("""COMPUTED_VALUE"""),0.0) -> 0 | P14: =IFERROR(__xludf.DUMMYFUNCTION("""COMPUTED_VALUE"""),836.0) -> 836 | Q14: =IFERROR(__xludf.DUMMYFUNCTION("""COMPUTED_VALUE"""),0.0) -> 0 | R14: =IFERROR(__xludf.DUMMYFUNCTION("""COMPUTED_VALUE"""),0.0) -> 0 | S14: =IFERROR(__xludf.DUMMYFUNCTION("""COMPUTED_VALUE"""),0.0) -> 0 | T14: =IFERROR(__xludf.DUMMYFUNCTION("""COMPUTED_VALUE"""),0.0) -> 0 | U14: =IFERROR(__xludf.DUMMYFUNCTION("""COMPUTED_VALUE"""),0.0) -> 0 | V14: =IFERROR(__xludf.DUMMYFUNCTION("""COMPUTED_VALUE"""),500.0) -> 500 | W14: =IFERROR(__xludf.DUMMYFUNCTION("""COMPUTED_VALUE"""),336.0) -> 336
B15: Anas | C15: 50 | D15: $ | E15: Money Out | H15: سعر تحويل من مصرف الى مصرف عند شراء الماكينه | L15: =IFERROR(__xludf.DUMMYFUNCTION("""COMPUTED_VALUE"""),"2024-12") -> 2024-12 | M15: =IFERROR(__xludf.DUMMYFUNCTION("""COMPUTED_VALUE"""),7553.0) -> 7553 | N15: =IFERROR(__xludf.DUMMYFUNCTION("""COMPUTED_VALUE"""),0.0) -> 0 | O15: =IFERROR(__xludf.DUMMYFUNCTION("""COMPUTED_VALUE"""),0.0) -> 0 | P15: =IFERROR(__xludf.DUMMYFUNCTION("""COMPUTED_VALUE"""),7553.0) -> 7553 | Q15: =IFERROR(__xludf.DUMMYFUNCTION("""COMPUTED_VALUE"""),0.0) -> 0 | R15: =IFERROR(__xludf.DUMMYFUNCTION("""COMPUTED_VALUE"""),0.0) -> 0 | S15: =IFERROR(__xludf.DUMMYFUNCTION("""COMPUTED_VALUE"""),0.0) -> 0 | T15: =IFERROR(__xludf.DUMMYFUNCTION("""COMPUTED_VALUE"""),0.0) -> 0 | U15: =IFERROR(__xludf.DUMMYFUNCTION("""COMPUTED_VALUE"""),2500.0) -> 2500 | V15: =IFERROR(__xludf.DUMMYFUNCTION("""COMPUTED_VALUE"""),500.0) -> 500 | W15: =IFERROR(__xludf.DUMMYFUNCTION("""COMPUTED_VALUE"""),7053.0) -> 7053
B16: Anas | C16: 750 | D16: LYD | E16: Money Out | F16: Product Restocking | H16: بضاعه | L16: =IFERROR(__xludf.DUMMYFUNCTION("""COMPUTED_VALUE"""),"2025-01") -> 2025-01 | M16: =IFERROR(__xludf.DUMMYFUNCTION("""COMPUTED_VALUE"""),8288.0) -> 8288 | N16: =IFERROR(__xludf.DUMMYFUNCTION("""COMPUTED_VALUE"""),0.0) -> 0 | O16: =IFERROR(__xludf.DUMMYFUNCTION("""COMPUTED_VALUE"""),0.0) -> 0 | P16: =IFERROR(__xludf.DUMMYFUNCTION("""COMPUTED_VALUE"""),8288.0) -> 8288 | Q16: =IFERROR(__xludf.DUMMYFUNCTION("""COMPUTED_VALUE"""),0.0) -> 0 | R16: =IFERROR(__xludf.DUMMYFUNCTION("""COMPUTED_VALUE"""),0.0) -> 0 | S16: =IFERROR(__xludf.DUMMYFUNCTION("""COMPUTED_VALUE"""),0.0) -> 0 | T16: =IFERROR(__xludf.DUMMYFUNCTION("""COMPUTED_VALUE"""),0.0) -> 0 | U16: =IFERROR(__xludf.DUMMYFUNCTION("""COMPUTED_VALUE"""),0.0) -> 0 | V16: =IFERROR(__xludf.DUMMYFUNCTION("""COMPUTED_VALUE"""),500.0) -> 500 | W16: =IFERROR(__xludf.DUMMYFUNCTION("""COMPUTED_VALUE"""),7788.0) -> 7788
B17: Anas | C17: 40 | D17: LYD | E17: Money Out | F17: Product Restocking | H17: بضاعه (مياه) | L17: =IFERROR(__xludf.DUMMYFUNCTION("""COMPUTED_VALUE"""),"2025-02") -> 2025-02 | M17: =IFERROR(__xludf.DUMMYFUNCTION("""COMPUTED_VALUE"""),7480.0) -> 7480 | N17: =IFERROR(__xludf.DUMMYFUNCTION("""COMPUTED_VALUE"""),0.0) -> 0 | O17: =IFERROR(__xludf.DUMMYFUNCTION("""COMPUTED_VALUE"""),0.0) -> 0 | P17: =IFERROR(__xludf.DUMMYFUNCTION("""COMPUTED_VALUE"""),7480.0) -> 7480 | Q17: =IFERROR(__xludf.DUMMYFUNCTION("""COMPUTED_VALUE"""),0.0) -> 0 | R17: =IFERROR(__xludf.DUMMYFUNCTION("""COMPUTED_VALUE"""),0.0) -> 0 | S17: =IFERROR(__xludf.DUMMYFUNCTION("""COMPUTED_VALUE"""),0.0) -> 0 | T17: =IFERROR(__xludf.DUMMYFUNCTION("""COMPUTED_VALUE"""),0.0) -> 0 | U17: =IFERROR(__xludf.DUMMYFUNCTION("""COMPUTED_VALUE"""),0.0) -> 0 | V17: =IFERROR(__xludf.DUMMYFUNCTION("""COMPUTED_VALUE"""),500.0) -> 500 | W17: =IFERROR(__xludf.DUMMYFUNCTION("""COMPUTED_VALUE"""),6980.0) -> 6980
B18: Anas | C18: 300 | D18: LYD | E18: Money Out | H18: توصيل الماكينه بالونش | L18: =IFERROR(__xludf.DUMMYFUNCTION("""COMPUTED_VALUE"""),"2025-03") -> 2025-03 | M18: =IFERROR(__xludf.DUMMYFUNCTION("""COMPUTED_VALUE"""),8925.0) -> 8925 | N18: =IFERROR(__xludf.DUMMYFUNCTION("""COMPUTED_VALUE"""),0.0) -> 0 | O18: =IFERROR(__xludf.DUMMYFUNCTION("""COMPUTED_VALUE"""),0.0) -> 0 | P18: =IFERROR(__xludf.DUMMYFUNCTION("""COMPUTED_VALUE"""),8925.0) -> 8925 | Q18: =IFERROR(__xludf.DUMMYFUNCTION("""COMPUTED_VALUE"""),0.0) -> 0 | R18: =IFERROR(__xludf.DUMMYFUNCTION("""COMPUTED_VALUE"""),0.0) -> 0 | S18: =IFERROR(__xludf.DUMMYFUNCTION("""COMPUTED_VALUE"""),0.0) -> 0 | T18: =IFERROR(__xludf.DUMMYFUNCTION("""COMPUTED_VALUE"""),0.0) -> 0 | U18: =IFERROR(__xludf.DUMMYFUNCTION("""COMPUTED_VALUE"""),1500.0) -> 1500 | V18: =IFERROR(__xludf.DUMMYFUNCTION("""COMPUTED_VALUE"""),500.0) -> 500 | W18: =IFERROR(__xludf.DUMMYFUNCTION("""COMPUTED_VALUE"""),8425.0) -> 8425
B19: Anas | C19: 70 | D19: LYD | E19: Money Out | H19: بضاعه (مياه) | L19: =IFERROR(__xludf.DUMMYFUNCTION("""COMPUTED_VALUE"""),"2025-04") -> 2025-04 | M19: =IFERROR(__xludf.DUMMYFUNCTION("""COMPUTED_VALUE"""),15847.0) -> 15847 | N19: =IFERROR(__xludf.DUMMYFUNCTION("""COMPUTED_VALUE"""),0.0) -> 0 | O19: =IFERROR(__xludf.DUMMYFUNCTION("""COMPUTED_VALUE"""),0.0) -> 0 | P19: =IFERROR(__xludf.DUMMYFUNCTION("""COMPUTED_VALUE"""),15847.0) -> 15847 | Q19: =IFERROR(__xludf.DUMMYFUNCTION("""COMPUTED_VALUE"""),0.0) -> 0 | R19: =IFERROR(__xludf.DUMMYFUNCTION("""COMPUTED_VALUE"""),0.0) -> 0 | S19: =IFERROR(__xludf.DUMMYFUNCTION("""COMPUTED_VALUE"""),0.0) -> 0 | T19: =IFERROR(__xludf.DUMMYFUNCTION("""COMPUTED_VALUE"""),0.0) -> 0 | U19: =IFERROR(__xludf.DUMMYFUNCTION("""COMPUTED_VALUE"""),1500.0) -> 1500 | V19: =IFERROR(__xludf.DUMMYFUNCTION("""COMPUTED_VALUE"""),500.0) -> 500 | W19: =IFERROR(__xludf.DUMMYFUNCTION("""COMPUTED_VALUE"""),15347.0) -> 15347
B20: Anas | C20: 340 | D20: LYD | E20: Money Out | H20: بضاعه | L20: =IFERROR(__xludf.DUMMYFUNCTION("""COMPUTED_VALUE"""),"2025-05") -> 2025-05 | M20: =IFERROR(__xludf.DUMMYFUNCTION("""COMPUTED_VALUE"""),8426.0) -> 8426 | N20: =IFERROR(__xludf.DUMMYFUNCTION("""COMPUTED_VALUE"""),1157.0) -> 1157 | O20: =IFERROR(__xludf.DUMMYFUNCTION("""COMPUTED_VALUE"""),0.0) -> 0 | P20: =IFERROR(__xludf.DUMMYFUNCTION("""COMPUTED_VALUE"""),7269.0) -> 7269 | Q20: =IFERROR(__xludf.DUMMYFUNCTION("""COMPUTED_VALUE"""),0.0) -> 0 | R20: =IFERROR(__xludf.DUMMYFUNCTION("""COMPUTED_VALUE"""),0.0) -> 0 | S20: =IFERROR(__xludf.DUMMYFUNCTION("""COMPUTED_VALUE"""),0.0) -> 0 | T20: =IFERROR(__xludf.DUMMYFUNCTION("""COMPUTED_VALUE"""),0.0) -> 0 | U20: =IFERROR(__xludf.DUMMYFUNCTION("""COMPUTED_VALUE"""),0.0) -> 0 | V20: =IFERROR(__xludf.DUMMYFUNCTION("""COMPUTED_VALUE"""),1500.0) -> 1500 | W20: =IFERROR(__xludf.DUMMYFUNCTION("""COMPUTED_VALUE"""),6926.0) -> 6926
B21: Anas | C21: 885 | D21: LYD | E21: Money Out | H21: طباعه وتصميم | L21: =IFERROR(__xludf.DUMMYFUNCTION("""COMPUTED_VALUE"""),"2025-06") -> 2025-06 | M21: =IFERROR(__xludf.DUMMYFUNCTION("""COMPUTED_VALUE"""),18609.0) -> 18609 | N21: =IFERROR(__xludf.DUMMYFUNCTION("""COMPUTED_VALUE"""),11413.0) -> 11413 | O21: =IFERROR(__xludf.DUMMYFUNCTION("""COMPUTED_VALUE"""),0.0) -> 0 | P21: =IFERROR(__xludf.DUMMYFUNCTION("""COMPUTED_VALUE"""),7196.0) -> 7196 | Q21: =IFERROR(__xludf.DUMMYFUNCTION("""COMPUTED_VALUE"""),0.0) -> 0 | R21: =IFERROR(__xludf.DUMMYFUNCTION("""COMPUTED_VALUE"""),0.0) -> 0 | S21: =IFERROR(__xludf.DUMMYFUNCTION("""COMPUTED_VALUE"""),0.0) -> 0 | T21: =IFERROR(__xludf.DUMMYFUNCTION("""COMPUTED_VALUE"""),0.0) -> 0 | U21: =IFERROR(__xludf.DUMMYFUNCTION("""COMPUTED_VALUE"""),3000.0) -> 3000 | V21: =IFERROR(__xludf.DUMMYFUNCTION("""COMPUTED_VALUE"""),1500.0) -> 1500 | W21: =IFERROR(__xludf.DUMMYFUNCTION("""COMPUTED_VALUE"""),17109.0) -> 17109
B22: Anas | C22: 702 | D22: LYD | E22: Money Out | H22: بضاعه | L22: =IFERROR(__xludf.DUMMYFUNCTION("""COMPUTED_VALUE"""),"2025-07") -> 2025-07 | M22: =IFERROR(__xludf.DUMMYFUNCTION("""COMPUTED_VALUE"""),19450.0) -> 19450 | N22: =IFERROR(__xludf.DUMMYFUNCTION("""COMPUTED_VALUE"""),8693.0) -> 8693 | O22: =IFERROR(__xludf.DUMMYFUNCTION("""COMPUTED_VALUE"""),0.0) -> 0 | P22: =IFERROR(__xludf.DUMMYFUNCTION("""COMPUTED_VALUE"""),7434.0) -> 7434 | Q22: =IFERROR(__xludf.DUMMYFUNCTION("""COMPUTED_VALUE"""),0.0) -> 0 | R22: =IFERROR(__xludf.DUMMYFUNCTION("""COMPUTED_VALUE"""),0.0) -> 0 | S22: =IFERROR(__xludf.DUMMYFUNCTION("""COMPUTED_VALUE"""),3323.0) -> 3323 | T22: =IFERROR(__xludf.DUMMYFUNCTION("""COMPUTED_VALUE"""),0.0) -> 0 | U22: =IFERROR(__xludf.DUMMYFUNCTION("""COMPUTED_VALUE"""),3000.0) -> 3000 | V22: =IFERROR(__xludf.DUMMYFUNCTION("""COMPUTED_VALUE"""),1500.0) -> 1500 | W22: =IFERROR(__xludf.DUMMYFUNCTION("""COMPUTED_VALUE"""),17950.0) -> 17950
B23: Anas | C23: 5 | D23: $ | E23: Money Out | H23: سعر الشحن من شاهين شحنة الخيط | L23: =IFERROR(__xludf.DUMMYFUNCTION("""COMPUTED_VALUE"""),"2025-08") -> 2025-08 | M23: =IFERROR(__xludf.DUMMYFUNCTION("""COMPUTED_VALUE"""),19750.0) -> 19750 | N23: =IFERROR(__xludf.DUMMYFUNCTION("""COMPUTED_VALUE"""),8500.0) -> 8500 | O23: =IFERROR(__xludf.DUMMYFUNCTION("""COMPUTED_VALUE"""),0.0) -> 0 | P23: =IFERROR(__xludf.DUMMYFUNCTION("""COMPUTED_VALUE"""),5622.0) -> 5622 | Q23: =IFERROR(__xludf.DUMMYFUNCTION("""COMPUTED_VALUE"""),0.0) -> 0 | R23: =IFERROR(__xludf.DUMMYFUNCTION("""COMPUTED_VALUE"""),0.0) -> 0 | S23: =IFERROR(__xludf.DUMMYFUNCTION("""COMPUTED_VALUE"""),5628.0) -> 5628 | T23: =IFERROR(__xludf.DUMMYFUNCTION("""COMPUTED_VALUE"""),0.0) -> 0 | U23: =IFERROR(__xludf.DUMMYFUNCTION("""COMPUTED_VALUE"""),0.0) -> 0 | V23: =IFERROR(__xludf.DUMMYFUNCTION("""COMPUTED_VALUE"""),1500.0) -> 1500 | W23: =IFERROR(__xludf.DUMMYFUNCTION("""COMPUTED_VALUE"""),18250.0) -> 18250
B24: Anas | C24: 59.5 | D24: LYD | E24: Money Out | H24: بضاعه (مياه) | L24: =IFERROR(__xludf.DUMMYFUNCTION("""COMPUTED_VALUE"""),"2025-09") -> 2025-09 | M24: =IFERROR(__xludf.DUMMYFUNCTION("""COMPUTED_VALUE"""),12927.0) -> 12927 | N24: =IFERROR(__xludf.DUMMYFUNCTION("""COMPUTED_VALUE"""),5884.0) -> 5884 | O24: =IFERROR(__xludf.DUMMYFUNCTION("""COMPUTED_VALUE"""),0.0) -> 0 | P24: =IFERROR(__xludf.DUMMYFUNCTION("""COMPUTED_VALUE"""),3091.0) -> 3091 | Q24: =IFERROR(__xludf.DUMMYFUNCTION("""COMPUTED_VALUE"""),0.0) -> 0 | R24: =IFERROR(__xludf.DUMMYFUNCTION("""COMPUTED_VALUE"""),0.0) -> 0 | S24: =IFERROR(__xludf.DUMMYFUNCTION("""COMPUTED_VALUE"""),3952.0) -> 3952 | T24: =IFERROR(__xludf.DUMMYFUNCTION("""COMPUTED_VALUE"""),0.0) -> 0 | U24: =IFERROR(__xludf.DUMMYFUNCTION("""COMPUTED_VALUE"""),10000.0) -> 10000 | V24: =IFERROR(__xludf.DUMMYFUNCTION("""COMPUTED_VALUE"""),1500.0) -> 1500 | W24: =IFERROR(__xludf.DUMMYFUNCTION("""COMPUTED_VALUE"""),11427.0) -> 11427
B25: Anas | C25: 60 | D25: LYD | E25: Money Out | H25: بضاعه (مياه) | L25: =IFERROR(__xludf.DUMMYFUNCTION("""COMPUTED_VALUE"""),"2025-10") -> 2025-10 | M25: =IFERROR(__xludf.DUMMYFUNCTION("""COMPUTED_VALUE"""),16451.0) -> 16451 | N25: =IFERROR(__xludf.DUMMYFUNCTION("""COMPUTED_VALUE"""),6696.0) -> 6696 | O25: =IFERROR(__xludf.DUMMYFUNCTION("""COMPUTED_VALUE"""),0.0) -> 0 | P25: =IFERROR(__xludf.DUMMYFUNCTION("""COMPUTED_VALUE"""),4636.0) -> 4636 | Q25: =IFERROR(__xludf.DUMMYFUNCTION("""COMPUTED_VALUE"""),0.0) -> 0 | R25: =IFERROR(__xludf.DUMMYFUNCTION("""COMPUTED_VALUE"""),0.0) -> 0 | S25: =IFERROR(__xludf.DUMMYFUNCTION("""COMPUTED_VALUE"""),5119.0) -> 5119 | T25: =IFERROR(__xludf.DUMMYFUNCTION("""COMPUTED_VALUE"""),0.0) -> 0 | U25: =IFERROR(__xludf.DUMMYFUNCTION("""COMPUTED_VALUE"""),0.0) -> 0 | V25: =IFERROR(__xludf.DUMMYFUNCTION("""COMPUTED_VALUE"""),1500.0) -> 1500 | W25: =IFERROR(__xludf.DUMMYFUNCTION("""COMPUTED_VALUE"""),14951.0) -> 14951
B26: Anas | C26: 15 | D26: LYD | E26: Money Out | H26: كرت LTT | L26: =IFERROR(__xludf.DUMMYFUNCTION("""COMPUTED_VALUE"""),"2025-11") -> 2025-11 | M26: =IFERROR(__xludf.DUMMYFUNCTION("""COMPUTED_VALUE"""),13267.0) -> 13267 | N26: =IFERROR(__xludf.DUMMYFUNCTION("""COMPUTED_VALUE"""),5090.0) -> 5090 | O26: =IFERROR(__xludf.DUMMYFUNCTION("""COMPUTED_VALUE"""),0.0) -> 0 | P26: =IFERROR(__xludf.DUMMYFUNCTION("""COMPUTED_VALUE"""),3893.0) -> 3893 | Q26: =IFERROR(__xludf.DUMMYFUNCTION("""COMPUTED_VALUE"""),0.0) -> 0 | R26: =IFERROR(__xludf.DUMMYFUNCTION("""COMPUTED_VALUE"""),0.0) -> 0 | S26: =IFERROR(__xludf.DUMMYFUNCTION("""COMPUTED_VALUE"""),4284.0) -> 4284 | T26: =IFERROR(__xludf.DUMMYFUNCTION("""COMPUTED_VALUE"""),0.0) -> 0 | U26: =IFERROR(__xludf.DUMMYFUNCTION("""COMPUTED_VALUE"""),0.0) -> 0 | V26: =IFERROR(__xludf.DUMMYFUNCTION("""COMPUTED_VALUE"""),1500.0) -> 1500 | W26: =IFERROR(__xludf.DUMMYFUNCTION("""COMPUTED_VALUE"""),11767.0) -> 11767
B27: Snacky | C27: 1882 | D27: LYD | E27: Money Out | F27: Product Restocking | H27: بضاعه | L27: =IFERROR(__xludf.DUMMYFUNCTION("""COMPUTED_VALUE"""),"2025-12") -> 2025-12 | M27: =IFERROR(__xludf.DUMMYFUNCTION("""COMPUTED_VALUE"""),17828.0) -> 17828 | N27: =IFERROR(__xludf.DUMMYFUNCTION("""COMPUTED_VALUE"""),8092.0) -> 8092 | O27: =IFERROR(__xludf.DUMMYFUNCTION("""COMPUTED_VALUE"""),0.0) -> 0 | P27: =IFERROR(__xludf.DUMMYFUNCTION("""COMPUTED_VALUE"""),4621.0) -> 4621 | Q27: =IFERROR(__xludf.DUMMYFUNCTION("""COMPUTED_VALUE"""),0.0) -> 0 | R27: =IFERROR(__xludf.DUMMYFUNCTION("""COMPUTED_VALUE"""),0.0) -> 0 | S27: =IFERROR(__xludf.DUMMYFUNCTION("""COMPUTED_VALUE"""),5115.0) -> 5115 | T27: =IFERROR(__xludf.DUMMYFUNCTION("""COMPUTED_VALUE"""),0.0) -> 0 | U27: =IFERROR(__xludf.DUMMYFUNCTION("""COMPUTED_VALUE"""),0.0) -> 0 | V27: =IFERROR(__xludf.DUMMYFUNCTION("""COMPUTED_VALUE"""),1500.0) -> 1500 | W27: =IFERROR(__xludf.DUMMYFUNCTION("""COMPUTED_VALUE"""),16328.0) -> 16328
B28: Anas | C28: 61 | D28: LYD | E28: Money Out | F28: Product Restocking | H28: بضاعه (مياه) | L28: =IFERROR(__xludf.DUMMYFUNCTION("""COMPUTED_VALUE"""),"2026-01") -> 2026-01 | M28: =IFERROR(__xludf.DUMMYFUNCTION("""COMPUTED_VALUE"""),21248.0) -> 21248 | N28: =IFERROR(__xludf.DUMMYFUNCTION("""COMPUTED_VALUE"""),10344.0) -> 10344 | O28: =IFERROR(__xludf.DUMMYFUNCTION("""COMPUTED_VALUE"""),0.0) -> 0 | P28: =IFERROR(__xludf.DUMMYFUNCTION("""COMPUTED_VALUE"""),2894.0) -> 2894 | Q28: =IFERROR(__xludf.DUMMYFUNCTION("""COMPUTED_VALUE"""),0.0) -> 0 | R28: =IFERROR(__xludf.DUMMYFUNCTION("""COMPUTED_VALUE"""),0.0) -> 0 | S28: =IFERROR(__xludf.DUMMYFUNCTION("""COMPUTED_VALUE"""),4992.0) -> 4992 | T28: =IFERROR(__xludf.DUMMYFUNCTION("""COMPUTED_VALUE"""),3018.0) -> 3018 | U28: =IFERROR(__xludf.DUMMYFUNCTION("""COMPUTED_VALUE"""),0.0) -> 0 | V28: =IFERROR(__xludf.DUMMYFUNCTION("""COMPUTED_VALUE"""),1500.0) -> 1500 | W28: =IFERROR(__xludf.DUMMYFUNCTION("""COMPUTED_VALUE"""),19748.0) -> 19748
A29: 45634 | B29: Snacky | C29: 1943 | D29: LYD | E29: Money In | F29: Revenue | G29: deplomacyMall | H29: قيمة اول 5 ايام | L29: =IFERROR(__xludf.DUMMYFUNCTION("""COMPUTED_VALUE"""),"2026-02") -> 2026-02 | M29: =IFERROR(__xludf.DUMMYFUNCTION("""COMPUTED_VALUE"""),25346.0) -> 25346 | N29: =IFERROR(__xludf.DUMMYFUNCTION("""COMPUTED_VALUE"""),7474.0) -> 7474 | O29: =IFERROR(__xludf.DUMMYFUNCTION("""COMPUTED_VALUE"""),4153.0) -> 4153 | P29: =IFERROR(__xludf.DUMMYFUNCTION("""COMPUTED_VALUE"""),2387.0) -> 2387 | Q29: =IFERROR(__xludf.DUMMYFUNCTION("""COMPUTED_VALUE"""),3577.0) -> 3577 | R29: =IFERROR(__xludf.DUMMYFUNCTION("""COMPUTED_VALUE"""),0.0) -> 0 | S29: =IFERROR(__xludf.DUMMYFUNCTION("""COMPUTED_VALUE"""),4241.0) -> 4241 | T29: =IFERROR(__xludf.DUMMYFUNCTION("""COMPUTED_VALUE"""),3514.0) -> 3514 | U29: =IFERROR(__xludf.DUMMYFUNCTION("""COMPUTED_VALUE"""),6000.0) -> 6000 | V29: =IFERROR(__xludf.DUMMYFUNCTION("""COMPUTED_VALUE"""),2300.0) -> 2300 | W29: =IFERROR(__xludf.DUMMYFUNCTION("""COMPUTED_VALUE"""),23046.0) -> 23046
A30: 45641 | B30: Snacky | C30: 779 | D30: LYD | E30: Money In | F30: Revenue | G30: deplomacyMall | L30: =IFERROR(__xludf.DUMMYFUNCTION("""COMPUTED_VALUE"""),"2026-03") -> 2026-03 | M30: =IFERROR(__xludf.DUMMYFUNCTION("""COMPUTED_VALUE"""),35177.0) -> 35177 | N30: =IFERROR(__xludf.DUMMYFUNCTION("""COMPUTED_VALUE"""),14346.0) -> 14346 | O30: =IFERROR(__xludf.DUMMYFUNCTION("""COMPUTED_VALUE"""),6583.0) -> 6583 | P30: =IFERROR(__xludf.DUMMYFUNCTION("""COMPUTED_VALUE"""),8453.0) -> 8453 | Q30: =IFERROR(__xludf.DUMMYFUNCTION("""COMPUTED_VALUE"""),1081.0) -> 1081 | R30: =IFERROR(__xludf.DUMMYFUNCTION("""COMPUTED_VALUE"""),0.0) -> 0 | S30: =IFERROR(__xludf.DUMMYFUNCTION("""COMPUTED_VALUE"""),4714.0) -> 4714 | T30: =IFERROR(__xludf.DUMMYFUNCTION("""COMPUTED_VALUE"""),0.0) -> 0 | U30: =IFERROR(__xludf.DUMMYFUNCTION("""COMPUTED_VALUE"""),0.0) -> 0 | V30: =IFERROR(__xludf.DUMMYFUNCTION("""COMPUTED_VALUE"""),2300.0) -> 2300 | W30: =IFERROR(__xludf.DUMMYFUNCTION("""COMPUTED_VALUE"""),32877.0) -> 32877
A31: 45644 | B31: Snacky | C31: 20 | D31: LYD | E31: Money Out | F31: Product Restocking | H31: بضاعه (مياه) | L31: =IFERROR(__xludf.DUMMYFUNCTION("""COMPUTED_VALUE"""),"2026-04") -> 2026-04 | M31: =IFERROR(__xludf.DUMMYFUNCTION("""COMPUTED_VALUE"""),46084.0) -> 46084 | N31: =IFERROR(__xludf.DUMMYFUNCTION("""COMPUTED_VALUE"""),7699.0) -> 7699 | O31: =IFERROR(__xludf.DUMMYFUNCTION("""COMPUTED_VALUE"""),5518.0) -> 5518 | P31: =IFERROR(__xludf.DUMMYFUNCTION("""COMPUTED_VALUE"""),0.0) -> 0 | Q31: =IFERROR(__xludf.DUMMYFUNCTION("""COMPUTED_VALUE"""),8263.0) -> 8263 | R31: =IFERROR(__xludf.DUMMYFUNCTION("""COMPUTED_VALUE"""),9830.0) -> 9830 | S31: =IFERROR(__xludf.DUMMYFUNCTION("""COMPUTED_VALUE"""),5871.0) -> 5871 | T31: =IFERROR(__xludf.DUMMYFUNCTION("""COMPUTED_VALUE"""),8903.0) -> 8903 | U31: =IFERROR(__xludf.DUMMYFUNCTION("""COMPUTED_VALUE"""),0.0) -> 0 | V31: =IFERROR(__xludf.DUMMYFUNCTION("""COMPUTED_VALUE"""),1800.0) -> 1800 | W31: =IFERROR(__xludf.DUMMYFUNCTION("""COMPUTED_VALUE"""),44284.0) -> 44284
A32: 45523 | B32: Snacky | C32: 46 | D32: LYD | E32: Money Out | H32: مياه + لصقة دبل فيس
A33: 45524 | B33: Snacky | C33: 1225 | D33: LYD | E33: Money In | F33: Revenue | G33: deplomacyMall
A34: 45525 | B34: Snacky | C34: 180 | D34: LYD | E34: Money Out | H34: طباعة توربو للايت بوكس
A35: 45525 | B35: Snacky | C35: 2500 | D35: LYD | E35: Money In | F35: ads | H35: دعاية توربو ( من نص 9 الى نص 12)
A36: 45528 | B36: Snacky | C36: 50 | D36: LYD | E36: Money Out
A37: 45528 | B37: Anas | C37: 50 | D37: LYD | E37: Money In
A38: 45528 | B38: Snacky | C38: 40 | D38: LYD | E38: Money Out | F38: Product Restocking | H38: بضاعه (مياه)
A39: 45530 | B39: Snacky | C39: 1140 | D39: LYD | E39: Money Out | F39: Product Restocking | H39: بضاعه
A40: 45530 | B40: Snacky | C40: 900 | D40: LYD | E40: Money In | F40: Revenue | G40: deplomacyMall
A41: 45533 | B41: Snacky | C41: 60 | D41: LYD | E41: Money Out | F41: Product Restocking | H41: بضاعه (مياه)
A42: 45535 | B42: Snacky | C42: 18 | D42: LYD | E42: Money Out | F42: Product Restocking | H42: بضاعه (مياه)
A43: 45535 | B43: Snacky | C43: 1158 | D43: LYD | E43: Money In | F43: Revenue | G43: deplomacyMall
A44: 45535 | B44: Anas | C44: 15 | D44: LYD | E44: Money In
A45: 45535 | B45: Snacky | C45: 15 | D45: LYD | E45: Money Out
A46: 45536 | B46: Snacky | C46: 190 | D46: LYD | E46: Money Out | H46: تعديل الميزانيه
A47: 45536 | B47: Snacky | C47: 827 | D47: LYD | E47: Money Out | F47: Product Restocking | H47: بضاعه
A48: 45537 | B48: Snacky | C48: 40 | D48: LYD | E48: Money Out | F48: Product Restocking | H48: بضاعه (مياه)
A49: 45539 | B49: Snacky | C49: 1082 | D49: LYD | E49: Money In | F49: Revenue | G49: deplomacyMall
A50: 45539 | B50: Snacky | C50: 40 | D50: LYD | E50: Money Out | F50: Product Restocking | H50: بضاعه (مياه)
A51: 45540 | B51: Snacky | C51: 64 | D51: LYD | E51: Money Out | F51: Product Restocking | H51: بضاعه (مياه)
A52: 45542 | B52: Snacky | C52: 1574 | D52: LYD | E52: Money Out | F52: Product Restocking | H52: بضاعه
A53: 45542 | B53: Snacky | C53: 20 | D53: LYD | E53: Money Out | F53: Product Restocking | H53: بضاعه (مياه)
A54: 45543 | B54: Snacky | C54: 40 | D54: LYD | E54: Money Out | F54: Product Restocking | H54: بضاعه (مياه)
A55: 45544 | B55: Snacky | C55: 1896 | D55: LYD | E55: Money In | F55: Revenue | G55: deplomacyMall
A56: 45544 | B56: Snacky | C56: 40 | D56: LYD | E56: Money Out | F56: Product Restocking | H56: بضاعه (مياه)
A57: 45545 | B57: Snacky | C57: 225 | D57: LYD | E57: Money Out | F57: Product Restocking
A58: 45545 | B58: Snacky | C58: 325 | D58: LYD | E58: Money Out | F58: Product Restocking
A59: 45546 | B59: Snacky | C59: 57.75 | D59: LYD | E59: Money Out | F59: Product Restocking | H59: بضاعه (مياه)
A60: 45547 | B60: Snacky | C60: 1134 | D60: LYD | E60: Money In | F60: Revenue | G60: deplomacyMall
A61: 45547 | B61: Snacky | C61: 446 | D61: LYD | E61: Money Out | F61: Product Restocking
A62: 45546 | B62: Snacky | C62: 61 | D62: LYD | E62: Money Out | F62: Product Restocking
A63: 45547 | B63: Snacky | C63: 72 | D63: LYD | E63: Money Out | F63: Product Restocking | H63: بضاعه (مياه)
A64: 45549 | B64: Snacky | C64: 177 | D64: LYD | E64: Money Out | F64: Product Restocking
A65: 45550 | B65: Snacky | C65: 1280 | D65: LYD | E65: Money In | F65: Revenue | G65: deplomacyMall
A66: 45551 | B66: Snacky | C66: 72 | D66: LYD | E66: Money Out | F66: Product Restocking | H66: بضاعه (مياه)
A67: 45551 | B67: Snacky | C67: 585 | D67: LYD | E67: Money In | F67: Revenue | G67: deplomacyMall
A68: 45551 | B68: Snacky | C68: 164 | D68: LYD | E68: Money Out | F68: Product Restocking
A69: 45553 | B69: Snacky | C69: 718 | D69: LYD | E69: Money Out | F69: Product Restocking
A70: 45554 | B70: Snacky | C70: 792 | D70: LYD | E70: Money In | F70: Revenue | G70: deplomacyMall
A71: 45554
A73: 45556 | B73: Snacky | C73: 1144 | D73: LYD | E73: Money In | F73: Revenue | G73: deplomacyMall
A74: 45556 | B74: Snacky | C74: 51 | D74: LYD | E74: Money Out | F74: Product Restocking | H74: بضاعه (مياه)
A75: 45557 | B75: Snacky | C75: 540 | D75: LYD | E75: Money Out | F75: Product Restocking
A76: 45556 | B76: Snacky | C76: 101 | D76: LYD | E76: Money Out | F76: Product Restocking
A77: 45560 | B77: Snacky | C77: 87 | D77: LYD | E77: Money Out | F77: Product Restocking
A78: 45561 | B78: Snacky | C78: 50.5 | D78: LYD | E78: Money Out | F78: Product Restocking | H78: بضاعه (مياه)
A79: 45561 | B79: Snacky | C79: 1311 | D79: LYD | E79: Money In | F79: Revenue | G79: deplomacyMall
A80: 45563 | B80: Snacky | C80: 960 | D80: LYD | E80: Money Out | F80: Product Restocking
A81: 45563 | B81: Snacky | C81: 49 | D81: LYD | E81: Money Out | F81: Product Restocking | H81: بضاعه (مياه)
A82: 45562 | B82: Snacky | C82: 80 | D82: LYD | E82: Money Out | H82: تركيب اللافته عل تلاجه
A83: 45566 | B83: Anas | C83: 375 | D83: LYD | E83: Money Out | H83: ارسال (change box, motherboard) الى الصين
B84: Snacky | C84: 100 | D84: LYD | E84: Money Out | F84: Anas
B85: Anas | C85: 100 | D85: LYD | E85: Money In | F85: from snacky
A86: 45567 | B86: Anas | C86: 1500 | D86: LYD | E86: Money Out | H86: ارجاع قيمة الى محمد العتيري
A87: 45565 | B87: Snacky | C87: 935 | D87: LYD | E87: Money In | F87: Revenue | G87: deplomacyMall
A88: 45625 | B88: Snacky | C88: 836 | D88: LYD | E88: Money In | F88: Revenue | G88: deplomacyMall
A89: 45625 | B89: Snacky | C89: 70 | D89: LYD | E89: Money Out | H89: ارجاع شحن (change box, motherboard)
A90: 45625 | B90: Snacky | C90: 65 | D90: LYD | E90: Money Out | F90: Product Restocking | H90: بضاعه من محل لجنب دبلوماسي
A91: 45626 | B91: Snacky | C91: 1029 | D91: LYD | E91: Money Out | F91: Product Restocking
A92: 45629 | B92: Snacky | C92: 50 | D92: LYD | E92: Money Out | H92: اجار فوركه لتحريك المكينه
A93: 45631 | B93: Snacky | C93: 850 | D93: LYD | E93: Money Out | F93: Product Restocking | H93: بضاعه من المتحده والمحل لديما ناخد منه
A94: 45627 | B94: Anas | C94: 1800 | D94: $ | E94: Money In | H94: تمت تسوية سعر الماكينه مع تيسير
A95: 45635 | B95: Snacky | C95: 1111 | D95: LYD | E95: Money In | F95: Revenue | G95: deplomacyMall
A96: 45636 | B96: Snacky | C96: 455 | D96: LYD | E96: Money Out | H96: فواتير
A97: 45637 | B97: Anas | C97: 9000 | D97: LYD | E97: Money In | H97: سحبت فلوس الايداع لفتح شركه
A98: 45640 | B98: Snacky | C98: 980 | D98: LYD | E98: Money In | F98: Revenue | G98: deplomacyMall
A100: 45641 | B100: Snacky | C100: 2500 | D100: LYD | E100: Money In | F100: ads | H100: توربو من نص 12 الى نص 3
A101: 45643 | B101: Snacky | C101: 1097 | D101: LYD | E101: Money Out | F101: Product Restocking
A102: 45645 | B102: Snacky | C102: 1600 | D102: LYD | E102: Money In | F102: Revenue | G102: deplomacyMall
A103: 45645 | B103: Snacky | C103: 1223 | D103: LYD | E103: Money Out | F103: Product Restocking
A104: 45648 | B104: Snacky | C104: 1140 | D104: LYD | E104: Money In | F104: Revenue | G104: deplomacyMall
...

Sheet Ahmed
A1: Date | B1: البضاعه | C1: مرتب | D1: Column 4 | E1: Column 5
A3: 45962 | C3: 1400
A4: 45992
A5: 46053 | C5: 1400
A6: 46081 | C6: 1600
A7: 46112 | C7: 1500
A8: 46142 | C8: 750

Sheet Lists
A1: Bucket | C1: Type | D1: Bucket
A2: Inventory | C2: Revenue | D2: Inflow
A3: Operations | C3: ads | D3: Inflow
A4: Fixed Costs | C4: Product Restocking | D4: Inventory
A5: Profit | C5: Ahmed | D5: Operations
C6: Anas | D6: Owner Draw
C7: Rent | D7: Fixed Costs
C8: charity | D8: Operations
C9: Transport | D9: Operations
C10: Storage | D10: Fixed Costs

Sheet Txn_Control
A1: =IFERROR(__xludf.DUMMYFUNCTION("FILTER(Transactions!A2:A1000,Transactions!A2:A1000<>"""")"),"Date") -> Date | B1: =IFERROR(__xludf.DUMMYFUNCTION("FILTER(Transactions!C2:C1000,Transactions!A2:A1000<>"""")"),"Transaction") -> Transaction | C1: =IFERROR(__xludf.DUMMYFUNCTION("FILTER(Transactions!E2:E1000,Transactions!A2:A1000<>"""")"),"Money Flow") -> Money Flow | D1: =IFERROR(__xludf.DUMMYFUNCTION("FILTER(Transactions!F2:F1000,Transactions!A2:A1000<>"""")"),"Transaction Type") -> Transaction Type | E1: =IFERROR(__xludf.DUMMYFUNCTION("FILTER(Transactions!G2:G1000,Transactions!A2:A1000<>"""")"),"Location") -> Location | F1: =IFERROR(__xludf.DUMMYFUNCTION("FILTER(Transactions!H2:H1000,Transactions!A2:A1000<>"""")"),"Transaction Description") -> Transaction Description | G1: Signed Amount | H1: Auto Bucket | I1: Bucket Override | J1: Final Bucket
A2: =IFERROR(__xludf.DUMMYFUNCTION("""COMPUTED_VALUE"""),45634.0) -> 45634 | B2: =IFERROR(__xludf.DUMMYFUNCTION("""COMPUTED_VALUE"""),1943.0) -> 1943 | C2: =IFERROR(__xludf.DUMMYFUNCTION("""COMPUTED_VALUE"""),"Money In") -> Money In | D2: =IFERROR(__xludf.DUMMYFUNCTION("""COMPUTED_VALUE"""),"Revenue") -> Revenue | E2: =IFERROR(__xludf.DUMMYFUNCTION("""COMPUTED_VALUE"""),"deplomacyMall") -> deplomacyMall | F2: =IFERROR(__xludf.DUMMYFUNCTION("""COMPUTED_VALUE"""),"قيمة اول 5 ايام") -> قيمة اول 5 ايام | G2: {=IF(A2:A1000="","",IF(C2:C1000="Money In",B2:B1000,-B2:B1000))} -> 1943 | H2: {=IF(A2:A1000="","",IFERROR(VLOOKUP(D2:D1000,Lists!C:D,2,FALSE),"Review"))} -> Inflow | J2: {=IF(A2:A1000="","",IF(I2:I1000<>"",I2:I1000,H2:H1000))} -> Inflow
A3: =IFERROR(__xludf.DUMMYFUNCTION("""COMPUTED_VALUE"""),45641.0) -> 45641 | B3: =IFERROR(__xludf.DUMMYFUNCTION("""COMPUTED_VALUE"""),779.0) -> 779 | C3: =IFERROR(__xludf.DUMMYFUNCTION("""COMPUTED_VALUE"""),"Money In") -> Money In | D3: =IFERROR(__xludf.DUMMYFUNCTION("""COMPUTED_VALUE"""),"Revenue") -> Revenue | E3: =IFERROR(__xludf.DUMMYFUNCTION("""COMPUTED_VALUE"""),"deplomacyMall") -> deplomacyMall | G3: 779 | H3: Inflow | J3: Inflow
A4: =IFERROR(__xludf.DUMMYFUNCTION("""COMPUTED_VALUE"""),45644.0) -> 45644 | B4: =IFERROR(__xludf.DUMMYFUNCTION("""COMPUTED_VALUE"""),20.0) -> 20 | C4: =IFERROR(__xludf.DUMMYFUNCTION("""COMPUTED_VALUE"""),"Money Out") -> Money Out | D4: =IFERROR(__xludf.DUMMYFUNCTION("""COMPUTED_VALUE"""),"Product Restocking") -> Product Restocking | F4: =IFERROR(__xludf.DUMMYFUNCTION("""COMPUTED_VALUE"""),"بضاعه (مياه)") -> بضاعه (مياه) | G4: -20 | H4: Inventory | J4: Inventory
A5: =IFERROR(__xludf.DUMMYFUNCTION("""COMPUTED_VALUE"""),45523.0) -> 45523 | B5: =IFERROR(__xludf.DUMMYFUNCTION("""COMPUTED_VALUE"""),46.0) -> 46 | C5: =IFERROR(__xludf.DUMMYFUNCTION("""COMPUTED_VALUE"""),"Money Out") -> Money Out | F5: =IFERROR(__xludf.DUMMYFUNCTION("""COMPUTED_VALUE"""),"مياه + لصقة دبل فيس") -> مياه + لصقة دبل فيس | G5: -46 | H5: Review | J5: Review
A6: =IFERROR(__xludf.DUMMYFUNCTION("""COMPUTED_VALUE"""),45524.0) -> 45524 | B6: =IFERROR(__xludf.DUMMYFUNCTION("""COMPUTED_VALUE"""),1225.0) -> 1225 | C6: =IFERROR(__xludf.DUMMYFUNCTION("""COMPUTED_VALUE"""),"Money In") -> Money In | D6: =IFERROR(__xludf.DUMMYFUNCTION("""COMPUTED_VALUE"""),"Revenue") -> Revenue | E6: =IFERROR(__xludf.DUMMYFUNCTION("""COMPUTED_VALUE"""),"deplomacyMall") -> deplomacyMall | G6: 1225 | H6: Inflow | J6: Inflow
A7: =IFERROR(__xludf.DUMMYFUNCTION("""COMPUTED_VALUE"""),45525.0) -> 45525 | B7: =IFERROR(__xludf.DUMMYFUNCTION("""COMPUTED_VALUE"""),180.0) -> 180 | C7: =IFERROR(__xludf.DUMMYFUNCTION("""COMPUTED_VALUE"""),"Money Out") -> Money Out | F7: =IFERROR(__xludf.DUMMYFUNCTION("""COMPUTED_VALUE"""),"طباعة توربو للايت بوكس") -> طباعة توربو للايت بوكس | G7: -180 | H7: Review | J7: Review
A8: =IFERROR(__xludf.DUMMYFUNCTION("""COMPUTED_VALUE"""),45525.0) -> 45525 | B8: =IFERROR(__xludf.DUMMYFUNCTION("""COMPUTED_VALUE"""),2500.0) -> 2500 | C8: =IFERROR(__xludf.DUMMYFUNCTION("""COMPUTED_VALUE"""),"Money In") -> Money In | D8: =IFERROR(__xludf.DUMMYFUNCTION("""COMPUTED_VALUE"""),"ads") -> ads | F8: =IFERROR(__xludf.DUMMYFUNCTION("""COMPUTED_VALUE""")," دعاية توربو ( من نص 9 الى نص 12)") -> دعاية توربو ( من نص 9 الى نص 12) | G8: 2500 | H8: Inflow | J8: Inflow
A9: =IFERROR(__xludf.DUMMYFUNCTION("""COMPUTED_VALUE"""),45528.0) -> 45528 | B9: =IFERROR(__xludf.DUMMYFUNCTION("""COMPUTED_VALUE"""),50.0) -> 50 | C9: =IFERROR(__xludf.DUMMYFUNCTION("""COMPUTED_VALUE"""),"Money Out") -> Money Out | G9: -50 | H9: Review | J9: Review
A10: =IFERROR(__xludf.DUMMYFUNCTION("""COMPUTED_VALUE"""),45528.0) -> 45528 | B10: =IFERROR(__xludf.DUMMYFUNCTION("""COMPUTED_VALUE"""),50.0) -> 50 | C10: =IFERROR(__xludf.DUMMYFUNCTION("""COMPUTED_VALUE"""),"Money In") -> Money In | G10: 50 | H10: Review | J10: Review
A11: =IFERROR(__xludf.DUMMYFUNCTION("""COMPUTED_VALUE"""),45528.0) -> 45528 | B11: =IFERROR(__xludf.DUMMYFUNCTION("""COMPUTED_VALUE"""),40.0) -> 40 | C11: =IFERROR(__xludf.DUMMYFUNCTION("""COMPUTED_VALUE"""),"Money Out") -> Money Out | D11: =IFERROR(__xludf.DUMMYFUNCTION("""COMPUTED_VALUE"""),"Product Restocking") -> Product Restocking | F11: =IFERROR(__xludf.DUMMYFUNCTION("""COMPUTED_VALUE"""),"بضاعه (مياه)") -> بضاعه (مياه) | G11: -40 | H11: Inventory | J11: Inventory
A12: =IFERROR(__xludf.DUMMYFUNCTION("""COMPUTED_VALUE"""),45530.0) -> 45530 | B12: =IFERROR(__xludf.DUMMYFUNCTION("""COMPUTED_VALUE"""),1140.0) -> 1140 | C12: =IFERROR(__xludf.DUMMYFUNCTION("""COMPUTED_VALUE"""),"Money Out") -> Money Out | D12: =IFERROR(__xludf.DUMMYFUNCTION("""COMPUTED_VALUE"""),"Product Restocking") -> Product Restocking | F12: =IFERROR(__xludf.DUMMYFUNCTION("""COMPUTED_VALUE"""),"بضاعه ") -> بضاعه | G12: -1140 | H12: Inventory | J12: Inventory
A13: =IFERROR(__xludf.DUMMYFUNCTION("""COMPUTED_VALUE"""),45530.0) -> 45530 | B13: =IFERROR(__xludf.DUMMYFUNCTION("""COMPUTED_VALUE"""),900.0) -> 900 | C13: =IFERROR(__xludf.DUMMYFUNCTION("""COMPUTED_VALUE"""),"Money In") -> Money In | D13: =IFERROR(__xludf.DUMMYFUNCTION("""COMPUTED_VALUE"""),"Revenue") -> Revenue | E13: =IFERROR(__xludf.DUMMYFUNCTION("""COMPUTED_VALUE"""),"deplomacyMall") -> deplomacyMall | G13: 900 | H13: Inflow | J13: Inflow
A14: =IFERROR(__xludf.DUMMYFUNCTION("""COMPUTED_VALUE"""),45533.0) -> 45533 | B14: =IFERROR(__xludf.DUMMYFUNCTION("""COMPUTED_VALUE"""),60.0) -> 60 | C14: =IFERROR(__xludf.DUMMYFUNCTION("""COMPUTED_VALUE"""),"Money Out") -> Money Out | D14: =IFERROR(__xludf.DUMMYFUNCTION("""COMPUTED_VALUE"""),"Product Restocking") -> Product Restocking | F14: =IFERROR(__xludf.DUMMYFUNCTION("""COMPUTED_VALUE"""),"بضاعه (مياه)") -> بضاعه (مياه) | G14: -60 | H14: Inventory | J14: Inventory
A15: =IFERROR(__xludf.DUMMYFUNCTION("""COMPUTED_VALUE"""),45535.0) -> 45535 | B15: =IFERROR(__xludf.DUMMYFUNCTION("""COMPUTED_VALUE"""),18.0) -> 18 | C15: =IFERROR(__xludf.DUMMYFUNCTION("""COMPUTED_VALUE"""),"Money Out") -> Money Out | D15: =IFERROR(__xludf.DUMMYFUNCTION("""COMPUTED_VALUE"""),"Product Restocking") -> Product Restocking | F15: =IFERROR(__xludf.DUMMYFUNCTION("""COMPUTED_VALUE"""),"بضاعه (مياه)") -> بضاعه (مياه) | G15: -18 | H15: Inventory | J15: Inventory
A16: =IFERROR(__xludf.DUMMYFUNCTION("""COMPUTED_VALUE"""),45535.0) -> 45535 | B16: =IFERROR(__xludf.DUMMYFUNCTION("""COMPUTED_VALUE"""),1158.0) -> 1158 | C16: =IFERROR(__xludf.DUMMYFUNCTION("""COMPUTED_VALUE"""),"Money In") -> Money In | D16: =IFERROR(__xludf.DUMMYFUNCTION("""COMPUTED_VALUE"""),"Revenue") -> Revenue | E16: =IFERROR(__xludf.DUMMYFUNCTION("""COMPUTED_VALUE"""),"deplomacyMall") -> deplomacyMall | G16: 1158 | H16: Inflow | J16: Inflow
A17: =IFERROR(__xludf.DUMMYFUNCTION("""COMPUTED_VALUE"""),45535.0) -> 45535 | B17: =IFERROR(__xludf.DUMMYFUNCTION("""COMPUTED_VALUE"""),15.0) -> 15 | C17: =IFERROR(__xludf.DUMMYFUNCTION("""COMPUTED_VALUE"""),"Money In") -> Money In | G17: 15 | H17: Review | J17: Review
A18: =IFERROR(__xludf.DUMMYFUNCTION("""COMPUTED_VALUE"""),45535.0) -> 45535 | B18: =IFERROR(__xludf.DUMMYFUNCTION("""COMPUTED_VALUE"""),15.0) -> 15 | C18: =IFERROR(__xludf.DUMMYFUNCTION("""COMPUTED_VALUE"""),"Money Out") -> Money Out | G18: -15 | H18: Review | J18: Review
A19: =IFERROR(__xludf.DUMMYFUNCTION("""COMPUTED_VALUE"""),45536.0) -> 45536 | B19: =IFERROR(__xludf.DUMMYFUNCTION("""COMPUTED_VALUE"""),190.0) -> 190 | C19: =IFERROR(__xludf.DUMMYFUNCTION("""COMPUTED_VALUE"""),"Money Out") -> Money Out | F19: =IFERROR(__xludf.DUMMYFUNCTION("""COMPUTED_VALUE"""),"تعديل الميزانيه") -> تعديل الميزانيه | G19: -190 | H19: Review | J19: Review
A20: =IFERROR(__xludf.DUMMYFUNCTION("""COMPUTED_VALUE"""),45536.0) -> 45536 | B20: =IFERROR(__xludf.DUMMYFUNCTION("""COMPUTED_VALUE"""),827.0) -> 827 | C20: =IFERROR(__xludf.DUMMYFUNCTION("""COMPUTED_VALUE"""),"Money Out") -> Money Out | D20: =IFERROR(__xludf.DUMMYFUNCTION("""COMPUTED_VALUE"""),"Product Restocking") -> Product Restocking | F20: =IFERROR(__xludf.DUMMYFUNCTION("""COMPUTED_VALUE"""),"بضاعه ") -> بضاعه | G20: -827 | H20: Inventory | J20: Inventory
A21: =IFERROR(__xludf.DUMMYFUNCTION("""COMPUTED_VALUE"""),45537.0) -> 45537 | B21: =IFERROR(__xludf.DUMMYFUNCTION("""COMPUTED_VALUE"""),40.0) -> 40 | C21: =IFERROR(__xludf.DUMMYFUNCTION("""COMPUTED_VALUE"""),"Money Out") -> Money Out | D21: =IFERROR(__xludf.DUMMYFUNCTION("""COMPUTED_VALUE"""),"Product Restocking") -> Product Restocking | F21: =IFERROR(__xludf.DUMMYFUNCTION("""COMPUTED_VALUE"""),"بضاعه (مياه)") -> بضاعه (مياه) | G21: -40 | H21: Inventory | J21: Inventory
A22: =IFERROR(__xludf.DUMMYFUNCTION("""COMPUTED_VALUE"""),45539.0) -> 45539 | B22: =IFERROR(__xludf.DUMMYFUNCTION("""COMPUTED_VALUE"""),1082.0) -> 1082 | C22: =IFERROR(__xludf.DUMMYFUNCTION("""COMPUTED_VALUE"""),"Money In") -> Money In | D22: =IFERROR(__xludf.DUMMYFUNCTION("""COMPUTED_VALUE"""),"Revenue") -> Revenue | E22: =IFERROR(__xludf.DUMMYFUNCTION("""COMPUTED_VALUE"""),"deplomacyMall") -> deplomacyMall | G22: 1082 | H22: Inflow | J22: Inflow
A23: =IFERROR(__xludf.DUMMYFUNCTION("""COMPUTED_VALUE"""),45539.0) -> 45539 | B23: =IFERROR(__xludf.DUMMYFUNCTION("""COMPUTED_VALUE"""),40.0) -> 40 | C23: =IFERROR(__xludf.DUMMYFUNCTION("""COMPUTED_VALUE"""),"Money Out") -> Money Out | D23: =IFERROR(__xludf.DUMMYFUNCTION("""COMPUTED_VALUE"""),"Product Restocking") -> Product Restocking | F23: =IFERROR(__xludf.DUMMYFUNCTION("""COMPUTED_VALUE"""),"بضاعه (مياه)") -> بضاعه (مياه) | G23: -40 | H23: Inventory | J23: Inventory
A24: =IFERROR(__xludf.DUMMYFUNCTION("""COMPUTED_VALUE"""),45540.0) -> 45540 | B24: =IFERROR(__xludf.DUMMYFUNCTION("""COMPUTED_VALUE"""),64.0) -> 64 | C24: =IFERROR(__xludf.DUMMYFUNCTION("""COMPUTED_VALUE"""),"Money Out") -> Money Out | D24: =IFERROR(__xludf.DUMMYFUNCTION("""COMPUTED_VALUE"""),"Product Restocking") -> Product Restocking | F24: =IFERROR(__xludf.DUMMYFUNCTION("""COMPUTED_VALUE"""),"بضاعه (مياه)") -> بضاعه (مياه) | G24: -64 | H24: Inventory | J24: Inventory
A25: =IFERROR(__xludf.DUMMYFUNCTION("""COMPUTED_VALUE"""),45542.0) -> 45542 | B25: =IFERROR(__xludf.DUMMYFUNCTION("""COMPUTED_VALUE"""),1574.0) -> 1574 | C25: =IFERROR(__xludf.DUMMYFUNCTION("""COMPUTED_VALUE"""),"Money Out") -> Money Out | D25: =IFERROR(__xludf.DUMMYFUNCTION("""COMPUTED_VALUE"""),"Product Restocking") -> Product Restocking | F25: =IFERROR(__xludf.DUMMYFUNCTION("""COMPUTED_VALUE"""),"بضاعه ") -> بضاعه | G25: -1574 | H25: Inventory | J25: Inventory
A26: =IFERROR(__xludf.DUMMYFUNCTION("""COMPUTED_VALUE"""),45542.0) -> 45542 | B26: =IFERROR(__xludf.DUMMYFUNCTION("""COMPUTED_VALUE"""),20.0) -> 20 | C26: =IFERROR(__xludf.DUMMYFUNCTION("""COMPUTED_VALUE"""),"Money Out") -> Money Out | D26: =IFERROR(__xludf.DUMMYFUNCTION("""COMPUTED_VALUE"""),"Product Restocking") -> Product Restocking | F26: =IFERROR(__xludf.DUMMYFUNCTION("""COMPUTED_VALUE"""),"بضاعه (مياه)") -> بضاعه (مياه) | G26: -20 | H26: Inventory | J26: Inventory
A27: =IFERROR(__xludf.DUMMYFUNCTION("""COMPUTED_VALUE"""),45543.0) -> 45543 | B27: =IFERROR(__xludf.DUMMYFUNCTION("""COMPUTED_VALUE"""),40.0) -> 40 | C27: =IFERROR(__xludf.DUMMYFUNCTION("""COMPUTED_VALUE"""),"Money Out") -> Money Out | D27: =IFERROR(__xludf.DUMMYFUNCTION("""COMPUTED_VALUE"""),"Product Restocking") -> Product Restocking | F27: =IFERROR(__xludf.DUMMYFUNCTION("""COMPUTED_VALUE"""),"بضاعه (مياه)") -> بضاعه (مياه) | G27: -40 | H27: Inventory | J27: Inventory
A28: =IFERROR(__xludf.DUMMYFUNCTION("""COMPUTED_VALUE"""),45544.0) -> 45544 | B28: =IFERROR(__xludf.DUMMYFUNCTION("""COMPUTED_VALUE"""),1896.0) -> 1896 | C28: =IFERROR(__xludf.DUMMYFUNCTION("""COMPUTED_VALUE"""),"Money In") -> Money In | D28: =IFERROR(__xludf.DUMMYFUNCTION("""COMPUTED_VALUE"""),"Revenue") -> Revenue | E28: =IFERROR(__xludf.DUMMYFUNCTION("""COMPUTED_VALUE"""),"deplomacyMall") -> deplomacyMall | G28: 1896 | H28: Inflow | J28: Inflow
A29: =IFERROR(__xludf.DUMMYFUNCTION("""COMPUTED_VALUE"""),45544.0) -> 45544 | B29: =IFERROR(__xludf.DUMMYFUNCTION("""COMPUTED_VALUE"""),40.0) -> 40 | C29: =IFERROR(__xludf.DUMMYFUNCTION("""COMPUTED_VALUE"""),"Money Out") -> Money Out | D29: =IFERROR(__xludf.DUMMYFUNCTION("""COMPUTED_VALUE"""),"Product Restocking") -> Product Restocking | F29: =IFERROR(__xludf.DUMMYFUNCTION("""COMPUTED_VALUE"""),"بضاعه (مياه)") -> بضاعه (مياه) | G29: -40 | H29: Inventory | J29: Inventory
A30: =IFERROR(__xludf.DUMMYFUNCTION("""COMPUTED_VALUE"""),45545.0) -> 45545 | B30: =IFERROR(__xludf.DUMMYFUNCTION("""COMPUTED_VALUE"""),225.0) -> 225 | C30: =IFERROR(__xludf.DUMMYFUNCTION("""COMPUTED_VALUE"""),"Money Out") -> Money Out | D30: =IFERROR(__xludf.DUMMYFUNCTION("""COMPUTED_VALUE"""),"Product Restocking") -> Product Restocking | G30: -225 | H30: Inventory | J30: Inventory
A31: =IFERROR(__xludf.DUMMYFUNCTION("""COMPUTED_VALUE"""),45545.0) -> 45545 | B31: =IFERROR(__xludf.DUMMYFUNCTION("""COMPUTED_VALUE"""),325.0) -> 325 | C31: =IFERROR(__xludf.DUMMYFUNCTION("""COMPUTED_VALUE"""),"Money Out") -> Money Out | D31: =IFERROR(__xludf.DUMMYFUNCTION("""COMPUTED_VALUE"""),"Product Restocking") -> Product Restocking | G31: -325 | H31: Inventory | J31: Inventory
A32: =IFERROR(__xludf.DUMMYFUNCTION("""COMPUTED_VALUE"""),45546.0) -> 45546 | B32: =IFERROR(__xludf.DUMMYFUNCTION("""COMPUTED_VALUE"""),57.75) -> 57.75 | C32: =IFERROR(__xludf.DUMMYFUNCTION("""COMPUTED_VALUE"""),"Money Out") -> Money Out | D32: =IFERROR(__xludf.DUMMYFUNCTION("""COMPUTED_VALUE"""),"Product Restocking") -> Product Restocking | F32: =IFERROR(__xludf.DUMMYFUNCTION("""COMPUTED_VALUE"""),"بضاعه (مياه)") -> بضاعه (مياه) | G32: -57.75 | H32: Inventory | J32: Inventory
A33: =IFERROR(__xludf.DUMMYFUNCTION("""COMPUTED_VALUE"""),45547.0) -> 45547 | B33: =IFERROR(__xludf.DUMMYFUNCTION("""COMPUTED_VALUE"""),1134.0) -> 1134 | C33: =IFERROR(__xludf.DUMMYFUNCTION("""COMPUTED_VALUE"""),"Money In") -> Money In | D33: =IFERROR(__xludf.DUMMYFUNCTION("""COMPUTED_VALUE"""),"Revenue") -> Revenue | E33: =IFERROR(__xludf.DUMMYFUNCTION("""COMPUTED_VALUE"""),"deplomacyMall") -> deplomacyMall | G33: 1134 | H33: Inflow | J33: Inflow
A34: =IFERROR(__xludf.DUMMYFUNCTION("""COMPUTED_VALUE"""),45547.0) -> 45547 | B34: =IFERROR(__xludf.DUMMYFUNCTION("""COMPUTED_VALUE"""),446.0) -> 446 | C34: =IFERROR(__xludf.DUMMYFUNCTION("""COMPUTED_VALUE"""),"Money Out") -> Money Out | D34: =IFERROR(__xludf.DUMMYFUNCTION("""COMPUTED_VALUE"""),"Product Restocking") -> Product Restocking | G34: -446 | H34: Inventory | J34: Inventory
A35: =IFERROR(__xludf.DUMMYFUNCTION("""COMPUTED_VALUE"""),45546.0) -> 45546 | B35: =IFERROR(__xludf.DUMMYFUNCTION("""COMPUTED_VALUE"""),61.0) -> 61 | C35: =IFERROR(__xludf.DUMMYFUNCTION("""COMPUTED_VALUE"""),"Money Out") -> Money Out | D35: =IFERROR(__xludf.DUMMYFUNCTION("""COMPUTED_VALUE"""),"Product Restocking") -> Product Restocking | G35: -61 | H35: Inventory | J35: Inventory
A36: =IFERROR(__xludf.DUMMYFUNCTION("""COMPUTED_VALUE"""),45547.0) -> 45547 | B36: =IFERROR(__xludf.DUMMYFUNCTION("""COMPUTED_VALUE"""),72.0) -> 72 | C36: =IFERROR(__xludf.DUMMYFUNCTION("""COMPUTED_VALUE"""),"Money Out") -> Money Out | D36: =IFERROR(__xludf.DUMMYFUNCTION("""COMPUTED_VALUE"""),"Product Restocking") -> Product Restocking | F36: =IFERROR(__xludf.DUMMYFUNCTION("""COMPUTED_VALUE"""),"بضاعه (مياه)") -> بضاعه (مياه) | G36: -72 | H36: Inventory | J36: Inventory
A37: =IFERROR(__xludf.DUMMYFUNCTION("""COMPUTED_VALUE"""),45549.0) -> 45549 | B37: =IFERROR(__xludf.DUMMYFUNCTION("""COMPUTED_VALUE"""),177.0) -> 177 | C37: =IFERROR(__xludf.DUMMYFUNCTION("""COMPUTED_VALUE"""),"Money Out") -> Money Out | D37: =IFERROR(__xludf.DUMMYFUNCTION("""COMPUTED_VALUE"""),"Product Restocking") -> Product Restocking | G37: -177 | H37: Inventory | J37: Inventory
A38: =IFERROR(__xludf.DUMMYFUNCTION("""COMPUTED_VALUE"""),45550.0) -> 45550 | B38: =IFERROR(__xludf.DUMMYFUNCTION("""COMPUTED_VALUE"""),1280.0) -> 1280 | C38: =IFERROR(__xludf.DUMMYFUNCTION("""COMPUTED_VALUE"""),"Money In") -> Money In | D38: =IFERROR(__xludf.DUMMYFUNCTION("""COMPUTED_VALUE"""),"Revenue") -> Revenue | E38: =IFERROR(__xludf.DUMMYFUNCTION("""COMPUTED_VALUE"""),"deplomacyMall") -> deplomacyMall | G38: 1280 | H38: Inflow | J38: Inflow
A39: =IFERROR(__xludf.DUMMYFUNCTION("""COMPUTED_VALUE"""),45551.0) -> 45551 | B39: =IFERROR(__xludf.DUMMYFUNCTION("""COMPUTED_VALUE"""),72.0) -> 72 | C39: =IFERROR(__xludf.DUMMYFUNCTION("""COMPUTED_VALUE"""),"Money Out") -> Money Out | D39: =IFERROR(__xludf.DUMMYFUNCTION("""COMPUTED_VALUE"""),"Product Restocking") -> Product Restocking | F39: =IFERROR(__xludf.DUMMYFUNCTION("""COMPUTED_VALUE"""),"بضاعه (مياه)") -> بضاعه (مياه) | G39: -72 | H39: Inventory | J39: Inventory
A40: =IFERROR(__xludf.DUMMYFUNCTION("""COMPUTED_VALUE"""),45551.0) -> 45551 | B40: =IFERROR(__xludf.DUMMYFUNCTION("""COMPUTED_VALUE"""),585.0) -> 585 | C40: =IFERROR(__xludf.DUMMYFUNCTION("""COMPUTED_VALUE"""),"Money In") -> Money In | D40: =IFERROR(__xludf.DUMMYFUNCTION("""COMPUTED_VALUE"""),"Revenue") -> Revenue | E40: =IFERROR(__xludf.DUMMYFUNCTION("""COMPUTED_VALUE"""),"deplomacyMall") -> deplomacyMall | G40: 585 | H40: Inflow | J40: Inflow
A41: =IFERROR(__xludf.DUMMYFUNCTION("""COMPUTED_VALUE"""),45551.0) -> 45551 | B41: =IFERROR(__xludf.DUMMYFUNCTION("""COMPUTED_VALUE"""),164.0) -> 164 | C41: =IFERROR(__xludf.DUMMYFUNCTION("""COMPUTED_VALUE"""),"Money Out") -> Money Out | D41: =IFERROR(__xludf.DUMMYFUNCTION("""COMPUTED_VALUE"""),"Product Restocking") -> Product Restocking | G41: -164 | H41: Inventory | J41: Inventory
A42: =IFERROR(__xludf.DUMMYFUNCTION("""COMPUTED_VALUE"""),45553.0) -> 45553 | B42: =IFERROR(__xludf.DUMMYFUNCTION("""COMPUTED_VALUE"""),718.0) -> 718 | C42: =IFERROR(__xludf.DUMMYFUNCTION("""COMPUTED_VALUE"""),"Money Out") -> Money Out | D42: =IFERROR(__xludf.DUMMYFUNCTION("""COMPUTED_VALUE"""),"Product Restocking") -> Product Restocking | G42: -718 | H42: Inventory | J42: Inventory
A43: =IFERROR(__xludf.DUMMYFUNCTION("""COMPUTED_VALUE"""),45554.0) -> 45554 | B43: =IFERROR(__xludf.DUMMYFUNCTION("""COMPUTED_VALUE"""),792.0) -> 792 | C43: =IFERROR(__xludf.DUMMYFUNCTION("""COMPUTED_VALUE"""),"Money In") -> Money In | D43: =IFERROR(__xludf.DUMMYFUNCTION("""COMPUTED_VALUE"""),"Revenue") -> Revenue | E43: =IFERROR(__xludf.DUMMYFUNCTION("""COMPUTED_VALUE"""),"deplomacyMall") -> deplomacyMall | G43: 792 | H43: Inflow | J43: Inflow
A44: =IFERROR(__xludf.DUMMYFUNCTION("""COMPUTED_VALUE"""),45554.0) -> 45554 | G44: 0 | H44: Review | J44: Review
A45: =IFERROR(__xludf.DUMMYFUNCTION("""COMPUTED_VALUE"""),45556.0) -> 45556 | B45: =IFERROR(__xludf.DUMMYFUNCTION("""COMPUTED_VALUE"""),1144.0) -> 1144 | C45: =IFERROR(__xludf.DUMMYFUNCTION("""COMPUTED_VALUE"""),"Money In") -> Money In | D45: =IFERROR(__xludf.DUMMYFUNCTION("""COMPUTED_VALUE"""),"Revenue") -> Revenue | E45: =IFERROR(__xludf.DUMMYFUNCTION("""COMPUTED_VALUE"""),"deplomacyMall") -> deplomacyMall | G45: 1144 | H45: Inflow | J45: Inflow
A46: =IFERROR(__xludf.DUMMYFUNCTION("""COMPUTED_VALUE"""),45556.0) -> 45556 | B46: =IFERROR(__xludf.DUMMYFUNCTION("""COMPUTED_VALUE"""),51.0) -> 51 | C46: =IFERROR(__xludf.DUMMYFUNCTION("""COMPUTED_VALUE"""),"Money Out") -> Money Out | D46: =IFERROR(__xludf.DUMMYFUNCTION("""COMPUTED_VALUE"""),"Product Restocking") -> Product Restocking | F46: =IFERROR(__xludf.DUMMYFUNCTION("""COMPUTED_VALUE"""),"بضاعه (مياه)") -> بضاعه (مياه) | G46: -51 | H46: Inventory | J46: Inventory
A47: =IFERROR(__xludf.DUMMYFUNCTION("""COMPUTED_VALUE"""),45557.0) -> 45557 | B47: =IFERROR(__xludf.DUMMYFUNCTION("""COMPUTED_VALUE"""),540.0) -> 540 | C47: =IFERROR(__xludf.DUMMYFUNCTION("""COMPUTED_VALUE"""),"Money Out") -> Money Out | D47: =IFERROR(__xludf.DUMMYFUNCTION("""COMPUTED_VALUE"""),"Product Restocking") -> Product Restocking | G47: -540 | H47: Inventory | J47: Inventory
A48: =IFERROR(__xludf.DUMMYFUNCTION("""COMPUTED_VALUE"""),45556.0) -> 45556 | B48: =IFERROR(__xludf.DUMMYFUNCTION("""COMPUTED_VALUE"""),101.0) -> 101 | C48: =IFERROR(__xludf.DUMMYFUNCTION("""COMPUTED_VALUE"""),"Money Out") -> Money Out | D48: =IFERROR(__xludf.DUMMYFUNCTION("""COMPUTED_VALUE"""),"Product Restocking") -> Product Restocking | G48: -101 | H48: Inventory | J48: Inventory
A49: =IFERROR(__xludf.DUMMYFUNCTION("""COMPUTED_VALUE"""),45560.0) -> 45560 | B49: =IFERROR(__xludf.DUMMYFUNCTION("""COMPUTED_VALUE"""),87.0) -> 87 | C49: =IFERROR(__xludf.DUMMYFUNCTION("""COMPUTED_VALUE"""),"Money Out") -> Money Out | D49: =IFERROR(__xludf.DUMMYFUNCTION("""COMPUTED_VALUE"""),"Product Restocking") -> Product Restocking | G49: -87 | H49: Inventory | J49: Inventory
A50: =IFERROR(__xludf.DUMMYFUNCTION("""COMPUTED_VALUE"""),45561.0) -> 45561 | B50: =IFERROR(__xludf.DUMMYFUNCTION("""COMPUTED_VALUE"""),50.5) -> 50.5 | C50: =IFERROR(__xludf.DUMMYFUNCTION("""COMPUTED_VALUE"""),"Money Out") -> Money Out | D50: =IFERROR(__xludf.DUMMYFUNCTION("""COMPUTED_VALUE"""),"Product Restocking") -> Product Restocking | F50: =IFERROR(__xludf.DUMMYFUNCTION("""COMPUTED_VALUE"""),"بضاعه (مياه)") -> بضاعه (مياه) | G50: -50.5 | H50: Inventory | J50: Inventory
A51: =IFERROR(__xludf.DUMMYFUNCTION("""COMPUTED_VALUE"""),45561.0) -> 45561 | B51: =IFERROR(__xludf.DUMMYFUNCTION("""COMPUTED_VALUE"""),1311.0) -> 1311 | C51: =IFERROR(__xludf.DUMMYFUNCTION("""COMPUTED_VALUE"""),"Money In") -> Money In | D51: =IFERROR(__xludf.DUMMYFUNCTION("""COMPUTED_VALUE"""),"Revenue") -> Revenue | E51: =IFERROR(__xludf.DUMMYFUNCTION("""COMPUTED_VALUE"""),"deplomacyMall") -> deplomacyMall | G51: 1311 | H51: Inflow | J51: Inflow
A52: =IFERROR(__xludf.DUMMYFUNCTION("""COMPUTED_VALUE"""),45563.0) -> 45563 | B52: =IFERROR(__xludf.DUMMYFUNCTION("""COMPUTED_VALUE"""),960.0) -> 960 | C52: =IFERROR(__xludf.DUMMYFUNCTION("""COMPUTED_VALUE"""),"Money Out") -> Money Out | D52: =IFERROR(__xludf.DUMMYFUNCTION("""COMPUTED_VALUE"""),"Product Restocking") -> Product Restocking | G52: -960 | H52: Inventory | J52: Inventory
A53: =IFERROR(__xludf.DUMMYFUNCTION("""COMPUTED_VALUE"""),45563.0) -> 45563 | B53: =IFERROR(__xludf.DUMMYFUNCTION("""COMPUTED_VALUE"""),49.0) -> 49 | C53: =IFERROR(__xludf.DUMMYFUNCTION("""COMPUTED_VALUE"""),"Money Out") -> Money Out | D53: =IFERROR(__xludf.DUMMYFUNCTION("""COMPUTED_VALUE"""),"Product Restocking") -> Product Restocking | F53: =IFERROR(__xludf.DUMMYFUNCTION("""COMPUTED_VALUE"""),"بضاعه (مياه)") -> بضاعه (مياه) | G53: -49 | H53: Inventory | J53: Inventory
A54: =IFERROR(__xludf.DUMMYFUNCTION("""COMPUTED_VALUE"""),45562.0) -> 45562 | B54: =IFERROR(__xludf.DUMMYFUNCTION("""COMPUTED_VALUE"""),80.0) -> 80 | C54: =IFERROR(__xludf.DUMMYFUNCTION("""COMPUTED_VALUE"""),"Money Out") -> Money Out | F54: =IFERROR(__xludf.DUMMYFUNCTION("""COMPUTED_VALUE"""),"تركيب اللافته عل تلاجه") -> تركيب اللافته عل تلاجه | G54: -80 | H54: Review | J54: Review
A55: =IFERROR(__xludf.DUMMYFUNCTION("""COMPUTED_VALUE"""),45566.0) -> 45566 | B55: =IFERROR(__xludf.DUMMYFUNCTION("""COMPUTED_VALUE"""),375.0) -> 375 | C55: =IFERROR(__xludf.DUMMYFUNCTION("""COMPUTED_VALUE"""),"Money Out") -> Money Out | F55: =IFERROR(__xludf.DUMMYFUNCTION("""COMPUTED_VALUE"""),"ارسال (change box, motherboard) الى الصين") -> ارسال (change box, motherboard) الى الصين | G55: -375 | H55: Review | J55: Review
A56: =IFERROR(__xludf.DUMMYFUNCTION("""COMPUTED_VALUE"""),45567.0) -> 45567 | B56: =IFERROR(__xludf.DUMMYFUNCTION("""COMPUTED_VALUE"""),1500.0) -> 1500 | C56: =IFERROR(__xludf.DUMMYFUNCTION("""COMPUTED_VALUE"""),"Money Out") -> Money Out | F56: =IFERROR(__xludf.DUMMYFUNCTION("""COMPUTED_VALUE"""),"ارجاع قيمة الى محمد العتيري") -> ارجاع قيمة الى محمد العتيري | G56: -1500 | H56: Review | J56: Review
A57: =IFERROR(__xludf.DUMMYFUNCTION("""COMPUTED_VALUE"""),45565.0) -> 45565 | B57: =IFERROR(__xludf.DUMMYFUNCTION("""COMPUTED_VALUE"""),935.0) -> 935 | C57: =IFERROR(__xludf.DUMMYFUNCTION("""COMPUTED_VALUE"""),"Money In") -> Money In | D57: =IFERROR(__xludf.DUMMYFUNCTION("""COMPUTED_VALUE"""),"Revenue") -> Revenue | E57: =IFERROR(__xludf.DUMMYFUNCTION("""COMPUTED_VALUE"""),"deplomacyMall") -> deplomacyMall | G57: 935 | H57: Inflow | J57: Inflow
A58: =IFERROR(__xludf.DUMMYFUNCTION("""COMPUTED_VALUE"""),45625.0) -> 45625 | B58: =IFERROR(__xludf.DUMMYFUNCTION("""COMPUTED_VALUE"""),836.0) -> 836 | C58: =IFERROR(__xludf.DUMMYFUNCTION("""COMPUTED_VALUE"""),"Money In") -> Money In | D58: =IFERROR(__xludf.DUMMYFUNCTION("""COMPUTED_VALUE"""),"Revenue") -> Revenue | E58: =IFERROR(__xludf.DUMMYFUNCTION("""COMPUTED_VALUE"""),"deplomacyMall") -> deplomacyMall | G58: 836 | H58: Inflow | J58: Inflow
A59: =IFERROR(__xludf.DUMMYFUNCTION("""COMPUTED_VALUE"""),45625.0) -> 45625 | B59: =IFERROR(__xludf.DUMMYFUNCTION("""COMPUTED_VALUE"""),70.0) -> 70 | C59: =IFERROR(__xludf.DUMMYFUNCTION("""COMPUTED_VALUE"""),"Money Out") -> Money Out | F59: =IFERROR(__xludf.DUMMYFUNCTION("""COMPUTED_VALUE"""),"ارجاع شحن (change box, motherboard)") -> ارجاع شحن (change box, motherboard) | G59: -70 | H59: Review | J59: Review
A60: =IFERROR(__xludf.DUMMYFUNCTION("""COMPUTED_VALUE"""),45625.0) -> 45625 | B60: =IFERROR(__xludf.DUMMYFUNCTION("""COMPUTED_VALUE"""),65.0) -> 65 | C60: =IFERROR(__xludf.DUMMYFUNCTION("""COMPUTED_VALUE"""),"Money Out") -> Money Out | D60: =IFERROR(__xludf.DUMMYFUNCTION("""COMPUTED_VALUE"""),"Product Restocking") -> Product Restocking | F60: =IFERROR(__xludf.DUMMYFUNCTION("""COMPUTED_VALUE"""),"بضاعه من محل لجنب دبلوماسي") -> بضاعه من محل لجنب دبلوماسي | G60: -65 | H60: Inventory | J60: Inventory
A61: =IFERROR(__xludf.DUMMYFUNCTION("""COMPUTED_VALUE"""),45626.0) -> 45626 | B61: =IFERROR(__xludf.DUMMYFUNCTION("""COMPUTED_VALUE"""),1029.0) -> 1029 | C61: =IFERROR(__xludf.DUMMYFUNCTION("""COMPUTED_VALUE"""),"Money Out") -> Money Out | D61: =IFERROR(__xludf.DUMMYFUNCTION("""COMPUTED_VALUE"""),"Product Restocking") -> Product Restocking | G61: -1029 | H61: Inventory | J61: Inventory
A62: =IFERROR(__xludf.DUMMYFUNCTION("""COMPUTED_VALUE"""),45629.0) -> 45629 | B62: =IFERROR(__xludf.DUMMYFUNCTION("""COMPUTED_VALUE"""),50.0) -> 50 | C62: =IFERROR(__xludf.DUMMYFUNCTION("""COMPUTED_VALUE"""),"Money Out") -> Money Out | F62: =IFERROR(__xludf.DUMMYFUNCTION("""COMPUTED_VALUE"""),"اجار فوركه لتحريك المكينه ") -> اجار فوركه لتحريك المكينه | G62: -50 | H62: Review | J62: Review
A63: =IFERROR(__xludf.DUMMYFUNCTION("""COMPUTED_VALUE"""),45631.0) -> 45631 | B63: =IFERROR(__xludf.DUMMYFUNCTION("""COMPUTED_VALUE"""),850.0) -> 850 | C63: =IFERROR(__xludf.DUMMYFUNCTION("""COMPUTED_VALUE"""),"Money Out") -> Money Out | D63: =IFERROR(__xludf.DUMMYFUNCTION("""COMPUTED_VALUE"""),"Product Restocking") -> Product Restocking | F63: =IFERROR(__xludf.DUMMYFUNCTION("""COMPUTED_VALUE"""),"بضاعه من المتحده والمحل لديما ناخد منه") -> بضاعه من المتحده والمحل لديما ناخد منه | G63: -850 | H63: Inventory | J63: Inventory
A64: =IFERROR(__xludf.DUMMYFUNCTION("""COMPUTED_VALUE"""),45627.0) -> 45627 | B64: =IFERROR(__xludf.DUMMYFUNCTION("""COMPUTED_VALUE"""),1800.0) -> 1800 | C64: =IFERROR(__xludf.DUMMYFUNCTION("""COMPUTED_VALUE"""),"Money In") -> Money In | F64: =IFERROR(__xludf.DUMMYFUNCTION("""COMPUTED_VALUE"""),"تمت تسوية سعر الماكينه مع تيسير") -> تمت تسوية سعر الماكينه مع تيسير | G64: 1800 | H64: Review | J64: Review
A65: =IFERROR(__xludf.DUMMYFUNCTION("""COMPUTED_VALUE"""),45635.0) -> 45635 | B65: =IFERROR(__xludf.DUMMYFUNCTION("""COMPUTED_VALUE"""),1111.0) -> 1111 | C65: =IFERROR(__xludf.DUMMYFUNCTION("""COMPUTED_VALUE"""),"Money In") -> Money In | D65: =IFERROR(__xludf.DUMMYFUNCTION("""COMPUTED_VALUE"""),"Revenue") -> Revenue | E65: =IFERROR(__xludf.DUMMYFUNCTION("""COMPUTED_VALUE"""),"deplomacyMall") -> deplomacyMall | G65: 1111 | H65: Inflow | J65: Inflow
A66: =IFERROR(__xludf.DUMMYFUNCTION("""COMPUTED_VALUE"""),45636.0) -> 45636 | B66: =IFERROR(__xludf.DUMMYFUNCTION("""COMPUTED_VALUE"""),455.0) -> 455 | C66: =IFERROR(__xludf.DUMMYFUNCTION("""COMPUTED_VALUE"""),"Money Out") -> Money Out | F66: =IFERROR(__xludf.DUMMYFUNCTION("""COMPUTED_VALUE"""),"فواتير") -> فواتير | G66: -455 | H66: Review | J66: Review
A67: =IFERROR(__xludf.DUMMYFUNCTION("""COMPUTED_VALUE"""),45637.0) -> 45637 | B67: =IFERROR(__xludf.DUMMYFUNCTION("""COMPUTED_VALUE"""),9000.0) -> 9000 | C67: =IFERROR(__xludf.DUMMYFUNCTION("""COMPUTED_VALUE"""),"Money In") -> Money In | F67: =IFERROR(__xludf.DUMMYFUNCTION("""COMPUTED_VALUE"""),"سحبت فلوس الايداع لفتح شركه") -> سحبت فلوس الايداع لفتح شركه | G67: 9000 | H67: Review | J67: Review
A68: =IFERROR(__xludf.DUMMYFUNCTION("""COMPUTED_VALUE"""),45640.0) -> 45640 | B68: =IFERROR(__xludf.DUMMYFUNCTION("""COMPUTED_VALUE"""),980.0) -> 980 | C68: =IFERROR(__xludf.DUMMYFUNCTION("""COMPUTED_VALUE"""),"Money In") -> Money In | D68: =IFERROR(__xludf.DUMMYFUNCTION("""COMPUTED_VALUE"""),"Revenue") -> Revenue | E68: =IFERROR(__xludf.DUMMYFUNCTION("""COMPUTED_VALUE"""),"deplomacyMall") -> deplomacyMall | G68: 980 | H68: Inflow | J68: Inflow
A69: =IFERROR(__xludf.DUMMYFUNCTION("""COMPUTED_VALUE"""),45641.0) -> 45641 | B69: =IFERROR(__xludf.DUMMYFUNCTION("""COMPUTED_VALUE"""),2500.0) -> 2500 | C69: =IFERROR(__xludf.DUMMYFUNCTION("""COMPUTED_VALUE"""),"Money In") -> Money In | D69: =IFERROR(__xludf.DUMMYFUNCTION("""COMPUTED_VALUE"""),"ads") -> ads | F69: =IFERROR(__xludf.DUMMYFUNCTION("""COMPUTED_VALUE"""),"توربو من نص 12 الى نص 3") -> توربو من نص 12 الى نص 3 | G69: 2500 | H69: Inflow | J69: Inflow
A70: =IFERROR(__xludf.DUMMYFUNCTION("""COMPUTED_VALUE"""),45643.0) -> 45643 | B70: =IFERROR(__xludf.DUMMYFUNCTION("""COMPUTED_VALUE"""),1097.0) -> 1097 | C70: =IFERROR(__xludf.DUMMYFUNCTION("""COMPUTED_VALUE"""),"Money Out") -> Money Out | D70: =IFERROR(__xludf.DUMMYFUNCTION("""COMPUTED_VALUE"""),"Product Restocking") -> Product Restocking | G70: -1097 | H70: Inventory | J70: Inventory
A71: =IFERROR(__xludf.DUMMYFUNCTION("""COMPUTED_VALUE"""),45645.0) -> 45645 | B71: =IFERROR(__xludf.DUMMYFUNCTION("""COMPUTED_VALUE"""),1600.0) -> 1600 | C71: =IFERROR(__xludf.DUMMYFUNCTION("""COMPUTED_VALUE"""),"Money In") -> Money In | D71: =IFERROR(__xludf.DUMMYFUNCTION("""COMPUTED_VALUE"""),"Revenue") -> Revenue | E71: =IFERROR(__xludf.DUMMYFUNCTION("""COMPUTED_VALUE"""),"deplomacyMall") -> deplomacyMall | G71: 1600 | H71: Inflow | J71: Inflow
A72: =IFERROR(__xludf.DUMMYFUNCTION("""COMPUTED_VALUE"""),45645.0) -> 45645 | B72: =IFERROR(__xludf.DUMMYFUNCTION("""COMPUTED_VALUE"""),1223.0) -> 1223 | C72: =IFERROR(__xludf.DUMMYFUNCTION("""COMPUTED_VALUE"""),"Money Out") -> Money Out | D72: =IFERROR(__xludf.DUMMYFUNCTION("""COMPUTED_VALUE"""),"Product Restocking") -> Product Restocking | G72: -1223 | H72: Inventory | J72: Inventory
A73: =IFERROR(__xludf.DUMMYFUNCTION("""COMPUTED_VALUE"""),45648.0) -> 45648 | B73: =IFERROR(__xludf.DUMMYFUNCTION("""COMPUTED_VALUE"""),1140.0) -> 1140 | C73: =IFERROR(__xludf.DUMMYFUNCTION("""COMPUTED_VALUE"""),"Money In") -> Money In | D73: =IFERROR(__xludf.DUMMYFUNCTION("""COMPUTED_VALUE"""),"Revenue") -> Revenue | E73: =IFERROR(__xludf.DUMMYFUNCTION("""COMPUTED_VALUE"""),"deplomacyMall") -> deplomacyMall | G73: 1140 | H73: Inflow | J73: Inflow
A74: =IFERROR(__xludf.DUMMYFUNCTION("""COMPUTED_VALUE"""),45654.0) -> 45654 | B74: =IFERROR(__xludf.DUMMYFUNCTION("""COMPUTED_VALUE"""),150.0) -> 150 | C74: =IFERROR(__xludf.DUMMYFUNCTION("""COMPUTED_VALUE"""),"Money Out") -> Money Out | F74: =IFERROR(__xludf.DUMMYFUNCTION("""COMPUTED_VALUE"""),"الى دعاء المصممه") -> الى دعاء المصممه | G74: -150 | H74: Review | J74: Review
A75: =IFERROR(__xludf.DUMMYFUNCTION("""COMPUTED_VALUE"""),45654.0) -> 45654 | B75: =IFERROR(__xludf.DUMMYFUNCTION("""COMPUTED_VALUE"""),60.0) -> 60 | C75: =IFERROR(__xludf.DUMMYFUNCTION("""COMPUTED_VALUE"""),"Money Out") -> Money Out | F75: =IFERROR(__xludf.DUMMYFUNCTION("""COMPUTED_VALUE"""),"طباعة الستكر لعصير البرتقال") -> طباعة الستكر لعصير البرتقال | G75: -60 | H75: Review | J75: Review
A76: =IFERROR(__xludf.DUMMYFUNCTION("""COMPUTED_VALUE"""),45659.0) -> 45659 | B76: =IFERROR(__xludf.DUMMYFUNCTION("""COMPUTED_VALUE"""),1047.0) -> 1047 | C76: =IFERROR(__xludf.DUMMYFUNCTION("""COMPUTED_VALUE"""),"Money In") -> Money In | D76: =IFERROR(__xludf.DUMMYFUNCTION("""COMPUTED_VALUE"""),"Revenue") -> Revenue | E76: =IFERROR(__xludf.DUMMYFUNCTION("""COMPUTED_VALUE"""),"deplomacyMall") -> deplomacyMall | G76: 1047 | H76: Inflow | J76: Inflow
A77: =IFERROR(__xludf.DUMMYFUNCTION("""COMPUTED_VALUE"""),45659.0) -> 45659 | B77: =IFERROR(__xludf.DUMMYFUNCTION("""COMPUTED_VALUE"""),769.0) -> 769 | C77: =IFERROR(__xludf.DUMMYFUNCTION("""COMPUTED_VALUE"""),"Money Out") -> Money Out | D77: =IFERROR(__xludf.DUMMYFUNCTION("""COMPUTED_VALUE"""),"Product Restocking") -> Product Restocking | G77: -769 | H77: Inventory | J77: Inventory
A78: =IFERROR(__xludf.DUMMYFUNCTION("""COMPUTED_VALUE"""),45662.0) -> 45662 | B78: =IFERROR(__xludf.DUMMYFUNCTION("""COMPUTED_VALUE"""),1189.0) -> 1189 | C78: =IFERROR(__xludf.DUMMYFUNCTION("""COMPUTED_VALUE"""),"Money In") -> Money In | D78: =IFERROR(__xludf.DUMMYFUNCTION("""COMPUTED_VALUE"""),"Revenue") -> Revenue | E78: =IFERROR(__xludf.DUMMYFUNCTION("""COMPUTED_VALUE"""),"deplomacyMall") -> deplomacyMall | G78: 1189 | H78: Inflow | J78: Inflow
A79: =IFERROR(__xludf.DUMMYFUNCTION("""COMPUTED_VALUE"""),45662.0) -> 45662 | B79: =IFERROR(__xludf.DUMMYFUNCTION("""COMPUTED_VALUE"""),221.0) -> 221 | C79: =IFERROR(__xludf.DUMMYFUNCTION("""COMPUTED_VALUE"""),"Money Out") -> Money Out | D79: =IFERROR(__xludf.DUMMYFUNCTION("""COMPUTED_VALUE"""),"Product Restocking") -> Product Restocking | G79: -221 | H79: Inventory | J79: Inventory
A80: =IFERROR(__xludf.DUMMYFUNCTION("""COMPUTED_VALUE"""),45663.0) -> 45663 | B80: =IFERROR(__xludf.DUMMYFUNCTION("""COMPUTED_VALUE"""),640.0) -> 640 | C80: =IFERROR(__xludf.DUMMYFUNCTION("""COMPUTED_VALUE"""),"Money Out") -> Money Out | D80: =IFERROR(__xludf.DUMMYFUNCTION("""COMPUTED_VALUE"""),"Product Restocking") -> Product Restocking | G80: -640 | H80: Inventory | J80: Inventory
A81: =IFERROR(__xludf.DUMMYFUNCTION("""COMPUTED_VALUE"""),45665.0) -> 45665 | B81: =IFERROR(__xludf.DUMMYFUNCTION("""COMPUTED_VALUE"""),782.0) -> 782 | C81: =IFERROR(__xludf.DUMMYFUNCTION("""COMPUTED_VALUE"""),"Money Out") -> Money Out | D81: =IFERROR(__xludf.DUMMYFUNCTION("""COMPUTED_VALUE"""),"Product Restocking") -> Product Restocking | G81: -782 | H81: Inventory | J81: Inventory
A82: =IFERROR(__xludf.DUMMYFUNCTION("""COMPUTED_VALUE"""),45665.0) -> 45665 | B82: =IFERROR(__xludf.DUMMYFUNCTION("""COMPUTED_VALUE"""),1768.0) -> 1768 | C82: =IFERROR(__xludf.DUMMYFUNCTION("""COMPUTED_VALUE"""),"Money In") -> Money In | D82: =IFERROR(__xludf.DUMMYFUNCTION("""COMPUTED_VALUE"""),"Revenue") -> Revenue | E82: =IFERROR(__xludf.DUMMYFUNCTION("""COMPUTED_VALUE"""),"deplomacyMall") -> deplomacyMall | G82: 1768 | H82: Inflow | J82: Inflow
A83: =IFERROR(__xludf.DUMMYFUNCTION("""COMPUTED_VALUE"""),45666.0) -> 45666 | B83: =IFERROR(__xludf.DUMMYFUNCTION("""COMPUTED_VALUE"""),1206.0) -> 1206 | C83: =IFERROR(__xludf.DUMMYFUNCTION("""COMPUTED_VALUE"""),"Money Out") -> Money Out | D83: =IFERROR(__xludf.DUMMYFUNCTION("""COMPUTED_VALUE"""),"Product Restocking") -> Product Restocking | G83: -1206 | H83: Inventory | J83: Inventory
A84: =IFERROR(__xludf.DUMMYFUNCTION("""COMPUTED_VALUE"""),45666.0) -> 45666 | B84: =IFERROR(__xludf.DUMMYFUNCTION("""COMPUTED_VALUE"""),1947.0) -> 1947 | C84: =IFERROR(__xludf.DUMMYFUNCTION("""COMPUTED_VALUE"""),"Money In") -> Money In | D84: =IFERROR(__xludf.DUMMYFUNCTION("""COMPUTED_VALUE"""),"Revenue") -> Revenue | E84: =IFERROR(__xludf.DUMMYFUNCTION("""COMPUTED_VALUE"""),"deplomacyMall") -> deplomacyMall | G84: 1947 | H84: Inflow | J84: Inflow
A85: =IFERROR(__xludf.DUMMYFUNCTION("""COMPUTED_VALUE"""),45668.0) -> 45668 | B85: =IFERROR(__xludf.DUMMYFUNCTION("""COMPUTED_VALUE"""),1191.0) -> 1191 | C85: =IFERROR(__xludf.DUMMYFUNCTION("""COMPUTED_VALUE"""),"Money In") -> Money In | D85: =IFERROR(__xludf.DUMMYFUNCTION("""COMPUTED_VALUE"""),"Revenue") -> Revenue | E85: =IFERROR(__xludf.DUMMYFUNCTION("""COMPUTED_VALUE"""),"deplomacyMall") -> deplomacyMall | G85: 1191 | H85: Inflow | J85: Inflow
A86: =IFERROR(__xludf.DUMMYFUNCTION("""COMPUTED_VALUE"""),45668.0) -> 45668 | B86: =IFERROR(__xludf.DUMMYFUNCTION("""COMPUTED_VALUE"""),525.0) -> 525 | C86: =IFERROR(__xludf.DUMMYFUNCTION("""COMPUTED_VALUE"""),"Money Out") -> Money Out | D86: =IFERROR(__xludf.DUMMYFUNCTION("""COMPUTED_VALUE"""),"Product Restocking") -> Product Restocking | G86: -525 | H86: Inventory | J86: Inventory
A87: =IFERROR(__xludf.DUMMYFUNCTION("""COMPUTED_VALUE"""),45667.0) -> 45667 | B87: =IFERROR(__xludf.DUMMYFUNCTION("""COMPUTED_VALUE"""),31.0) -> 31 | C87: =IFERROR(__xludf.DUMMYFUNCTION("""COMPUTED_VALUE"""),"Money Out") -> Money Out | D87: =IFERROR(__xludf.DUMMYFUNCTION("""COMPUTED_VALUE"""),"Product Restocking") -> Product Restocking | G87: -31 | H87: Inventory | J87: Inventory
A88: =IFERROR(__xludf.DUMMYFUNCTION("""COMPUTED_VALUE"""),45671.0) -> 45671 | B88: =IFERROR(__xludf.DUMMYFUNCTION("""COMPUTED_VALUE"""),8217.0) -> 8217 | C88: =IFERROR(__xludf.DUMMYFUNCTION("""COMPUTED_VALUE"""),"Money Out") -> Money Out | D88: =IFERROR(__xludf.DUMMYFUNCTION("""COMPUTED_VALUE"""),"to snacky") -> to snacky | F88: =IFERROR(__xludf.DUMMYFUNCTION("""COMPUTED_VALUE"""),"لشراء ماكينات") -> لشراء ماكينات | G88: -8217 | H88: Review | J88: Review
A89: =IFERROR(__xludf.DUMMYFUNCTION("""COMPUTED_VALUE"""),45671.0) -> 45671 | B89: =IFERROR(__xludf.DUMMYFUNCTION("""COMPUTED_VALUE"""),13000.0) -> 13000 | C89: =IFERROR(__xludf.DUMMYFUNCTION("""COMPUTED_VALUE"""),"Money Out") -> Money Out | F89: =IFERROR(__xludf.DUMMYFUNCTION("""COMPUTED_VALUE"""),"دفع قيمة 21,217 دينار لشراء عدد اثنان مكينات") -> دفع قيمة 21,217 دينار لشراء عدد اثنان مكينات | G89: -13000 | H89: Review | J89: Review
A90: =IFERROR(__xludf.DUMMYFUNCTION("""COMPUTED_VALUE"""),45673.0) -> 45673 | B90: =IFERROR(__xludf.DUMMYFUNCTION("""COMPUTED_VALUE"""),448.0) -> 448 | C90: =IFERROR(__xludf.DUMMYFUNCTION("""COMPUTED_VALUE"""),"Money Out") -> Money Out | D90: =IFERROR(__xludf.DUMMYFUNCTION("""COMPUTED_VALUE"""),"Product Restocking") -> Product Restocking | G90: -448 | H90: Inventory | J90: Inventory
A91: =IFERROR(__xludf.DUMMYFUNCTION("""COMPUTED_VALUE"""),45679.0) -> 45679 | B91: =IFERROR(__xludf.DUMMYFUNCTION("""COMPUTED_VALUE"""),70.0) -> 70 | C91: =IFERROR(__xludf.DUMMYFUNCTION("""COMPUTED_VALUE"""),"Money Out") -> Money Out | D91: =IFERROR(__xludf.DUMMYFUNCTION("""COMPUTED_VALUE"""),"shipping") -> shipping | F91: =IFERROR(__xludf.DUMMYFUNCTION("""COMPUTED_VALUE"""),"توصيل change box من شاهين") -> توصيل change box من شاهين | G91: -70 | H91: Review | J91: Review
A92: =IFERROR(__xludf.DUMMYFUNCTION("""COMPUTED_VALUE"""),45681.0) -> 45681 | B92: =IFERROR(__xludf.DUMMYFUNCTION("""COMPUTED_VALUE"""),693.0) -> 693 | C92: =IFERROR(__xludf.DUMMYFUNCTION("""COMPUTED_VALUE"""),"Money In") -> Money In | D92: =IFERROR(__xludf.DUMMYFUNCTION("""COMPUTED_VALUE"""),"Revenue") -> Revenue | E92: =IFERROR(__xludf.DUMMYFUNCTION("""COMPUTED_VALUE"""),"deplomacyMall") -> deplomacyMall | G92: 693 | H92: Inflow | J92: Inflow
A93: =IFERROR(__xludf.DUMMYFUNCTION("""COMPUTED_VALUE"""),45682.0) -> 45682 | B93: =IFERROR(__xludf.DUMMYFUNCTION("""COMPUTED_VALUE"""),559.0) -> 559 | C93: =IFERROR(__xludf.DUMMYFUNCTION("""COMPUTED_VALUE"""),"Money Out") -> Money Out | D93: =IFERROR(__xludf.DUMMYFUNCTION("""COMPUTED_VALUE"""),"Product Restocking") -> Product Restocking | G93: -559 | H93: Inventory | J93: Inventory
A94: =IFERROR(__xludf.DUMMYFUNCTION("""COMPUTED_VALUE"""),45683.0) -> 45683 | B94: =IFERROR(__xludf.DUMMYFUNCTION("""COMPUTED_VALUE"""),453.0) -> 453 | C94: =IFERROR(__xludf.DUMMYFUNCTION("""COMPUTED_VALUE"""),"Money In") -> Money In | D94: =IFERROR(__xludf.DUMMYFUNCTION("""COMPUTED_VALUE"""),"Revenue") -> Revenue | E94: =IFERROR(__xludf.DUMMYFUNCTION("""COMPUTED_VALUE"""),"deplomacyMall") -> deplomacyMall | G94: 453 | H94: Inflow | J94: Inflow
A95: =IFERROR(__xludf.DUMMYFUNCTION("""COMPUTED_VALUE"""),45689.0) -> 45689 | B95: =IFERROR(__xludf.DUMMYFUNCTION("""COMPUTED_VALUE"""),491.0) -> 491 | C95: =IFERROR(__xludf.DUMMYFUNCTION("""COMPUTED_VALUE"""),"Money Out") -> Money Out | D95: =IFERROR(__xludf.DUMMYFUNCTION("""COMPUTED_VALUE"""),"Product Restocking") -> Product Restocking | G95: -491 | H95: Inventory | J95: Inventory
A96: =IFERROR(__xludf.DUMMYFUNCTION("""COMPUTED_VALUE"""),45692.0) -> 45692 | B96: =IFERROR(__xludf.DUMMYFUNCTION("""COMPUTED_VALUE"""),1240.0) -> 1240 | C96: =IFERROR(__xludf.DUMMYFUNCTION("""COMPUTED_VALUE"""),"Money In") -> Money In | D96: =IFERROR(__xludf.DUMMYFUNCTION("""COMPUTED_VALUE"""),"Revenue") -> Revenue | E96: =IFERROR(__xludf.DUMMYFUNCTION("""COMPUTED_VALUE"""),"deplomacyMall") -> deplomacyMall | G96: 1240 | H96: Inflow | J96: Inflow
A97: =IFERROR(__xludf.DUMMYFUNCTION("""COMPUTED_VALUE"""),45694.0) -> 45694 | B97: =IFERROR(__xludf.DUMMYFUNCTION("""COMPUTED_VALUE"""),357.0) -> 357 | C97: =IFERROR(__xludf.DUMMYFUNCTION("""COMPUTED_VALUE"""),"Money Out") -> Money Out | D97: =IFERROR(__xludf.DUMMYFUNCTION("""COMPUTED_VALUE"""),"Product Restocking") -> Product Restocking | G97: -357 | H97: Inventory | J97: Inventory
A98: =IFERROR(__xludf.DUMMYFUNCTION("""COMPUTED_VALUE"""),45701.0) -> 45701 | B98: =IFERROR(__xludf.DUMMYFUNCTION("""COMPUTED_VALUE"""),1809.0) -> 1809 | C98: =IFERROR(__xludf.DUMMYFUNCTION("""COMPUTED_VALUE"""),"Money In") -> Money In | D98: =IFERROR(__xludf.DUMMYFUNCTION("""COMPUTED_VALUE"""),"Revenue") -> Revenue | E98: =IFERROR(__xludf.DUMMYFUNCTION("""COMPUTED_VALUE"""),"deplomacyMall") -> deplomacyMall | G98: 1809 | H98: Inflow | J98: Inflow
A99: =IFERROR(__xludf.DUMMYFUNCTION("""COMPUTED_VALUE"""),45701.0) -> 45701 | B99: =IFERROR(__xludf.DUMMYFUNCTION("""COMPUTED_VALUE"""),548.0) -> 548 | C99: =IFERROR(__xludf.DUMMYFUNCTION("""COMPUTED_VALUE"""),"Money Out") -> Money Out | G99: -548 | H99: Review | J99: Review
A100: =IFERROR(__xludf.DUMMYFUNCTION("""COMPUTED_VALUE"""),45703.0) -> 45703 | B100: =IFERROR(__xludf.DUMMYFUNCTION("""COMPUTED_VALUE"""),1381.0) -> 1381 | C100: =IFERROR(__xludf.DUMMYFUNCTION("""COMPUTED_VALUE"""),"Money In") -> Money In | D100: =IFERROR(__xludf.DUMMYFUNCTION("""COMPUTED_VALUE"""),"Revenue") -> Revenue | E100: =IFERROR(__xludf.DUMMYFUNCTION("""COMPUTED_VALUE"""),"deplomacyMall") -> deplomacyMall | G100: 1381 | H100: Inflow | J100: Inflow
...

Sheet Cash Control
A1: Control Start Date | B1: 46113
A2: Starting Inventory Balance | B2: 0
A3: Starting Operations Balance | B3: 0
A4: Starting Fixed Costs Balance | B4: 0
A5: Starting Profit Balance | B5: 0
A8: Bucket | B8: Starting Balance | C8: Current Balance | E8: Bucket | F8: This Month | G8: Remaining
A9: Inflow | B9: =$B$2 -> 0 | C9: =SUMIFS(Txn_Control!G:G, Txn_Control!J:J, "Inflow", Txn_Control!A:A, ">="&$B$1) -> 46084 | E9: Inventory | F9: =SUMIFS(Txn_Control!G:G,Txn_Control!J:J,E9,Txn_Control!A:A,">="&EOMONTH(TODAY(),-1)+1,Txn_Control!A:A,"<="&TODAY()) -> -3516 | G9: =C9 -> 46084
A10: Inventory | B10: =$B$3 -> 0 | C10: =SUMIFS(Txn_Control!G:G, Txn_Control!J:J, "Inventory", Txn_Control!A:A, ">="&$B$1) -> -26637 | E10: Operations | F10: =SUMIFS(Txn_Control!G:G,Txn_Control!J:J,E10,Txn_Control!A:A,">="&EOMONTH(TODAY(),-1)+1,Txn_Control!A:A,"<="&TODAY()) -> 0 | G10: =C10 -> -26637
A11: Operations | B11: =$B$4 -> 0 | C11: =SUMIFS(Txn_Control!G:G, Txn_Control!J:J, "Operations", Txn_Control!A:A, ">="&$B$1) -> 0 | E11: Fixed Costs | F11: =SUMIFS(Txn_Control!G:G,Txn_Control!J:J,E11,Txn_Control!A:A,">="&EOMONTH(TODAY(),-1)+1,Txn_Control!A:A,"<="&TODAY()) -> 0 | G11: =C11 -> 0
A12: Fixed Costs | B12: =$B$5 -> 0 | C12: =SUMIFS(Txn_Control!G:G, Txn_Control!J:J, "Fixed Costs", Txn_Control!A:A, ">="&$B$1) -> -3000 | E12: Profit | F12: =SUMIFS(Txn_Control!G:G,Txn_Control!J:J,E12,Txn_Control!A:A,">="&EOMONTH(TODAY(),-1)+1,Txn_Control!A:A,"<="&TODAY()) -> 0 | G12: =C12 -> -3000
A13: Owner Draw | C13: =SUMIFS(Txn_Control!G:G, Txn_Control!J:J, "Owner Draw", Txn_Control!A:A, ">="&$B$1) -> -1430
A15: Real Profit Remaining
B16: =SUM(B17:B20) -> 72721
A17: Bucket | B17: Actual | C17: Target | D17: Status
A18: Inflow | B18: =SUMIFS(Txn_Control!G:G,Txn_Control!J:J,"Inflow",Txn_Control!A:A,">="&$B$1) -> 46084
A19: Inventory | B19: =ABS(SUMIFS(Txn_Control!G:G,Txn_Control!J:J,"Inventory",Txn_Control!A:A,">="&$B$1)) -> 26637 | C19: =B19 * VLOOKUP(A19, Targets!A:B,2, FALSE) -> 13318.5 | D19: =IF(B19 > C19, "OVER", "OK") -> OVER
A20: Operations | B20: =ABS(SUMIFS(Txn_Control!G:G, Txn_Control!J:J, A20, Txn_Control!A:A, ">="&$B$1)) -> 0 | C20: =B20 * VLOOKUP(A20, Targets!A:B,2, FALSE) -> 0 | D20: =IF(B20 > C20, "OVER", "OK") -> OK
A21: Fixed Costs | B21: =ABS(SUMIFS(Txn_Control!G:G,Txn_Control!J:J,"Fixed Costs",Txn_Control!A:A,">="&$B$1)) -> 3000 | C21: =B21 * VLOOKUP(A21, Targets!A:B,2, FALSE) -> 450 | D21: =IF(B21 > C21, "OVER", "OK") -> OVER
A22: Owner Draw | B22: =ABS(SUMIFS(Txn_Control!G:G,Txn_Control!J:J,"Owner Draw",Txn_Control!A:A,">="&$B$1)) -> 1430 | C22: =B22 * VLOOKUP(A22, Targets!A:B,2, FALSE) -> 214.5 | D22: =IF(B22 > C22, "OVER", "OK") -> OVER
A23: Cash Remaining | B23: =B18-B19-B20-B21-B22 -> 15017

Sheet Targets
A1: Bucket | B1: Target %
A2: Inventory | B2: 0.5
A3: Operations | B3: 0.2
A4: Fixed Costs | B4: 0.15
A5: Owner Draw | B5: 0.15

Sheet Places
A1: Date Added | B1: Place Name | C1: Contact Name | D1: Phone Number | E1: Location/Address | F1: Type of Place | G1: Priority | H1: Status | I1: Notes | K1: Date Added | L1: Company name | M1: Product | N1: Phone # | O1: Status | P1: Notes
A2: 45844 | B2: روضة اورانج | C2: اسماء محمد عريبي | D2: 918065207 | E2: السياحية ... سوق القبب حي الوحدة العربية | F2: روضه | G2: Low | H2: Interested | K2: 45848 | L2: مزن الدوليه | M2: مشروب هيلتي كولا | N2: 912207990
A3: 45844 | B3: مدرسة المدارات الدولية | D3: 916957260 | E3: السياحية | F3: مدرسه | G3: Medium | H3: Waiting for Machine | I3: تم موافقتهم ب نسبه 10% من المبيعات ك ايجار | K3: 45850 | L3: غداء الموسم | M3: بطاطا سبدز | N3: 918164242
A4: 45845 | B4: ترانيم (زناته) | C4: احمد | D4: 926760616 | E4: زناته | F4: مركز كورسات | G4: Medium | H4: Interested
A5: 45845 | B5: منارات | C5: احمد | E5: حي الاندلس | F5: مركز كورسات | G5: Medium | H5: Interested
A6: 45846 | B6: المواصفات | C6: ابوبكر شويشين | D6: 912123706 | E6: طريق المطار | F6: مشفى | G6: High | H6: Installed
A7: 45846 | B7: مدرسة الائتلاف الأفضل للتعليم الفرنسي | C7: فرح بن عثمان | D7: 0914712323 0925174633 | E7: خلف مخبز ابونواس | F7: مدرسه | G7: Low | H7: Interested
A8: 45847 | B8: مدرسة سي كوست | C8: عبد السلام رمضان | D8: 928634810 | E8: حي الاندلس, حي دمشق, بقرب جامعة ناصر | F8: مدرسه | G8: High | H8: Installed | I8: تم التفاهم عل 750 شهريا بنائا على 400 طالب
A9: 45850 | B9: الكلية الدولية | C9: نبيل | D9: 911561483 | E9: زناته | F9: مركز كورسات | G9: Low | H9: Follow-Up Later
A10: 45850 | B10: مركز عافية لطب الاسنان | C10: د.ساره الكوحة | D10: 927157091 | E10: 11 يونيو | F10: عياده | G10: Low | H10: Interested
A11: 45850 | B11: مستشفى رويال الطبي | C11: حسين الشاوش | D11: =+218954300044 -> 218954300044 | E11: الزاويه | F11: مستشفى | G11: High | H11: Interested
A12: 45861 | B12: المدرسه الكنديه | D12: 923320534 | E12: السياحيه | F12: مدرسه | G12: Medium | H12: Interested
A13: 45861 | B13: جامعة طرابلس
A14: 45862 | B14: شركة هواوي | C14: علي المقطوف | D14: 925928463 | E14: النوفليين | F14: شركه | G14: Medium | H14: New Lead
A15: 45885 | B15: مختبرالسراي | C15: وليد | D15: 926161208 | E15: حي الاندلس | F15: مختبر | G15: Low | H15: Interested
A16: 45885 | B16: مصحة الاستقلال | C16: محمد حسين احمد | D16: 912124696 | E16: سوق الجمعة | F16: مستشفى | G16: High | H16: Interested
A17: 45889 | B17: كلية ومعهد طرابلس العالي والمتوسط للعلوم الطبية والادارية | C17: د افراح سليم | D17: 910187505 / 0945154518 | E17: فرع عين زارة | F17: كلية | G17: Low | H17: Interested
A18: 45891 | B18: معهد ليبيا التميز العالي للعلوم الطبية | C18: عبدالعزيزالدرهوبي | D18: 926861251 | E18: فرع قصر بن غشير | F18: معهد خصوصي متوسط وعالي | G18: Low | H18: Interested
A19: 45892 | B19: مدرسه لسان العرب | C19: احمد رجب سليمان | D19: 916436072 | E19: السبعه | F19: مدرسه | G19: Low | H19: Interested
A20: 45897 | B20: مدرسة شمس الوطن | C20: بسمة رجب علي بالخير | D20: 926770720 | E20: عين زاره السدرة | F20: مدرسه | G20: High | H20: Interested | I20: 800 طالب
A21: 45898 | B21: XGYM | C21: ناجي بن نو به | D21: 919322228 | E21: طريق الشط فتحت النادي البحري | F21: صالة رياضه | G21: Low | H21: Interested
A22: 45899 | B22: أكاديمية باز لعلوم الطيران | C22: ونيس فوزي الشلماني | D22: 926737125 | E22: السراج | F22: أكاديمية طيران دولية | G22: Low | H22: Interested
A23: 45899 | B23: اكادمية سيناء | C23: امين القماطي | D23: 925058379 | E23: سوق الجمعة / جزيرة اولاد دياب معيتيقة | F23: اكادمية | G23: Low | H23: New Lead
A24: 45900 | B24: شركة بريستو ايت | C24: احمد نجومه | D24: 914449901 | F24: شركه | G24: Medium | H24: Interested | I24: شركة توصيل تحتوي على 200 موظف في مبنى الادارة الرئيسية
A25: 45900 | B25: مركز المستقبل للدورات المنهجية | C25: ايناس | D25: 911135555 | F25: مركز كورسات | G25: Low | H25: Interested
A26: 45909 | B26: ثانوية افريقيا | C26: حواء ادم | D26: 913379230 | E26: السراج | F26: مدرسه | G26: High | H26: Interested | I26: مدرسه بها 600 طالب و 150 معلمه

Sheet Summary
A3: Category | B3: Total COGS | C3: Total Revenue | D3: Total Profit
A4: Drinks | B4: =sum(B12+B19) -> 11471.33 | C4: =sum(C12+C19) -> 19077 | D4: =sum(D12+D19) -> 7873.99
A5: Snacks | B5: =sum(B13+B20) -> 7066.064 | C5: =sum(C13+C20) -> 10667 | D5: =sum(D13+D20) -> 3600.936
A6: Chips | B6: =sum(B14+B21) -> 8419.47 | C6: =sum(C14+C21) -> 13351 | D6: =sum(D14+D21) -> 6639.04
A7: Total | B7: =SUM(B4:B6) -> 26956.864 | C7: =SUM(C4:C6) -> 43095 | D7: =SUM(D4:D6) -> 18113.966
A11: Column 1 | B11: Total COGS | C11: Total Revenue | D11: Total Profit | F11: Category | G11: Total COGS | H11: Total Revenue | I11: Total Profit | K11: Category | L11: Total COGS | M11: Total Revenue | N11: Total Profit | P11: Category | Q11: Total COGS | R11: Total Revenue | S11: Total Profit
A12: Drinks | B12: =(Drinks!N40) -> 7541.61 | C12: =(Drinks!O40) -> 12450 | D12: =(Drinks!P40) -> 4908.39 | F12: Drinks | G12: =(Drinks!N13) -> 2665.95 | H12: =(Drinks!O13) -> 4554 | I12: =(Drinks!P13) -> 1888.05 | K12: Drinks | L12: =(Drinks!N28) -> 3077.34 | M12: =(Drinks!O28) -> 5172 | N12: =(Drinks!P28) -> 2094.66 | P12: Drinks | Q12: =(Drinks!N38) -> 1798.32 | R12: =(Drinks!O38) -> 2724 | S12: =(Drinks!P38) -> 925.68
A13: Snacks | B13: =(Snacks!N41) -> 2809.964 | C13: =(Snacks!O41) -> 3946 | D13: =(Snacks!P41) -> 1136.036 | F13: Snacks | G13: =(Snacks!N15) -> 1206.68 | H13: =(Snacks!O15) -> 1700 | I13: =(Snacks!P15) -> 493.32 | K13: Snacks | L13: =(Snacks!N30) -> 853.284 | M13: =(Snacks!O30) -> 1214 | N13: =(Snacks!P30) -> 360.716 | P13: Snacks | Q13: =(Snacks!N39) -> 750 | R13: =(Snacks!O39) -> 1032 | S13: =(Snacks!P39) -> 282
A14: Chips | B14: =(Chips!N31) -> 1811.66 | C14: =(Chips!O31) -> 2663 | D14: =(Chips!P32) -> 2558.85 | F14: Chips | G14: =(Chips!N6) -> 1519.8 | H14: =(Chips!O6) -> 2118 | I14: =(Chips!P6) -> 598.2 | K14: Chips | L14: =(Chips!N17) -> 1513.69 | M14: =(Chips!O17) -> 2623 | N14: =(Chips!P17) -> 1109.31 | P14: Chips | Q14: =(Chips!N31) -> 1811.66 | R14: =(Chips!O31) -> 2663 | S14: =(Chips!P31) -> 851.34
A15: Total | B15: =SUM(B12:B14) -> 12163.234 | C15: =SUM(C12:C14) -> 19059 | D15: =SUM(D12:D14) -> 8603.276 | F15: Total | G15: =SUM(G12:G14) -> 5392.43 | H15: =SUM(H12:H14) -> 8372 | I15: =SUM(I12:I14) -> 2979.57 | K15: Total | L15: =SUM(L12:L14) -> 5444.314 | M15: =SUM(M12:M14) -> 9009 | N15: =SUM(N12:N14) -> 3564.686 | P15: Total | Q15: =SUM(Q12:Q14) -> 4359.98 | R15: =SUM(R12:R14) -> 6419 | S15: =SUM(S12:S14) -> 2059.02
A18: Column 1 | B18: Column 2 | C18: Column 3 | D18: Column 4 | F18: Category | G18: Total COGS | H18: Total Revenue | I18: Total Profit | K18: Category | L18: Total COGS | M18: Total Revenue | N18: Total Profit | P18: Category | Q18: Total COGS | R18: Total Revenue | S18: Total Profit | U18: Commodity type | V18: Pay by cash | W18: Quantity | X18: Profit | Y18: Gross margin | Z18: Proportion | AA18: Total amount | AB18: Total quantity | AD18: Commodity type | AE18: Pay by cash | AF18: Quantity | AG18: Profit | AH18: Gross margin | AI18: Proportion | AJ18: Total amount | AK18: Total quantity
A19: Drinks | B19: =(Drinks!N108) -> 3929.72 | C19: =(Drinks!O108) -> 6627 | D19: =(Drinks!P108) -> 2965.6 | F19: Drinks | G19: =(Drinks!N57) -> 1638.68 | H19: =(Drinks!O57) -> 2799 | I19: =(Drinks!P57) -> 1160.32 | K19: Drinks | L19: =(Drinks!N74) -> 1027.2 | M19: =(Drinks!O74) -> 1656 | N19: =(Drinks!P74) -> 897.12 | P19: Drinks | Q19: =(Drinks!N90) -> 1263.84 | R19: =(Drinks!O90) -> 2172 | S19: =(Drinks!P90) -> 908.16 | U19: Water | V19: 712 | W19: 712 | X19: 497.88 | Y19: 0.6993 | Z19: 0.0501 | AA19: 712 | AB19: 712 | AD19: Water | AE19: 416 | AF19: 412 | AG19: 296.52 | AH19: 0.7128 | AI19: 0.059 | AJ19: 416 | AK19: 412
A20: Snacks | B20: =(Snacks!N104) -> 4256.1 | C20: =(Snacks!O104) -> 6721 | D20: =(Snacks!P104) -> 2464.9 | F20: Snacks | G20: =(Snacks!N53) -> 742.68 | H20: =(Snacks!O53) -> 1133 | I20: =(Snacks!P53) -> 390.32 | K20: Snacks | L20: =(Snacks!N67) -> 1368.24 | M20: =(Snacks!O67) -> 2262 | N20: =(Snacks!P67) -> 893.76 | P20: Snacks | Q20: =(Snacks!N84) -> 2145.18 | R20: =(Snacks!O84) -> 3326 | S20: =(Snacks!P84) -> 1180.82 | U20: Drink | V20: 2972 | W20: 1242 | X20: 944.62 | Y20: 0.3178 | Z20: 0.2092 | AA20: 2972 | AB20: 1242 | AD20: Chocolates | AE20: 1646 | AF20: 687 | AG20: 638.78 | AH20: 0.3881 | AI20: 0.2336 | AJ20: 1646 | AK20: 687
A21: Chips | B21: =(Chips!N80) -> 6607.81 | C21: =(Chips!O80) -> 10688 | D21: =(Chips!P80) -> 4080.19 | F21: Chips | G21: =(Chips!N47) -> 1986.63 | H21: =(Chips!O47) -> 3429 | I21: =(Chips!P47) -> 1442.37 | K21: Chips | L21: =(Chips!N58) -> 2251.36 | M21: =(Chips!O58) -> 3446 | N21: =(Chips!P58) -> 1194.64 | P21: Chips | Q21: =(Chips!N69) -> 2369.82 | R21: =(Chips!O69) -> 3813 | S21: =(Chips!P69) -> 1443.18 | U21: Chocolates | V21: 3418 | W21: 1328 | X21: 1273.17 | Y21: 0.3725 | Z21: 0.2406 | AA21: 3418 | AB21: 1328 | AD21: Drink | AE21: 1969 | AF21: 726 | AG21: 619.41 | AH21: 0.3146 | AI21: 0.2794 | AJ21: 1969 | AK21: 726
A22: Total | B22: =SUM(B19:B21) -> 14793.63 | C22: =SUM(C19:C21) -> 24036 | D22: =SUM(D19:D21) -> 9510.69 | F22: Total | G22: =SUM(G19:G21) -> 4367.99 | H22: =SUM(H19:H21) -> 7361 | I22: =SUM(I19:I21) -> 2993.01 | K22: Total | L22: =SUM(L19:L21) -> 4646.8 | M22: =SUM(M19:M21) -> 7364 | N22: =SUM(N19:N21) -> 2985.52 | P22: Total | Q22: =SUM(Q19:Q21) -> 5778.84 | R22: =SUM(R19:R21) -> 9311 | S22: =SUM(S19:S21) -> 3532.16 | U22: Chips | V22: 7102 | W22: 1551 | X22: 3122.8 | Y22: 0.4397 | Z22: 0.5 | AA22: 7102 | AB22: 1551 | AD22: Chips | AE22: 3016 | AF22: 589 | AG22: 1337.06 | AH22: 0.4433 | AI22: 0.428 | AJ22: 3016 | AK22: 589
U23: Total | V23: 15847 | W23: 4833 | X23: 6513.117 | Y23: 0.411 | Z23: 1 | AA23: 14204 | AB23: 4833 | AD23: Total | AE23: 7047 | AF23: 2414 | AG23: 2891.77 | AH23: 0.4104 | AI23: 1 | AJ23: 7047 | AK23: 2414

Sheet REstock prod
A4: Date | B4: Description
A5: 45705 | B5: تم ادخال فاتوره
A6: 45708
A7: 45714
A8: 45716
A9: 45724
A10: 45728
A11: 45729
A12: 45732
A13: 45733
A14: 45735
A15: 45736
A16: 45738
A17: 45741
... A30: 45773

Sheet Drinks
A1: Product Name | B1: # pack | C1: items inside the pack | D1: Initial Stock | E1: Cost per Unit | F1: Selling Price per Unit | G1: margin profit | H1: # packs sold | I1: Quantity Sold | J1: # pack Restoked | K1: Restocked Quantity | L1: # Curremt packs | M1: Current Stock | N1: COGS | O1: Revenue | P1: Gross Profit | Q1: Month
A2: Water | B2: 133 | C2: 12 | D2: =(B2*C2) -> 1596 | E2: 0.3 | F2: 1 | G2: =((F2-E2)/F2)*100 & "%" -> 70% | H2: 133 | I2: =(C2*H2) -> 1596 | J2: 0 | K2: =(C2*J2) -> 0 | L2: =(B2+J2-H2) -> 0 | M2: =(D2+K2)-I2 -> 0 | N2: =(D2 + K2 - M2) * E2 -> 478.8 | O2: =(I2*F2) -> 1596 | P2: =(O2-N2) -> 1117.2 | Q2: 8
A3: Green | B3: 5 | C3: 24 | D3: 120 | E3: 2.58 | F3: 3 | G3: =((F3-E3)/F3)*100 & "%" -> 14.% | H3: 5 | I3: =(C3*H3) -> 120 | K3: =(C3*J3) -> 0 | M3: =(D3+K3)-I3 -> 0 | N3: =(D3 + K3 - M3) * E3 -> 309.6 | O3: =(I3*F3) -> 360 | P3: =(O3-N3) -> 50.4 | Q3: 8
A4: X!R | B4: 9 | C4: 24 | D4: 216 | E4: 2.91 | F4: 4 | G4: =((F4-E4)/F4)*100 & "%" -> 27.25% | H4: 9 | I4: =(C4*H4) -> 216 | J4: 0 | K4: =(C4*J4) -> 0 | L4: =(B4+J4-H4) -> 0 | M4: =(D4+K4)-I4 -> 0 | N4: =(D4 + K4 - M4) * E4 -> 628.56 | O4: =(I4*F4) -> 864 | P4: =(O4-N4) -> 235.44 | Q4: 8
A5: King | B5: 4 | C5: 24 | D5: =B5*C5 -> 96 | E5: 1.75 | F5: 2 | G5: =((F5-E5)/F5)*100 & "%" -> 12.5% | H5: 4 | I5: =(C5*H5) -> 96 | J5: 0 | K5: =(C5*J5) -> 0 | M5: =(D5+K5)-I5 -> 0 | N5: =(D5 + K5 - M5) * E5 -> 168 | O5: =(I5*F5) -> 192 | P5: =(O5-N5) -> 24 | Q5: 8
A6: Power | B6: 3 | C6: 24 | D6: =B6*C6 -> 72 | E6: 2.5 | F6: 3 | G6: =((F6-E6)/F6)*100 & "%" -> 16.6666666666667% | H6: 3 | I6: =(C6*H6) -> 72 | J6: 0 | K6: =(C6*J6) -> 0 | M6: =(D6+K6)-I6 -> 0 | N6: =(D6 + K6 - M6) * E6 -> 180 | O6: =(I6*F6) -> 216 | P6: =(O6-N6) -> 36 | Q6: 8
A7: Mogu Mogu | B7: 1 | C7: 24 | D7: =(B7*C7) -> 24 | E7: 8.54 | F7: 10 | G7: =((F7-E7)/F7)*100 & "%" -> 14.6% | H7: 1 | I7: =(C7*H7) -> 24 | K7: =(C7*J7) -> 0 | L7: 0 | M7: =(D7+K7)-I7 -> 0 | N7: =(D7 + K7 - M7) * E7 -> 204.96 | O7: =(I7*F7) -> 240 | P7: =(O7-N7) -> 35.04 | Q7: 8
A8: سن توب سعودي | B8: 30 | C8: 24 | D8: =(B8*C8) -> 720 | E8: 0.6 | F8: 1 | G8: =((F8-E8)/F8)*100 & "%" -> 40% | H8: 30 | I8: =(C8*H8) -> 720 | J8: 0 | K8: =(C8*J8) -> 0 | M8: =(D8+K8)-I8 -> 0 | N8: =(D8 + K8 - M8) * E8 -> 432 | O8: =(I8*F8) -> 720 | P8: =(O8-N8) -> 288 | Q8: 8
A9: الندى زنجبيل | D9: 18 | E9: 2.055 | F9: 3 | G9: =((F9-E9)/F9)*100 & "%" -> 31.5% | I9: 18 | K9: =(C9*J9) -> 0 | M9: =(D9+K9)-I9 -> 0 | N9: =(D9 + K9 - M9) * E9 -> 36.99 | O9: =(I9*F9) -> 54 | P9: =(O9-N9) -> 17.01 | Q9: 8
A10: بتري الندى | D10: 18 | E10: 1.56 | F10: 2 | G10: =((F10-E10)/F10)*100 & "%" -> 22.% | I10: 18 | K10: =(C10*J10) -> 0 | M10: =(D10+K10)-I10 -> 0 | N10: =(D10 + K10 - M10) * E10 -> 28.08 | O10: =(I10*F10) -> 36 | P10: =(O10-N10) -> 7.92 | Q10: 8
A11: الندى عنب | D11: 36 | E11: 2.61 | F11: 3 | G11: =((F11-E11)/F11)*100 & "%" -> 13.% | I11: 36 | K11: =(C11*J11) -> 0 | M11: =(D11+K11)-I11 -> 0 | N11: =(D11 + K11 - M11) * E11 -> 93.96 | O11: =(I11*F11) -> 108 | P11: =(O11-N11) -> 14.04 | Q11: 8
A12: العين طلقه | D12: 84 | E12: 1.25 | F12: 2 | G12: =((F12-E12)/F12)*100 & "%" -> 37.5% | I12: 84 | K12: =(C12*J12) -> 0 | M12: =(D12+K12)-I12 -> 0 | N12: =(D12 + K12 - M12) * E12 -> 105 | O12: =(I12*F12) -> 168 | P12: =(O12-N12) -> 63 | Q12: 8
A13: Total (8) | G13: =((F13-E13)/F13)*100 & "%" -> #DIV/0! | K13: =(C13*J13) -> 0 | M13: =(D13+K13)-I13 -> 0 | N13: =SUM(N2:N12) -> 2665.95 | O13: =SUM(O2:O12) -> 4554 | P13: =SUM(P2:P12) -> 1888.05 | Q13: 8
A14: Water | B14: 51 | C14: 12 | D14: =B14*C14 -> 612 | E14: 0.33 | F14: 1 | G14: =((F14-E14)/F14)*100 & "%" -> 67% | H14: 51 | I14: =(C14*H14) -> 612 | J14: 0 | K14: =(C14*J14) -> 0 | L14: =(B14+$J$14)-H14 -> 0 | M14: =(D14+K14)-I14 -> 0 | N14: =(D14 + K14 - M14) * E14 -> 201.96 | O14: =I14*F14 -> 612 | P14: =O14-N14 -> 410.04 | Q14: 9
A15: Green | B15: 1 | C15: 24 | D15: =B15*C15 -> 24 | E15: 2.58 | F15: 3 | G15: =((F15-E15)/F15)*100 & "%" -> 14.% | H15: 1 | I15: =(C15*H15) -> 24 | J15: 0 | K15: =(C15*J15) -> 0 | L15: =(B15+$J$14)-H15 -> 0 | M15: =(D15+K15)-I15 -> 0 | N15: =(D15 + K15 - M15) * E15 -> 61.92 | O15: =I15*F15 -> 72 | P15: =O15-N15 -> 10.08
A16: X!R | B16: 3 | C16: 24 | D16: =B16*C16 -> 72 | E16: 2.83 | F16: 4 | G16: =((F16-E16)/F16)*100 & "%" -> 29.25% | H16: 3 | I16: =(C16*H16) -> 72 | J16: 0 | K16: =(C16*J16) -> 0 | L16: =(B16+$J$14)-H16 -> 0 | M16: =(D16+K16)-I16 -> 0 | N16: =(D16 + K16 - M16) * E16 -> 203.76 | O16: =I16*F16 -> 288 | P16: =O16-N16 -> 84.24
A17: King | B17: 5 | C17: 24 | D17: =B17*C17 -> 120 | E17: 1.75 | F17: 2 | G17: =((F17-E17)/F17)*100 & "%" -> 12.5% | H17: 5 | I17: =(C17*H17) -> 120 | J17: 0 | K17: =(C17*J17) -> 0 | L17: =(B17+$J$14)-H17 -> 0 | M17: =(D17+K17)-I17 -> 0 | N17: =(D17 + K17 - M17) * E17 -> 210 | O17: =I17*F17 -> 240 | P17: =O17-N17 -> 30
A18: Power | B18: 9 | C18: 24 | D18: =B18*C18 -> 216 | E18: 2.5 | F18: 3 | G18: =((F18-E18)/F18)*100 & "%" -> 16.6666666666667% | H18: 9 | I18: =(C18*H18) -> 216 | J18: 0 | K18: =(C18*J18) -> 0 | L18: =(B18+$J$14)-H18 -> 0 | M18: =(D18+K18)-I18 -> 0 | N18: =(D18 + K18 - M18) * E18 -> 540 | O18: =I18*F18 -> 648 | P18: =O18-N18 -> 108
A19: سن توب سعودي | B19: 34 | C19: 24 | D19: =B19*C19 -> 816 | E19: 0.6 | F19: 1 | G19: =((F19-E19)/F19)*100 & "%" -> 40% | H19: 34 | I19: =(C19*H19) -> 816 | J19: 0 | K19: =(C19*J19) -> 0 | L19: =(B19+$J$14)-H19 -> 0 | M19: =(D19+K19)-I19 -> 0 | N19: =(D19 + K19 - M19) * E19 -> 489.6 | O19: =I19*F19 -> 816 | P19: =O19-N19 -> 326.4
A20: Boss | B20: 3 | C20: 24 | D20: =B20*C20 -> 72 | E20: 2.41 | F20: 3 | G20: =((F20-E20)/F20)*100 & "%" -> 19.6666666666667% | H20: 2 | I20: =(C20*H20) -> 48 | J20: 0 | K20: =(C20*J20) -> 0 | L20: =(B20+$J$14)-H20 -> 1 | M20: =(D20+K20)-I20 -> 24 | N20: =(D20 + K20 - M20) * E20 -> 115.68 | O20: =I20*F20 -> 144 | P20: =O20-N20 -> 28.32
A21: Nada Energy Drink | B21: 1 | C21: 18 | D21: =B21*C21 -> 18 | E21: 3.05 | F21: 4 | G21: =((F21-E21)/F21)*100 & "%" -> 23.75% | H21: 1 | I21: =(C21*H21) -> 18 | J21: 0 | K21: =(C21*J21) -> 0 | L21: =(B21+$J$14)-H21 -> 0 | M21: =(D21+K21)-I21 -> 0 | N21: =(D21 + K21 - M21) * E21 -> 54.9 | O21: =I21*F21 -> 72 | P21: =O21-N21 -> 17.1
A22: Water | B22: 89 | C22: 12 | D22: =B22*C22 -> 1068 | E22: 0.3 | F22: 1 | G22: =((F22-E22)/F22)*100 & "%" -> 70% | H22: 89 | I22: =(C22*H22) -> 1068 | J22: 0 | K22: =(C22*J22) -> 0 | L22: =(B22+$J$14)-H22 -> 0 | M22: =(D22+K22)-I22 -> 0 | N22: =(D22 + K22 - M22) * E22 -> 320.4 | O22: =I22*F22 -> 1068 | P22: =O22-N22 -> 747.6
A23: X!R | B23: 9 | C23: 24 | D23: =B23*C23 -> 216 | E23: 2.87 | F23: 4 | G23: =((F23-E23)/F23)*100 & "%" -> 28.25% | H23: 9 | I23: =(C23*H23) -> 216 | J23: 0 | K23: =(C23*J23) -> 0 | L23: =(B23+$J$14)-H23 -> 0 | M23: =(D23+K23)-I23 -> 0 | N23: =(D23 + K23 - M23) * E23 -> 619.92 | O23: =I23*F23 -> 864 | P23: =O23-N23 -> 244.08
A24: العين حكه | B24: 1 | C24: 24 | D24: =B24*C24 -> 24 | E24: 2.87 | F24: 3 | G24: =((F24-E24)/F24)*100 & "%" -> 4.33333333333333% | H24: 1 | I24: =(C24*H24) -> 24 | J24: 0 | K24: =(C24*J24) -> 0 | L24: =(B24+$J$14)-H24 -> 0 | M24: =(D24+K24)-I24 -> 0 | N24: =(D24 + K24 - M24) * E24 -> 68.88 | O24: =I24*F24 -> 72 | P24: =O24-N24 -> 3.12
A25: الندى بتري | B25: 2 | C25: 18 | D25: =B25*C25 -> 36 | E25: 1.16 | F25: 2 | G25: =((F25-E25)/F25)*100 & "%" -> 42.% | H25: 2 | I25: =(C25*H25) -> 36 | J25: 0 | K25: =(C25*J25) -> 0 | L25: =(B25+$J$14)-H25 -> 0 | M25: =(D25+K25)-I25 -> 0 | N25: =(D25 + K25 - M25) * E25 -> 41.76 | O25: =I25*F25 -> 72 | P25: =O25-N25 -> 30.24
A26: الندى زنجبيل | B26: 2 | C26: 18 | D26: =B26*C26 -> 36 | E26: 2.16 | F26: 3 | G26: =((F26-E26)/F26)*100 & "%" -> 28.% | H26: 2 | I26: =(C26*H26) -> 36 | J26: 0 | K26: =(C26*J26) -> 0 | L26: =(B26+$J$14)-H26 -> 0 | M26: =(D26+K26)-I26 -> 0 | N26: =(D26 + K26 - M26) * E26 -> 77.76 | O26: =I26*F26 -> 108 | P26: =O26-N26 -> 30.24
A27: X!R Mojito | B27: 1 | C27: 24 | D27: =B27*C27 -> 24 | E27: 2.95 | F27: 4 | G27: =((F27-E27)/F27)*100 & "%" -> 26.25% | H27: 1 | I27: =(C27*H27) -> 24 | K27: =(C27*J27) -> 0 | L27: =(B27+$J$14)-H27 -> 0 | M27: =(D27+K27)-I27 -> 0 | N27: =(D27 + K27 - M27) * E27 -> 70.8 | O27: =I27*F27 -> 96 | P27: =O27-N27 -> 25.2
A28: Total (9) | G28: =((F28-E28)/F28)*100 & "%" -> #DIV/0! | K28: =(C28*J28) -> 0 | L28: =(B28+$J$14)-H28 -> 0 | M28: =(D28+K28)-I28 -> 0 | N28: =SUM(N14:N27) -> 3077.34 | O28: =SUM(O14:O27) -> 5172 | P28: =SUM(P14:P27) -> 2094.66 | Q28: 9
A29: sunTop Saudi | B29: 15 | C29: 24 | D29: =B29*C29 -> 360 | E29: 0.6 | F29: 1 | G29: =((F29-E29)/F29)*100 & "%" -> 40% | H29: 15 | I29: =C29*H29 -> 360 | J29: 0 | K29: =(C29*J29) -> 0 | L29: =(B29+$J$14)-H29 -> 0 | M29: =(D29+K29)-I29 -> 0 | N29: =(D29 + K29 - M29) * E29 -> 216 | O29: =I29*F29 -> 360 | P29: =O29-N29 -> 144
A30: X!R | B30: 5 | C30: 24 | D30: =B30*C30 -> 120 | E30: 2.91 | F30: 4 | G30: =((F30-E30)/F30)*100 & "%" -> 27.25% | H30: 5 | I30: =C30*H30 -> 120 | J30: 0 | K30: =(C30*J30) -> 0 | L30: =(B30+$J$14)-H30 -> 0 | M30: =(D30+K30)-I30 -> 0 | N30: =(D30 + K30 - M30) * E30 -> 349.2 | O30: =I30*F30 -> 480 | P30: =O30-N30 -> 130.8
A31: X!R 500ml | B31: 2 | C31: 24 | D31: =B31*C31 -> 48 | E31: 4.45 | F31: 6 | G31: =((F31-E31)/F31)*100 & "%" -> 25.8333333333333% | H31: 2 | I31: =C31*H31 -> 48 | J31: 0 | K31: =(C31*J31) -> 0 | L31: =(B31+$J$14)-H31 -> 0 | M31: =(D31+K31)-I31 -> 0 | N31: =(D31 + K31 - M31) * E31 -> 213.6 | O31: =I31*F31 -> 288 | P31: =O31-N31 -> 74.4
A32: Power | B32: 3 | C32: 24 | D32: =B32*C32 -> 72 | E32: 2.5 | F32: 3 | G32: =((F32-E32)/F32)*100 & "%" -> 16.6666666666667% | H32: 3 | I32: =C32*H32 -> 72 | J32: 0 | K32: =(C32*J32) -> 0 | L32: =(B32+$J$14)-H32 -> 0 | M32: =(D32+K32)-I32 -> 0 | N32: =(D32 + K32 - M32) * E32 -> 180 | O32: =I32*F32 -> 216 | P32: =O32-N32 -> 36
A33: Power 500ml | B33: 3 | C33: 24 | D33: =B33*C33 -> 72 | E33: 3.66 | F33: 5 | G33: =((F33-E33)/F33)*100 & "%" -> 26.8% | H33: 3 | I33: =C33*H33 -> 72 | J33: 0 | K33: =(C33*J33) -> 0 | L33: =(B33+$J$14)-H33 -> 0 | M33: =(D33+K33)-I33 -> 0 | N33: =(D33 + K33 - M33) * E33 -> 263.52 | O33: =I33*F33 -> 360 | P33: =O33-N33 -> 96.48
A34: Green | B34: 5 | C34: 24 | D34: =B34*C34 -> 120 | E34: 2.7 | F34: 4 | G34: =((F34-E34)/F34)*100 & "%" -> 32.5% | H34: 5 | I34: =C34*H34 -> 120 | J34: 0 | K34: =(C34*J34) -> 0 | L34: =(B34+$J$14)-H34 -> 0 | M34: =(D34+K34)-I34 -> 0 | N34: =(D34 + K34 - M34) * E34 -> 324 | O34: =I34*F34 -> 480 | P34: =O34-N34 -> 156
A35: sunTop Masa | B35: 10 | C35: 24 | D35: =B35*C35 -> 240 | E35: 0.45 | F35: 1 | G35: =((F35-E35)/F35)*100 & "%" -> 55.% | H35: 10 | I35: =C35*H35 -> 240 | J35: 0 | K35: =(C35*J35) -> 0 | L35: =(B35+$J$14)-H35 -> 0 | M35: =(D35+K35)-I35 -> 0 | N35: =(D35 + K35 - M35) * E35 -> 108 | O35: =I35*F35 -> 240 | P35: =O35-N35 -> 132
A36: water | B36: 15 | C36: 12 | D36: =B36*C36 -> 180 | E36: 0.3 | F36: 1 | G36: =((F36-E36)/F36)*100 & "%" -> 70% | H36: 15 | I36: =C36*H36 -> 180 | J36: 0 | K36: =(C36*J36) -> 0 | L36: =(B36+$J$14)-H36 -> 0 | M36: =(D36+K36)-I36 -> 0 | N36: =(D36 + K36 - M36) * E36 -> 54 | O36: =I36*F36 -> 180 | P36: =O36-N36 -> 126
A37: freez | B37: 1 | C37: 24 | D37: =B37*C37 -> 24 | E37: 3.75 | F37: 5 | G37: =((F37-E37)/F37)*100 & "%" -> 25% | H37: 1 | I37: =C37*H37 -> 24 | J37: 0 | K37: =(C37*J37) -> 0 | L37: =(B37+$J$14)-H37 -> 0 | M37: =(D37+K37)-I37 -> 0 | N37: =(D37 + K37 - M37) * E37 -> 90 | O37: =I37*F37 -> 120 | P37: =O37-N37 -> 30
A38: Total (12) | D38: =B38*C38 -> 0 | G38: =((F38-E38)/F38)*100 & "%" -> #DIV/0! | I38: =C38*H38 -> 0 | J38: 0 | K38: =(C38*J38) -> 0 | L38: =(B38+$J$14)-H38 -> 0 | M38: =(D38+K38)-I38 -> 0 | N38: =SUM(N29:N37) -> 1798.32 | O38: =SUM(O29:O37) -> 2724 | P38: =SUM(P29:P37) -> 925.68 | Q38: 12
D39: =B39*C39 -> 0 | I39: =C39*H39 -> 0 | K39: =(C39*J39) -> 0 | L39: =(B39+$J$14)-H39 -> 0
A40: Total 2024 | D40: =B40*C40 -> 0 | I40: =C40*H40 -> 0 | K40: =(C40*J40) -> 0 | L40: =(B40+$J$14)-H40 -> 0 | M40: =(D40+K40)-I40 -> 0 | N40: =SUM(N13+N28+N38) -> 7541.61 | O40: =SUM(O13+O28+O38) -> 12450 | P40: =SUM(P13+P28+P38) -> 4908.39
A41: water | B41: 35 | C41: 12 | D41: =B41*C41 -> 420 | E41: 0.29 | F41: 1 | G41: =((F41-E41)/F41)*100 & "%" -> 71% | H41: 35 | I41: =C41*H41 -> 420 | J41: 0 | K41: =(C41*J41) -> 0 | L41: =(B41+$J$14)-H41 -> 0 | M41: =(D41+K41)-I41 -> 0 | N41: =(D41 + K41 - M41) * E41 -> 121.8 | O41: =I41*F41 -> 420 | P41: =O41-N41 -> 298.2
A42: Green | B42: 1 | C42: 24 | D42: =B42*C42 -> 24 | E42: 2.66 | F42: 4 | G42: =((F42-E42)/F42)*100 & "%" -> 33.5% | I42: =C42*H42 -> 0 | J42: 0 | K42: =(C42*J42) -> 0 | L42: =(B42+$J$14)-H42 -> 1 | M42: =(D42+K42)-I42 -> 24 | N42: =(D42 + K42 - M42) * E42 -> 0 | O42: =I42*F42 -> 0 | P42: =O42-N42 -> 0
A43: Green | B43: 3 | C43: 24 | D43: =B43*C43 -> 72 | E43: 2.7 | F43: 4 | G43: =((F43-E43)/F43)*100 & "%" -> 32.5% | H43: 2 | I43: =C43*H43 -> 48 | J43: 0 | K43: =(C43*J43) -> 0 | L43: =(B43+$J$14)-H43 -> 1 | M43: =(D43+K43)-I43 -> 24 | N43: =(D43 + K43 - M43) * E43 -> 129.6 | O43: =I43*F43 -> 192 | P43: =O43-N43 -> 62.4
A44: freez lower price | B44: 1 | C44: 24 | D44: =B44*C44 -> 24 | E44: 3.41 | F44: 5 | G44: =((F44-E44)/F44)*100 & "%" -> 31.8% | H44: 1 | I44: =C44*H44 -> 24 | K44: =(C44*J44) -> 0 | L44: =(B44+$J$14)-H44 -> 0 | M44: =(D44+K44)-I44 -> 0 | N44: =(D44 + K44 - M44) * E44 -> 81.84 | O44: =I44*F44 -> 120 | P44: =O44-N44 -> 38.16
A45: freez | B45: 2 | C45: 24 | D45: =B45*C45 -> 48 | E45: 3.75 | F45: 5 | G45: =((F45-E45)/F45)*100 & "%" -> 25% | H45: 1 | I45: =C45*H45 -> 24 | J45: 0 | K45: =(C45*J45) -> 0 | L45: =(B45+$J$14)-H45 -> 1 | M45: =(D45+K45)-I45 -> 24 | N45: =(D45 + K45 - M45) * E45 -> 90 | O45: =I45*F45 -> 120 | P45: =O45-N45 -> 30
A46: suntop | B46: 23 | C46: 24 | D46: =B46*C46 -> 552 | E46: 0.6 | F46: 1 | G46: =((F46-E46)/F46)*100 & "%" -> 40% | H46: 23 | I46: =C46*H46 -> 552 | J46: 0 | K46: =(C46*J46) -> 0 | L46: =(B46+$J$14)-H46 -> 0 | M46: =(D46+K46)-I46 -> 0 | N46: =(D46 + K46 - M46) * E46 -> 331.2 | O46: =I46*F46 -> 552 | P46: =O46-N46 -> 220.8
A47: masa suntop | B47: 13 | C47: 24 | D47: =B47*C47 -> 312 | E47: 0.45 | F47: 1 | G47: =((F47-E47)/F47)*100 & "%" -> 55.% | H47: 13 | I47: =C47*H47 -> 312 | J47: 0 | K47: =(C47*J47) -> 0 | L47: =(B47+$J$14)-H47 -> 0 | M47: =(D47+K47)-I47 -> 0 | N47: =(D47 + K47 - M47) * E47 -> 140.4 | O47: =I47*F47 -> 312 | P47: =O47-N47 -> 171.6
A48: dark blue | B48: 1 | C48: 24 | D48: =B48*C48 -> 24 | E48: 2.17 | F48: 3 | G48: =((F48-E48)/F48)*100 & "%" -> 27.6666666666667% | H48: 1 | I48: =C48*H48 -> 24 | J48: 0 | K48: =(C48*J48) -> 0 | L48: =(B48+$J$14)-H48 -> 0 | M48: =(D48+K48)-I48 -> 0 | N48: =(D48 + K48 - M48) * E48 -> 52.08 | O48: =I48*F48 -> 72 | P48: =O48-N48 -> 19.92
A49: al ain can | B49: 2 | C49: 24 | D49: =B49*C49 -> 48 | E49: 1.91 | F49: 3 | G49: =((F49-E49)/F49)*100 & "%" -> 36.3333333333333% | H49: 1 | I49: =C49*H49 -> 24 | J49: 0 | K49: =(C49*J49) -> 0 | L49: =(B49+$J$14)-H49 -> 1 | M49: =(D49+K49)-I49 -> 24 | N49: =(D49 + K49 - M49) * E49 -> 45.84 | O49: =I49*F49 -> 72 | P49: =O49-N49 -> 26.16
A50: x!r | B50: 2 | C50: 24 | D50: =B50*C50 -> 48 | E50: 2.83 | F50: 4 | G50: =((F50-E50)/F50)*100 & "%" -> 29.25% | H50: 2 | I50: =C50*H50 -> 48 | J50: 0 | K50: =(C50*J50) -> 0 | L50: =(B50+$J$14)-H50 -> 0 | M50: =(D50+K50)-I50 -> 0 | N50: =(D50 + K50 - M50) * E50 -> 135.84 | O50: =I50*F50 -> 192 | P50: =O50-N50 -> 56.16
A51: power 500ml | B51: 2 | C51: 24 | D51: =B51*C51 -> 48 | E51: 3.58 | F51: 5 | G51: =((F51-E51)/F51)*100 & "%" -> 28.4% | H51: 2 | I51: =C51*H51 -> 48 | J51: 0 | K51: =(C51*J51) -> 0 | L51: =(B51+$J$14)-H51 -> 0 | M51: =(D51+K51)-I51 -> 0 | N51: =(D51 + K51 - M51) * E51 -> 171.84 | O51: =I51*F51 -> 240 | P51: =O51-N51 -> 68.16
A52: snacky orange | B52: 1 | C52: 17 | D52: =B52*C52 -> 17 | E52: 1.6 | F52: 3 | G52: =((F52-E52)/F52)*100 & "%" -> 46.6666666666667% | H52: 1 | I52: =C52*H52 -> 17 | J52: 0 | K52: =(C52*J52) -> 0 | L52: =(B52+$J$14)-H52 -> 0 | M52: =(D52+K52)-I52 -> 0 | N52: =(D52 + K52 - M52) * E52 -> 27.2 | O52: =I52*F52 -> 51 | P52: =O52-N52 -> 23.8
A53: x!r 500ml | B53: 1 | C53: 24 | D53: =B53*C53 -> 24 | E53: 4.41 | F53: 6 | G53: =((F53-E53)/F53)*100 & "%" -> 26.5% | H53: 1 | I53: =C53*H53 -> 24 | J53: 0 | K53: =(C53*J53) -> 0 | L53: =(B53+$J$14)-H53 -> 0 | M53: =(D53+K53)-I53 -> 0 | N53: =(D53 + K53 - M53) * E53 -> 105.84 | O53: =I53*F53 -> 144 | P53: =O53-N53 -> 38.16
A54: x!r | B54: 2 | C54: 24 | D54: =B54*C54 -> 48 | E54: 2.7 | F54: 4 | G54: =((F54-E54)/F54)*100 & "%" -> 32.5% | H54: 2 | I54: =C54*H54 -> 48 | J54: 0 | K54: =(C54*J54) -> 0 | L54: =(B54+$J$14)-H54 -> 0 | M54: =(D54+K54)-I54 -> 0 | N54: =(D54 + K54 - M54) * E54 -> 129.6 | O54: =I54*F54 -> 192 | P54: =O54-N54 -> 62.4
A55: monster | B55: 1 | C55: 12 | D55: =B55*C55 -> 12 | E55: 9.16 | F55: 12 | G55: =((F55-E55)/F55)*100 & "%" -> 23.6666666666667% | I55: =C55*H55 -> 0 | K55: =(C55*J55) -> 0 | L55: =(B55+$J$14)-H55 -> 1 | M55: =(D55+K55)-I55 -> 12 | N55: =(D55 + K55 - M55) * E55 -> 0 | O55: =I55*F55 -> 0 | P55: =O55-N55 -> 0
A56: kinza | B56: 2 | C56: 30 | D56: =B56*C56 -> 60 | E56: 1.26 | F56: 2 | G56: =((F56-E56)/F56)*100 & "%" -> 37% | H56: 2 | I56: =C56*H56 -> 60 | J56: 0 | K56: =(C56*J56) -> 0 | L56: =(B56+$J$14)-H56 -> 0 | M56: =(D56+K56)-I56 -> 0 | N56: =(D56 + K56 - M56) * E56 -> 75.6 | O56: =I56*F56 -> 120 | P56: =O56-N56 -> 44.4
A57: Total (1)2025 | D57: =B57*C57 -> 0 | G57: =((F57-E57)/F57)*100 & "%" -> #DIV/0! | I57: =C57*H57 -> 0 | K57: =(C57*J57) -> 0 | L57: =(B57+$J$14)-H57 -> 0 | M57: =(D57+K57)-I57 -> 0 | N57: =SUM(N41:N56) -> 1638.68 | O57: =SUM(O41:O56) -> 2799 | P57: =SUM(P41:P56) -> 1160.32
A58: water | B58: 24 | C58: 12 | D58: =B58*C58 -> 288 | E58: 0.33 | F58: 1 | G58: =((F58-E58)/F58)*100 & "%" -> 67% | H58: 24 | I58: =C58*H58 -> 288 | J58: 0 | K58: =(C58*J58) -> 0 | L58: =(B58+$J$14)-H58 -> 0 | M58: =(D58+K58)-I58 -> 0 | N58: =(D58 + K58 - M58) * E58 -> 95.04 | O58: =I58*F58 -> 288 | P58: =O58-N58 -> 192.96
A59: power | B59: 1 | C59: 24 | D59: =B59*C59 -> 24 | E59: 2.5 | F59: 3 | G59: =((F59-E59)/F59)*100 & "%" -> 16.6666666666667% | H59: 1 | I59: =C59*H59 -> 24 | K59: =(C59*J59) -> 0 | L59: =(B59+$J$14)-H59 -> 0 | M59: =(D59+K59)-I59 -> 0 | N59: =(D59 + K59 - M59) * E59 -> 60 | O59: =I59*F59 -> 72 | P59: =O59-N59 -> 12
A60: power lower price | B60: 1 | C60: 24 | D60: =B60*C60 -> 24 | E60: 2.37 | F60: 3 | G60: =((F60-E60)/F60)*100 & "%" -> 21.% | H60: 1 | I60: =C60*H60 -> 24 | K60: =(C60*J60) -> 0 | L60: =(B60+$J$14)-H60 -> 0 | M60: =(D60+K60)-I60 -> 0 | N60: =(D60 + K60 - M60) * E60 -> 56.88 | O60: =I60*F60 -> 72 | P60: =O60-N60 -> 15.12
A61: xo energy | B61: 2 | C61: 24 | D61: =B61*C61 -> 48 | E61: 3.37 | F61: 5 | G61: =((F61-E61)/F61)*100 & "%" -> 32.6% | H61: 2 | I61: =C61*H61 -> 48 | K61: =(C61*J61) -> 0 | L61: =(B61+$J$14)-H61 -> 0 | M61: =(D61+K61)-I61 -> 0 | N61: =(D61 + K61 - M61) * E61 -> 161.76 | O61: =I61*F61 -> 240 | P61: =O61-N61 -> 78.24
A62: x!r | B62: 1 | C62: 24 | D62: =B62*C62 -> 24 | E62: 2.91 | F62: 4 | G62: =((F62-E62)/F62)*100 & "%" -> 27.25% | H62: 1 | I62: =C62*H62 -> 24 | K62: =(C62*J62) -> 0 | L62: =(B62+$J$14)-H62 -> 0 | M62: =(D62+K62)-I62 -> 0 | N62: =(D62 + K62 - M62) * E62 -> 69.84 | O62: =I62*F62 -> 96 | P62: =O62-N62 -> 26.16
A63: x!r lower | B63: 5 | C63: 24 | D63: =B63*C63 -> 120 | E63: 2.7 | F63: 4 | G63: =((F63-E63)/F63)*100 & "%" -> 32.5% | H63: 5 | I63: =C63*H63 -> 120 | J63: 0 | K63: =(C63*J63) -> 0 | L63: =(B63+$J$14)-H63 -> 0 | M63: =(D63+K63)-I63 -> 0 | N63: =(D63 + K63 - M63) * E63 -> 324 | O63: =I63*F63 -> 480 | P63: =O63-N63 -> 156
A64: suntop | B64: 13 | C64: 24 | D64: =B64*C64 -> 312 | E64: 0.6 | F64: 1 | G64: =((F64-E64)/F64)*100 & "%" -> 40% | H64: 13 | I64: =C64*H64 -> 312 | J64: 0 | K64: =(C64*J64) -> 0 | L64: =(B64+$J$14)-H64 -> 0 | M64: =(D64+K64)-I64 -> 0 | N64: =(D64 + K64 - M64) * E64 -> 187.2 | O64: =I64*F64 -> 312 | P64: =O64-N64 -> 124.8
A65: suntop masa | B65: 10 | C65: 24 | D65: =B65*C65 -> 240 | E65: 0.45 | F65: 1 | G65: =((F65-E65)/F65)*100 & "%" -> 55.% | H65: 10 | I65: =C65*H65 -> 240 | J65: 0 | K65: =(C65*J65) -> 0 | L65: =(B65+$J$14)-H65 -> 0 | M65: =(D65+K65)-I65 -> 0 | N65: =(D65 + K65 - M65) * E65 -> 108 | O65: =I65*F65 -> 240 | P65: =O65-N65 -> 132
A66: pepsi 500ml | B66: 6 | C66: 12 | D66: =B66*C66 -> 72 | E66: 1.66 | F66: 3 | G66: =((F66-E66)/F66)*100 & "%" -> 44.6666666666667% | H66: 6 | I66: =C66*H66 -> 72 | J66: 0 | K66: =(C66*J66) -> 0 | L66: =(B66+$J$14)-H66 -> 0 | M66: =(D66+K66)-I66 -> 0 | N66: =(D66 + K66 - M66) * E66 -> 119.52 | O66: =I66*F66 -> 216 | P66: =O66-N66 -> 96.48
A67: sprite 300ml | B67: 1 | C67: 24 | D67: =B67*C67 -> 24 | E67: 0.91 | F67: 2 | G67: =((F67-E67)/F67)*100 & "%" -> 54.5% | H67: 1 | I67: =C67*H67 -> 24 | K67: =(C67*J67) -> 0 | L67: =(B67+$J$14)-H67 -> 0 | M67: =(D67+K67)-I67 -> 0 | N67: =(D67 + K67 - M67) * E67 -> 21.84 | O67: =I67*F67 -> 48 | P67: =O67-N67 -> 26.16
A68: kinza | B68: 1 | C68: 24 | D68: =B68*C68 -> 24 | E68: 1.5 | F68: 2 | G68: =((F68-E68)/F68)*100 & "%" -> 25% | H68: 1 | I68: =C68*H68 -> 24 | K68: =(C68*J68) -> 0 | L68: =(B68+$J$14)-H68 -> 0 | M68: =(D68+K68)-I68 -> 0 | N68: =(D68 + K68 - M68) * E68 -> 36 | O68: =I68*F68 -> 48 | P68: =O68-N68 -> 12
A69: shewppers | B69: 1 | C69: 24 | D69: =B69*C69 -> 24 | E69: 1.95 | F69: 3 | G69: =((F69-E69)/F69)*100 & "%" -> 35% | H69: 1 | I69: =C69*H69 -> 24 | K69: =(C69*J69) -> 0 | L69: =(B69+$J$14)-H69 -> 0 | M69: =(D69+K69)-I69 -> 0 | N69: =(D69 + K69 - M69) * E69 -> 46.8 | O69: =I69*F69 -> 72 | P69: =O69-N69 -> 25.2
A70: green | B70: 1 | C70: 24 | D70: =B70*C70 -> 24 | E70: 2.62 | F70: 4 | G70: =((F70-E70)/F70)*100 & "%" -> 34.5% | I70: =C70*H70 -> 0 | K70: =(C70*J70) -> 0 | L70: =(B70+$J$14)-H70 -> 1 | M70: =(D70+K70)-I70 -> 24 | N70: =(D70 + K70 - M70) * E70 -> 0 | O70: =I70*F70 -> 0 | P70: =O70-N70 -> 0
A71: x!r 500ml | B71: 1 | C71: 24 | D71: =B71*C71 -> 24 | E71: 4.16 | F71: 6 | G71: =((F71-E71)/F71)*100 & "%" -> 30.6666666666667% | I71: =C71*H71 -> 0 | K71: =(C71*J71) -> 0 | L71: =(B71+$J$14)-H71 -> 1 | M71: =(D71+K71)-I71 -> 24 | N71: =(D71 + K71 - M71) * E71 -> 0 | O71: =I71*F71 -> 0 | P71: =O71-N71 -> 0
A72: barbican | B72: 1 | C72: 24 | D72: =B72*C72 -> 24 | E72: 2.87 | F72: 4 | G72: =((F72-E72)/F72)*100 & "%" -> 28.25% | I72: =C72*H72 -> 0 | K72: =(C72*J72) -> 0 | L72: =(B72+$J$14)-H72 -> 1 | M72: =(D72+K72)-I72 -> 24 | N72: =(D72 + K72 - M72) * E72 -> 0 | O72: =I72*F72 -> 0 | P72: =O72-N72 -> 0
D73: =B73*C73 -> 0 | G73: =((F73-E73)/F73)*100 & "%" -> #DIV/0! | I73: =C73*H73 -> 0 | K73: =(C73*J73) -> 0 | L73: =(B73+$J$14)-H73 -> 0 | M73: =(D73+K73)-I73 -> 0 | N73: =(D73 + K73 - M73) * E73 -> 0 | O73: =I73*F73 -> 0 | P73: =O73-N73 -> 0
A74: Total (2)2025 | D74: =B74*C74 -> 0 | G74: =((F74-E74)/F74)*100 & "%" -> #DIV/0! | I74: =C74*H74 -> 0 | K74: =(C74*J74) -> 0 | L74: =(B74+$J$14)-H74 -> 0 | M74: =(D74+K74)-I74 -> 0 | N74: =SUM(N60:N66) -> 1027.2 | O74: =SUM(O60:O66) -> 1656 | P74: =SUM(P58:P73) -> 897.12
A75: water | B75: 36 | C75: 12 | D75: =B75*C75 -> 432 | E75: 0.33 | F75: 1 | G75: =((F75-E75)/F75)*100 & "%" -> 67% | H75: 36 | I75: =C75*H75 -> 432 | J75: 0 | K75: =(C75*J75) -> 0 | L75: =(B75+$J$75)-H75 -> 0 | M75: =(D75+K75)-I75 -> 0 | N75: =(D75 + K75 - M75) * E75 -> 142.56 | O75: =I75*F75 -> 432 | P75: =O75-N75 -> 289.44
A76: x!r | B76: 6 | C76: 24 | D76: =B76*C76 -> 144 | E76: 2.83 | F76: 4 | G76: =((F76-E76)/F76)*100 & "%" -> 29.25% | H76: 6 | I76: =C76*H76 -> 144 | J76: 0 | K76: =(C76*J76) -> 0 | L76: =(B76+$J$14)-H76 -> 0 | M76: =(D76+K76)-I76 -> 0 | N76: =(D76 + K76 - M76) * E76 -> 407.52 | O76: =I76*F76 -> 576 | P76: =O76-N76 -> 168.48
A77: kinza | B77: 2 | C77: 24 | D77: =B77*C77 -> 48 | E77: 1.23 | F77: 2 | G77: =((F77-E77)/F77)*100 & "%" -> 38.5% | H77: 2 | I77: =C77*H77 -> 48 | J77: 0 | K77: =(C77*J77) -> 0 | L77: =(B77+$J$14)-H77 -> 0 | M77: =(D77+K77)-I77 -> 0 | N77: =(D77 + K77 - M77) * E77 -> 59.04 | O77: =I77*F77 -> 96 | P77: =O77-N77 -> 36.96
A78: pepsi 500ml | B78: 5 | C78: 12 | D78: =B78*C78 -> 60 | E78: 1.66 | F78: 3 | G78: =((F78-E78)/F78)*100 & "%" -> 44.6666666666667% | H78: 5 | I78: =C78*H78 -> 60 | J78: 0 | K78: =(C78*J78) -> 0 | L78: =(B78+$J$14)-H78 -> 0 | M78: =(D78+K78)-I78 -> 0 | N78: =(D78 + K78 - M78) * E78 -> 99.6 | O78: =I78*F78 -> 180 | P78: =O78-N78 -> 80.4
A79: shewppers | B79: 1 | C79: 24 | D79: =B79*C79 -> 24 | E79: 1.95 | F79: 3 | G79: =((F79-E79)/F79)*100 & "%" -> 35% | H79: 1 | I79: =C79*H79 -> 24 | K79: =(C79*J79) -> 0 | L79: =(B79+$J$14)-H79 -> 0 | M79: =(D79+K79)-I79 -> 0 | N79: =(D79 + K79 - M79) * E79 -> 46.8 | O79: =I79*F79 -> 72 | P79: =O79-N79 -> 25.2
A80: maxfly | B80: 1 | C80: 24 | D80: =B80*C80 -> 24 | E80: 2.83 | F80: 4 | G80: =((F80-E80)/F80)*100 & "%" -> 29.25% | H80: 1 | L80: =(B80+$J$14)-H80 -> 0 | M80: =(D80+K80)-I80 -> 24 | N80: =(D80 + K80 - M80) * E80 -> 0 | O80: =I80*F80 -> 0 | P80: =O80-N80 -> 0
A81: power 500ml | B81: 1 | C81: 24 | D81: =B81*C81 -> 24 | E81: 3.8 | F81: 5 | G81: =((F81-E81)/F81)*100 & "%" -> 24.% | H81: 1 | I81: =C81*H81 -> 24 | J81: 0 | K81: =(C81*J81) -> 0 | L81: =(B81+$J$14)-H81 -> 0 | M81: =(D81+K81)-I81 -> 0 | N81: =(D81 + K81 - M81) * E81 -> 91.2 | O81: =I81*F81 -> 120 | P81: =O81-N81 -> 28.8
M82: =(D82+K82)-I82 -> 0 | N82: =(D82 + K82 - M82) * E82 -> 0 | O82: =I82*F82 -> 0 | P82: =O82-N82 -> 0
A83: suntop saudi | B83: 8 | C83: 24 | D83: =B83*C83 -> 192 | E83: 0.6 | F83: 1 | G83: =((F83-E83)/F83)*100 & "%" -> 40% | H83: 8 | I83: =C83*H83 -> 192 | J83: 0 | K83: =(C83*J83) -> 0 | L83: =(B83+$J$14)-H83 -> 0 | M83: =(D83+K83)-I83 -> 0 | N83: =(D83 + K83 - M83) * E83 -> 115.2 | O83: =I83*F83 -> 192 | P83: =O83-N83 -> 76.8
A84: suntop masa | B84: 8 | C84: 24 | D84: =B84*C84 -> 192 | E84: 0.45 | F84: 1 | G84: =((F84-E84)/F84)*100 & "%" -> 55.% | H84: 8 | I84: =C84*H84 -> 192 | J84: 0 | K84: =(C84*J84) -> 0 | L84: =(B84+$J$14)-H84 -> 0 | M84: =(D84+K84)-I84 -> 0 | N84: =(D84 + K84 - M84) * E84 -> 86.4 | O84: =I84*F84 -> 192 | P84: =O84-N84 -> 105.6
A85: suntop alrihan | B85: 8 | C85: 24 | D85: =B85*C85 -> 192 | E85: 0.66 | F85: 1 | G85: =((F85-E85)/F85)*100 & "%" -> 34% | H85: 8 | I85: =C85*H85 -> 192 | J85: 0 | L85: =(B85+$J$14)-H85 -> 0 | M85: =(D85+K85)-I85 -> 0 | N85: =(D85 + K85 - M85) * E85 -> 126.72 | O85: =I85*F85 -> 192 | P85: =O85-N85 -> 65.28
A86: xo energy | B86: 1 | C86: 24 | D86: =B86*C86 -> 24 | E86: 3.7 | F86: 5 | G86: =((F86-E86)/F86)*100 & "%" -> 26.% | H86: 1 | I86: =C86*H86 -> 24 | K86: =(C86*J86) -> 0 | L86: =(B86+$J$14)-H86 -> 0 | M86: =(D86+K86)-I86 -> 0 | N86: =(D86 + K86 - M86) * E86 -> 88.8 | O86: =I86*F86 -> 120 | P86: =O86-N86 -> 31.2
A87: boba tea | B87: 1 | C87: 12 | D87: =B87*C87 -> 12 | E87: 9.5 | F87: 12 | G87: =((F87-E87)/F87)*100 & "%" -> 20.8333333333333% | I87: =C87*H87 -> 0 | K87: =(C87*J87) -> 0 | L87: =(B87+$J$14)-H87 -> 1 | M87: =(D87+K87)-I87 -> 12 | N87: =(D87 + K87 - M87) * E87 -> 0 | O87: =I87*F87 -> 0 | P87: =O87-N87 -> 0
A88: maxbrew | B88: 1 | C88: 12 | D88: =B88*C88 -> 12 | E88: 4.75 | F88: 6 | G88: =((F88-E88)/F88)*100 & "%" -> 20.8333333333333% | I88: =C88*H88 -> 0 | K88: =(C88*J88) -> 0 | L88: =(B88+$J$14)-H88 -> 1 | M88: =(D88+K88)-I88 -> 12 | N88: =(D88 + K88 - M88) * E88 -> 0 | O88: =I88*F88 -> 0 | P88: =O88-N88 -> 0
D89: =B89*C89 -> 0 | G89: =((F89-E89)/F89)*100 & "%" -> #DIV/0! | I89: =C89*H89 -> 0 | K89: =(C89*J89) -> 0 | L89: =(B89+$J$14)-H89 -> 0 | M89: =(D89+K89)-I89 -> 0 | N89: =(D89 + K89 - M89) * E89 -> 0 | O89: =I89*F89 -> 0 | P89: =O89-N89 -> 0
A90: Total (3)2025 | D90: =B90*C90 -> 0 | G90: =((F90-E90)/F90)*100 & "%" -> #DIV/0! | I90: =C90*H90 -> 0 | K90: =(C90*J90) -> 0 | L90: =(B90+$J$14)-H90 -> 0 | M90: =(D90+K90)-I90 -> 0 | N90: =SUM(N75:N86) -> 1263.84 | O90: =SUM(O75:O86) -> 2172 | P90: =SUM(P75:P86) -> 908.16
A91: water | B91: 20 | C91: 12 | D91: =B91*C91 -> 240 | E91: 0.33 | F91: 1 | G91: =((F91-E91)/F91)*100 & "%" -> 67% | I91: =C91*H91 -> 0 | J91: 0 | K91: =(C91*J91) -> 0 | L91: =(B91+$J$75)-H91 -> 20 | M91: =(D91+K91)-I91 -> 240 | N91: =(D91 + K91 - M91) * E91 -> 0 | O91: =I91*F91 -> 0 | P91: =O91-N91 -> 0
A92: x!r | B92: 3 | C92: 24 | D92: =B92*C92 -> 72 | E92: 2.83 | F92: 4 | G92: =((F92-E92)/F92)*100 & "%" -> 29.25% | I92: =C92*H92 -> 0 | J92: 0 | K92: =(C92*J92) -> 0 | L92: =(B92+$J$14)-H92 -> 3 | M92: =(D92+K92)-I92 -> 72 | N92: =(D92 + K92 - M92) * E92 -> 0 | O92: =I92*F92 -> 0 | P92: =O92-N92 -> 0
A93: x!r price increase | B93: 9 | C93: 24 | D93: =B93*C93 -> 216 | E93: 3 | F93: 4 | G93: =((F93-E93)/F93)*100 & "%" -> 25% | I93: =C93*H93 -> 0 | J93: 0 | K93: =(C93*J93) -> 0 | L93: =(B93+$J$14)-H93 -> 9 | M93: =(D93+K93)-I93 -> 216 | N93: =(D93 + K93 - M93) * E93 -> 0 | O93: =I93*F93 -> 0 | P93: =O93-N93 -> 0
A94: shewppers | B94: 2 | C94: 24 | D94: =B94*C94 -> 48 | E94: 2.08 | F94: 3 | G94: =((F94-E94)/F94)*100 & "%" -> 30.6666666666667% | I94: =C94*H94 -> 0 | J94: 0 | K94: =(C94*J94) -> 0 | L94: =(B94+$J$14)-H94 -> 2 | M94: =(D94+K94)-I94 -> 48 | N94: =(D94 + K94 - M94) * E94 -> 0 | O94: =I94*F94 -> 0 | P94: =O94-N94 -> 0
A95: shewppers | B95: 1 | C95: 24 | D95: =B95*C95 -> 24 | E95: 1.91 | F95: 3 | G95: =((F95-E95)/F95)*100 & "%" -> 36.3333333333333% | I95: =C95*H95 -> 0 | J95: 0 | K95: =(C95*J95) -> 0 | L95: =(B95+$J$14)-H95 -> 1 | M95: =(D95+K95)-I95 -> 24 | N95: =(D95 + K95 - M95) * E95 -> 0 | O95: =I95*F95 -> 0 | P95: =O95-N95 -> 0
A96: kinza | B96: 5 | C96: 24 | D96: =B96*C96 -> 120 | E96: 1.23 | F96: 2 | G96: =((F96-E96)/F96)*100 & "%" -> 38.5% | I96: =C96*H96 -> 0 | J96: 0 | K96: =(C96*J96) -> 0 | L96: =(B96+$J$14)-H96 -> 5 | M96: =(D96+K96)-I96 -> 120 | N96: =(D96 + K96 - M96) * E96 -> 0 | O96: =I96*F96 -> 0 | P96: =O96-N96 -> 0
A97: pepsi 500ml | B97: 3 | C97: 12 | D97: =B97*C97 -> 36 | E97: 1.66 | F97: 3 | G97: =((F97-E97)/F97)*100 & "%" -> 44.6666666666667% | I97: =C97*H97 -> 0 | J97: 0 | K97: =(C97*J97) -> 0 | L97: =(B97+$J$14)-H97 -> 3 | M97: =(D97+K97)-I97 -> 36 | N97: =(D97 + K97 - M97) * E97 -> 0 | O97: =I97*F97 -> 0 | P97: =O97-N97 -> 0
A98: suntop | B98: 12 | C98: 24 | D98: =B98*C98 -> 288 | E98: 0.62 | F98: 1 | G98: =((F98-E98)/F98)*100 & "%" -> 38% | I98: =C98*H98 -> 0 | J98: 0 | K98: =(C98*J98) -> 0 | L98: =(B98+$J$14)-H98 -> 12 | M98: =(D98+K98)-I98 -> 288 | N98: =(D98 + K98 - M98) * E98 -> 0 | O98: =I98*F98 -> 0 | P98: =O98-N98 -> 0
A99: al rihan | B99: 7 | C99: 24 | D99: =B99*C99 -> 168 | E99: 0.66 | F99: 1 | G99: =((F99-E99)/F99)*100 & "%" -> 34% | I99: =C99*H99 -> 0 | J99: 0 | K99: =(C99*J99) -> 0 | L99: =(B99+$J$14)-H99 -> 7 | M99: =(D99+K99)-I99 -> 168 | N99: =(D99 + K99 - M99) * E99 -> 0 | O99: =I99*F99 -> 0 | P99: =O99-N99 -> 0
A100: suntop masa | B100: 5 | C100: 24 | D100: =B100*C100 -> 120 | E100: 0.45 | F100: 1 | G100: =((F100-E100)/F100)*100 & "%" -> 55.% | I100: =C100*H100 -> 0 | J100: 0 | K100: =(C100*J100) -> 0 | L100: =(B100+$J$14)-H100 -> 5 | M100: =(D100+K100)-I100 -> 120 | N100: =(D100 + K100 - M100) * E100 -> 0 | O100: =I100*F100 -> 0 | P100: =O100-N100 -> 0
...

Sheet Chips
A1: Product Name | B1: # packs | C1: items in pack | D1: Initial Stock | E1: Cost per Unit | F1: Selling Price per Unit | G1: Column 1 | H1: # packs sold | I1: Quantity Sold | J1: # pack Restoked | K1: Restocked Quantity | L1: # Curremt packs | M1: Current Stock | N1: COGS | O1: Revenue | P1: Gross Profit | Q1: Month/year
A2: Tiger Family | B2: 2 | C2: 12 | D2: =(C2*B2) -> 24 | E2: 2.6 | F2: 4 | H2: 2 | I2: =(C2*H2) -> 24 | J2: 0 | K2: =(C2*J2) -> 0 | L2: =(B2+J2)-H2 -> 0 | M2: =(D2+K2-I2) -> 0 | N2: =(D2 + K2 - M2) * E2 -> 62.4 | O2: =(I2*F2) -> 96 | P2: =(O2-N2) -> 33.6
A3: Tiger meduim | B3: 9 | C3: 16 | D3: =(C3*B3) -> 144 | E3: 1.75 | F3: 3 | H3: 9 | I3: =(C3*H3) -> 144 | J3: 0 | K3: =(C3*J3) -> 0 | L3: =(B3+J3)-H3 -> 0 | M3: =(D3+K3-I3) -> 0 | N3: =(D3 + K3 - M3) * E3 -> 252 | O3: =(I3*F3) -> 432 | P3: =(O3-N3) -> 180
A4: 79g Master Sitos | B4: 1 | C4: 30 | D4: =(C4*B4) -> 30 | E4: 4.5 | F4: 5 | H4: 1 | I4: =(C4*H4) -> 30 | K4: =(C4*J4) -> 0 | L4: =(B4+J4)-H4 -> 0 | M4: =(D4+K4-I4) -> 0 | N4: =(D4 + K4 - M4) * E4 -> 135 | O4: =(I4*F4) -> 150 | P4: =(O4-N4) -> 15
A5: Sitos Meduim | B5: 16 | C5: 30 | D5: =(C5*B5) -> 480 | E5: 2.23 | F5: 3 | H5: 16 | I5: =(C5*H5) -> 480 | J5: 0 | K5: =(C5*J5) -> 0 | L5: =(B5+J5)-H5 -> 0 | M5: =(D5+K5-I5) -> 0 | N5: =(D5 + K5 - M5) * E5 -> 1070.4 | O5: =(I5*F5) -> 1440 | P5: =(O5-N5) -> 369.6
A6: Total (8) | D6: =(C6*B6) -> 0 | I6: =(C6*H6) -> 0 | K6: =(C6*J6) -> 0 | L6: =(B6+J6)-H6 -> 0 | M6: =(D6+K6-I6) -> 0 | N6: =sum(N2:N5) -> 1519.8 | O6: =sum(O2:O5) -> 2118 | P6: =sum(P2:P5) -> 598.2 | Q6: 8
A7: Sitos Small | B7: 1 | C7: 30 | D7: =(C7*B7) -> 30 | E7: 0.9 | F7: 1 | H7: 1 | I7: =(C7*H7) -> 30 | K7: =(C7*J7) -> 0 | L7: =(B7+J7)-H7 -> 0 | M7: =(D7+K7-I7) -> 0 | N7: =(D7 + K7 - M7) * E7 -> 27 | O7: =(I7*F7) -> 30 | P7: =(O7-N7) -> 3
A8: spuds family | B8: 2 | C8: 10 | D8: =(C8*B8) -> 20 | E8: 3.35 | F8: 4 | H8: 2 | I8: =(C8*H8) -> 20 | K8: =(C8*J8) -> 0 | L8: =(B8+J8)-H8 -> 0 | M8: =(D8+K8-I8) -> 0 | N8: =(D8 + K8 - M8) * E8 -> 67 | O8: =(I8*F8) -> 80 | P8: =(O8-N8) -> 13
A9: Spuds 40g | B9: 9 | C9: 15 | D9: =(C9*B9) -> 135 | E9: 2.03 | F9: 3 | H9: 9 | I9: =(C9*H9) -> 135 | J9: 0 | K9: =(C9*J9) -> 0 | L9: =(B9+J9)-H9 -> 0 | M9: =(D9+K9-I9) -> 0 | N9: =(D9 + K9 - M9) * E9 -> 274.05 | O9: =(I9*F9) -> 405 | P9: =(O9-N9) -> 130.95
A10: marshmallow haribo | B10: 1 | C10: 24 | D10: =(C10*B10) -> 24 | E10: 4.17 | F10: 5 | H10: 1 | I10: =(C10*H10) -> 24 | K10: =(C10*J10) -> 0 | L10: =(B10+J10)-H10 -> 0 | M10: =(D10+K10-I10) -> 0 | N10: =(D10 + K10 - M10) * E10 -> 100.08 | O10: =(I10*F10) -> 120 | P10: =(O10-N10) -> 19.92
A11: MrCrunch | B11: 14 | C11: 15 | D11: =(C11*B11) -> 210 | E11: 2.22 | F11: 3 | H11: 14 | I11: =(C11*H11) -> 210 | J11: 0 | K11: =(C11*J11) -> 0 | L11: =(B11+J11)-H11 -> 0 | M11: =(D11+K11-I11) -> 0 | N11: =(D11 + K11 - M11) * E11 -> 466.2 | O11: =(I11*F11) -> 630 | P11: =(O11-N11) -> 163.8
A12: MrCrunch طبيعيه | B12: 2 | C12: 18 | D12: =(C12*B12) -> 36 | E12: 2.11 | F12: 3 | H12: 2 | I12: =(C12*H12) -> 36 | K12: =(C12*J12) -> 0 | L12: =(B12+J12)-H12 -> 0 | M12: =(D12+K12-I12) -> 0 | N12: =(D12 + K12 - M12) * E12 -> 75.96 | O12: =(I12*F12) -> 108 | P12: =(O12-N12) -> 32.04
A13: الابطال شيبس | B13: 1 | C13: 50 | D13: =(C13*B13) -> 50 | E13: 0.42 | F13: 1 | H13: 1 | I13: =(C13*H13) -> 50 | K13: =(C13*J13) -> 0 | L13: =(B13+J13)-H13 -> 0 | M13: =(D13+K13-I13) -> 0 | N13: =(D13 + K13 - M13) * E13 -> 21 | O13: =(I13*F13) -> 50 | P13: =(O13-N13) -> 29
A14: شيبستي | B14: 2 | C14: 15 | D14: =(C14*B14) -> 30 | E14: 0.8 | F14: 2 | H14: 0 | I14: =(C14*H14) -> 0 | J14: 0 | K14: =(C14*J14) -> 0 | L14: =(B14+J14)-H14 -> 2 | M14: =(D14+K14-I14) -> 30 | N14: =(D14 + K14 - M14) * E14 -> 0 | O14: =(I14*F14) -> 0 | P14: =(O14-N14) -> 0
A15: Tiger meduim*40 | B15: 6 | C15: 40 | D15: =(C15*B15) -> 240 | E15: 0.72 | F15: 2 | H15: 6 | I15: =(C15*H15) -> 240 | J15: 0 | K15: =(C15*J15) -> 0 | L15: =(B15+J15)-H15 -> 0 | M15: =(D15+K15-I15) -> 0 | N15: =(D15 + K15 - M15) * E15 -> 172.8 | O15: =(I15*F15) -> 480 | P15: =(O15-N15) -> 307.2
A16: Tiger meduim | B16: 12 | C16: 30 | D16: =(C16*B16) -> 360 | E16: 0.86 | F16: 2 | H16: 12 | I16: =(C16*H16) -> 360 | J16: 0 | K16: =(C16*J16) -> 0 | L16: =(B16+J16)-H16 -> 0 | M16: =(D16+K16-I16) -> 0 | N16: =(D16 + K16 - M16) * E16 -> 309.6 | O16: =(I16*F16) -> 720 | P16: =(O16-N16) -> 410.4
A17: Total (9) | N17: =sum(N7:N16) -> 1513.69 | O17: =sum(O7:O16) -> 2623 | P17: =sum(P7:P16) -> 1109.31 | Q17: 9
A18: mrCrunch | B18: 8 | C18: 18 | D18: =C18*B18 -> 144 | E18: 2.27 | F18: 3 | H18: 8 | I18: =C18*H18 -> 144 | J18: 0 | K18: =(C18*J18) -> 0 | L18: =(B18+J18)-H18 -> 0 | M18: =(D18+K18)-I18 -> 0 | N18: =(D18 + K18 - M18) * E18 -> 326.88 | O18: =(I18*F18) -> 432 | P18: =O18-N18 -> 105.12
A19: tiger *12 | B19: 10 | C19: 12 | D19: =C19*B19 -> 120 | E19: 2.66 | F19: 4 | H19: 10 | I19: =C19*H19 -> 120 | J19: 0 | K19: =(C19*J19) -> 0 | L19: =(B19+J19)-H19 -> 0 | M19: =(D19+K19)-I19 -> 0 | N19: =(D19 + K19 - M19) * E19 -> 319.2 | O19: =(I19*F19) -> 480 | P19: =O19-N19 -> 160.8
A20: tiger *16 | B20: 1 | C20: 16 | D20: =C20*B20 -> 16 | E20: 1.75 | F20: 3 | H20: 1 | I20: =C20*H20 -> 16 | K20: =(C20*J20) -> 0 | L20: =(B20+J20)-H20 -> 0 | M20: =(D20+K20)-I20 -> 0 | N20: =(D20 + K20 - M20) * E20 -> 28 | O20: =(I20*F20) -> 48 | P20: =O20-N20 -> 20
A21: Tiger *40 | B21: 6 | C21: 40 | D21: =C21*B21 -> 240 | E21: 0.9 | F21: 2 | H21: 6 | I21: =C21*H21 -> 240 | J21: 0 | K21: =(C21*J21) -> 0 | L21: =(B21+J21)-H21 -> 0 | M21: =(D21+K21)-I21 -> 0 | N21: =(D21 + K21 - M21) * E21 -> 216 | O21: =(I21*F21) -> 480 | P21: =O21-N21 -> 264
A22: Spuds *10 | B22: 2 | C22: 10 | D22: =C22*B22 -> 20 | E22: 3.5 | F22: 4 | H22: 2 | I22: =C22*H22 -> 20 | J22: 0 | K22: =(C22*J22) -> 0 | L22: =(B22+J22)-H22 -> 0 | M22: =(D22+K22)-I22 -> 0 | N22: =(D22 + K22 - M22) * E22 -> 70 | O22: =(I22*F22) -> 80 | P22: =O22-N22 -> 10
A23: Spuds *15 | B23: 4 | C23: 15 | D23: =C23*B23 -> 60 | E23: 2.06 | F23: 3 | H23: 3 | I23: =C23*H23 -> 45 | J23: 0 | K23: =(C23*J23) -> 0 | L23: =(B23+J23)-H23 -> 1 | M23: =(D23+K23)-I23 -> 15 | N23: =(D23 + K23 - M23) * E23 -> 92.7 | O23: =(I23*F23) -> 135 | P23: =O23-N23 -> 42.3
A24: Stix DrFood | B24: 6 | C24: 6 | D24: =C24*B24 -> 36 | E24: 1.83 | F24: 2 | H24: 6 | I24: =C24*H24 -> 36 | K24: =(C24*J24) -> 0 | L24: =(B24+J24)-H24 -> 0 | M24: =(D24+K24)-I24 -> 0 | N24: =(D24 + K24 - M24) * E24 -> 65.88 | O24: =(I24*F24) -> 72 | P24: =O24-N24 -> 6.12
A25: Stix DrFood | B25: 6 | C25: 6 | D25: =C25*B25 -> 36 | E25: 1.83 | F25: 4 | H25: 6 | I25: =C25*H25 -> 36 | J25: 0 | K25: =(C25*J25) -> 0 | L25: =(B25+J25)-H25 -> 0 | M25: =(D25+K25)-I25 -> 0 | N25: =(D25 + K25 - M25) * E25 -> 65.88 | O25: =(I25*F25) -> 144 | P25: =O25-N25 -> 78.12
A26: Sitos 90g | B26: 1 | D26: =C26*B26 -> 0 | F26: 6 | H26: 1 | I26: =C26*H26 -> 0 | K26: =(C26*J26) -> 0 | L26: =(B26+J26)-H26 -> 0 | M26: =(D26+K26)-I26 -> 0 | N26: =(D26 + K26 - M26) * E26 -> 0 | O26: =(I26*F26) -> 0 | P26: =O26-N26 -> 0
A27: Sitos 50g | B27: 1 | C27: 30 | D27: =C27*B27 -> 30 | E27: 2.26 | F27: 3 | I27: =C27*H27 -> 0 | K27: =(C27*J27) -> 0 | L27: =(B27+J27)-H27 -> 1 | M27: =(D27+K27)-I27 -> 30 | N27: =(D27 + K27 - M27) * E27 -> 0 | O27: =(I27*F27) -> 0 | P27: =O27-N27 -> 0
A28: Maxxx chips | B28: 6 | C28: 12 | D28: =C28*B28 -> 72 | E28: 3.67 | F28: 5 | H28: 6 | I28: =C28*H28 -> 72 | J28: 0 | K28: =(C28*J28) -> 0 | L28: =(B28+J28)-H28 -> 0 | M28: =(D28+K28)-I28 -> 0 | N28: =(D28 + K28 - M28) * E28 -> 264.24 | O28: =(I28*F28) -> 360 | P28: =O28-N28 -> 95.76
A29: popcorn funday | B29: 3 | C29: 12 | D29: =C29*B29 -> 36 | E29: 3.08 | F29: 4 | H29: 3 | I29: =C29*H29 -> 36 | J29: 0 | K29: =(C29*J29) -> 0 | L29: =(B29+J29)-H29 -> 0 | M29: =(D29+K29)-I29 -> 0 | N29: =(D29 + K29 - M29) * E29 -> 110.88 | O29: =(I29*F29) -> 144 | P29: =O29-N29 -> 33.12
A30: Takis *18 | B30: 1 | C30: 18 | D30: =C30*B30 -> 18 | E30: 14 | F30: 16 | H30: 1 | I30: =C30*H30 -> 18 | K30: =(C30*J30) -> 0 | L30: =(B30+J30)-H30 -> 0 | M30: =(D30+K30)-I30 -> 0 | N30: =(D30 + K30 - M30) * E30 -> 252 | O30: =(I30*F30) -> 288 | P30: =O30-N30 -> 36
A31: Total (12) | D31: =C31*B31 -> 0 | I31: =C31*H31 -> 0 | K31: =(C31*J31) -> 0 | L31: =(B31+J31)-H31 -> 0 | N31: =sum(N18:N30) -> 1811.66 | O31: =sum(O18:O30) -> 2663 | P31: =sum(P18:P30) -> 851.34 | Q31: 12
A32: Total 2024 | D32: =B32*C32 -> 0 | I32: =C32*H32 -> 0 | K32: =(C32*J32) -> 0 | L32: =(B32+$J$14)-H32 -> 0 | M32: =(D32+K32)-I32 -> 0 | N32: =SUM(N31+N17+N6) -> 4845.15 | O32: =SUM(O31+O17+O6) -> 7404 | P32: =SUM(P31+P17+P6) -> 2558.85
D33: =C33*B33 -> 0 | I33: =C33*H33 -> 0 | K33: =(C33*J33) -> 0 | L33: =(B33+J33)-H33 -> 0
A34: master sitos 90g | B34: 1 | C34: 12 | D34: =C34*B34 -> 12 | E34: 4.75 | F34: 6 | I34: =C34*H34 -> 0 | K34: =(C34*J34) -> 0 | L34: =(B34+J34)-H34 -> 1 | M34: =(D34+K34)-I34 -> 12 | N34: =(D34 + K34 - M34) * E34 -> 0 | O34: =(I34*F34) -> 0 | P34: =O34-N34 -> 0
A35: popcorn funday pizza | B35: 3 | C35: 15 | D35: =C35*B35 -> 45 | E35: 2.47 | F35: 5 | H35: 3 | I35: =C35*H35 -> 45 | J35: 0 | K35: =(C35*J35) -> 0 | L35: =(B35+J35)-H35 -> 0 | M35: =(D35+K35)-I35 -> 0 | N35: =(D35 + K35 - M35) * E35 -> 111.15 | O35: =(I35*F35) -> 225 | P35: =O35-N35 -> 113.85
A36: Maxxx chips | B36: 8 | C36: 12 | D36: =C36*B36 -> 96 | E36: 3.67 | F36: 5 | H36: 8 | I36: =C36*H36 -> 96 | J36: 0 | K36: =(C36*J36) -> 0 | L36: =(B36+J36)-H36 -> 0 | M36: =(D36+K36)-I36 -> 0 | N36: =(D36 + K36 - M36) * E36 -> 352.32 | O36: =(I36*F36) -> 480 | P36: =O36-N36 -> 127.68
A37: tiger *12 | B37: 13 | C37: 12 | D37: =C37*B37 -> 156 | E37: 2.6 | F37: 4 | H37: 13 | I37: =C37*H37 -> 156 | J37: 0 | K37: =(C37*J37) -> 0 | L37: =(B37+J37)-H37 -> 0 | M37: =(D37+K37)-I37 -> 0 | N37: =(D37 + K37 - M37) * E37 -> 405.6 | O37: =(I37*F37) -> 624 | P37: =O37-N37 -> 218.4
A38: tiger excllence | B38: 10 | C38: 10 | D38: =C38*B38 -> 100 | E38: 3.2 | F38: 5 | H38: 10 | I38: =C38*H38 -> 100 | J38: 0 | K38: =(C38*J38) -> 0 | L38: =(B38+J38)-H38 -> 0 | M38: =(D38+K38)-I38 -> 0 | N38: =(D38 + K38 - M38) * E38 -> 320 | O38: =(I38*F38) -> 500 | P38: =O38-N38 -> 180
A39: buffies | B39: 1 | C39: 30 | D39: =C39*B39 -> 30 | E39: 2.27 | F39: 4 | H39: 1 | I39: =C39*H39 -> 30 | K39: =(C39*J39) -> 0 | L39: =(B39+J39)-H39 -> 0 | M39: =(D39+K39)-I39 -> 0 | N39: =(D39 + K39 - M39) * E39 -> 68.1 | O39: =(I39*F39) -> 120 | P39: =O39-N39 -> 51.9
A40: mr crunch normal | B40: 1 | C40: 18 | D40: =C40*B40 -> 18 | E40: 2.16 | F40: 4 | H40: 1 | I40: =C40*H40 -> 18 | K40: =(C40*J40) -> 0 | L40: =(B40+J40)-H40 -> 0 | M40: =(D40+K40)-I40 -> 0 | N40: =(D40 + K40 - M40) * E40 -> 38.88 | O40: =(I40*F40) -> 72 | P40: =O40-N40 -> 33.12
A41: mr crunch | B41: 4 | C41: 18 | D41: =C41*B41 -> 72 | E41: 2.27 | F41: 4 | H41: 4 | I41: =C41*H41 -> 72 | J41: 0 | K41: =(C41*J41) -> 0 | L41: =(B41+J41)-H41 -> 0 | M41: =(D41+K41)-I41 -> 0 | N41: =(D41 + K41 - M41) * E41 -> 163.44 | O41: =(I41*F41) -> 288 | P41: =O41-N41 -> 124.56
A42: mr crunch cheez top | B42: 4 | C42: 18 | D42: =C42*B42 -> 72 | E42: 1.55 | F42: 4 | H42: 4 | I42: =C42*H42 -> 72 | J42: 0 | K42: =(C42*J42) -> 0 | L42: =(B42+J42)-H42 -> 0 | M42: =(D42+K42)-I42 -> 0 | N42: =(D42 + K42 - M42) * E42 -> 111.6 | O42: =(I42*F42) -> 288 | P42: =O42-N42 -> 176.4
A43: mr crucnh | B43: 1 | C43: 18 | D43: =C43*B43 -> 18 | E43: 2.33 | F43: 4 | H43: 1 | I43: =C43*H43 -> 18 | K43: =(C43*J43) -> 0 | L43: =(B43+J43)-H43 -> 0 | M43: =(D43+K43)-I43 -> 0 | N43: =(D43 + K43 - M43) * E43 -> 41.94 | O43: =(I43*F43) -> 72 | P43: =O43-N43 -> 30.06
A44: Takis *18 | B44: 1 | C44: 18 | D44: =C44*B44 -> 18 | E44: 10 | F44: 20 | H44: 1 | I44: =C44*H44 -> 18 | K44: =(C44*J44) -> 0 | L44: =(B44+J44)-H44 -> 0 | M44: =(D44+K44)-I44 -> 0 | N44: =(D44 + K44 - M44) * E44 -> 180 | O44: =(I44*F44) -> 360 | P44: =O44-N44 -> 180
A45: Takis *18 | B45: 1 | C45: 18 | D45: =C45*B45 -> 18 | E45: 8.8 | F45: 20 | H45: 1 | I45: =C45*H45 -> 18 | K45: =(C45*J45) -> 0 | L45: =(B45+J45)-H45 -> 0 | M45: =(D45+K45)-I45 -> 0 | N45: =(D45 + K45 - M45) * E45 -> 158.4 | O45: =(I45*F45) -> 360 | P45: =O45-N45 -> 201.6
A46: Takis * | B46: 1 | C46: 10 | D46: =C46*B46 -> 10 | E46: 8.8 | F46: 10 | H46: 0.4 | I46: =C46*H46 -> 4 | K46: =(C46*J46) -> 0 | L46: =(B46+J46)-H46 -> 0.6 | M46: =(D46+K46)-I46 -> 6 | N46: =(D46 + K46 - M46) * E46 -> 35.2 | O46: =(I46*F46) -> 40 | P46: =O46-N46 -> 4.8
A47: total (1)2025 | D47: =C47*B47 -> 0 | I47: =C47*H47 -> 0 | K47: =(C47*J47) -> 0 | L47: =(B47+J47)-H47 -> 0 | M47: =(D47+K47)-I47 -> 0 | N47: =sum(N34:N46) -> 1986.63 | O47: =sum(O34:O46) -> 3429 | P47: =sum(P34:P46) -> 1442.37
A48: Takis | B48: 1 | C48: 18 | D48: =C48*B48 -> 18 | E48: 13.4 | F48: 20 | G48: =((F48-E48)/F48)*100 & "%" -> 33.% | H48: 1 | I48: =C48*H48 -> 18 | K48: =(C48*J48) -> 0 | L48: =(B48+J48)-H48 -> 0 | M48: =(D48+K48)-I48 -> 0 | N48: =(D48 + K48 - M48) * E48 -> 241.2 | O48: =(I48*F48) -> 360 | P48: =O48-N48 -> 118.8
A49: Takis | B49: 2 | C49: 18 | D49: =C49*B49 -> 36 | E49: 13.3 | F49: 20 | G49: =((F49-E49)/F49)*100 & "%" -> 33.5% | H49: 2 | I49: =C49*H49 -> 36 | J49: 0 | K49: =(C49*J49) -> 0 | L49: =(B49+J49)-H49 -> 0 | M49: =(D49+K49)-I49 -> 0 | N49: =(D49 + K49 - M49) * E49 -> 478.8 | O49: =(I49*F49) -> 720 | P49: =O49-N49 -> 241.2
A50: mr crunch | B50: 3 | C50: 18 | D50: =C50*B50 -> 54 | E50: 2.33 | F50: 4 | G50: =((F50-E50)/F50)*100 & "%" -> 41.75% | H50: 3 | I50: =C50*H50 -> 54 | J50: 0 | K50: =(C50*J50) -> 0 | L50: =(B50+J50)-H50 -> 0 | M50: =(D50+K50)-I50 -> 0 | N50: =(D50 + K50 - M50) * E50 -> 125.82 | O50: =(I50*F50) -> 216 | P50: =O50-N50 -> 90.18
A51: mr crunch top cheez | B51: 1 | C51: 18 | D51: =C51*B51 -> 18 | E51: 1.55 | F51: 4 | G51: =((F51-E51)/F51)*100 & "%" -> 61.25% | H51: 1 | I51: =C51*H51 -> 18 | K51: =(C51*J51) -> 0 | L51: =(B51+J51)-H51 -> 0 | M51: =(D51+K51)-I51 -> 0 | N51: =(D51 + K51 - M51) * E51 -> 27.9 | O51: =(I51*F51) -> 72 | P51: =O51-N51 -> 44.1
A52: tiger *12 | B52: 18 | C52: 12 | D52: =C52*B52 -> 216 | E52: 2.66 | F52: 4 | G52: =((F52-E52)/F52)*100 & "%" -> 33.5% | H52: 18 | I52: =C52*H52 -> 216 | J52: 0 | K52: =(C52*J52) -> 0 | L52: =(B52+J52)-H52 -> 0 | M52: =(D52+K52)-I52 -> 0 | N52: =(D52 + K52 - M52) * E52 -> 574.56 | O52: =(I52*F52) -> 864 | P52: =O52-N52 -> 289.44
A53: tiger excllence medium | B53: 9 | C53: 20 | D53: =C53*B53 -> 180 | E53: 3.2 | F53: 5 | G53: =((F53-E53)/F53)*100 & "%" -> 36% | H53: 9 | I53: =C53*H53 -> 180 | J53: 0 | K53: =(C53*J53) -> 0 | L53: =(B53+J53)-H53 -> 0 | M53: =(D53+K53)-I53 -> 0 | N53: =(D53 + K53 - M53) * E53 -> 576 | O53: =(I53*F53) -> 900 | P53: =O53-N53 -> 324
A54: tiger excellence jumbo | B54: 1 | C54: 10 | D54: =C54*B54 -> 10 | E54: 4 | F54: 5 | G54: =((F54-E54)/F54)*100 & "%" -> 20% | H54: 1 | I54: =C54*H54 -> 10 | K54: =(C54*J54) -> 0 | L54: =(B54+J54)-H54 -> 0 | M54: =(D54+K54)-I54 -> 0 | N54: =(D54 + K54 - M54) * E54 -> 40 | O54: =(I54*F54) -> 50 | P54: =O54-N54 -> 10
A55: chips pattes | B55: 2 | C55: 12 | D55: =C55*B55 -> 24 | E55: 4.42 | F55: 6 | G55: =((F55-E55)/F55)*100 & "%" -> 26.3333333333333% | H55: 2 | I55: =C55*H55 -> 24 | J55: 0 | K55: =(C55*J55) -> 0 | L55: =(B55+J55)-H55 -> 0 | M55: =(D55+K55)-I55 -> 0 | N55: =(D55 + K55 - M55) * E55 -> 106.08 | O55: =(I55*F55) -> 144 | P55: =O55-N55 -> 37.92
A56: pringles | B56: 1 | C56: 12 | D56: =C56*B56 -> 12 | E56: 4.25 | F56: 6 | G56: =((F56-E56)/F56)*100 & "%" -> 29.1666666666667% | H56: 1 | I56: =C56*H56 -> 12 | K56: =(C56*J56) -> 0 | L56: =(B56+J56)-H56 -> 0 | M56: =(D56+K56)-I56 -> 0 | N56: =(D56 + K56 - M56) * E56 -> 51 | O56: =(I56*F56) -> 72 | P56: =O56-N56 -> 21
A57: dorits | B57: 1 | C57: 12 | D57: =C57*B57 -> 12 | E57: 2.5 | F57: 4 | G57: =((F57-E57)/F57)*100 & "%" -> 37.5% | H57: 1 | I57: =C57*H57 -> 12 | K57: =(C57*J57) -> 0 | L57: =(B57+J57)-H57 -> 0 | M57: =(D57+K57)-I57 -> 0 | N57: =(D57 + K57 - M57) * E57 -> 30 | O57: =(I57*F57) -> 48 | P57: =O57-N57 -> 18
A58: total (2)2025 | D58: =C58*B58 -> 0 | I58: =C58*H58 -> 0 | K58: =(C58*J58) -> 0 | L58: =(B58+J58)-H58 -> 0 | N58: =sum(N48:N57) -> 2251.36 | O58: =sum(O48:O57) -> 3446 | P58: =sum(P48:P57) -> 1194.64
A59: tiger *12 | B59: 18 | C59: 12 | D59: =C59*B59 -> 216 | E59: 2.66 | F59: 4 | G59: =((F59-E59)/F59)*100 & "%" -> 33.5% | H59: 18 | I59: =C59*H59 -> 216 | J59: 0 | K59: =(C59*J59) -> 0 | L59: =(B59+J59)-H59 -> 0 | M59: =(D59+K59)-I59 -> 0 | N59: =(D59 + K59 - M59) * E59 -> 574.56 | O59: =(I59*F59) -> 864 | P59: =O59-N59 -> 289.44
A60: tiger excllence medium | B60: 5 | C60: 20 | D60: =C60*B60 -> 100 | E60: 3.2 | F60: 5 | G60: =((F60-E60)/F60)*100 & "%" -> 36% | H60: 5 | I60: =C60*H60 -> 100 | J60: 0 | K60: =(C60*J60) -> 0 | L60: =(B60+J60)-H60 -> 0 | M60: =(D60+K60)-I60 -> 0 | N60: =(D60 + K60 - M60) * E60 -> 320 | O60: =(I60*F60) -> 500 | P60: =O60-N60 -> 180
A61: Spuds *15 | B61: 1 | C61: 15 | D61: =C61*B61 -> 15 | E61: 2.06 | F61: 3 | G61: =((F61-E61)/F61)*100 & "%" -> 31.3333333333333% | H61: 1 | I61: =C61*H61 -> 15 | K61: =(C61*J61) -> 0 | L61: =(B61+J61)-H61 -> 0 | M61: =(D61+K61)-I61 -> 0 | N61: =(D61 + K61 - M61) * E61 -> 30.9 | O61: =(I61*F61) -> 45 | P61: =O61-N61 -> 14.1
A62: mr crunch | B62: 2 | C62: 18 | D62: =C62*B62 -> 36 | E62: 2.27 | F62: 4 | G62: =((F62-E62)/F62)*100 & "%" -> 43.25% | H62: 2 | I62: =C62*H62 -> 36 | K62: =(C62*J62) -> 0 | L62: =(B62+J62)-H62 -> 0 | M62: =(D62+K62)-I62 -> 0 | N62: =(D62 + K62 - M62) * E62 -> 81.72 | O62: =(I62*F62) -> 144 | P62: =O62-N62 -> 62.28
A63: pringles bugle | B63: 3 | C63: 18 | D63: =C63*B63 -> 54 | E63: 2.5 | F63: 4 | G63: =((F63-E63)/F63)*100 & "%" -> 37.5% | H63: 3 | I63: =C63*H63 -> 54 | K63: =(C63*J63) -> 0 | L63: =(B63+J63)-H63 -> 0 | M63: =(D63+K63)-I63 -> 0 | N63: =(D63 + K63 - M63) * E63 -> 135 | O63: =(I63*F63) -> 216 | P63: =O63-N63 -> 81
A64: dDoritos | B64: 32 | C64: 12 | D64: =C64*B64 -> 384 | E64: 2.5 | F64: 4 | G64: =((F64-E64)/F64)*100 & "%" -> 37.5% | H64: 32 | I64: =C64*H64 -> 384 | J64: 0 | K64: =(C64*J64) -> 0 | L64: =(B64+J64)-H64 -> 0 | M64: =(D64+K64)-I64 -> 0 | N64: =(D64 + K64 - M64) * E64 -> 960 | O64: =(I64*F64) -> 1536 | P64: =O64-N64 -> 576
A65: bugles | B65: 1 | C65: 12 | D65: =C65*B65 -> 12 | E65: 2.5 | F65: 4 | G65: =((F65-E65)/F65)*100 & "%" -> 37.5% | I65: =C65*H65 -> 0 | K65: =(C65*J65) -> 0 | L65: =(B65+J65)-H65 -> 1 | M65: =(D65+K65)-I65 -> 12 | N65: =(D65 + K65 - M65) * E65 -> 0 | O65: =(I65*F65) -> 0 | P65: =O65-N65 -> 0
A66: takis | B66: 8 | C66: 1 | D66: =C66*B66 -> 8 | E66: 14 | F66: 20 | G66: =((F66-E66)/F66)*100 & "%" -> 30% | H66: 8 | I66: =C66*H66 -> 8 | K66: =(C66*J66) -> 0 | L66: =(B66+J66)-H66 -> 0 | M66: =(D66+K66)-I66 -> 0 | N66: =(D66 + K66 - M66) * E66 -> 112 | O66: =(I66*F66) -> 160 | P66: =O66-N66 -> 48
A67: Chots | B67: 9 | C67: 12 | D67: =C67*B67 -> 108 | E67: 1.33 | F67: 3 | G67: =((F67-E67)/F67)*100 & "%" -> 55.6666666666667% | H67: 9 | I67: =C67*H67 -> 108 | J67: 0 | K67: =(C67*J67) -> 0 | L67: =(B67+J67)-H67 -> 0 | M67: =(D67+K67)-I67 -> 0 | N67: =(D67 + K67 - M67) * E67 -> 143.64 | O67: =(I67*F67) -> 324 | P67: =O67-N67 -> 180.36
A68: Maxxx chips | B68: 1 | C68: 6 | D68: =C68*B68 -> 6 | E68: 2 | F68: 4 | G68: =((F68-E68)/F68)*100 & "%" -> 50% | H68: 1 | I68: =C68*H68 -> 6 | K68: =(C68*J68) -> 0 | L68: =(B68+J68)-H68 -> 0 | M68: =(D68+K68)-I68 -> 0 | N68: =(D68 + K68 - M68) * E68 -> 12 | O68: =(I68*F68) -> 24 | P68: =O68-N68 -> 12
A69: Total | D69: =C69*B69 -> 0 | I69: =C69*H69 -> 0 | K69: =(C69*J69) -> 0 | L69: =(B69+J69)-H69 -> 0 | N69: =sum(N59:N68) -> 2369.82 | O69: =sum(O59:O68) -> 3813 | P69: =sum(P59:P68) -> 1443.18
A70: tiger *12 | B70: 58 | C70: 12 | D70: =C70*B70 -> 696 | E70: 2.66 | F70: 4 | G70: =((F70-E70)/F70)*100 & "%" -> 33.5% | H70: 20 | I70: =C70*H70 -> 240 | J70: 0 | K70: =(C70*J70) -> 0 | L70: =(B70+J70)-H70 -> 38 | M70: =(D70+K70)-I70 -> 456 | N70: =(D70 + K70 - M70) * E70 -> 638.4 | O70: =(I70*F70) -> 960 | P70: =O70-N70 -> 321.6
A71: Chots | B71: 10 | C71: 12 | D71: =C71*B71 -> 120 | E71: 1.33 | F71: 3 | G71: =((F71-E71)/F71)*100 & "%" -> 55.6666666666667% | I71: =C71*H71 -> 0 | J71: 0 | K71: =(C71*J71) -> 0 | L71: =(B71+J71)-H71 -> 10 | M71: =(D71+K71)-I71 -> 120 | N71: =(D71 + K71 - M71) * E71 -> 0 | O71: =(I71*F71) -> 0 | P71: =O71-N71 -> 0
A72: tiger excllence medium | B72: 12 | C72: 20 | D72: =C72*B72 -> 240 | E72: 3.2 | F72: 5 | G72: =((F72-E72)/F72)*100 & "%" -> 36% | I72: =C72*H72 -> 0 | J72: 0 | K72: =(C72*J72) -> 0 | L72: =(B72+J72)-H72 -> 12 | M72: =(D72+K72)-I72 -> 240 | N72: =(D72 + K72 - M72) * E72 -> 0 | O72: =(I72*F72) -> 0 | P72: =O72-N72 -> 0
A73: mr crunch | B73: 10 | C73: 18 | D73: =C73*B73 -> 180 | E73: 2.27 | F73: 4 | G73: =((F73-E73)/F73)*100 & "%" -> 43.25% | H73: 1 | I73: =C73*H73 -> 18 | J73: 0 | K73: =(C73*J73) -> 0 | L73: =(B73+J73)-H73 -> 9 | M73: =(D73+K73)-I73 -> 162 | N73: =(D73 + K73 - M73) * E73 -> 40.86 | O73: =(I73*F73) -> 72 | P73: =O73-N73 -> 31.14
A74: Dorits fake | B74: 6 | C74: 10 | D74: =C74*B74 -> 60 | E74: 2.2 | F74: 5 | G74: =((F74-E74)/F74)*100 & "%" -> 56.% | H74: 6 | I74: =C74*H74 -> 60 | K74: =(C74*J74) -> 0 | L74: =(B74+J74)-H74 -> 0 | M74: =(D74+K74)-I74 -> 0 | N74: =(D74 + K74 - M74) * E74 -> 132 | O74: =(I74*F74) -> 300 | P74: =O74-N74 -> 168
A75: Doritos f | B75: 24 | C75: 12 | D75: =C75*B75 -> 288 | E75: 3 | F75: 5 | G75: =((F75-E75)/F75)*100 & "%" -> 40% | I75: =C75*H75 -> 0 | J75: 0 | K75: =(C75*J75) -> 0 | L75: =(B75+J75)-H75 -> 24 | M75: =(D75+K75)-I75 -> 288 | N75: =(D75 + K75 - M75) * E75 -> 0 | O75: =(I75*F75) -> 0 | P75: =O75-N75 -> 0
A76: Doritos f- | B76: 20 | C76: 12 | D76: =C76*B76 -> 240 | E76: 2.91 | F76: 5 | G76: =((F76-E76)/F76)*100 & "%" -> 41.8% | I76: =C76*H76 -> 0 | J76: 0 | K76: =(C76*J76) -> 0 | L76: =(B76+J76)-H76 -> 20 | M76: =(D76+K76)-I76 -> 240 | N76: =(D76 + K76 - M76) * E76 -> 0 | O76: =(I76*F76) -> 0 | P76: =O76-N76 -> 0
A77: Doritos | B77: 3 | C77: 10 | D77: =C77*B77 -> 30 | E77: 5.1 | F77: 7 | G77: =((F77-E77)/F77)*100 & "%" -> 27.1428571428571% | I77: =C77*H77 -> 0 | K77: =(C77*J77) -> 0 | L77: =(B77+J77)-H77 -> 3 | M77: =(D77+K77)-I77 -> 30 | N77: =(D77 + K77 - M77) * E77 -> 0 | O77: =(I77*F77) -> 0 | P77: =O77-N77 -> 0
A78: pringles bugle | B78: 1 | C78: 18 | D78: =C78*B78 -> 18 | E78: 2.5 | F78: 4 | G78: =((F78-E78)/F78)*100 & "%" -> 37.5% | I78: =C78*H78 -> 0 | K78: =(C78*J78) -> 0 | L78: =(B78+J78)-H78 -> 1 | M78: =(D78+K78)-I78 -> 18 | N78: =(D78 + K78 - M78) * E78 -> 0 | O78: =(I78*F78) -> 0 | P78: =O78-N78 -> 0
A79: takis | B79: 1 | C79: 7 | D79: =C79*B79 -> 7 | E79: 14 | F79: 20 | G79: =((F79-E79)/F79)*100 & "%" -> 30% | I79: =C79*H79 -> 0 | K79: =(C79*J79) -> 0 | L79: =(B79+J79)-H79 -> 1 | M79: =(D79+K79)-I79 -> 7 | N79: =(D79 + K79 - M79) * E79 -> 0 | O79: =(I79*F79) -> 0 | P79: =O79-N79 -> 0
A80: Total 2025 | D80: =B80*C80 -> 0 | I80: =C80*H80 -> 0 | K80: =(C80*J80) -> 0 | L80: =(B80+$J$14)-H80 -> 0 | M80: =(D80+K80)-I80 -> 0 | N80: =SUM(N47+N58+N69) -> 6607.81 | O80: =SUM(O47+O58+O69) -> 10688 | P80: =SUM(P47+P58+P69) -> 4080.19
D81: =C81*B81 -> 0 | I81: =C81*H81 -> 0 | K81: =(C81*J81) -> 0 | L81: =(B81+J81)-H81 -> 0
D82: =C82*B82 -> 0 | I82: =C82*H82 -> 0 | K82: =(C82*J82) -> 0 | L82: =(B82+J82)-H82 -> 0
D83: =C83*B83 -> 0 | I83: =C83*H83 -> 0 | K83: =(C83*J83) -> 0 | L83: =(B83+J83)-H83 -> 0
D84: =C84*B84 -> 0 | K84: =(C84*J84) -> 0 | L84: =(B84+J84)-H84 -> 0
D85: =C85*B85 -> 0 | K85: =(C85*J85) -> 0 | L85: =(B85+J85)-H85 -> 0
D86: =C86*B86 -> 0 | K86: =(C86*J86) -> 0 | L86: =(B86+J86)-H86 -> 0
D87: =C87*B87 -> 0 | K87: =(C87*J87) -> 0 | L87: =(B87+J87)-H87 -> 0
D88: =C88*B88 -> 0 | K88: =(C88*J88) -> 0 | L88: =(B88+J88)-H88 -> 0

Sheet Snacks
A1: Product Name | B1: # pack | C1: items inside the pack | D1: Initial Stock | E1: Cost per Unit | F1: Selling Price per Unit | G1: Column 1 | H1: # packs sold | I1: Quantity Sold | J1: # pack Restoked | K1: Restocked Quantity | L1: # Curremt packs | M1: Current Stock | N1: COGS | O1: Revenue | P1: Gross Profit | Q1: Column 16
A2: Laviva | B2: 17 | C2: 24 | D2: =(B2*C2) -> 408 | E2: 1.56 | F2: 2 | G2: =((F2-E2)/F2)*100 & "%" -> 22.% | H2: 17 | I2: =(C2*H2) -> 408 | J2: 0 | K2: =(J2*C2) -> 0 | L2: =(B2+J2-H2) -> 0 | M2: =(D2+K2-I2) -> 0 | N2: =(D2 + K2 - M2) * E2 -> 636.48 | O2: =(I2*F2) -> 816 | P2: =(O2-N2) -> 179.52 | Q2: 8
A3: Bella | B3: 8 | C3: 24 | D3: =(B3*C3) -> 192 | E3: 0.58 | F3: 1 | G3: =((F3-E3)/F3)*100 & "%" -> 42.% | H3: 8 | I3: =(C3*H3) -> 192 | J3: 0 | K3: =(J3*C3) -> 0 | L3: =(B3+J3-H3) -> 0 | M3: =(D3+K3-I3) -> 0 | N3: =(D3 + K3 - M3) * E3 -> 111.36 | O3: =(I3*F3) -> 192 | P3: =(O3-N3) -> 80.64 | Q3: 8
A4: Winky cake | D4: 144 | E4: 0.68 | F4: 1 | G4: =((F4-E4)/F4)*100 & "%" -> 32.% | I4: 144 | K4: =(J4*C4) -> 0 | L4: =(B4+J4-H4) -> 0 | M4: =(D4+K4-I4) -> 0 | N4: =(D4 + K4 - M4) * E4 -> 97.92 | O4: =(I4*F4) -> 144 | P4: =(O4-N4) -> 46.08 | Q4: 8
A5: Janaty biscuit | D5: 24 | E5: 1.16 | F5: 2 | G5: =((F5-E5)/F5)*100 & "%" -> 42.% | I5: 24 | K5: =(J5*C5) -> 0 | L5: =(B5+J5-H5) -> 0 | M5: =(D5+K5-I5) -> 0 | N5: =(D5 + K5 - M5) * E5 -> 27.84 | O5: =(I5*F5) -> 48 | P5: =(O5-N5) -> 20.16 | Q5: 8
A6: Regno | D6: 16 | E6: 2.31 | F6: 3 | G6: =((F6-E6)/F6)*100 & "%" -> 23% | I6: 16 | K6: =(J6*C6) -> 0 | L6: =(B6+J6-H6) -> 0 | M6: =(D6+K6-I6) -> 0 | N6: =(D6 + K6 - M6) * E6 -> 36.96 | O6: =(I6*F6) -> 48 | P6: =(O6-N6) -> 11.04 | Q6: 8
A7: Gerdena Love me | D7: 24 | E7: 1.14 | F7: 2 | G7: =((F7-E7)/F7)*100 & "%" -> 43.% | I7: 24 | K7: =(J7*C7) -> 0 | L7: =(B7+J7-H7) -> 0 | M7: =(D7+K7-I7) -> 0 | N7: =(D7 + K7 - M7) * E7 -> 27.36 | O7: =(I7*F7) -> 48 | P7: =(O7-N7) -> 20.64 | Q7: 8
A8: wafe'up extra | B8: 4 | C8: 24 | D8: =(B8*C8) -> 96 | E8: 1.33 | F8: 2 | G8: =((F8-E8)/F8)*100 & "%" -> 33.5% | H8: 4 | I8: =C8*H8 -> 96 | J8: 0 | K8: =(J8*C8) -> 0 | L8: =(B8+J8-H8) -> 0 | M8: =(D8+K8-I8) -> 0 | N8: =(D8 + K8 - M8) * E8 -> 127.68 | O8: =(I8*F8) -> 192 | P8: =(O8-N8) -> 64.32 | Q8: 8
A9: Today cake | D9: 144 | E9: 1.1 | F9: 2 | G9: =((F9-E9)/F9)*100 & "%" -> 45.% | I9: 10 | K9: =(J9*C9) -> 0 | L9: =(B9+J9-H9) -> 0 | M9: =(D9+K9-I9) -> 134 | N9: =(D9 + K9 - M9) * E9 -> 11 | O9: =(I9*F9) -> 20 | P9: =(O9-N9) -> 9 | Q9: 8
A10: Reflex Fingers | B10: 2 | C10: 24 | D10: =B10*C10 -> 48 | E10: 0.4 | F10: 1 | G10: =((F10-E10)/F10)*100 & "%" -> 60% | H10: 2 | I10: =C10*H10 -> 48 | J10: 0 | K10: =(J10*C10) -> 0 | L10: =(B10+J10-H10) -> 0 | M10: =(D10+K10-I10) -> 0 | N10: =(D10 + K10 - M10) * E10 -> 19.2 | O10: =(I10*F10) -> 48 | P10: =(O10-N10) -> 28.8 | Q10: 8
A11: Wanted chocolate | B11: 1 | C11: 24 | D11: =B11*C11 -> 24 | E11: 1.12 | F11: 2 | G11: =((F11-E11)/F11)*100 & "%" -> 44.% | I11: 24 | K11: =(J11*C11) -> 0 | L11: =(B11+J11-H11) -> 1 | M11: =(D11+K11-I11) -> 0 | N11: =(D11 + K11 - M11) * E11 -> 26.88 | O11: =(I11*F11) -> 48 | P11: =(O11-N11) -> 21.12 | Q11: 8
A12: DrFood | D12: =B12*C12 -> 0 | G12: =((F12-E12)/F12)*100 & "%" -> #DIV/0! | K12: =(J12*C12) -> 0 | L12: =(B12+J12-H12) -> 0 | M12: =(D12+K12-I12) -> 0 | N12: =(D12 + K12 - M12) * E12 -> 0 | O12: =(I12*F12) -> 0 | P12: =(O12-N12) -> 0
A13: Power Chocolate | B13: 1 | C13: 24 | D13: =B13*C13 -> 24 | E13: 1.3 | F13: 2 | G13: =((F13-E13)/F13)*100 & "%" -> 35% | K13: =(J13*C13) -> 0 | L13: =(B13+J13-H13) -> 1 | M13: =(D13+K13-I13) -> 24 | N13: =(D13 + K13 - M13) * E13 -> 0 | O13: =(I13*F13) -> 0 | P13: =(O13-N13) -> 0 | Q13: 8
A14: Adicto Dark | B14: 2 | C14: 24 | D14: =B14*C14 -> 48 | E14: 1.75 | F14: 2 | G14: =((F14-E14)/F14)*100 & "%" -> 12.5% | H14: 2 | I14: =C14*H14 -> 48 | J14: 0 | K14: =(J14*C14) -> 0 | L14: =(B14+J14-H14) -> 0 | M14: =(D14+K14-I14) -> 0 | N14: =(D14 + K14 - M14) * E14 -> 84 | O14: =(I14*F14) -> 96 | P14: =(O14-N14) -> 12 | Q14: 8
A15: Total (8) | G15: =((F15-E15)/F15)*100 & "%" -> #DIV/0! | K15: =(J15*C15) -> 0 | L15: =(B15+J15-H15) -> 0 | M15: =(D15+K15-I15) -> 0 | N15: =sum(N2:N14) -> 1206.68 | O15: =sum(O2:O14) -> 1700 | P15: =sum(P2:P14) -> 493.32
A16: Laviva | B16: 6 | C16: 24 | D16: =B16*C16 -> 144 | E16: 1.77 | F16: 2 | G16: =((F16-E16)/F16)*100 & "%" -> 11.5% | H16: 6 | I16: =C16*H16 -> 144 | K16: =J16*C16 -> 0 | L16: =(B16+J16-H16) -> 0 | M16: =(D16+K16-I16) -> 0 | N16: =(D16 + K16 - M16) * E16 -> 254.88 | O16: =I16*F16 -> 288 | P16: =O16-N16 -> 33.12 | Q16: 9
A17: Laviva | B17: 7 | C17: 24 | D17: =B17*C17 -> 168 | E17: 1.58 | F17: 2 | G17: =((F17-E17)/F17)*100 & "%" -> 21.% | H17: 7 | I17: =C17*H17 -> 168 | K17: =J17*C17 -> 0 | L17: =(B17+J17-H17) -> 0 | M17: =(D17+K17-I17) -> 0 | N17: =(D17 + K17 - M17) * E17 -> 265.44 | O17: =I17*F17 -> 336 | P17: =O17-N17 -> 70.56
A18: Laviva wafer | B18: 1 | C18: 24 | D18: =B18*C18 -> 24 | E18: 1.45 | F18: 2 | G18: =((F18-E18)/F18)*100 & "%" -> 27.5% | H18: 1 | I18: =C18*H18 -> 24 | K18: =J18*C18 -> 0 | L18: =(B18+J18-H18) -> 0 | M18: =(D18+K18-I18) -> 0 | N18: =(D18 + K18 - M18) * E18 -> 34.8 | O18: =I18*F18 -> 48 | P18: =O18-N18 -> 13.2
A19: Crash | B19: 2 | C19: 24 | D19: =B19*C19 -> 48 | E19: 1.29 | F19: 2 | G19: =((F19-E19)/F19)*100 & "%" -> 35.5% | H19: 1 | I19: =C19*H19 -> 24 | K19: =J19*C19 -> 0 | L19: =(B19+J19-H19) -> 1 | M19: =(D19+K19-I19) -> 24 | N19: =(D19 + K19 - M19) * E19 -> 30.96 | O19: =I19*F19 -> 48 | P19: =O19-N19 -> 17.04 | Q19: 9
A20: كيكة دانه | B20: 2 | C20: 50 | D20: =B20*C20 -> 100 | E20: 0.66 | F20: 1 | G20: =((F20-E20)/F20)*100 & "%" -> 34% | H20: 1 | I20: =C20*H20 -> 50 | J20: 0 | K20: =J20*C20 -> 0 | L20: =(B20+J20-H20) -> 1 | M20: =(D20+K20-I20) -> 50 | N20: =(D20 + K20 - M20) * E20 -> 33 | O20: =I20*F20 -> 50 | P20: =O20-N20 -> 17 | Q20: 9
A21: wafe'up extra | B21: 3 | C21: 24 | D21: =B21*C21 -> 72 | E21: 1.37 | F21: 2 | G21: =((F21-E21)/F21)*100 & "%" -> 31.5% | H21: 3 | I21: =C21*H21 -> 72 | K21: =J21*C21 -> 0 | L21: =(B21+J21-H21) -> 0 | M21: =(D21+K21-I21) -> 0 | N21: =(D21 + K21 - M21) * E21 -> 98.64 | O21: =I21*F21 -> 144 | P21: =O21-N21 -> 45.36
A22: Wanted chocolate | B22: 1 | C22: 24 | D22: =B22*C22 -> 24 | E22: 1.166 | F22: 2 | G22: =((F22-E22)/F22)*100 & "%" -> 41.7% | H22: 1 | I22: =C22*H22 -> 24 | K22: =J22*C22 -> 0 | L22: =(B22+J22-H22) -> 0 | M22: =(D22+K22-I22) -> 0 | N22: =(D22 + K22 - M22) * E22 -> 27.984 | O22: =I22*F22 -> 48 | P22: =O22-N22 -> 20.016
A23: Cake Vatile | B23: 2 | C23: 24 | D23: =B23*C23 -> 48 | E23: 0.41 | F23: 1 | G23: =((F23-E23)/F23)*100 & "%" -> 59.% | H23: 2 | I23: =C23*H23 -> 48 | K23: =J23*C23 -> 0 | L23: =(B23+J23-H23) -> 0 | M23: =(D23+K23-I23) -> 0 | N23: =(D23 + K23 - M23) * E23 -> 19.68 | O23: =I23*F23 -> 48 | P23: =O23-N23 -> 28.32
A24: Dounate | B24: 4 | C24: 24 | D24: =B24*C24 -> 96 | E24: 0.41 | F24: 1 | G24: =((F24-E24)/F24)*100 & "%" -> 59.% | H24: 3 | I24: =C24*H24 -> 72 | J24: 0 | K24: =J24*C24 -> 0 | L24: =(B24+J24-H24) -> 1 | M24: =(D24+K24-I24) -> 24 | N24: =(D24 + K24 - M24) * E24 -> 29.52 | O24: =I24*F24 -> 72 | P24: =O24-N24 -> 42.48
A25: fun tom cake | B25: 5 | C25: 24 | D25: =B25*C25 -> 120 | E25: 0.45 | F25: 1 | G25: =((F25-E25)/F25)*100 & "%" -> 55.% | H25: 2 | I25: =C25*H25 -> 48 | K25: =J25*C25 -> 0 | L25: =(B25+J25-H25) -> 3 | M25: =(D25+K25-I25) -> 72 | N25: =(D25 + K25 - M25) * E25 -> 21.6 | O25: =I25*F25 -> 48 | P25: =O25-N25 -> 26.4
A26: brawnie | B26: 2 | C26: 30 | D26: =B26*C26 -> 60 | E26: 0.333 | F26: 1 | G26: =((F26-E26)/F26)*100 & "%" -> 66.7% | H26: 2 | I26: =C26*H26 -> 60 | K26: =J26*C26 -> 0 | L26: =(B26+J26-H26) -> 0 | M26: =(D26+K26-I26) -> 0 | N26: =(D26 + K26 - M26) * E26 -> 19.98 | O26: =I26*F26 -> 60 | P26: =O26-N26 -> 40.02
D27: =B27*C27 -> 0 | G27: =((F27-E27)/F27)*100 & "%" -> #DIV/0! | I27: =C27*H27 -> 0 | K27: =J27*C27 -> 0 | L27: =(B27+J27-H27) -> 0 | M27: =(D27+K27-I27) -> 0 | N27: =(D27 + K27 - M27) * E27 -> 0 | O27: =I27*F27 -> 0 | P27: =O27-N27 -> 0
A28: bella | B28: 2 | C28: 24 | D28: =B28*C28 -> 48 | E28: 0.625 | F28: 1 | G28: =((F28-E28)/F28)*100 & "%" -> 37.5% | I28: =C28*H28 -> 0 | K28: =J28*C28 -> 0 | L28: =(B28+J28-H28) -> 2 | M28: =(D28+K28-I28) -> 48 | N28: =(D28 + K28 - M28) * E28 -> 0 | O28: =I28*F28 -> 0 | P28: =O28-N28 -> 0
B29: 1 | C29: 24 | D29: =B29*C29 -> 24 | E29: 0.7 | F29: 1 | G29: =((F29-E29)/F29)*100 & "%" -> 30.% | H29: 1 | I29: =C29*H29 -> 24 | K29: =J29*C29 -> 0 | L29: =(B29+J29-H29) -> 0 | M29: =(D29+K29-I29) -> 0 | N29: =(D29 + K29 - M29) * E29 -> 16.8 | O29: =I29*F29 -> 24 | P29: =O29-N29 -> 7.2
A30: Total(9) | G30: =((F30-E30)/F30)*100 & "%" -> #DIV/0! | K30: =(J30*C30) -> 0 | L30: =(B30+J30-H30) -> 0 | M30: =(D30+K30-I30) -> 0 | N30: =sum( N16:N29) -> 853.284 | O30: =sum( O16:O29) -> 1214 | P30: =sum( P16:P29) -> 360.716 | Q30: 9
A31: Laviva | B31: 11 | C31: 24 | D31: =B31*C31 -> 264 | E31: 1.54 | F31: 2 | G31: =((F31-E31)/F31)*100 & "%" -> 23% | H31: 11 | I31: =C31*H31 -> 264 | J31: 0 | K31: =(J31*C31) -> 0 | L31: =(B31+J31-H31) -> 0 | M31: =(D31+K31-I31) -> 0 | N31: =(D31 + K31 - M31) * E31 -> 406.56 | O31: =I31*F31 -> 528 | P31: =O31-N31 -> 121.44
A32: wanted | B32: 2 | C32: 24 | D32: =B32*C32 -> 48 | E32: 1.2 | F32: 2 | G32: =((F32-E32)/F32)*100 & "%" -> 40% | H32: 2 | I32: =C32*H32 -> 48 | K32: =(J32*C32) -> 0 | L32: =(B32+J32-H32) -> 0 | M32: =(D32+K32-I32) -> 0 | N32: =(D32 + K32 - M32) * E32 -> 57.6 | O32: =I32*F32 -> 96 | P32: =O32-N32 -> 38.4
A33: wafe'up | B33: 3 | C33: 24 | D33: =B33*C33 -> 72 | E33: 1.37 | F33: 2 | G33: =((F33-E33)/F33)*100 & "%" -> 31.5% | H33: 3 | I33: =C33*H33 -> 72 | J33: 0 | K33: =(J33*C33) -> 0 | L33: =(B33+J33-H33) -> 0 | M33: =(D33+K33-I33) -> 0 | N33: =(D33 + K33 - M33) * E33 -> 98.64 | O33: =I33*F33 -> 144 | P33: =O33-N33 -> 45.36
A34: cake rolles | B34: 1 | C34: 24 | D34: =B34*C34 -> 24 | E34: 0.83 | F34: 1 | G34: =((F34-E34)/F34)*100 & "%" -> 17.% | H34: 1 | I34: =C34*H34 -> 24 | K34: =(J34*C34) -> 0 | L34: =(B34+J34-H34) -> 0 | M34: =(D34+K34-I34) -> 0 | N34: =(D34 + K34 - M34) * E34 -> 19.92 | O34: =I34*F34 -> 24 | P34: =O34-N34 -> 4.08
A35: Dana cake | B35: 1 | C35: 50 | D35: =B35*C35 -> 50 | E35: 0.66 | F35: 1 | G35: =((F35-E35)/F35)*100 & "%" -> 34% | I35: =C35*H35 -> 0 | K35: =(J35*C35) -> 0 | L35: =(B35+J35-H35) -> 1 | M35: =(D35+K35-I35) -> 50 | N35: =(D35 + K35 - M35) * E35 -> 0 | O35: =I35*F35 -> 0 | P35: =O35-N35 -> 0
A36: cake wahat | B36: 6 | C36: 24 | D36: =B36*C36 -> 144 | E36: 0.67 | F36: 1 | G36: =((F36-E36)/F36)*100 & "%" -> 33.% | H36: 6 | I36: =C36*H36 -> 144 | J36: 0 | K36: =(J36*C36) -> 0 | L36: =(B36+J36-H36) -> 0 | M36: =(D36+K36-I36) -> 0 | N36: =(D36 + K36 - M36) * E36 -> 96.48 | O36: =I36*F36 -> 144 | P36: =O36-N36 -> 47.52
A37: cake camar spong | B37: 1 | C37: 24 | D37: =B37*C37 -> 24 | E37: 0.45 | F37: 1 | G37: =((F37-E37)/F37)*100 & "%" -> 55.% | H37: 1 | I37: =C37*H37 -> 24 | K37: =(J37*C37) -> 0 | L37: =(B37+J37-H37) -> 0 | M37: =(D37+K37-I37) -> 0 | N37: =(D37 + K37 - M37) * E37 -> 10.8 | O37: =I37*F37 -> 24 | P37: =O37-N37 -> 13.2
A38: Roshen | B38: 1 | C38: 24 | D38: =B38*C38 -> 24 | E38: 2.5 | F38: 3 | G38: =((F38-E38)/F38)*100 & "%" -> 16.6666666666667% | H38: 1 | I38: =C38*H38 -> 24 | K38: =(J38*C38) -> 0 | L38: =(B38+J38-H38) -> 0 | M38: =(D38+K38-I38) -> 0 | N38: =(D38 + K38 - M38) * E38 -> 60 | O38: =I38*F38 -> 72 | P38: =O38-N38 -> 12
A39: TOtal(12) | D39: =B39*C39 -> 0 | G39: =((F39-E39)/F39)*100 & "%" -> #DIV/0! | I39: =C39*H39 -> 0 | K39: =(J39*C39) -> 0 | L39: =(B39+J39-H39) -> 0 | M39: =(D39+K39-I39) -> 0 | N39: =sum(N31:N38) -> 750 | O39: =sum(O31:O38) -> 1032 | P39: =sum(P31:P38) -> 282
D40: =B40*C40 -> 0 | G40: =((F40-E40)/F40)*100 & "%" -> #DIV/0! | I40: =C40*H40 -> 0 | K40: =(J40*C40) -> 0 | L40: =(B40+J40-H40) -> 0 | M40: =(D40+K40-I40) -> 0 | N40: =(D40 + K40 - M40) * E40 -> 0 | O40: =I40*F40 -> 0 | P40: =O40-N40 -> 0
A41: Total 2024 | D41: =B41*C41 -> 0 | I41: =C41*H41 -> 0 | K41: =(C41*J41) -> 0 | L41: =(B41+$J$14)-H41 -> 0 | M41: =(D41+K41)-I41 -> 0 | N41: =SUM(N15+N30+N39) -> 2809.964 | O41: =SUM(O15+O30+O39) -> 3946 | P41: =SUM(P15+P30+P39) -> 1136.036
D42: =B42*C42 -> 0 | I42: =C42*H42 -> 0
A43: Roshen | B43: 2 | C43: 24 | D43: =B43*C43 -> 48 | E43: 2.5 | F43: 3 | G43: =((F43-E43)/F43)*100 & "%" -> 16.6666666666667% | H43: 1 | I43: =C43*H43 -> 24 | J43: 0 | K43: =(J43*C43) -> 0 | L43: =(B43+J43-H43) -> 1 | M43: =(D43+K43-I43) -> 24 | N43: =(D43 + K43 - M43) * E43 -> 60 | O43: =I43*F43 -> 72 | P43: =O43-N43 -> 12
A44: chocolate flick flack | B44: 2 | C44: 24 | D44: =B44*C44 -> 48 | E44: 0.42 | F44: 1 | G44: =((F44-E44)/F44)*100 & "%" -> 58.% | I44: =C44*H44 -> 0 | K44: =(J44*C44) -> 0 | L44: =(B44+J44-H44) -> 2 | M44: =(D44+K44-I44) -> 48 | N44: =(D44 + K44 - M44) * E44 -> 0 | O44: =I44*F44 -> 0 | P44: =O44-N44 -> 0
A45: cake ono | B45: 12 | C45: 24 | D45: =B45*C45 -> 288 | E45: 0.45 | F45: 1 | G45: =((F45-E45)/F45)*100 & "%" -> 55.% | H45: 10 | I45: =C45*H45 -> 240 | J45: 0 | K45: =(J45*C45) -> 0 | L45: =(B45+J45-H45) -> 2 | M45: =(D45+K45-I45) -> 48 | N45: =(D45 + K45 - M45) * E45 -> 108 | O45: =I45*F45 -> 240 | P45: =O45-N45 -> 132
A46: vimto candy | B46: 3 | C46: 12 | D46: =B46*C46 -> 36 | E46: 1.8 | F46: 3 | G46: =((F46-E46)/F46)*100 & "%" -> 40% | H46: 2 | I46: =C46*H46 -> 24 | J46: 0 | K46: =(J46*C46) -> 0 | L46: =(B46+J46-H46) -> 1 | M46: =(D46+K46-I46) -> 12 | N46: =(D46 + K46 - M46) * E46 -> 43.2 | O46: =I46*F46 -> 72 | P46: =O46-N46 -> 28.8
A47: nileno | B47: 1 | C47: 24 | D47: =B47*C47 -> 24 | E47: 2.7 | F47: 3 | G47: =((F47-E47)/F47)*100 & "%" -> 9.99999999999999% | I47: =C47*H47 -> 0 | K47: =(J47*C47) -> 0 | L47: =(B47+J47-H47) -> 1 | M47: =(D47+K47-I47) -> 24 | N47: =(D47 + K47 - M47) * E47 -> 0 | O47: =I47*F47 -> 0 | P47: =O47-N47 -> 0
A48: Gerdena | B48: 2 | C48: 25 | D48: =B48*C48 -> 50 | E48: 3 | F48: 5 | G48: =((F48-E48)/F48)*100 & "%" -> 40% | H48: 1 | I48: =C48*H48 -> 25 | K48: =(J48*C48) -> 0 | L48: =(B48+J48-H48) -> 1 | M48: =(D48+K48-I48) -> 25 | N48: =(D48 + K48 - M48) * E48 -> 75 | O48: =I48*F48 -> 125 | P48: =O48-N48 -> 50
A49: wafer loacker | B49: 1 | C49: 30 | D49: =B49*C49 -> 30 | E49: 1.9 | F49: 3 | G49: =((F49-E49)/F49)*100 & "%" -> 36.6666666666667% | I49: =C49*H49 -> 0 | K49: =(J49*C49) -> 0 | L49: =(B49+J49-H49) -> 1 | M49: =(D49+K49-I49) -> 30 | N49: =(D49 + K49 - M49) * E49 -> 0 | O49: =I49*F49 -> 0 | P49: =O49-N49 -> 0
A50: mr bite | B50: 3 | C50: 24 | D50: =B50*C50 -> 72 | E50: 1.25 | F50: 2 | G50: =((F50-E50)/F50)*100 & "%" -> 37.5% | H50: 2 | I50: =C50*H50 -> 48 | J50: 0 | K50: =(J50*C50) -> 0 | L50: =(B50+J50-H50) -> 1 | M50: =(D50+K50-I50) -> 24 | N50: =(D50 + K50 - M50) * E50 -> 60 | O50: =I50*F50 -> 96 | P50: =O50-N50 -> 36
A51: Laviva | B51: 11 | C51: 24 | D51: =B51*C51 -> 264 | E51: 1.54 | F51: 2 | G51: =((F51-E51)/F51)*100 & "%" -> 23% | H51: 9 | I51: =C51*H51 -> 216 | J51: 0 | K51: =(J51*C51) -> 0 | L51: =(B51+J51-H51) -> 2 | M51: =(D51+K51-I51) -> 48 | N51: =(D51 + K51 - M51) * E51 -> 332.64 | O51: =I51*F51 -> 432 | P51: =O51-N51 -> 99.36
A52: wafe'up | B52: 3 | C52: 24 | D52: =B52*C52 -> 72 | E52: 1.33 | F52: 2 | G52: =((F52-E52)/F52)*100 & "%" -> 33.5% | H52: 2 | I52: =C52*H52 -> 48 | J52: 0 | K52: =(J52*C52) -> 0 | L52: =(B52+J52-H52) -> 1 | M52: =(D52+K52-I52) -> 24 | N52: =(D52 + K52 - M52) * E52 -> 63.84 | O52: =I52*F52 -> 96 | P52: =O52-N52 -> 32.16
A53: total 1 (2025) | D53: =B53*C53 -> 0 | G53: =((F53-E53)/F53)*100 & "%" -> #DIV/0! | I53: =C53*H53 -> 0 | K53: =(J53*C53) -> 0 | L53: =(B53+J53-H53) -> 0 | M53: =(D53+K53-I53) -> 0 | N53: =sum( N43:N52) -> 742.68 | O53: =sum( O43:O52) -> 1133 | P53: =sum( P43:P52) -> 390.32
A54: vivaldia | B54: 1 | C54: 24 | D54: =B54*C54 -> 24 | E54: 0.91 | F54: 2 | G54: =((F54-E54)/F54)*100 & "%" -> 54.5% | H54: 1 | I54: =C54*H54 -> 24 | K54: =(J54*C54) -> 0 | L54: =(B54+J54-H54) -> 0 | M54: =(D54+K54-I54) -> 0 | N54: =(D54 + K54 - M54) * E54 -> 21.84 | O54: =I54*F54 -> 48 | P54: =O54-N54 -> 26.16
A55: mr bite | B55: 5 | C55: 24 | D55: =B55*C55 -> 120 | E55: 1.12 | F55: 2 | G55: =((F55-E55)/F55)*100 & "%" -> 44.% | H55: 5 | I55: =C55*H55 -> 120 | J55: 0 | K55: =(J55*C55) -> 0 | L55: =(B55+J55-H55) -> 0 | M55: =(D55+K55-I55) -> 0 | N55: =(D55 + K55 - M55) * E55 -> 134.4 | O55: =I55*F55 -> 240 | P55: =O55-N55 -> 105.6
A56: marshmello | B56: 1 | C56: 12 | D56: =B56*C56 -> 12 | E56: 1.83 | F56: 3 | G56: =((F56-E56)/F56)*100 & "%" -> 39.% | H56: 1 | I56: =C56*H56 -> 12 | K56: =(J56*C56) -> 0 | L56: =(B56+J56-H56) -> 0 | M56: =(D56+K56-I56) -> 0 | N56: =(D56 + K56 - M56) * E56 -> 21.96 | O56: =I56*F56 -> 36 | P56: =O56-N56 -> 14.04
A57: kinder bueno | B57: 3 | C57: 30 | D57: =B57*C57 -> 90 | E57: 3.86 | F57: 5 | G57: =((F57-E57)/F57)*100 & "%" -> 22.8% | H57: 3 | I57: =C57*H57 -> 90 | K57: =(J57*C57) -> 0 | L57: =(B57+J57-H57) -> 0 | M57: =(D57+K57-I57) -> 0 | N57: =(D57 + K57 - M57) * E57 -> 347.4 | O57: =I57*F57 -> 450 | P57: =O57-N57 -> 102.6
A58: kinder country | B58: 1 | C58: 40 | D58: =B58*C58 -> 40 | E58: 1.5 | F58: 3 | G58: =((F58-E58)/F58)*100 & "%" -> 50% | H58: 1 | I58: =C58*H58 -> 40 | K58: =(J58*C58) -> 0 | L58: =(B58+J58-H58) -> 0 | M58: =(D58+K58-I58) -> 0 | N58: =(D58 + K58 - M58) * E58 -> 60 | O58: =I58*F58 -> 120 | P58: =O58-N58 -> 60
A59: m&m | B59: 3 | C59: 24 | D59: =B59*C59 -> 72 | E59: 2.41 | F59: 4 | G59: =((F59-E59)/F59)*100 & "%" -> 39.75% | H59: 3 | I59: =C59*H59 -> 72 | J59: 0 | K59: =(J59*C59) -> 0 | L59: =(B59+J59-H59) -> 0 | M59: =(D59+K59-I59) -> 0 | N59: =(D59 + K59 - M59) * E59 -> 173.52 | O59: =I59*F59 -> 288 | P59: =O59-N59 -> 114.48
A60: skittles | B60: 3 | C60: 14 | D60: =B60*C60 -> 42 | E60: 3 | F60: 4 | G60: =((F60-E60)/F60)*100 & "%" -> 25% | H60: 3 | I60: =C60*H60 -> 42 | K60: =(J60*C60) -> 0 | L60: =(B60+J60-H60) -> 0 | M60: =(D60+K60-I60) -> 0 | N60: =(D60 + K60 - M60) * E60 -> 126 | O60: =I60*F60 -> 168 | P60: =O60-N60 -> 42
A61: kitkat | B61: 1 | C61: 24 | D61: =B61*C61 -> 24 | E61: 2 | F61: 3 | G61: =((F61-E61)/F61)*100 & "%" -> 33.3333333333333% | H61: 1 | I61: =C61*H61 -> 24 | K61: =(J61*C61) -> 0 | L61: =(B61+J61-H61) -> 0 | M61: =(D61+K61-I61) -> 0 | N61: =(D61 + K61 - M61) * E61 -> 48 | O61: =I61*F61 -> 72 | P61: =O61-N61 -> 24
A62: vimto candy | B62: 2 | C62: 12 | D62: =B62*C62 -> 24 | E62: 0.91 | F62: 3 | G62: =((F62-E62)/F62)*100 & "%" -> 69.6666666666667% | H62: 2 | I62: =C62*H62 -> 24 | K62: =(J62*C62) -> 0 | L62: =(B62+J62-H62) -> 0 | M62: =(D62+K62-I62) -> 0 | N62: =(D62 + K62 - M62) * E62 -> 21.84 | O62: =I62*F62 -> 72 | P62: =O62-N62 -> 50.16
A63: bonart sweet | B63: 4 | C63: 12 | D63: =B63*C63 -> 48 | E63: 2.83 | F63: 4 | G63: =((F63-E63)/F63)*100 & "%" -> 29.25% | H63: 4 | I63: =C63*H63 -> 48 | J63: 0 | K63: =(J63*C63) -> 0 | L63: =(B63+J63-H63) -> 0 | M63: =(D63+K63-I63) -> 0 | N63: =(D63 + K63 - M63) * E63 -> 135.84 | O63: =I63*F63 -> 192 | P63: =O63-N63 -> 56.16
A64: helo kitty | B64: 1 | C64: 12 | D64: =B64*C64 -> 12 | E64: 4.42 | F64: 6 | G64: =((F64-E64)/F64)*100 & "%" -> 26.3333333333333% | H64: 1 | I64: =C64*H64 -> 12 | K64: =(J64*C64) -> 0 | L64: =(B64+J64-H64) -> 0 | M64: =(D64+K64-I64) -> 0 | N64: =(D64 + K64 - M64) * E64 -> 53.04 | O64: =I64*F64 -> 72 | P64: =O64-N64 -> 18.96
A65: flik flak | B65: 19 | C65: 24 | D65: =B65*C65 -> 456 | E65: 0.42 | F65: 1 | G65: =((F65-E65)/F65)*100 & "%" -> 58.% | H65: 19 | I65: =C65*H65 -> 456 | J65: 0 | K65: =(J65*C65) -> 0 | L65: =(B65+J65-H65) -> 0 | M65: =(D65+K65-I65) -> 0 | N65: =(D65 + K65 - M65) * E65 -> 191.52 | O65: =I65*F65 -> 456 | P65: =O65-N65 -> 264.48
A66: wafe up | B66: 1 | C66: 24 | D66: =B66*C66 -> 24 | E66: 1.37 | F66: 2 | G66: =((F66-E66)/F66)*100 & "%" -> 31.5% | H66: 1 | I66: =C66*H66 -> 24 | K66: =(J66*C66) -> 0 | L66: =(B66+J66-H66) -> 0 | M66: =(D66+K66-I66) -> 0 | N66: =(D66 + K66 - M66) * E66 -> 32.88 | O66: =I66*F66 -> 48 | P66: =O66-N66 -> 15.12
A67: total 2 (2025) | D67: =B67*C67 -> 0 | G67: =((F67-E67)/F67)*100 & "%" -> #DIV/0! | I67: =C67*H67 -> 0 | K67: =(J67*C67) -> 0 | L67: =(B67+J67-H67) -> 0 | M67: =(D67+K67-I67) -> 0 | N67: =sum( N54:N66) -> 1368.24 | O67: =sum( O54:O66) -> 2262 | P67: =sum( P54:P66) -> 893.76
A68: bonart sweet | B68: 7 | C68: 12 | D68: =B68*C68 -> 84 | E68: 2.83 | F68: 5 | G68: =((F68-E68)/F68)*100 & "%" -> 43.4% | H68: 7 | I68: =C68*H68 -> 84 | J68: 0 | K68: =(J68*C68) -> 0 | L68: =(B68+J68-H68) -> 0 | M68: =(D68+K68-I68) -> 0 | N68: =(D68 + K68 - M68) * E68 -> 237.72 | O68: =I68*F68 -> 420 | P68: =O68-N68 -> 182.28
A69: helo kitty | B69: 2 | C69: 12 | D69: =B69*C69 -> 24 | E69: 4.42 | F69: 6 | G69: =((F69-E69)/F69)*100 & "%" -> 26.3333333333333% | H69: 2 | I69: =C69*H69 -> 24 | K69: =(J69*C69) -> 0 | L69: =(B69+J69-H69) -> 0 | M69: =(D69+K69-I69) -> 0 | N69: =(D69 + K69 - M69) * E69 -> 106.08 | O69: =I69*F69 -> 144 | P69: =O69-N69 -> 37.92
A70: jelly | B70: 2 | C70: 12 | D70: =B70*C70 -> 24 | E70: 1.83 | F70: 3 | G70: =((F70-E70)/F70)*100 & "%" -> 39.% | H70: 2 | I70: =C70*H70 -> 24 | K70: =(J70*C70) -> 0 | L70: =(B70+J70-H70) -> 0 | M70: =(D70+K70-I70) -> 0 | N70: =(D70 + K70 - M70) * E70 -> 43.92 | O70: =I70*F70 -> 72 | P70: =O70-N70 -> 28.08
A71: flik flak | B71: 22 | C71: 24 | D71: =B71*C71 -> 528 | E71: 0.42 | F71: 1 | G71: =((F71-E71)/F71)*100 & "%" -> 58.% | H71: 22 | I71: =C71*H71 -> 528 | J71: 0 | K71: =(J71*C71) -> 0 | L71: =(B71+J71-H71) -> 0 | M71: =(D71+K71-I71) -> 0 | N71: =(D71 + K71 - M71) * E71 -> 221.76 | O71: =I71*F71 -> 528 | P71: =O71-N71 -> 306.24
A72: doubla | B72: 1 | C72: 24 | D72: =B72*C72 -> 24 | E72: 2.9 | F72: 4 | G72: =((F72-E72)/F72)*100 & "%" -> 27.5% | I72: =C72*H72 -> 0 | K72: =(J72*C72) -> 0 | L72: =(B72+J72-H72) -> 1 | M72: =(D72+K72-I72) -> 24 | N72: =(D72 + K72 - M72) * E72 -> 0 | O72: =I72*F72 -> 0 | P72: =O72-N72 -> 0
A73: m&m | B73: 1 | C73: 24 | D73: =B73*C73 -> 24 | E73: 2.41 | F73: 4 | G73: =((F73-E73)/F73)*100 & "%" -> 39.75% | H73: 1 | I73: =C73*H73 -> 24 | J73: 0 | K73: =(J73*C73) -> 0 | L73: =(B73+J73-H73) -> 0 | M73: =(D73+K73-I73) -> 0 | N73: =(D73 + K73 - M73) * E73 -> 57.84 | O73: =I73*F73 -> 96 | P73: =O73-N73 -> 38.16
A74: skittles | B74: 6 | C74: 14 | D74: =B74*C74 -> 84 | E74: 3 | F74: 4 | G74: =((F74-E74)/F74)*100 & "%" -> 25% | H74: 6 | I74: =C74*H74 -> 84 | J74: 0 | K74: =(J74*C74) -> 0 | L74: =(B74+J74-H74) -> 0 | M74: =(D74+K74-I74) -> 0 | N74: =(D74 + K74 - M74) * E74 -> 252 | O74: =I74*F74 -> 336 | P74: =O74-N74 -> 84
A75: kinder bueno | B75: 2 | C75: 30 | D75: =B75*C75 -> 60 | E75: 3.83 | F75: 5 | G75: =((F75-E75)/F75)*100 & "%" -> 23.4% | H75: 2 | I75: =C75*H75 -> 60 | K75: =(J75*C75) -> 0 | L75: =(B75+J75-H75) -> 0 | M75: =(D75+K75-I75) -> 0 | N75: =(D75 + K75 - M75) * E75 -> 229.8 | O75: =I75*F75 -> 300 | P75: =O75-N75 -> 70.2
A76: kinder bueno | B76: 3 | C76: 30 | D76: =B76*C76 -> 90 | E76: 3.93 | F76: 5 | G76: =((F76-E76)/F76)*100 & "%" -> 21.4% | H76: 3 | I76: =C76*H76 -> 90 | J76: 0 | K76: =(J76*C76) -> 0 | L76: =(B76+J76-H76) -> 0 | M76: =(D76+K76-I76) -> 0 | N76: =(D76 + K76 - M76) * E76 -> 353.7 | O76: =I76*F76 -> 450 | P76: =O76-N76 -> 96.3
A77: wafe up | B77: 4 | C77: 24 | D77: =B77*C77 -> 96 | E77: 1.37 | F77: 2 | G77: =((F77-E77)/F77)*100 & "%" -> 31.5% | H77: 4 | I77: =C77*H77 -> 96 | J77: 0 | K77: =(J77*C77) -> 0 | L77: =(B77+J77-H77) -> 0 | M77: =(D77+K77-I77) -> 0 | N77: =(D77 + K77 - M77) * E77 -> 131.52 | O77: =I77*F77 -> 192 | P77: =O77-N77 -> 60.48
A78: Gerdena | B78: 1 | C78: 25 | D78: =B78*C78 -> 25 | E78: 2.76 | F78: 4 | G78: =((F78-E78)/F78)*100 & "%" -> 31.% | H78: 1 | I78: =C78*H78 -> 25 | K78: =(J78*C78) -> 0 | L78: =(B78+J78-H78) -> 0 | M78: =(D78+K78-I78) -> 0 | N78: =(D78 + K78 - M78) * E78 -> 69 | O78: =I78*F78 -> 100 | P78: =O78-N78 -> 31
A79: laviva | B79: 2 | C79: 24 | D79: =B79*C79 -> 48 | E79: 1.79 | F79: 3 | G79: =((F79-E79)/F79)*100 & "%" -> 40.3333333333333% | H79: 2 | I79: =C79*H79 -> 48 | J79: 0 | K79: =(J79*C79) -> 0 | L79: =(B79+J79-H79) -> 0 | M79: =(D79+K79-I79) -> 0 | N79: =(D79 + K79 - M79) * E79 -> 85.92 | O79: =I79*F79 -> 144 | P79: =O79-N79 -> 58.08
A80: mr bite | B80: 4 | C80: 24 | D80: =B80*C80 -> 96 | E80: 1.12 | F80: 2 | G80: =((F80-E80)/F80)*100 & "%" -> 44.% | H80: 4 | I80: =C80*H80 -> 96 | J80: 0 | K80: =(J80*C80) -> 0 | L80: =(B80+J80-H80) -> 0 | M80: =(D80+K80-I80) -> 0 | N80: =(D80 + K80 - M80) * E80 -> 107.52 | O80: =I80*F80 -> 192 | P80: =O80-N80 -> 84.48
A81: kitkat | B81: 1 | C81: 24 | D81: =B81*C81 -> 24 | E81: 2.58 | F81: 3 | G81: =((F81-E81)/F81)*100 & "%" -> 14.% | H81: 1 | I81: =C81*H81 -> 24 | K81: =(J81*C81) -> 0 | L81: =(B81+J81-H81) -> 0 | M81: =(D81+K81-I81) -> 0 | N81: =(D81 + K81 - M81) * E81 -> 61.92 | O81: =I81*F81 -> 72 | P81: =O81-N81 -> 10.08
A82: kitkat | B82: 1 | C82: 24 | D82: =B82*C82 -> 24 | E82: 2.58 | F82: 4 | G82: =((F82-E82)/F82)*100 & "%" -> 35.5% | H82: 0 | I82: =C82*H82 -> 0 | J82: 0 | K82: =(J82*C82) -> 0 | L82: =(B82+J82-H82) -> 1 | M82: =(D82+K82-I82) -> 24 | N82: =(D82 + K82 - M82) * E82 -> 0 | O82: =I82*F82 -> 0 | P82: =O82-N82 -> 0
A83: kinder bones | B83: 7 | C83: 8 | D83: =B83*C83 -> 56 | E83: 3.33 | F83: 5 | G83: =((F83-E83)/F83)*100 & "%" -> 33.4% | H83: 7 | I83: =C83*H83 -> 56 | K83: =(J83*C83) -> 0 | L83: =(B83+J83-H83) -> 0 | M83: =(D83+K83-I83) -> 0 | N83: =(D83 + K83 - M83) * E83 -> 186.48 | O83: =I83*F83 -> 280 | P83: =O83-N83 -> 93.52
A84: total 3 (2025) | D84: =B84*C84 -> 0 | G84: =((F84-E84)/F84)*100 & "%" -> #DIV/0! | I84: =C84*H84 -> 0 | K84: =(J84*C84) -> 0 | L84: =(B84+J84-H84) -> 0 | M84: =(D84+K84-I84) -> 0 | N84: =sum( N68:N83) -> 2145.18 | O84: =sum( O68:O83) -> 3326 | P84: =sum( P68:P83) -> 1180.82
A85: laviva | B85: 3 | C85: 24 | D85: =B85*C85 -> 72 | E85: 1.79 | F85: 3 | G85: =((F85-E85)/F85)*100 & "%" -> 40.3333333333333% | I85: =C85*H85 -> 0 | J85: 0 | K85: =(J85*C85) -> 0 | L85: =(B85+J85-H85) -> 3 | M85: =(D85+K85-I85) -> 72 | N85: =(D85 + K85 - M85) * E85 -> 0 | O85: =I85*F85 -> 0 | P85: =O85-N85 -> 0
A86: mr bite | B86: 4 | C86: 24 | D86: =B86*C86 -> 96 | E86: 1.12 | F86: 2 | G86: =((F86-E86)/F86)*100 & "%" -> 44.% | I86: =C86*H86 -> 0 | J86: 0 | K86: =(J86*C86) -> 0 | L86: =(B86+J86-H86) -> 4 | M86: =(D86+K86-I86) -> 96 | N86: =(D86 + K86 - M86) * E86 -> 0 | O86: =I86*F86 -> 0 | P86: =O86-N86 -> 0
A87: snickers | B87: 1 | C87: 40 | D87: =B87*C87 -> 40 | E87: 3.12 | F87: 4 | G87: =((F87-E87)/F87)*100 & "%" -> 22.% | I87: =C87*H87 -> 0 | K87: =(J87*C87) -> 0 | L87: =(B87+J87-H87) -> 1 | M87: =(D87+K87-I87) -> 40 | N87: =(D87 + K87 - M87) * E87 -> 0 | O87: =I87*F87 -> 0 | P87: =O87-N87 -> 0
A88: snickers | B88: 1 | C88: 40 | D88: =B88*C88 -> 40 | E88: 4.12 | F88: 5 | G88: =((F88-E88)/F88)*100 & "%" -> 17.6% | I88: =C88*H88 -> 0 | K88: =(J88*C88) -> 0 | L88: =(B88+J88-H88) -> 1 | M88: =(D88+K88-I88) -> 40 | N88: =(D88 + K88 - M88) * E88 -> 0 | O88: =I88*F88 -> 0 | P88: =O88-N88 -> 0
A89: marshmello | B89: 3 | C89: 12 | D89: =B89*C89 -> 36 | E89: 1.83 | F89: 3 | G89: =((F89-E89)/F89)*100 & "%" -> 39.% | I89: =C89*H89 -> 0 | K89: =(J89*C89) -> 0 | L89: =(B89+J89-H89) -> 3 | M89: =(D89+K89-I89) -> 36 | N89: =(D89 + K89 - M89) * E89 -> 0 | O89: =I89*F89 -> 0 | P89: =O89-N89 -> 0
A90: wafe up | B90: 3 | C90: 24 | D90: =B90*C90 -> 72 | E90: 1.37 | F90: 2 | G90: =((F90-E90)/F90)*100 & "%" -> 31.5% | I90: =C90*H90 -> 0 | J90: 0 | K90: =(J90*C90) -> 0 | L90: =(B90+J90-H90) -> 3 | M90: =(D90+K90-I90) -> 72 | N90: =(D90 + K90 - M90) * E90 -> 0 | O90: =I90*F90 -> 0 | P90: =O90-N90 -> 0
A91: wafe up | B91: 2 | C91: 24 | D91: =B91*C91 -> 48 | E91: 1.75 | F91: 3 | G91: =((F91-E91)/F91)*100 & "%" -> 41.6666666666667% | I91: =C91*H91 -> 0 | J91: 0 | K91: =(J91*C91) -> 0 | L91: =(B91+J91-H91) -> 2 | M91: =(D91+K91-I91) -> 48 | N91: =(D91 + K91 - M91) * E91 -> 0 | O91: =I91*F91 -> 0 | P91: =O91-N91 -> 0
A92: skittles | B92: 9 | C92: 14 | D92: =B92*C92 -> 126 | E92: 3 | F92: 5 | G92: =((F92-E92)/F92)*100 & "%" -> 40% | I92: =C92*H92 -> 0 | J92: 0 | K92: =(J92*C92) -> 0 | L92: =(B92+J92-H92) -> 9 | M92: =(D92+K92-I92) -> 126 | N92: =(D92 + K92 - M92) * E92 -> 0 | O92: =I92*F92 -> 0 | P92: =O92-N92 -> 0
A93: skittles | B93: 1 | C93: 14 | D93: =B93*C93 -> 14 | E93: 3.5 | F93: 5 | G93: =((F93-E93)/F93)*100 & "%" -> 30% | I93: =C93*H93 -> 0 | J93: 0 | K93: =(J93*C93) -> 0 | L93: =(B93+J93-H93) -> 1 | M93: =(D93+K93-I93) -> 14 | N93: =(D93 + K93 - M93) * E93 -> 0 | O93: =I93*F93 -> 0 | P93: =O93-N93 -> 0
A94: bonart sweet | B94: 18 | C94: 12 | D94: =B94*C94 -> 216 | E94: 2.83 | F94: 5 | G94: =((F94-E94)/F94)*100 & "%" -> 43.4% | I94: =C94*H94 -> 0 | J94: 0 | K94: =(J94*C94) -> 0 | L94: =(B94+J94-H94) -> 18 | M94: =(D94+K94-I94) -> 216 | N94: =(D94 + K94 - M94) * E94 -> 0 | O94: =I94*F94 -> 0 | P94: =O94-N94 -> 0
A95: helo kitty | B95: 3 | C95: 12 | D95: =B95*C95 -> 36 | E95: 4.42 | F95: 6 | G95: =((F95-E95)/F95)*100 & "%" -> 26.3333333333333% | I95: =C95*H95 -> 0 | J95: 0 | K95: =(J95*C95) -> 0 | L95: =(B95+J95-H95) -> 3 | M95: =(D95+K95-I95) -> 36 | N95: =(D95 + K95 - M95) * E95 -> 0 | O95: =I95*F95 -> 0 | P95: =O95-N95 -> 0
A96: flik flak | B96: 34 | C96: 24 | D96: =B96*C96 -> 816 | E96: 0.42 | F96: 1 | G96: =((F96-E96)/F96)*100 & "%" -> 58.% | I96: =C96*H96 -> 0 | J96: 0 | K96: =(J96*C96) -> 0 | L96: =(B96+J96-H96) -> 34 | M96: =(D96+K96-I96) -> 816 | N96: =(D96 + K96 - M96) * E96 -> 0 | O96: =I96*F96 -> 0 | P96: =O96-N96 -> 0
A97: kinder bueno | B97: 3 | C97: 30 | D97: =B97*C97 -> 90 | E97: 3.93 | F97: 5 | G97: =((F97-E97)/F97)*100 & "%" -> 21.4% | I97: =C97*H97 -> 0 | J97: 0 | K97: =(J97*C97) -> 0 | L97: =(B97+J97-H97) -> 3 | M97: =(D97+K97-I97) -> 90 | N97: =(D97 + K97 - M97) * E97 -> 0 | O97: =I97*F97 -> 0 | P97: =O97-N97 -> 0
A98: m&m | B98: 1 | C98: 24 | D98: =B98*C98 -> 24 | E98: 3.2 | F98: 4 | G98: =((F98-E98)/F98)*100 & "%" -> 20.% | I98: =C98*H98 -> 0 | J98: 0 | K98: =(J98*C98) -> 0 | L98: =(B98+J98-H98) -> 1 | M98: =(D98+K98-I98) -> 24 | N98: =(D98 + K98 - M98) * E98 -> 0 | O98: =I98*F98 -> 0 | P98: =O98-N98 -> 0
A99: kitkat | B99: 1 | C99: 24 | D99: =B99*C99 -> 24 | E99: 2.58 | F99: 4 | G99: =((F99-E99)/F99)*100 & "%" -> 35.5% | H99: 0 | I99: =C99*H99 -> 0 | J99: 0 | K99: =(J99*C99) -> 0 | L99: =(B99+J99-H99) -> 1 | M99: =(D99+K99-I99) -> 24 | N99: =(D99 + K99 - M99) * E99 -> 0 | O99: =I99*F99 -> 0 | P99: =O99-N99 -> 0
A100: twix | B100: 1 | C100: 20 | D100: =B100*C100 -> 20 | E100: 0.5 | F100: 1 | G100: =((F100-E100)/F100)*100 & "%" -> 50% | I100: =C100*H100 -> 0 | K100: =(J100*C100) -> 0 | L100: =(B100+J100-H100) -> 1 | M100: =(D100+K100-I100) -> 20 | N100: =(D100 + K100 - M100) * E100 -> 0 | O100: =I100*F100 -> 0 | P100: =O100-N100 -> 0
...

Sheet Product Master
A1: Product Name | B1: Category | C1: Unit Cost | D1: Selling Price | E1: Pack Size | F1: Margin | G1: Effective Date
A2: Water | B2: Drink | C2: 0.3 | D2: 1 | E2: 12 | G2: 0
A3: Green | B3: Drink | C3: 2.58 | D3: 3 | E3: 24 | G3: 0
A4: X!R | B4: Drink | C4: 2.91 | D4: 4 | E4: 24 | G4: 0
A5: King | B5: Drink | C5: 1.75 | D5: 2 | E5: 24 | G5: 0
A6: Power | B6: Drink | C6: 2.5 | D6: 3 | E6: 24 | G6: 0
A7: Mogu Mogu | B7: Drink | C7: 8.54 | D7: 10 | E7: 24 | G7: 0
A8: Water | B8: Drink | C8: 0.33 | D8: 1 | E8: 12 | G8: 0
A9: Green | B9: Drink | C9: 2.58 | D9: 3 | E9: 24 | G9: 0
A10: X!R | B10: Drink | C10: 2.83 | D10: 4 | E10: 24 | G10: 0
A11: King | B11: Drink | C11: 1.75 | D11: 2 | E11: 24 | G11: 0
A12: Power | B12: Drink | C12: 2.5 | D12: 3 | E12: 24 | G12: 0
A13: سن توب سعودي | B13: Drink | C13: 0.6 | D13: 1 | E13: 24 | G13: 0
... A21: X!R Mojito | B21: Drink | C21: 2.95 | D21: 4 | E21: 24 | G21: 0
A22: Total (9) | C22: 0 | D22: 0 | E22: 0 | G22: 0
A23: sunTop Saudi | B23: Drink | C23: 0.6 | D23: 1 | E23: 24 | G23: 0
A24: X!R | B24: Drink | C24: 2.91 | D24: 4 | E24: 24 | G24: 0
A25: X!R 500ml | B25: Drink | C25: 4.45 | D25: 6 | E25: 24 | G25: 0
A26: Power | B26: Drink | C26: 2.5 | D26: 3 | E26: 24 | G26: 0
A27: Power 500ml | B27: Drink | C27: 3.66 | D27: 5 | E27: 24 | G27: 0
A28: Green | B28: Drink | C28: 2.7 | D28: 4 | E28: 24 | G28: 0
A29: sunTop Masa | B29: Drink | C29: 0.45 | D29: 1 | E29: 24 | G29: 0
A30: water | B30: Drink | C30: 0.3 | D30: 1 | E30: 12 | G30: 0
A31: freez | B31: Drink | C31: 3.75 | D31: 5 | E31: 24 | G31: 0
A32: Total (12) | C32: 0 | D32: 0 | E32: 0 | G32: 0
A33: Total 2024 | C33: 0 | D33: 0 | E33: 0 | G33: 0
A34: water | B34: Drink | C34: 0.29 | D34: 1 | E34: 12 | G34: 0
A35: Green | B35: Drink | C35: 2.66 | D35: 4 | E35: 24 | G35: 0
A36: Green | B36: Drink | C36: 2.7 | D36: 4 | E36: 24 | G36: 0
A37: freez lower price | B37: Drink | C37: 3.41 | D37: 5 | E37: 24 | G37: 0
A38: freez | B38: Drink | C38: 3.75 | D38: 5 | E38: 24 | G38: 0
A39: suntop | B39: Drink | C39: 0.6 | D39: 1 | E39: 24 | G39: 0
A40: masa suntop | B40: Drink | C40: 0.45 | D40: 1 | E40: 24 | G40: 0
A41: dark blue | B41: Drink | C41: 2.17 | D41: 3 | E41: 24 | G41: 0
A42: al ain can | B42: Drink | C42: 1.91 | D42: 3 | E42: 24 | G42: 0
A43: x!r | B43: Drink | C43: 2.83 | D43: 4 | E43: 24 | G43: 0
A44: power 500ml | B44: Drink | C44: 3.58 | D44: 5 | E44: 24 | G44: 0
A45: snacky orange | B45: Drink | C45: 1.6 | D45: 3 | E45: 17 | G45: 0
... A49: kinza | B49: Drink | C49: 1.26 | D49: 2 | E49: 30 | G49: 0
A50: Total (1)2025 | C50: 0 | D50: 0 | E50: 0 | G50: 0
A51: water | B51: Drink | C51: 0.33 | D51: 1 | E51: 12 | G51: 0
A52: power | B52: Drink | C52: 2.5 | D52: 3 | E52: 24 | G52: 0
A53: power lower price | B53: Drink | C53: 2.37 | D53: 3 | E53: 24 | G53: 0
A54: xo energy | B54: Drink | C54: 3.37 | D54: 5 | E54: 24 | G54: 0
A55: x!r | B55: Drink | C55: 2.91 | D55: 4 | E55: 24 | G55: 0
A56: x!r lower | B56: Drink | C56: 2.7 | D56: 4 | E56: 24 | G56: 0
A57: suntop | B57: Drink | C57: 0.6 | D57: 1 | E57: 24 | G57: 0
A58: suntop masa | B58: Drink | C58: 0.45 | D58: 1 | E58: 24 | G58: 0
A59: pepsi 500ml | B59: Drink | C59: 1.66 | D59: 3 | E59: 12 | G59: 0
A60: sprite 300ml | B60: Drink | C60: 0.91 | D60: 2 | E60: 24 | G60: 0
A61: kinza | B61: Drink | C61: 1.5 | D61: 2 | E61: 24 | G61: 0
A62: shewppers | B62: Drink | C62: 1.95 | D62: 3 | E62: 24 | G62: 0
... A65: barbican | B65: Drink | C65: 2.87 | D65: 4 | E65: 24 | G65: 0
A66: Total (2)2025 | C66: 0 | D66: 0 | E66: 0 | G66: 0
A67: water | B67: Drink | C67: 0.33 | D67: 1 | E67: 12 | G67: 0
A68: x!r | B68: Drink | C68: 2.83 | D68: 4 | E68: 24 | G68: 0
A69: kinza | B69: Drink | C69: 1.23 | D69: 2 | E69: 24 | G69: 0
A70: pepsi 500ml | B70: Drink | C70: 1.66 | D70: 3 | E70: 12 | G70: 0
A71: shewppers | B71: Drink | C71: 1.95 | D71: 3 | E71: 24 | G71: 0
A72: maxfly | B72: Drink | C72: 2.83 | D72: 4 | E72: 24 | G72: 0
A73: power 500ml | B73: Drink | C73: 3.8 | D73: 5 | E73: 24 | G73: 0
A74: suntop saudi | B74: Drink | C74: 0.6 | D74: 1 | E74: 24 | G74: 0
A75: suntop masa | B75: Drink | C75: 0.45 | D75: 1 | E75: 24 | G75: 0
A76: suntop alrihan | B76: Drink | C76: 0.66 | D76: 1 | E76: 24 | G76: 0
A77: xo energy | B77: Drink | C77: 3.7 | D77: 5 | E77: 24 | G77: 0
A78: boba tea | B78: Drink | C78: 9.5 | D78: 12 | E78: 12 | G78: 0
A79: maxbrew | B79: Drink | C79: 4.75 | D79: 6 | E79: 12 | G79: 0
A80: Total (3)2025 | C80: 0 | D80: 0 | E80: 0 | G80: 0
A81: water | B81: Drink | C81: 0.33 | D81: 1 | E81: 12 | G81: 0
A82: x!r | B82: Drink | C82: 2.83 | D82: 4 | E82: 24 | G82: 0
A83: x!r price increase | B83: Drink | C83: 3 | D83: 4 | E83: 24 | G83: 0
A84: shewppers | B84: Drink | C84: 2.08 | D84: 3 | E84: 24 | G84: 0
A85: shewppers | B85: Drink | C85: 1.91 | D85: 3 | E85: 24 | G85: 0
A86: kinza | B86: Drink | C86: 1.23 | D86: 2 | E86: 24 | G86: 0
A87: pepsi 500ml | B87: Drink | C87: 1.66 | D87: 3 | E87: 12 | G87: 0
A88: suntop | B88: Drink | C88: 0.62 | D88: 1 | E88: 24 | G88: 0
A89: al rihan | B89: Drink | C89: 0.66 | D89: 1 | E89: 24 | G89: 0
A90: suntop masa | B90: Drink | C90: 0.45 | D90: 1 | E90: 24 | G90: 0
A91: vitaGo suntop | B91: Drink | C91: 1.75 | D91: 3 | E91: 8 | G91: 0
A92: freez | B92: Drink | C92: 3.7 | D92: 5 | E92: 24 | G92: 0
... A96: skitelies drink | B96: Drink | C96: 4.75 | D96: 7 | E96: 12 | G96: 0
A97: Total 2025 | C97: 0 | D97: 0 | E97: 0 | G97: 0
A98: Tiger Family | B98: Chips | C98: 2.6 | D98: 4 | E98: 12 | G98: 0
A99: Tiger meduim | B99: Chips | C99: 1.75 | D99: 3 | E99: 16 | F99: 79g Master Sitos | G99: 0
A100: 79 | B100: Chips | C100: 4.5 | D100: 5 | E100: 30 | G100: 0
A101: Sitos Meduim | B101: Chips | C101: 2.23 | D101: 3 | E101: 30 | G101: 0
A102: Total (8) | C102: 0 | D102: 0 | E102: 0 | G102: 0
A103: Sitos Small | B103: Chips | C103: 0.9 | D103: 1 | E103: 30 | G103: 0
A104: spuds family | B104: Chips | C104: 3.35 | D104: 4 | E104: 10 | G104: 0
A105: Spuds 40g | B105: Chips | C105: 2.03 | D105: 3 | E105: 15 | G105: 0
A106: marshmallow haribo | B106: Chips | C106: 4.17 | D106: 5 | E106: 24 | G106: 0
A107: MrCrunch | B107: Chips | C107: 2.22 | D107: 3 | E107: 15 | G107: 0
A108: MrCrunch طبيعيه | B108: Chips | C108: 2.11 | D108: 3 | E108: 18 | G108: 0
A109: الابطال شيبس | B109: Chips | C109: 0.42 | D109: 1 | E109: 50 | G109: 0
A110: شيبستي | B110: Chips | C110: 0.8 | D110: 2 | E110: 15 | G110: 0
A111: Tiger meduim*40 | B111: Chips | C111: 0.72 | D111: 2 | E111: 40 | G111: 0
A112: Tiger meduim | B112: Chips | C112: 0.86 | D112: 2 | E112: 30 | G112: 0
A113: Total (9) | C113: 0 | D113: 0 | E113: 0 | G113: 0
A114: mrCrunch | B114: Chips | C114: 2.27 | D114: 3 | E114: 18 | G114: 0
A115: tiger *12 | B115: Chips | C115: 2.66 | D115: 4 | E115: 12 | G115: 0
...
