Workbook

Sheet KPI_Calc
F1: Ads Income | G1: Rent | H1: Net Profit | I1: Avg Price | J1: SPI_Traffic | K1: SPI_Profit | L1: SPI_Final | M1: Rank per month
G2: {=IFERROR(XLOOKUP(B2, Machines!A:A, Machines!C:C), 0)} -> 0 | H2: =IFERROR( D2 + F2 - G2, 0) -> 439.36 | I2: =IF(OR($B2="",RIGHT($A2,5)="Total"),"", $C2 / $E2) -> 4.2164751 | J2: =IFERROR(__xludf.DUMMYFUNCTION("IF($B2="""","""", 100 * $E2 / MAX(FILTER($E:$E, $A:$A=$A2, $B:$B<>"""")) ) "),100.0) -> 100 | K2: =IFERROR(__xludf.DUMMYFUNCTION("IF($B2="""","""", 100 * $H2 / MAX(FILTER($H:$H, $A:$A=$A2, $B:$B<>"""")) ) "),100.0) -> 100 | L2: =IF($B2="","", 0.4*$I2 + 0.6*$J2) -> 61.68659 | M2: =IFERROR(__xludf.DUMMYFUNCTION("IF($B2="""","""", RANK($K2, FILTER($K:$K, $A:$A=$A2, $B:$B<>""""), 0) ) "),1.0) -> 1 | N2: =IF($B2="","", IF($L2>=60,"🟢 Strong", IF($L2>=35,"🟡 Watch", "🔴 Action Needed"))) -> 🟢 Strong | O2: =IF($B2="","", IF($N2="🟢 Strong","OK", IF($K2<$J2,"Profit issue → pricing/cost/rent", "Traffic issue → location/product mix"))) -> OK
F3: 1000 | G3: 500 | H3: =IFERROR( D3 + F3 - G3, 0) -> 3949.24 | I3: =IF(OR($B3="",RIGHT($A3,5)="Total"),"", $C3 / $E3) -> 3.4337553 | J3: =IFERROR(__xludf.DUMMYFUNCTION("IF($B3="""","""", 100 * $E3 / MAX(FILTER($E:$E, $A:$A=$A3, $B:$B<>"""")) ) "),52.3756906077348) -> 52.375691 | K3: =IFERROR(__xludf.DUMMYFUNCTION("IF($B3="""","""", 100 * $H3 / MAX(FILTER($H:$H, $A:$A=$A3, $B:$B<>"""")) ) "),73.06155371705124) -> 73.061554 | L3: =IF($B3="","", 0.4*$I3 + 0.6*$J3) -> 32.798916 | M3: =IFERROR(__xludf.DUMMYFUNCTION("IF($B3="""","""", RANK($K3, FILTER($K:$K, $A:$A=$A3, $B:$B<>""""), 0) ) "),4.0) -> 4 | N3: =IF($B3="","", IF($L3>=60,"🟢 Strong", IF($L3>=35,"🟡 Watch", "🔴 Action Needed"))) -> 🔴 Action Needed | O3: =IF($B3="","", IF($N3="🟢 Strong","OK", IF($K3<$J3,"Profit issue → pricing/cost/rent", "Traffic issue → location/product mix"))) -> Traffic issue → location/product mix
H4: =IFERROR( D4 + F4 - G4, 0) -> 1626.18 | I4: =IF(OR($B4="",RIGHT($A4,5)="Total"),"", $C4 / $E4) -> 3.3972603 | J4: =IFERROR(__xludf.DUMMYFUNCTION("IF($B4="""","""", 100 * $E4 / MAX(FILTER($E:$E, $A:$A=$A4, $B:$B<>"""")) ) "),30.65193370165746) -> 30.651934 | K4: =IFERROR(__xludf.DUMMYFUNCTION("IF($B4="""","""", 100 * $H4 / MAX(FILTER($H:$H, $A:$A=$A4, $B:$B<>"""")) ) "),30.084582710494768) -> 30.084583 | L4: =IF($B4="","", 0.4*$I4 + 0.6*$J4) -> 19.750064 | M4: =IFERROR(__xludf.DUMMYFUNCTION("IF($B4="""","""", RANK($K4, FILTER($K:$K, $A:$A=$A4, $B:$B<>""""), 0) ) "),13.0) -> 13 | N4: =IF($B4="","", IF($L4>=60,"🟢 Strong", IF($L4>=35,"🟡 Watch", "🔴 Action Needed"))) -> 🔴 Action Needed | O4: =IF($B4="","", IF($N4="🟢 Strong","OK", IF($K4<$J4,"Profit issue → pricing/cost/rent", "Traffic issue → location/product mix"))) -> Profit issue → pricing/cost/rent
F5: 1000 | H5: =IFERROR( D5 + F5 - G5, 0) -> 3587.57 | I5: =IF(OR($B5="",RIGHT($A5,5)="Total"),"", $C5 / $E5) -> 3.2060277 | J5: =IFERROR(__xludf.DUMMYFUNCTION("IF($B5="""","""", 100 * $E5 / MAX(FILTER($E:$E, $A:$A=$A5, $B:$B<>"""")) ) "),44.729281767955804) -> 44.729282 | K5: =IFERROR(__xludf.DUMMYFUNCTION("IF($B5="""","""", 100 * $H5 / MAX(FILTER($H:$H, $A:$A=$A5, $B:$B<>"""")) ) "),66.37060251306113) -> 66.370603 | L5: =IF($B5="","", 0.4*$I5 + 0.6*$J5) -> 28.11998 | M5: =IFERROR(__xludf.DUMMYFUNCTION("IF($B5="""","""", RANK($K5, FILTER($K:$K, $A:$A=$A5, $B:$B<>""""), 0) ) "),5.0) -> 5 | N5: =IF($B5="","", IF($L5>=60,"🟢 Strong", IF($L5>=35,"🟡 Watch", "🔴 Action Needed"))) -> 🔴 Action Needed | O5: =IF($B5="","", IF($N5="🟢 Strong","OK", IF($K5<$J5,"Profit issue → pricing/cost/rent", "Traffic issue → location/product mix"))) -> Traffic issue → location/product mix
G6: {=IFERROR(XLOOKUP(B6, Machines!A:A, Machines!C:C), 0)} -> 1000 | H6: =IFERROR( D6 + F6 - G6, 0) -> 5405.36 | I6: =IF(OR($B6="",RIGHT($A6,5)="Total"),"", $C6 / $E6) -> 3.2948066 | J6: =IFERROR(__xludf.DUMMYFUNCTION("IF($B6="""","""", 100 * $E6 / MAX(FILTER($E:$E, $A:$A=$A6, $B:$B<>"""")) ) "),100.0) -> 100 | K6: =IFERROR(__xludf.DUMMYFUNCTION("IF($B6="""","""", 100 * $H6 / MAX(FILTER($H:$H, $A:$A=$A6, $B:$B<>"""")) ) "),100.0) -> 100 | L6: =IF($B6="","", 0.4*$I6 + 0.6*$J6) -> 61.317923 | M6: =IFERROR(__xludf.DUMMYFUNCTION("IF($B6="""","""", RANK($K6, FILTER($K:$K, $A:$A=$A6, $B:$B<>""""), 0) ) "),1.0) -> 1 | N6: =IF($B6="","", IF($L6>=60,"🟢 Strong", IF($L6>=35,"🟡 Watch", "🔴 Action Needed"))) -> 🟢 Strong | O6: =IF($B6="","", IF($N6="🟢 Strong","OK", IF($K6<$J6,"Profit issue → pricing/cost/rent", "Traffic issue → location/product mix"))) -> OK
H7: =IFERROR( D7 + F7 - G7, 0) -> 1445.9 | I7: =IF(OR($B7="",RIGHT($A7,5)="Total"),"", $C7 / $E7) -> 3.0787901 | J7: =IFERROR(__xludf.DUMMYFUNCTION("IF($B7="""","""", 100 * $E7 / MAX(FILTER($E:$E, $A:$A=$A7, $B:$B<>"""")) ) "),29.591160220994475) -> 29.59116 | K7: =IFERROR(__xludf.DUMMYFUNCTION("IF($B7="""","""", 100 * $H7 / MAX(FILTER($H:$H, $A:$A=$A7, $B:$B<>"""")) ) "),26.74937469474744) -> 26.749375 | L7: =IF($B7="","", 0.4*$I7 + 0.6*$J7) -> 18.986212 | M7: =IFERROR(__xludf.DUMMYFUNCTION("IF($B7="""","""", RANK($K7, FILTER($K:$K, $A:$A=$A7, $B:$B<>""""), 0) ) "),16.0) -> 16 | N7: =IF($B7="","", IF($L7>=60,"🟢 Strong", IF($L7>=35,"🟡 Watch", "🔴 Action Needed"))) -> 🔴 Action Needed | O7: =IF($B7="","", IF($N7="🟢 Strong","OK", IF($K7<$J7,"Profit issue → pricing/cost/rent", "Traffic issue → location/product mix"))) -> Profit issue → pricing/cost/rent
H8: =IFERROR( D8 + F9 - G8, 0) -> 447.8 | I8: =IF(OR($B8="",RIGHT($A8,5)="Total"),"", $C8 / $E8) -> 4.6079545 | J8: =IFERROR(__xludf.DUMMYFUNCTION("IF($B8="""","""", 100 * $E8 / MAX(FILTER($E:$E, $A:$A=$A8, $B:$B<>"""")) ) "),3.889502762430939) -> 3.8895028 | K8: =IFERROR(__xludf.DUMMYFUNCTION("IF($B8="""","""", 100 * $H8 / MAX(FILTER($H:$H, $A:$A=$A8, $B:$B<>"""")) ) "),8.284369588704548) -> 8.2843696 | L8: =IF($B8="","", 0.4*$I8 + 0.6*$J8) -> 4.1768835 | M8: =IFERROR(__xludf.DUMMYFUNCTION("IF($B8="""","""", RANK($K8, FILTER($K:$K, $A:$A=$A8, $B:$B<>""""), 0) ) "),24.0) -> 24 | N8: =IF($B8="","", IF($L8>=60,"🟢 Strong", IF($L8>=35,"🟡 Watch", "🔴 Action Needed"))) -> 🔴 Action Needed | O8: =IF($B8="","", IF($N8="🟢 Strong","OK", IF($K8<$J8,"Profit issue → pricing/cost/rent", "Traffic issue → location/product mix"))) -> Traffic issue → location/product mix
H9: =IFERROR( D9 + F9 - G9, 0) -> 16401.41 | I9: =IF(OR($B9="",RIGHT($A9,5)="Total"),"", $C9 / $E9) | J9: =IFERROR(__xludf.DUMMYFUNCTION("IF($B9="""","""", 100 * $E9 / MAX(FILTER($E:$E, $A:$A=$A9, $B:$B<>"""")) ) "),"") | K9: =IFERROR(__xludf.DUMMYFUNCTION("IF($B9="""","""", 100 * $H9 / MAX(FILTER($H:$H, $A:$A=$A9, $B:$B<>"""")) ) "),"") | L9: =IF($B9="","", 0.4*$I9 + 0.6*$J9) | M9: =IFERROR(__xludf.DUMMYFUNCTION("IF($B9="""","""", RANK($K9, FILTER($K:$K, $A:$A=$A9, $B:$B<>""""), 0) ) "),"") | N9: =IF($B9="","", IF($L9>=60,"🟢 Strong", IF($L9>=35,"🟡 Watch", "🔴 Action Needed"))) | O9: =IF($B9="","", IF($N9="🟢 Strong","OK", IF($K9<$J9,"Profit issue → pricing/cost/rent", "Traffic issue → location/product mix")))
G10: {=IFERROR(XLOOKUP(B10, Machines!A:A, Machines!C:C), 0)} -> 0 | H10: =IFERROR( D10 + F10 - G10, 0) -> 1306.17 | I10: =IF(OR($B10="",RIGHT($A10,5)="Total"),"", $C10 / $E10) -> 3.4069586 | J10: =IFERROR(__xludf.DUMMYFUNCTION("IF($B10="""","""", 100 * $E10 / MAX(FILTER($E:$E, $A:$A=$A10, $B:$B<>"""")) ) "),100.0) -> 100 | K10: =IFERROR(__xludf.DUMMYFUNCTION("IF($B10="""","""", 100 * $H10 / MAX(FILTER($H:$H, $A:$A=$A10, $B:$B<>"""")) ) "),100.0) -> 100 | L10: =IF($B10="","", 0.4*$I10 + 0.6*$J10) -> 61.362783 | M10: =IFERROR(__xludf.DUMMYFUNCTION("IF($B10="""","""", RANK($K10, FILTER($K:$K, $A:$A=$A10, $B:$B<>""""), 0) ) "),1.0) -> 1 | N10: =IF($B10="","", IF($L10>=60,"🟢 Strong", IF($L10>=35,"🟡 Watch", "🔴 Action Needed"))) -> 🟢 Strong | O10: =IF($B10="","", IF($N10="🟢 Strong","OK", IF($K10<$J10,"Profit issue → pricing/cost/rent", "Traffic issue → location/product mix"))) -> OK
F11: 1000 | G11: {=IFERROR(XLOOKUP(B11, Machines!A:A, Machines!C:C), 0)} -> 500 | H11: =IFERROR( D11 + F11 - G11, 0) -> 1515.1 | I11: =IF(OR($B11="",RIGHT($A11,5)="Total"),"", $C11 / $E11) -> 3.1438547 | J11: =IFERROR(__xludf.DUMMYFUNCTION("IF($B11="""","""", 100 * $E11 / MAX(FILTER($E:$E, $A:$A=$A11, $B:$B<>"""")) ) "),15.823204419889503) -> 15.823204 | K11: =IFERROR(__xludf.DUMMYFUNCTION("IF($B11="""","""", 100 * $H11 / MAX(FILTER($H:$H, $A:$A=$A11, $B:$B<>"""")) ) "),28.029585448517775) -> 28.029585 | L11: =IF($B11="","", 0.4*$I11 + 0.6*$J11) -> 10.751465 | M11: =IFERROR(__xludf.DUMMYFUNCTION("IF($B11="""","""", RANK($K11, FILTER($K:$K, $A:$A=$A11, $B:$B<>""""), 0) ) "),15.0) -> 15 | N11: =IF($B11="","", IF($L11>=60,"🟢 Strong", IF($L11>=35,"🟡 Watch", "🔴 Action Needed"))) -> 🔴 Action Needed | O11: =IF($B11="","", IF($N11="🟢 Strong","OK", IF($K11<$J11,"Profit issue → pricing/cost/rent", "Traffic issue → location/product mix"))) -> Traffic issue → location/product mix
H12: =IFERROR( D12 + F12 - G12, 0) -> 1368.57 | I12: =IF(OR($B12="",RIGHT($A12,5)="Total"),"", $C12 / $E12) -> 3.362916 | J12: =IFERROR(__xludf.DUMMYFUNCTION("IF($B12="""","""", 100 * $E12 / MAX(FILTER($E:$E, $A:$A=$A12, $B:$B<>"""")) ) "),27.88950276243094) -> 27.889503 | K12: =IFERROR(__xludf.DUMMYFUNCTION("IF($B12="""","""", 100 * $H12 / MAX(FILTER($H:$H, $A:$A=$A12, $B:$B<>"""")) ) "),25.318757677564502) -> 25.318758 | L12: =IF($B12="","", 0.4*$I12 + 0.6*$J12) -> 18.078868 | M12: =IFERROR(__xludf.DUMMYFUNCTION("IF($B12="""","""", RANK($K12, FILTER($K:$K, $A:$A=$A12, $B:$B<>""""), 0) ) "),17.0) -> 17 | N12: =IF($B12="","", IF($L12>=60,"🟢 Strong", IF($L12>=35,"🟡 Watch", "🔴 Action Needed"))) -> 🔴 Action Needed | O12: =IF($B12="","", IF($N12="🟢 Strong","OK", IF($K12<$J12,"Profit issue → pricing/cost/rent", "Traffic issue → location/product mix"))) -> Profit issue → pricing/cost/rent
H13: =IFERROR( D13 + F13 - G13, 0) -> 2969.46 | I13: =IF(OR($B13="",RIGHT($A13,5)="Total"),"", $C13 / $E13) -> 3.2778269 | J13: =IFERROR(__xludf.DUMMYFUNCTION("IF($B13="""","""", 100 * $E13 / MAX(FILTER($E:$E, $A:$A=$A13, $B:$B<>"""")) ) "),50.033149171270715) -> 50.033149 | K13: =IFERROR(__xludf.DUMMYFUNCTION("IF($B13="""","""", 100 * $H13 / MAX(FILTER($H:$H, $A:$A=$A13, $B:$B<>"""")) ) "),54.93547145796024) -> 54.935471 | L13: =IF($B13="","", 0.4*$I13 + 0.6*$J13) -> 31.33102 | M13: =IFERROR(__xludf.DUMMYFUNCTION("IF($B13="""","""", RANK($K13, FILTER($K:$K, $A:$A=$A13, $B:$B<>""""), 0) ) "),7.0) -> 7 | N13: =IF($B13="","", IF($L13>=60,"🟢 Strong", IF($L13>=35,"🟡 Watch", "🔴 Action Needed"))) -> 🔴 Action Needed | O13: =IF($B13="","", IF($N13="🟢 Strong","OK", IF($K13<$J13,"Profit issue → pricing/cost/rent", "Traffic issue → location/product mix"))) -> Traffic issue → location/product mix
F14: 1000 | G14: 1000 | H14: =IFERROR( D14 + F14 - G14, 0) -> 1639.68 | I14: =IF(OR($B14="",RIGHT($A14,5)="Total"),"", $C14 / $E14) -> 2.7793034 | J14: =IFERROR(__xludf.DUMMYFUNCTION("IF($B14="""","""", 100 * $E14 / MAX(FILTER($E:$E, $A:$A=$A14, $B:$B<>"""")) ) "),32.994475138121544) -> 32.994475 | K14: =IFERROR(__xludf.DUMMYFUNCTION("IF($B14="""","""", 100 * $H14 / MAX(FILTER($H:$H, $A:$A=$A14, $B:$B<>"""")) ) "),30.334334808412393) -> 30.334335 | L14: =IF($B14="","", 0.4*$I14 + 0.6*$J14) -> 20.908406 | M14: =IFERROR(__xludf.DUMMYFUNCTION("IF($B14="""","""", RANK($K14, FILTER($K:$K, $A:$A=$A14, $B:$B<>""""), 0) ) "),12.0) -> 12 | N14: =IF($B14="","", IF($L14>=60,"🟢 Strong", IF($L14>=35,"🟡 Watch", "🔴 Action Needed"))) -> 🔴 Action Needed | O14: =IF($B14="","", IF($N14="🟢 Strong","OK", IF($K14<$J14,"Profit issue → pricing/cost/rent", "Traffic issue → location/product mix"))) -> Profit issue → pricing/cost/rent
G15: {=IFERROR(XLOOKUP(B15, Machines!A:A, Machines!C:C), 0)} -> 0 | H15: =IFERROR( D15 + F15 - G15, 0) -> 1033.65 | I15: =IF(OR($B15="",RIGHT($A15,5)="Total"),"", $C15 / $E15) -> 3.1209752 | J15: =IFERROR(__xludf.DUMMYFUNCTION("IF($B15="""","""", 100 * $E15 / MAX(FILTER($E:$E, $A:$A=$A15, $B:$B<>"""")) ) "),24.022099447513813) -> 24.022099 | K15: =IFERROR(__xludf.DUMMYFUNCTION("IF($B15="""","""", 100 * $H15 / MAX(FILTER($H:$H, $A:$A=$A15, $B:$B<>"""")) ) "),19.1226856305593) -> 19.122686 | L15: =IF($B15="","", 0.4*$I15 + 0.6*$J15) -> 15.66165 | M15: =IFERROR(__xludf.DUMMYFUNCTION("IF($B15="""","""", RANK($K15, FILTER($K:$K, $A:$A=$A15, $B:$B<>""""), 0) ) "),20.0) -> 20 | N15: =IF($B15="","", IF($L15>=60,"🟢 Strong", IF($L15>=35,"🟡 Watch", "🔴 Action Needed"))) -> 🔴 Action Needed | O15: =IF($B15="","", IF($N15="🟢 Strong","OK", IF($K15<$J15,"Profit issue → pricing/cost/rent", "Traffic issue → location/product mix"))) -> Profit issue → pricing/cost/rent
G16: 300 | H16: =IFERROR( D16 + F18 - G16, 0) -> 4136.55 | I16: =IF(OR($B16="",RIGHT($A16,5)="Total"),"", $C16 / $E16) -> 4.1022831 | J16: =IFERROR(__xludf.DUMMYFUNCTION("IF($B16="""","""", 100 * $E16 / MAX(FILTER($E:$E, $A:$A=$A16, $B:$B<>"""")) ) "),24.19889502762431) -> 24.198895 | K16: =IFERROR(__xludf.DUMMYFUNCTION("IF($B16="""","""", 100 * $H16 / MAX(FILTER($H:$H, $A:$A=$A16, $B:$B<>"""")) ) "),76.52681782526975) -> 76.526818 | L16: =IF($B16="","", 0.4*$I16 + 0.6*$J16) -> 16.16025 | M16: =IFERROR(__xludf.DUMMYFUNCTION("IF($B16="""","""", RANK($K16, FILTER($K:$K, $A:$A=$A16, $B:$B<>""""), 0) ) "),2.0) -> 2 | N16: =IF($B16="","", IF($L16>=60,"🟢 Strong", IF($L16>=35,"🟡 Watch", "🔴 Action Needed"))) -> 🔴 Action Needed | O16: =IF($B16="","", IF($N16="🟢 Strong","OK", IF($K16<$J16,"Profit issue → pricing/cost/rent", "Traffic issue → location/product mix"))) -> Traffic issue → location/product mix
H17: =IFERROR( D17 + F17 - G17, 0) -> 572.33 | I17: =IF(OR($B17="",RIGHT($A17,5)="Total"),"", $C17 / $E17) -> 4.4933921 | J17: =IFERROR(__xludf.DUMMYFUNCTION("IF($B17="""","""", 100 * $E17 / MAX(FILTER($E:$E, $A:$A=$A17, $B:$B<>"""")) ) "),5.016574585635359) -> 5.0165746 | K17: =IFERROR(__xludf.DUMMYFUNCTION("IF($B17="""","""", 100 * $H17 / MAX(FILTER($H:$H, $A:$A=$A17, $B:$B<>"""")) ) "),10.588193940829107) -> 10.588194 | L17: =IF($B17="","", 0.4*$I17 + 0.6*$J17) -> 4.8073016 | M17: =IFERROR(__xludf.DUMMYFUNCTION("IF($B17="""","""", RANK($K17, FILTER($K:$K, $A:$A=$A17, $B:$B<>""""), 0) ) "),22.0) -> 22 | N17: =IF($B17="","", IF($L17>=60,"🟢 Strong", IF($L17>=35,"🟡 Watch", "🔴 Action Needed"))) -> 🔴 Action Needed | O17: =IF($B17="","", IF($N17="🟢 Strong","OK", IF($K17<$J17,"Profit issue → pricing/cost/rent", "Traffic issue → location/product mix"))) -> Traffic issue → location/product mix
F18: =SUM(F10:F16) -> 2000 | H18: =IFERROR( D18 + F18 - G18, 0) -> 14341.51 | I18: =IF(OR($B18="",RIGHT($A18,5)="Total"),"", $C18 / $E18) | J18: =IFERROR(__xludf.DUMMYFUNCTION("IF($B18="""","""", 100 * $E18 / MAX(FILTER($E:$E, $A:$A=$A18, $B:$B<>"""")) ) "),"") | K18: =IFERROR(__xludf.DUMMYFUNCTION("IF($B18="""","""", 100 * $H18 / MAX(FILTER($H:$H, $A:$A=$A18, $B:$B<>"""")) ) "),"") | L18: =IF($B18="","", 0.4*$I18 + 0.6*$J18) | M18: =IFERROR(__xludf.DUMMYFUNCTION("IF($B18="""","""", RANK($K18, FILTER($K:$K, $A:$A=$A18, $B:$B<>""""), 0) ) "),"") | N18: =IF($B18="","", IF($L18>=60,"🟢 Strong", IF($L18>=35,"🟡 Watch", "🔴 Action Needed"))) | O18: =IF($B18="","", IF($N18="🟢 Strong","OK", IF($K18<$J18,"Profit issue → pricing/cost/rent", "Traffic issue → location/product mix")))
F19: 1000 | G19: 500 | H19: =IFERROR( D19 + F19 - G19, 0) -> 1677.36 | I19: =IF(OR($B19="",RIGHT($A19,5)="Total"),"", $C19 / $E19) -> 2.749004 | J19: =IFERROR(__xludf.DUMMYFUNCTION("IF($B19="""","""", 100 * $E19 / MAX(FILTER($E:$E, $A:$A=$A19, $B:$B<>"""")) ) "),100.0) -> 100 | K19: =IFERROR(__xludf.DUMMYFUNCTION("IF($B19="""","""", 100 * $H19 / MAX(FILTER($H:$H, $A:$A=$A19, $B:$B<>"""")) ) "),99.99999999999999) -> 100 | L19: =IF($B19="","", 0.4*$I19 + 0.6*$J19) -> 61.099602 | M19: =IFERROR(__xludf.DUMMYFUNCTION("IF($B19="""","""", RANK($K19, FILTER($K:$K, $A:$A=$A19, $B:$B<>""""), 0) ) "),1.0) -> 1 | N19: =IF($B19="","", IF($L19>=60,"🟢 Strong", IF($L19>=35,"🟡 Watch", "🔴 Action Needed"))) -> 🟢 Strong | O19: =IF($B19="","", IF($N19="🟢 Strong","OK", IF($K19<$J19,"Profit issue → pricing/cost/rent", "Traffic issue → location/product mix"))) -> OK
G20: {=IFERROR(XLOOKUP(B20, Machines!A:A, Machines!C:C), 0)} -> 0 | H20: =IFERROR( D20 + F20 - G20, 0) -> 1567.26 | I20: =IF(OR($B20="",RIGHT($A20,5)="Total"),"", $C20 / $E20) -> 3.153506 | J20: =IFERROR(__xludf.DUMMYFUNCTION("IF($B20="""","""", 100 * $E20 / MAX(FILTER($E:$E, $A:$A=$A20, $B:$B<>"""")) ) "),34.98342541436464) -> 34.983425 | K20: =IFERROR(__xludf.DUMMYFUNCTION("IF($B20="""","""", 100 * $H20 / MAX(FILTER($H:$H, $A:$A=$A20, $B:$B<>"""")) ) "),28.994553554249862) -> 28.994554 | L20: =IF($B20="","", 0.4*$I20 + 0.6*$J20) -> 22.251458 | M20: =IFERROR(__xludf.DUMMYFUNCTION("IF($B20="""","""", RANK($K20, FILTER($K:$K, $A:$A=$A20, $B:$B<>""""), 0) ) "),14.0) -> 14 | N20: =IF($B20="","", IF($L20>=60,"🟢 Strong", IF($L20>=35,"🟡 Watch", "🔴 Action Needed"))) -> 🔴 Action Needed | O20: =IF($B20="","", IF($N20="🟢 Strong","OK", IF($K20<$J20,"Profit issue → pricing/cost/rent", "Traffic issue → location/product mix"))) -> Profit issue → pricing/cost/rent
F21: 1000 | G21: {=IFERROR(XLOOKUP(B21, Machines!A:A, Machines!C:C), 0)} -> 1000 | H21: =IFERROR( D21 + F21 - G21, 0) -> 4118.83 | I21: =IF(OR($B21="",RIGHT($A21,5)="Total"),"", $C21 / $E21) -> 2.9687951 | J21: =IFERROR(__xludf.DUMMYFUNCTION("IF($B21="""","""", 100 * $E21 / MAX(FILTER($E:$E, $A:$A=$A21, $B:$B<>"""")) ) "),76.48618784530387) -> 76.486188 | K21: =IFERROR(__xludf.DUMMYFUNCTION("IF($B21="""","""", 100 * $H21 / MAX(FILTER($H:$H, $A:$A=$A21, $B:$B<>"""")) ) "),76.1989950715586) -> 76.198995 | L21: =IF($B21="","", 0.4*$I21 + 0.6*$J21) -> 47.079231 | M21: =IFERROR(__xludf.DUMMYFUNCTION("IF($B21="""","""", RANK($K21, FILTER($K:$K, $A:$A=$A21, $B:$B<>""""), 0) ) "),3.0) -> 3 | N21: =IF($B21="","", IF($L21>=60,"🟢 Strong", IF($L21>=35,"🟡 Watch", "🔴 Action Needed"))) -> 🟡 Watch | O21: =IF($B21="","", IF($N21="🟢 Strong","OK", IF($K21<$J21,"Profit issue → pricing/cost/rent", "Traffic issue → location/product mix"))) -> Profit issue → pricing/cost/rent
H22: =IFERROR( D22 + F22 - G22, 0) -> 1014.02 | I22: =IF(OR($B22="",RIGHT($A22,5)="Total"),"", $C22 / $E22) -> 3.2355876 | J22: =IFERROR(__xludf.DUMMYFUNCTION("IF($B22="""","""", 100 * $E22 / MAX(FILTER($E:$E, $A:$A=$A22, $B:$B<>"""")) ) "),19.933701657458563) -> 19.933702 | K22: =IFERROR(__xludf.DUMMYFUNCTION("IF($B22="""","""", 100 * $H22 / MAX(FILTER($H:$H, $A:$A=$A22, $B:$B<>"""")) ) "),18.759527580031676) -> 18.759528 | L22: =IF($B22="","", 0.4*$I22 + 0.6*$J22) -> 13.254456 | M22: =IFERROR(__xludf.DUMMYFUNCTION("IF($B22="""","""", RANK($K22, FILTER($K:$K, $A:$A=$A22, $B:$B<>""""), 0) ) "),21.0) -> 21 | N22: =IF($B22="","", IF($L22>=60,"🟢 Strong", IF($L22>=35,"🟡 Watch", "🔴 Action Needed"))) -> 🔴 Action Needed | O22: =IF($B22="","", IF($N22="🟢 Strong","OK", IF($K22<$J22,"Profit issue → pricing/cost/rent", "Traffic issue → location/product mix"))) -> Profit issue → pricing/cost/rent
G23: 200 | H23: =IFERROR( D23 + F23 - G23, 0) -> 2245.81 | I23: =IF(OR($B23="",RIGHT($A23,5)="Total"),"", $C23 / $E23) -> 3.4748521 | J23: =IFERROR(__xludf.DUMMYFUNCTION("IF($B23="""","""", 100 * $E23 / MAX(FILTER($E:$E, $A:$A=$A23, $B:$B<>"""")) ) "),29.87845303867403) -> 29.878453 | K23: =IFERROR(__xludf.DUMMYFUNCTION("IF($B23="""","""", 100 * $H23 / MAX(FILTER($H:$H, $A:$A=$A23, $B:$B<>"""")) ) "),41.547834001805626) -> 41.547834 | L23: =IF($B23="","", 0.4*$I23 + 0.6*$J23) -> 19.317013 | M23: =IFERROR(__xludf.DUMMYFUNCTION("IF($B23="""","""", RANK($K23, FILTER($K:$K, $A:$A=$A23, $B:$B<>""""), 0) ) "),8.0) -> 8 | N23: =IF($B23="","", IF($L23>=60,"🟢 Strong", IF($L23>=35,"🟡 Watch", "🔴 Action Needed"))) -> 🔴 Action Needed | O23: =IF($B23="","", IF($N23="🟢 Strong","OK", IF($K23<$J23,"Profit issue → pricing/cost/rent", "Traffic issue → location/product mix"))) -> Traffic issue → location/product mix
F24: =SUM(F19:F23) -> 2000 | H24: =IFERROR( D24 + F24 - G24, 0) -> 12323.28 | I24: =IF(OR($B24="",RIGHT($A24,5)="Total"),"", $C24 / $E24) | J24: =IFERROR(__xludf.DUMMYFUNCTION("IF($B24="""","""", 100 * $E24 / MAX(FILTER($E:$E, $A:$A=$A24, $B:$B<>"""")) ) "),"") | K24: =IFERROR(__xludf.DUMMYFUNCTION("IF($B24="""","""", 100 * $H24 / MAX(FILTER($H:$H, $A:$A=$A24, $B:$B<>"""")) ) "),"") | L24: =IF($B24="","", 0.4*$I24 + 0.6*$J24) | M24: =IFERROR(__xludf.DUMMYFUNCTION("IF($B24="""","""", RANK($K24, FILTER($K:$K, $A:$A=$A24, $B:$B<>""""), 0) ) "),"") | N24: =IF($B24="","", IF($L24>=60,"🟢 Strong", IF($L24>=35,"🟡 Watch", "🔴 Action Needed"))) | O24: =IF($B24="","", IF($N24="🟢 Strong","OK", IF($K24<$J24,"Profit issue → pricing/cost/rent", "Traffic issue → location/product mix")))
F25: 1000 | H25: =IFERROR( D25 + F25 - G25, 0) -> 5270 | I25: =IF(OR($B25="",RIGHT($A25,5)="Total"),"", $C25 / $E25) -> 2.5584182 | J25: =IFERROR(__xludf.DUMMYFUNCTION("IF($B25="""","""", 100 * $E25 / MAX(FILTER($E:$E, $A:$A=$A25, $B:$B<>"""")) ) "),100.0) -> 100 | K25: =IFERROR(__xludf.DUMMYFUNCTION("IF($B25="""","""", 100 * $H25 / MAX(FILTER($H:$H, $A:$A=$A25, $B:$B<>"""")) ) "),100.0) -> 100 | L25: =IF($B25="","", 0.4*$I25 + 0.6*$J25) -> 61.023367 | M25: =IFERROR(__xludf.DUMMYFUNCTION("IF($B25="""","""", RANK($K25, FILTER($K:$K, $A:$A=$A25, $B:$B<>""""), 0) ) "),1.0) -> 1 | N25: =IF($B25="","", IF($L25>=60,"🟢 Strong", IF($L25>=35,"🟡 Watch", "🔴 Action Needed"))) -> 🟢 Strong | O25: =IF($B25="","", IF($N25="🟢 Strong","OK", IF($K25<$J25,"Profit issue → pricing/cost/rent", "Traffic issue → location/product mix"))) -> OK
H26: =IFERROR( D26 + F26 - G26, 0) -> 1786.24 | I26: =IF(OR($B26="",RIGHT($A26,5)="Total"),"", $C26 / $E26) -> 2.9173184 | J26: =IFERROR(__xludf.DUMMYFUNCTION("IF($B26="""","""", 100 * $E26 / MAX(FILTER($E:$E, $A:$A=$A26, $B:$B<>"""")) ) "),39.55801104972376) -> 39.558011 | K26: =IFERROR(__xludf.DUMMYFUNCTION("IF($B26="""","""", 100 * $H26 / MAX(FILTER($H:$H, $A:$A=$A26, $B:$B<>"""")) ) "),33.04571758402771) -> 33.045718 | L26: =IF($B26="","", 0.4*$I26 + 0.6*$J26) -> 24.901734 | M26: =IFERROR(__xludf.DUMMYFUNCTION("IF($B26="""","""", RANK($K26, FILTER($K:$K, $A:$A=$A26, $B:$B<>""""), 0) ) "),9.0) -> 9 | N26: =IF($B26="","", IF($L26>=60,"🟢 Strong", IF($L26>=35,"🟡 Watch", "🔴 Action Needed"))) -> 🔴 Action Needed | O26: =IF($B26="","", IF($N26="🟢 Strong","OK", IF($K26<$J26,"Profit issue → pricing/cost/rent", "Traffic issue → location/product mix"))) -> Profit issue → pricing/cost/rent
I27: =IF(OR($B27="",RIGHT($A27,5)="Total"),"", $C27 / $E27) -> 2.7702795 | J27: =IFERROR(__xludf.DUMMYFUNCTION("IF($B27="""","""", 100 * $E27 / MAX(FILTER($E:$E, $A:$A=$A27, $B:$B<>"""")) ) "),64.83977900552486) -> 64.839779 | K27: =IFERROR(__xludf.DUMMYFUNCTION("IF($B27="""","""", 100 * $H27 / MAX(FILTER($H:$H, $A:$A=$A27, $B:$B<>"""")) ) "),0.0) -> 0 | L27: =IF($B27="","", 0.4*$I27 + 0.6*$J27) -> 40.011979 | M27: =IFERROR(__xludf.DUMMYFUNCTION("IF($B27="""","""", RANK($K27, FILTER($K:$K, $A:$A=$A27, $B:$B<>""""), 0) ) "),25.0) -> 25 | N27: =IF($B27="","", IF($L27>=60,"🟢 Strong", IF($L27>=35,"🟡 Watch", "🔴 Action Needed"))) -> 🟡 Watch | O27: =IF($B27="","", IF($N27="🟢 Strong","OK", IF($K27<$J27,"Profit issue → pricing/cost/rent", "Traffic issue → location/product mix"))) -> Profit issue → pricing/cost/rent
F28: 1000 | G28: 1000 | H28: =IFERROR( D28 + F28 - G28, 0) -> 1752.25 | I28: =IF(OR($B28="",RIGHT($A28,5)="Total"),"", $C28 / $E28) -> 3.3529412 | J28: =IFERROR(__xludf.DUMMYFUNCTION("IF($B28="""","""", 100 * $E28 / MAX(FILTER($E:$E, $A:$A=$A28, $B:$B<>"""")) ) "),23.668508287292816) -> 23.668508 | K28: =IFERROR(__xludf.DUMMYFUNCTION("IF($B28="""","""", 100 * $H28 / MAX(FILTER($H:$H, $A:$A=$A28, $B:$B<>"""")) ) "),32.41689730193735) -> 32.416897 | L28: =IF($B28="","", 0.4*$I28 + 0.6*$J28) -> 15.542281 | M28: =IFERROR(__xludf.DUMMYFUNCTION("IF($B28="""","""", RANK($K28, FILTER($K:$K, $A:$A=$A28, $B:$B<>""""), 0) ) "),10.0) -> 10 | N28: =IF($B28="","", IF($L28>=60,"🟢 Strong", IF($L28>=35,"🟡 Watch", "🔴 Action Needed"))) -> 🔴 Action Needed | O28: =IF($B28="","", IF($N28="🟢 Strong","OK", IF($K28<$J28,"Profit issue → pricing/cost/rent", "Traffic issue → location/product mix"))) -> Traffic issue → location/product mix
F29: =SUM(F25:F28) -> 2000 | G29: 1000 | H29: =IFERROR( D29 + F29 - G29, 0) -> 12033.01 | I29: =IF(OR($B29="",RIGHT($A29,5)="Total"),"", $C29 / $E29) | J29: =IFERROR(__xludf.DUMMYFUNCTION("IF($B29="""","""", 100 * $E29 / MAX(FILTER($E:$E, $A:$A=$A29, $B:$B<>"""")) ) "),"") | K29: =IFERROR(__xludf.DUMMYFUNCTION("IF($B29="""","""", 100 * $H29 / MAX(FILTER($H:$H, $A:$A=$A29, $B:$B<>"""")) ) "),"") | L29: =IF($B29="","", 0.4*$I29 + 0.6*$J29) | M29: =IFERROR(__xludf.DUMMYFUNCTION("IF($B29="""","""", RANK($K29, FILTER($K:$K, $A:$A=$A29, $B:$B<>""""), 0) ) "),"") | N29: =IF($B29="","", IF($L29>=60,"🟢 Strong", IF($L29>=35,"🟡 Watch", "🔴 Action Needed"))) | O29: =IF($B29="","", IF($N29="🟢 Strong","OK", IF($K29<$J29,"Profit issue → pricing/cost/rent", "Traffic issue → location/product mix")))
F30: 1000 | H30: =IFERROR( D30 + F29 - G30, 0) -> 5760 | I30: =IF(OR($B30="",RIGHT($A30,5)="Total"),"", $C30 / $E30) -> 2.7187274 | J30: =IFERROR(__xludf.DUMMYFUNCTION("IF($B30="""","""", 100 * $E30 / MAX(FILTER($E:$E, $A:$A=$A30, $B:$B<>"""")) ) "),100.0) -> 100 | K30: =IFERROR(__xludf.DUMMYFUNCTION("IF($B30="""","""", 100 * $H30 / MAX(FILTER($H:$H, $A:$A=$A30, $B:$B<>"""")) ) "),100.0) -> 100 | L30: =IF($B30="","", 0.4*$I30 + 0.6*$J30) -> 61.087491 | M30: =IFERROR(__xludf.DUMMYFUNCTION("IF($B30="""","""", RANK($K30, FILTER($K:$K, $A:$A=$A30, $B:$B<>""""), 0) ) "),1.0) -> 1 | N30: =IF($B30="","", IF($L30>=60,"🟢 Strong", IF($L30>=35,"🟡 Watch", "🔴 Action Needed"))) -> 🟢 Strong | O30: =IF($B30="","", IF($N30="🟢 Strong","OK", IF($K30<$J30,"Profit issue → pricing/cost/rent", "Traffic issue → location/product mix"))) -> OK
H31: =IFERROR( D31 + F31 - G31, 0) -> 1140.2 | I31: =IF(OR($B31="",RIGHT($A31,5)="Total"),"", $C31 / $E31) -> 2.8326558 | J31: =IFERROR(__xludf.DUMMYFUNCTION("IF($B31="""","""", 100 * $E31 / MAX(FILTER($E:$E, $A:$A=$A31, $B:$B<>"""")) ) "),32.61878453038674) -> 32.618785 | K31: =IFERROR(__xludf.DUMMYFUNCTION("IF($B31="""","""", 100 * $H31 / MAX(FILTER($H:$H, $A:$A=$A31, $B:$B<>"""")) ) "),21.093877188568385) -> 21.093877 | L31: =IF($B31="","", 0.4*$I31 + 0.6*$J31) -> 20.704333 | M31: =IFERROR(__xludf.DUMMYFUNCTION("IF($B31="""","""", RANK($K31, FILTER($K:$K, $A:$A=$A31, $B:$B<>""""), 0) ) "),18.0) -> 18 | N31: =IF($B31="","", IF($L31>=60,"🟢 Strong", IF($L31>=35,"🟡 Watch", "🔴 Action Needed"))) -> 🔴 Action Needed | O31: =IF($B31="","", IF($N31="🟢 Strong","OK", IF($K31<$J31,"Profit issue → pricing/cost/rent", "Traffic issue → location/product mix"))) -> Profit issue → pricing/cost/rent
F32: 1000 | G32: 350 | I32: =IF(OR($B32="",RIGHT($A32,5)="Total"),"", $C32 / $E32) -> 2.6260959 | J32: =IFERROR(__xludf.DUMMYFUNCTION("IF($B32="""","""", 100 * $E32 / MAX(FILTER($E:$E, $A:$A=$A32, $B:$B<>"""")) ) "),42.850828729281766) -> 42.850829 | K32: =IFERROR(__xludf.DUMMYFUNCTION("IF($B32="""","""", 100 * $H32 / MAX(FILTER($H:$H, $A:$A=$A32, $B:$B<>"""")) ) "),0.0) -> 0 | L32: =IF($B32="","", 0.4*$I32 + 0.6*$J32) -> 26.760936 | M32: =IFERROR(__xludf.DUMMYFUNCTION("IF($B32="""","""", RANK($K32, FILTER($K:$K, $A:$A=$A32, $B:$B<>""""), 0) ) "),25.0) -> 25 | N32: =IF($B32="","", IF($L32>=60,"🟢 Strong", IF($L32>=35,"🟡 Watch", "🔴 Action Needed"))) -> 🔴 Action Needed | O32: =IF($B32="","", IF($N32="🟢 Strong","OK", IF($K32<$J32,"Profit issue → pricing/cost/rent", "Traffic issue → location/product mix"))) -> Profit issue → pricing/cost/rent
G33: 1000 | H33: =IFERROR( D33 + F33 - G33, 0) -> 570.52 | I33: =IF(OR($B33="",RIGHT($A33,5)="Total"),"", $C33 / $E33) -> 2.4701107 | J33: =IFERROR(__xludf.DUMMYFUNCTION("IF($B33="""","""", 100 * $E33 / MAX(FILTER($E:$E, $A:$A=$A33, $B:$B<>"""")) ) "),29.944751381215468) -> 29.944751 | K33: =IFERROR(__xludf.DUMMYFUNCTION("IF($B33="""","""", 100 * $H33 / MAX(FILTER($H:$H, $A:$A=$A33, $B:$B<>"""")) ) "),10.55470865955275) -> 10.554709 | L33: =IF($B33="","", 0.4*$I33 + 0.6*$J33) -> 18.954895 | M33: =IFERROR(__xludf.DUMMYFUNCTION("IF($B33="""","""", RANK($K33, FILTER($K:$K, $A:$A=$A33, $B:$B<>""""), 0) ) "),23.0) -> 23 | N33: =IF($B33="","", IF($L33>=60,"🟢 Strong", IF($L33>=35,"🟡 Watch", "🔴 Action Needed"))) -> 🔴 Action Needed | O33: =IF($B33="","", IF($N33="🟢 Strong","OK", IF($K33<$J33,"Profit issue → pricing/cost/rent", "Traffic issue → location/product mix"))) -> Profit issue → pricing/cost/rent
F34: =SUM(F30:F33) -> 2000 | G34: 0 | H34: =IFERROR( D34 + F34 - G34, 0) -> 10217.22 | I34: =IF(OR($B34="",RIGHT($A34,5)="Total"),"", $C34 / $E34) | J34: =IFERROR(__xludf.DUMMYFUNCTION("IF($B34="""","""", 100 * $E34 / MAX(FILTER($E:$E, $A:$A=$A34, $B:$B<>"""")) ) "),"") | K34: =IFERROR(__xludf.DUMMYFUNCTION("IF($B34="""","""", 100 * $H34 / MAX(FILTER($H:$H, $A:$A=$A34, $B:$B<>"""")) ) "),"") | L34: =IF($B34="","", 0.4*$I34 + 0.6*$J34) | M34: =IFERROR(__xludf.DUMMYFUNCTION("IF($B34="""","""", RANK($K34, FILTER($K:$K, $A:$A=$A34, $B:$B<>""""), 0) ) "),"") | N34: =IF($B34="","", IF($L34>=60,"🟢 Strong", IF($L34>=35,"🟡 Watch", "🔴 Action Needed"))) | O34: =IF($B34="","", IF($N34="🟢 Strong","OK", IF($K34<$J34,"Profit issue → pricing/cost/rent", "Traffic issue → location/product mix")))
H35: =IFERROR( D35 + F35 - G35, 0) -> 4317 | I35: =IF(OR($B35="",RIGHT($A35,5)="Total"),"", $C35 / $E35) -> 2.8934316 | J35: =IFERROR(__xludf.DUMMYFUNCTION("IF($B35="""","""", 100 * $E35 / MAX(FILTER($E:$E, $A:$A=$A35, $B:$B<>"""")) ) "),100.0) -> 100 | K35: =IFERROR(__xludf.DUMMYFUNCTION("IF($B35="""","""", 100 * $H35 / MAX(FILTER($H:$H, $A:$A=$A35, $B:$B<>"""")) ) "),100.0) -> 100 | L35: =IF($B35="","", 0.4*$I35 + 0.6*$J35) -> 61.157373 | M35: =IFERROR(__xludf.DUMMYFUNCTION("IF($B35="""","""", RANK($K35, FILTER($K:$K, $A:$A=$A35, $B:$B<>""""), 0) ) "),1.0) -> 1 | N35: =IF($B35="","", IF($L35>=60,"🟢 Strong", IF($L35>=35,"🟡 Watch", "🔴 Action Needed"))) -> 🟢 Strong | O35: =IF($B35="","", IF($N35="🟢 Strong","OK", IF($K35<$J35,"Profit issue → pricing/cost/rent", "Traffic issue → location/product mix"))) -> OK
G36: 350 | H36: =IFERROR( D36 + F36 - G36, 0) -> 1057.54 | I36: =IF(OR($B36="",RIGHT($A36,5)="Total"),"", $C36 / $E36) -> 3.1443489 | J36: =IFERROR(__xludf.DUMMYFUNCTION("IF($B36="""","""", 100 * $E36 / MAX(FILTER($E:$E, $A:$A=$A36, $B:$B<>"""")) ) "),35.97790055248619) -> 35.977901 | K36: =IFERROR(__xludf.DUMMYFUNCTION("IF($B36="""","""", 100 * $H36 / MAX(FILTER($H:$H, $A:$A=$A36, $B:$B<>"""")) ) "),19.56465434309649) -> 19.564654 | L36: =IF($B36="","", 0.4*$I36 + 0.6*$J36) -> 22.84448 | M36: =IFERROR(__xludf.DUMMYFUNCTION("IF($B36="""","""", RANK($K36, FILTER($K:$K, $A:$A=$A36, $B:$B<>""""), 0) ) "),19.0) -> 19 | N36: =IF($B36="","", IF($L36>=60,"🟢 Strong", IF($L36>=35,"🟡 Watch", "🔴 Action Needed"))) -> 🔴 Action Needed | O36: =IF($B36="","", IF($N36="🟢 Strong","OK", IF($K36<$J36,"Profit issue → pricing/cost/rent", "Traffic issue → location/product mix"))) -> Profit issue → pricing/cost/rent
F38: 1000 | G38: 1000 | H38: =IFERROR( D38 + F38 - G38, 0) -> 1704.18 | I38: =IF(OR($B38="",RIGHT($A38,5)="Total"),"", $C38 / $E38) -> 2.6682792 | J38: =IFERROR(__xludf.DUMMYFUNCTION("IF($B38="""","""", 100 * $E38 / MAX(FILTER($E:$E, $A:$A=$A38, $B:$B<>"""")) ) "),31.977900552486187) -> 31.977901 | K38: =IFERROR(__xludf.DUMMYFUNCTION("IF($B38="""","""", 100 * $H38 / MAX(FILTER($H:$H, $A:$A=$A38, $B:$B<>"""")) ) "),31.5275948317966) -> 31.527595 | L38: =IF($B38="","", 0.4*$I38 + 0.6*$J38) -> 20.254052 | M38: =IFERROR(__xludf.DUMMYFUNCTION("IF($B38="""","""", RANK($K38, FILTER($K:$K, $A:$A=$A38, $B:$B<>""""), 0) ) "),11.0) -> 11 | N38: =IF($B38="","", IF($L38>=60,"🟢 Strong", IF($L38>=35,"🟡 Watch", "🔴 Action Needed"))) -> 🔴 Action Needed | O38: =IF($B38="","", IF($N38="🟢 Strong","OK", IF($K38<$J38,"Profit issue → pricing/cost/rent", "Traffic issue → location/product mix"))) -> Profit issue → pricing/cost/rent
F39: 1000 | G39: 0 | H39: =IFERROR( D39 + F39 - G39, 0) -> 11001.51 | I39: =IF(OR($B39="",RIGHT($A39,5)="Total"),"", $C39 / $E39) | J39: =IFERROR(__xludf.DUMMYFUNCTION("IF($B39="""","""", 100 * $E39 / MAX(FILTER($E:$E, $A:$A=$A39, $B:$B<>"""")) ) "),"") | K39: =IFERROR(__xludf.DUMMYFUNCTION("IF($B39="""","""", 100 * $H39 / MAX(FILTER($H:$H, $A:$A=$A39, $B:$B<>"""")) ) "),"") | L39: =IF($B39="","", 0.4*$I39 + 0.6*$J39) | M39: =IFERROR(__xludf.DUMMYFUNCTION("IF($B39="""","""", RANK($K39, FILTER($K:$K, $A:$A=$A39, $B:$B<>""""), 0) ) "),"") | N39: =IF($B39="","", IF($L39>=60,"🟢 Strong", IF($L39>=35,"🟡 Watch", "🔴 Action Needed"))) | O39: =IF($B39="","", IF($N39="🟢 Strong","OK", IF($K39<$J39,"Profit issue → pricing/cost/rent", "Traffic issue → location/product mix")))
G40: 0 | H40: =IFERROR( D40 + F40 - G40, 0) -> 0 | I40: =IF(OR($B40="",RIGHT($A40,5)="Total"),"", $C40 / $E40) | J40: =IFERROR(__xludf.DUMMYFUNCTION("IF($B40="""","""", 100 * $E40 / MAX(FILTER($E:$E, $A:$A=$A40, $B:$B<>"""")) ) "),"") | K40: =IFERROR(__xludf.DUMMYFUNCTION("IF($B40="""","""", 100 * $H40 / MAX(FILTER($H:$H, $A:$A=$A40, $B:$B<>"""")) ) "),"") | L40: =IF($B40="","", 0.4*$I40 + 0.6*$J40) | M40: =IFERROR(__xludf.DUMMYFUNCTION("IF($B40="""","""", RANK($K40, FILTER($K:$K, $A:$A=$A40, $B:$B<>""""), 0) ) "),"") | N40: =IF($B40="","", IF($L40>=60,"🟢 Strong", IF($L40>=35,"🟡 Watch", "🔴 Action Needed"))) | O40: =IF($B40="","", IF($N40="🟢 Strong","OK", IF($K40<$J40,"Profit issue → pricing/cost/rent", "Traffic issue → location/product mix")))
G41: 150 | H41: =IFERROR( D41 + F41 - G41, 0) -> 3557 | I41: =IF(OR($B41="",RIGHT($A41,5)="Total"),"", $C41 / $E41) -> 2.5149254 | J41: =IFERROR(__xludf.DUMMYFUNCTION("IF($B41="""","""", 100 * $E41 / MAX(FILTER($E:$E, $A:$A=$A41, $B:$B<>"""")) ) "),32.574585635359114) -> 32.574586 | K41: =IFERROR(__xludf.DUMMYFUNCTION("IF($B41="""","""", 100 * $H41 / MAX(FILTER($H:$H, $A:$A=$A41, $B:$B<>"""")) ) "),65.80505276244322) -> 65.805053 | L41: =IF($B41="","", 0.4*$I41 + 0.6*$J41) -> 20.550722 | M41: =IFERROR(__xludf.DUMMYFUNCTION("IF($B41="""","""", RANK($K41, FILTER($K:$K, $A:$A=$A41, $B:$B<>""""), 0) ) "),6.0) -> 6 | N41: =IF($B41="","", IF($L41>=60,"🟢 Strong", IF($L41>=35,"🟡 Watch", "🔴 Action Needed"))) -> 🔴 Action Needed | O41: =IF($B41="","", IF($N41="🟢 Strong","OK", IF($K41<$J41,"Profit issue → pricing/cost/rent", "Traffic issue → location/product mix"))) -> Traffic issue → location/product mix

Sheet VMS_Sales
A1: Machine code | B1: Machine name | C1: Product Number | D1: product name | E1: Commodity price | F1: Number of transaction | G1: Transaction amount | H1: The refund count | I1: Refund amount | J1: Total Transaction Quantity | K1: Total Transaction Amount | L1: Cost Price | M1: Cost Amount | N1: Profits | O1: MonthKey_Row | P1: MonthKey
A2: 2404120076 | B2: DPMall | D2: Tiger Medium 16 | F2: 19 | G2: 77 | J2: 19 | K2: 77 | L2: 0 | M2: 0 | N2: 77 | O2: 45658 | P2: 45658
A3: 2404120076 | B3: DPMall | D3: Takis | F3: 46 | G3: 820 | J3: 46 | K3: 820 | L3: 0 | M3: 0 | N3: 820 | O3: 45658
A4: 2404120076 | B4: DPMall | D4: Tiger excellence *10 | F4: 88 | G4: 430 | J4: 88 | K4: 430 | L4: 0 | M4: 0 | N4: 430 | O4: 45658
A5: 2404120076 | B5: DPMall | D5: kinza | F5: 29 | G5: 58 | J5: 29 | K5: 58 | L5: 0 | M5: 0 | N5: 58 | O5: 45658
A6: 2404120076 | B6: DPMall | D6: Dark blue energy | F6: 19 | G6: 57 | J6: 19 | K6: 57 | L6: 0 | M6: 0 | N6: 57 | O6: 45658
A7: 2404120076 | B7: DPMall | D7: tiger chips *12 | F7: 152 | G7: 608 | J7: 152 | K7: 608 | L7: 0 | M7: 0 | N7: 608 | O7: 45658
A8: 2404120076 | B8: DPMall | D8: Mr Crunch cheez top | F8: 50 | G8: 200 | J8: 50 | K8: 200 | L8: 0 | M8: 0 | N8: 200 | O8: 45658
A9: 2404120076 | B9: DPMall | D9: popcorn pizza funday | F9: 3 | G9: 15 | J9: 3 | K9: 15 | L9: 0 | M9: 0 | N9: 15 | O9: 45658
A10: 2404120076 | B10: DPMall | D10: ono cake | F10: 88 | G10: 88 | J10: 88 | K10: 88 | L10: 0 | M10: 0 | N10: 88 | O10: 45658
A11: 2404120076 | B11: DPMall | D11: Masa suntop | F11: 320 | G11: 333 | J11: 320 | K11: 333 | L11: 0 | M11: 0 | N11: 333 | O11: 45658
A12: 2404120076 | B12: DPMall | D12: Mr Crunch | F12: 108 | G12: 420 | J12: 108 | K12: 420 | L12: 0 | M12: 0 | N12: 420 | O12: 45658
A13: 2404120076 | B13: DPMall | D13: Roshen Chocolate | F13: 34 | G13: 97 | J13: 34 | K13: 97 | L13: 0 | M13: 0 | N13: 97 | O13: 45658
A14: 2404120076 | B14: DPMall | D14: GoOn Energy chocolate | F14: 1 | G14: 3 | J14: 1 | K14: 3 | L14: 0 | M14: 0 | N14: 3 | O14: 45658
... A38: 2404120076 | B38: DPMall | D38: Tiger Small | F38: 2 | G38: 6 | J38: 2 | K38: 6 | L38: 0 | M38: 0 | N38: 6 | O38: 45658
J39: 0 | K39: 0 | L39: 0 | M39: 0 | N39: 0
A40: 2404120076 | B40: DPMall | D40: Tiger Medium 16 | F40: 31 | G40: 93 | J40: 31 | K40: 93 | L40: 0 | M40: 0 | N40: 93 | O40: 45689 | P40: 45689
A41: 2404120076 | B41: DPMall | D41: Takis | F41: 40 | G41: 768 | J41: 40 | K41: 768 | L41: 0 | M41: 0 | N41: 768 | O41: 45689
A42: 2404120076 | B42: DPMall | D42: Marshmellow sweetBag | F42: 9 | G42: 27 | J42: 9 | K42: 27 | L42: 0 | M42: 0 | N42: 27 | O42: 45689
A43: 2404120076 | B43: DPMall | D43: Tiger excellence *10 | F43: 54 | G43: 268 | J43: 54 | K43: 268 | L43: 0 | M43: 0 | N43: 268 | O43: 45689
A44: 2404120076 | B44: DPMall | D44: vivaldi | F44: 22 | G44: 44 | J44: 22 | K44: 44 | L44: 0 | M44: 0 | N44: 44 | O44: 45689
A45: 2404120076 | B45: DPMall | D45: kinza | F45: 69 | G45: 138 | J45: 69 | K45: 138 | L45: 0 | M45: 0 | N45: 138 | O45: 45689
A46: 2404120076 | B46: DPMall | D46: Tiger excellence super jambo | F46: 10 | G46: 50 | J46: 10 | K46: 50 | L46: 0 | M46: 0 | N46: 50 | O46: 45689
A47: 2404120076 | B47: DPMall | D47: xo energy | F47: 31 | G47: 156 | J47: 31 | K47: 156 | L47: 0 | M47: 0 | N47: 156 | O47: 45689
A48: 2404120076 | B48: DPMall | D48: tiger chips *12 | F48: 174 | G48: 691 | J48: 174 | K48: 691 | L48: 0 | M48: 0 | N48: 691 | O48: 45689
A49: 2404120076 | B49: DPMall | D49: Mr Crunch cheez top | F49: 50 | G49: 200 | J49: 50 | K49: 200 | L49: 0 | M49: 0 | N49: 200 | O49: 45689
A50: 2404120076 | B50: DPMall | D50: popcorn pizza funday | F50: 18 | G50: 84 | J50: 18 | K50: 84 | L50: 0 | M50: 0 | N50: 84 | O50: 45689
A51: 2404120076 | B51: DPMall | D51: ono cake | F51: 61 | G51: 61 | J51: 61 | K51: 61 | L51: 0 | M51: 0 | N51: 61 | O51: 45689
A52: 2404120076 | B52: DPMall | D52: flik flak | F52: 363 | G52: 363 | J52: 363 | K52: 363 | L52: 0 | M52: 0 | N52: 363 | O52: 45689
... A88: 2404120076 | B88: DPMall | D88: Spuds noraml | F88: 8 | G88: 41 | J88: 8 | K88: 41 | L88: 0 | M88: 0 | N88: 41 | O88: 45689
J89: 0 | K89: 0 | L89: 0 | M89: 0 | N89: 0
J90: 0 | K90: 0 | L90: 0 | M90: 0 | N90: 0
J91: 0 | K91: 0 | L91: 0 | M91: 0 | N91: 0
J92: 0 | K92: 0 | L92: 0 | M92: 0 | N92: 0
J93: 0 | K93: 0 | L93: 0 | M93: 0 | N93: 0
A94: 2404120076 | B94: DPMall | D94: Takis | F94: 23 | G94: 428 | J94: 23 | K94: 428 | L94: 0 | M94: 0 | N94: 428 | O94: 45717 | P94: 45717
A95: 2404120076 | B95: DPMall | D95: Tiger excellence *10 | F95: 64 | G95: 320 | J95: 64 | K95: 320 | L95: 0 | M95: 0 | N95: 320 | O95: 45717
A96: 2404120076 | B96: DPMall | D96: kinza | F96: 39 | G96: 78 | J96: 39 | K96: 78 | L96: 0 | M96: 0 | N96: 78 | O96: 45717
A97: 2404120076 | B97: DPMall | D97: xo energy | F97: 30 | G97: 150 | J97: 30 | K97: 150 | L97: 0 | M97: 0 | N97: 150 | O97: 45717
A98: 2404120076 | B98: DPMall | D98: Tiger *12 | F98: 211 | G98: 841 | J98: 211 | K98: 841 | L98: 0 | M98: 0 | N98: 841 | O98: 45717
A99: 2404120076 | B99: DPMall | D99: Mr Crunch cheez top | F99: 2 | G99: 8 | J99: 2 | K99: 8 | L99: 0 | M99: 0 | N99: 8 | O99: 45717
A100: 2404120076 | B100: DPMall | D100: flik flak | F100: 465 | G100: 465 | J100: 465 | K100: 465 | L100: 0 | M100: 0 | N100: 465 | O100: 45717
A101: 2404120076 | B101: DPMall | D101: Masa suntop | F101: 106 | G101: 106 | J101: 106 | K101: 106 | L101: 0 | M101: 0 | N101: 106 | O101: 45717
A102: 2404120076 | B102: DPMall | D102: Mr Crunch | F102: 35 | G102: 145 | J102: 35 | K102: 145 | L102: 0 | M102: 0 | N102: 145 | O102: 45717
A103: 2404120076 | B103: DPMall | D103: pattes chips | F103: 8 | G103: 42 | J103: 8 | K103: 42 | L103: 0 | M103: 0 | N103: 42 | O103: 45717
A104: 2404120076 | B104: DPMall | D104: maxxx chips 65g | F104: 7 | G104: 28 | J104: 7 | K104: 28 | L104: 0 | M104: 0 | N104: 28 | O104: 45717
A105: 2404120076 | B105: DPMall | D105: monster energy | F105: 2 | G105: 10 | J105: 2 | K105: 10 | L105: 0 | M105: 0 | N105: 10 | O105: 45717
A106: 2404120076 | B106: DPMall | D106: Freez drink | F106: 8 | G106: 40 | J106: 8 | K106: 40 | L106: 0 | M106: 0 | N106: 40 | O106: 45717
... A139: 2404120076 | B139: DPMall | D139: prigles bugle | F139: 44 | G139: 176 | J139: 44 | K139: 176 | L139: 0 | M139: 0 | N139: 176 | O139: 45717
J140: 0 | K140: 0 | L140: 0 | M140: 0 | N140: 0
J141: 0 | K141: 0 | L141: 0 | M141: 0 | N141: 0
J142: 0 | K142: 0 | L142: 0 | M142: 0 | N142: 0
J143: 0 | K143: 0 | L143: 0 | M143: 0 | N143: 0
J144: 0 | K144: 0 | L144: 0 | M144: 0 | N144: 0
A145: 2404120076 | B145: DPMall | D145: Takis | F145: 9 | G145: 165 | J145: 9 | K145: 165 | L145: 0 | M145: 0 | N145: 165 | O145: 45748 | P145: 45748
A146: 2404120076 | B146: DPMall | D146: Marshmellow sweetBag | F146: 57 | G146: 208 | J146: 57 | K146: 208 | L146: 0 | M146: 0 | N146: 208 | O146: 45748
A147: 2404120076 | B147: DPMall | D147: Tiger excellence *10 | F147: 109 | G147: 511 | J147: 109 | K147: 511 | L147: 0 | M147: 0 | N147: 511 | O147: 45748
A148: 2404120076 | B148: DPMall | D148: kinza | F148: 106 | G148: 212 | J148: 106 | K148: 212 | L148: 0 | M148: 0 | N148: 212 | O148: 45748
A149: 2404120076 | B149: DPMall | D149: xo energy | F149: 22 | G149: 110 | J149: 22 | K149: 110 | L149: 0 | M149: 0 | N149: 110 | O149: 45748
A150: 2404120076 | B150: DPMall | D150: Tiger *12 | F150: 499 | G150: 2294 | J150: 499 | K150: 2294 | L150: 0 | M150: 0 | N150: 2294 | O150: 45748
A151: 2404120076 | B151: DPMall | D151: flik flak | F151: 566 | G151: 566 | J151: 566 | K151: 566 | L151: 0 | M151: 0 | N151: 566 | O151: 45748
A152: 2404120076 | B152: DPMall | D152: Masa suntop | F152: 22 | G152: 22 | J152: 22 | K152: 22 | L152: 0 | M152: 0 | N152: 22 | O152: 45748
A153: 2404120076 | B153: DPMall | D153: Mr Crunch | F153: 170 | G153: 683 | J153: 170 | K153: 683 | L153: 0 | M153: 0 | N153: 683 | O153: 45748
A154: 2404120076 | B154: DPMall | D154: Freez drink | F154: 42 | G154: 210 | J154: 42 | K154: 210 | L154: 0 | M154: 0 | N154: 210 | O154: 45748
A155: 2404120076 | B155: DPMall | D155: snickers | F155: 15 | G155: 75 | J155: 15 | K155: 75 | L155: 0 | M155: 0 | N155: 75 | O155: 45748
A156: 2404120076 | B156: DPMall | D156: Green | F156: 17 | G156: 68 | J156: 17 | K156: 68 | L156: 0 | M156: 0 | N156: 68 | O156: 45748
A157: 2404120076 | B157: DPMall | D157: skittles drink | F157: 20 | G157: 140 | J157: 20 | K157: 140 | L157: 0 | M157: 0 | N157: 140 | O157: 45748
... A185: 2404120076 | B185: DPMall | D185: prigles bugle | F185: 101 | G185: 417 | J185: 101 | K185: 417 | L185: 0 | M185: 0 | N185: 417 | O185: 45748
J186: 0 | K186: 0 | L186: 0 | M186: 0 | N186: 0
A187: 2404120076 | B187: DPMall | D187: Takis | F187: 2 | G187: 50 | J187: 2 | K187: 50 | L187: 0 | M187: 0 | N187: 50 | O187: 45778 | P187: 45778
A188: 2404120076 | B188: DPMall | D188: Marshmellow sweetBag | F188: 16 | G188: 56 | J188: 16 | K188: 56 | L188: 0 | M188: 0 | N188: 56 | O188: 45778
A189: 2404120076 | B189: DPMall | D189: kinza | F189: 59 | G189: 115 | J189: 59 | K189: 115 | L189: 0 | M189: 0 | N189: 115 | O189: 45778
A190: 2404120076 | B190: DPMall | D190: xo energy | F190: 24 | G190: 120 | J190: 24 | K190: 120 | L190: 0 | M190: 0 | N190: 120 | O190: 45778
A191: 2404120076 | B191: DPMall | D191: Tiger *12 | F191: 233 | G191: 1172 | J191: 233 | K191: 1172 | L191: 0 | M191: 0 | N191: 1172 | O191: 45778
A192: 2404120076 | B192: DPMall | D192: ono cake | F192: 60 | G192: 74 | J192: 60 | K192: 74 | L192: 0 | M192: 0 | N192: 74 | O192: 45778
A193: 2404120076 | B193: DPMall | D193: flik flak | F193: 279 | G193: 290 | J193: 279 | K193: 290 | L193: 0 | M193: 0 | N193: 290 | O193: 45778
A194: 2404120076 | B194: DPMall | D194: Mr Crunch | F194: 7 | G194: 28 | J194: 7 | K194: 28 | L194: 0 | M194: 0 | N194: 28 | O194: 45778
A195: 2404120076 | B195: DPMall | D195: Freez drink | F195: 18 | G195: 90 | J195: 18 | K195: 90 | L195: 0 | M195: 0 | N195: 90 | O195: 45778
A196: 2404120076 | B196: DPMall | D196: snickers | F196: 5 | G196: 25 | J196: 5 | K196: 25 | L196: 0 | M196: 0 | N196: 25 | O196: 45778
A197: 2404120076 | B197: DPMall | D197: Green | F197: 8 | G197: 32 | J197: 8 | K197: 32 | L197: 0 | M197: 0 | N197: 32 | O197: 45778
A198: 2404120076 | B198: DPMall | D198: waffle cones | F198: 3 | G198: 12 | J198: 3 | K198: 12 | L198: 0 | M198: 0 | N198: 12 | O198: 45778
A199: 2404120076 | B199: DPMall | D199: skittles drink | F199: 34 | G199: 236 | J199: 34 | K199: 236 | L199: 0 | M199: 0 | N199: 236 | O199: 45778
... A221: 2404120076 | B221: DPMall | D221: ifrui juice | F221: 12 | G221: 24 | J221: 12 | K221: 24 | L221: 0 | M221: 0 | N221: 24 | O221: 45778
J222: 0 | K222: 0 | L222: 0 | M222: 0 | N222: 0
J223: 0 | K223: 0 | L223: 0 | M223: 0 | N223: 0
J224: 0 | K224: 0 | L224: 0 | M224: 0 | N224: 0
J225: 0 | K225: 0 | L225: 0 | M225: 0 | N225: 0
J226: 0 | K226: 0 | L226: 0 | M226: 0 | N226: 0
J227: 0 | K227: 0 | L227: 0 | M227: 0 | N227: 0
J228: 0 | K228: 0 | L228: 0 | M228: 0 | N228: 0
J229: 0 | K229: 0 | L229: 0 | M229: 0 | N229: 0
J230: 0 | K230: 0 | L230: 0 | M230: 0 | N230: 0
J231: 0 | K231: 0 | L231: 0 | M231: 0 | N231: 0
J232: 0 | K232: 0 | L232: 0 | M232: 0 | N232: 0
A233: 2503000216 | B233: HTMall | C233: 1 | D233: Doritos cool ranc | E233: 5 | F233: 332 | G233: 1660 | H233: 0 | I233: 0 | J233: 332 | K233: 1660 | L233: 2.8 | M233: 929.6 | N233: 730.4 | O233: 45809 | P233: 45809
A234: 2503000216 | B234: HTMall | C234: 2 | D234: Water | E234: 1 | F234: 1024 | G234: 1024 | H234: 0 | I234: 0 | J234: 1024 | K234: 1024 | L234: 0.3 | M234: 307.2 | N234: 716.8 | O234: 45809
A235: 2503000216 | B235: HTMall | C235: 3 | D235: Maltesers | E235: 7 | F235: 127 | G235: 635 | H235: 0 | I235: 0 | J235: 127 | K235: 635 | L235: 6.2 | M235: 787.4 | N235: -152.4 | O235: 45809
A236: 2503000216 | B236: HTMall | C236: 4 | D236: Skittles drink | E236: 8 | F236: 21 | G236: 149 | H236: 0 | I236: 0 | J236: 21 | K236: 149 | L236: 4.75 | M236: 99.75 | N236: 49.25 | O236: 45809
A237: 2503000216 | B237: HTMall | C237: 5 | D237: Schweppes | E237: 3 | F237: 46 | G237: 138 | H237: 0 | I237: 0 | J237: 46 | K237: 138 | L237: 2 | M237: 92 | N237: 46 | O237: 45809
A238: 2503000216 | B238: HTMall | C238: 6 | D238: Tiger *12 | E238: 5 | F238: 269 | G238: 1368 | H238: 0 | I238: 0 | J238: 269 | K238: 1368 | L238: 3.08 | M238: 828.52 | N238: 539.48 | O238: 45809
...

Sheet forcast
A1: Product Name | B1: Last Month | C1: Avg 3M | D1: Forecast | E1: Cost | F1: Forecast Cost | G1: Purchased This Month | H1: Current Stock | I1: Need to Buy | J1: Buy Cost | L1: 46113 | N1: =IFERROR(__xludf.DUMMYFUNCTION("QUERY(A1:J1497,""select * where A is not null and D > 0 order by J desc"",1)"),"Product Name") -> Product Name | O1: =IFERROR(__xludf.DUMMYFUNCTION("""COMPUTED_VALUE"""),"Last Month") -> Last Month | P1: =IFERROR(__xludf.DUMMYFUNCTION("""COMPUTED_VALUE"""),"Avg 3M") -> Avg 3M | Q1: =IFERROR(__xludf.DUMMYFUNCTION("""COMPUTED_VALUE"""),"Forecast") -> Forecast | R1: =IFERROR(__xludf.DUMMYFUNCTION("""COMPUTED_VALUE"""),"Cost") -> Cost | S1: =IFERROR(__xludf.DUMMYFUNCTION("""COMPUTED_VALUE"""),"Forecast Cost") -> Forecast Cost | T1: =IFERROR(__xludf.DUMMYFUNCTION("""COMPUTED_VALUE"""),"Purchased This Month") -> Purchased This Month | U1: =IFERROR(__xludf.DUMMYFUNCTION("""COMPUTED_VALUE"""),"Current Stock") -> Current Stock | V1: =IFERROR(__xludf.DUMMYFUNCTION("""COMPUTED_VALUE"""),"Need to Buy") -> Need to Buy | W1: =IFERROR(__xludf.DUMMYFUNCTION("""COMPUTED_VALUE"""),"Buy Cost") -> Buy Cost
A2: =IFERROR(__xludf.DUMMYFUNCTION("UNIQUE(FILTER( VMS_Sales!D2:D1497, VMS_Sales!D2:D1497<>"""", VMS_Sales!D2:D1497<>""æœ•àë®¾ç½®"", VMS_Sales!O2:O1497>=EDATE($L$1,-2), VMS_Sales!B2:B1497<>""DPMall"" ))"),"Doritos cool ranc") -> Doritos cool ranc | B2: =IF(A2="","",SUMIFS(VMS_Sales!F:F,VMS_Sales!D:D,A2,VMS_Sales!O:O,$L$2)) -> 974 | C2: =IF(A2="","",ROUND(( SUMIFS(VMS_Sales!F:F,VMS_Sales!D:D,A2,VMS_Sales!O:O,$L$1)+ SUMIFS(VMS_Sales!F:F,VMS_Sales!D:D,A2,VMS_Sales!O:O,$L$2)+ SUMIFS(VMS_Sales!F:F,VMS_Sales!D:D,A2,VMS_Sales!O:O,$L$3) )/3,2)) -> 471 | D2: =IF(C2="","",ROUND(C2*1.15,0)) -> 542 | E2: =IFERROR(__xludf.DUMMYFUNCTION("IFERROR(XLOOKUP(A2,FILTER(VMS_Sales!$D:$D,VMS_Sales!$O:$O=$L$2),FILTER(VMS_Sales!$L:$L,VMS_Sales!$O:$O=$L$2),""""),"""")"),2.93) -> 2.93 | F2: =IF(OR(D2="",E2=""),"",ROUND(D2*E2,2)) -> 1588.06 | G2: {=IFERROR( SUMIFS( PurchaseLines_Import!$I:$I, PurchaseLines_Import!$C:$C, TEXT(XLOOKUP(A2,Map!$A:$A,Map!$B:$B,""),"0000"), PurchaseLines_Import!$H:$H, $L$1 ), 0)} -> 750 | H2: {=IFERROR( SUMIFS( Inventory_Import!$D:$D, Inventory_Import!$B:$B, TEXT(XLOOKUP(A2,Map!$A:$A,Map!$B:$B,""),"0000") ), 0)} -> 148 | I2: =IF(A2="","",MAX(D2-H2,0)) -> 394 | J2: =IF(OR(I2="",E2=""),"",ROUND(I2*E2,2)) -> 1154.42 | L2: =EDATE(L1,-1) -> 46082 | N2: =IFERROR(__xludf.DUMMYFUNCTION("""COMPUTED_VALUE"""),"X!R") -> X!R | O2: =IFERROR(__xludf.DUMMYFUNCTION("""COMPUTED_VALUE"""),740.0) -> 740 | P2: =IFERROR(__xludf.DUMMYFUNCTION("""COMPUTED_VALUE"""),383.0) -> 383 | Q2: =IFERROR(__xludf.DUMMYFUNCTION("""COMPUTED_VALUE"""),440.0) -> 440 | R2: =IFERROR(__xludf.DUMMYFUNCTION("""COMPUTED_VALUE"""),4.29) -> 4.29 | S2: =IFERROR(__xludf.DUMMYFUNCTION("""COMPUTED_VALUE"""),1887.6) -> 1887.6 | T2: =IFERROR(__xludf.DUMMYFUNCTION("""COMPUTED_VALUE"""),360.0) -> 360 | U2: =IFERROR(__xludf.DUMMYFUNCTION("""COMPUTED_VALUE"""),59.0) -> 59 | V2: =IFERROR(__xludf.DUMMYFUNCTION("""COMPUTED_VALUE"""),381.0) -> 381 | W2: =IFERROR(__xludf.DUMMYFUNCTION("""COMPUTED_VALUE"""),1634.49) -> 1634.49
A3: =IFERROR(__xludf.DUMMYFUNCTION("""COMPUTED_VALUE"""),"Water") -> Water | B3: =IF(A3="","",SUMIFS(VMS_Sales!F:F,VMS_Sales!D:D,A3,VMS_Sales!O:O,$L$2)) -> 2806 | C3: =IF(A3="","",ROUND(( SUMIFS(VMS_Sales!F:F,VMS_Sales!D:D,A3,VMS_Sales!O:O,$L$1)+ SUMIFS(VMS_Sales!F:F,VMS_Sales!D:D,A3,VMS_Sales!O:O,$L$2)+ SUMIFS(VMS_Sales!F:F,VMS_Sales!D:D,A3,VMS_Sales!O:O,$L$3) )/3,2)) -> 1785.67 | D3: =IF(C3="","",ROUND(C3*1.15,0)) -> 2054 | E3: =IFERROR(__xludf.DUMMYFUNCTION("IFERROR(XLOOKUP(A3,FILTER(VMS_Sales!$D:$D,VMS_Sales!$O:$O=$L$2),FILTER(VMS_Sales!$L:$L,VMS_Sales!$O:$O=$L$2),""""),"""")"),0.28) -> 0.28 | F3: =IF(OR(D3="",E3=""),"",ROUND(D3*E3,2)) -> 575.12 | G3: {=IFERROR( SUMIFS( PurchaseLines_Import!$I:$I, PurchaseLines_Import!$C:$C, TEXT(XLOOKUP(A3,Map!$A:$A,Map!$B:$B,""),"0000"), PurchaseLines_Import!$H:$H, $L$1 ), 0)} -> 2328 | H3: {=IFERROR( SUMIFS( Inventory_Import!$D:$D, Inventory_Import!$B:$B, TEXT(XLOOKUP(A3,Map!$A:$A,Map!$B:$B,""),"0000") ), 0)} -> 84 | I3: =IF(A3="","",MAX(D3-H3,0)) -> 1970 | J3: =IF(OR(I3="",E3=""),"",ROUND(I3*E3,2)) -> 551.6 | L3: =EDATE(L1,-2) -> 46054 | N3: =IFERROR(__xludf.DUMMYFUNCTION("""COMPUTED_VALUE"""),"Doritos cool ranc") -> Doritos cool ranc | O3: =IFERROR(__xludf.DUMMYFUNCTION("""COMPUTED_VALUE"""),974.0) -> 974 | P3: =IFERROR(__xludf.DUMMYFUNCTION("""COMPUTED_VALUE"""),471.0) -> 471 | Q3: =IFERROR(__xludf.DUMMYFUNCTION("""COMPUTED_VALUE"""),542.0) -> 542 | R3: =IFERROR(__xludf.DUMMYFUNCTION("""COMPUTED_VALUE"""),2.93) -> 2.93 | S3: =IFERROR(__xludf.DUMMYFUNCTION("""COMPUTED_VALUE"""),1588.06) -> 1588.06 | T3: =IFERROR(__xludf.DUMMYFUNCTION("""COMPUTED_VALUE"""),750.0) -> 750 | U3: =IFERROR(__xludf.DUMMYFUNCTION("""COMPUTED_VALUE"""),148.0) -> 148 | V3: =IFERROR(__xludf.DUMMYFUNCTION("""COMPUTED_VALUE"""),394.0) -> 394 | W3: =IFERROR(__xludf.DUMMYFUNCTION("""COMPUTED_VALUE"""),1154.42) -> 1154.42
A4: =IFERROR(__xludf.DUMMYFUNCTION("""COMPUTED_VALUE"""),"Maltesers") -> Maltesers | B4: =IF(A4="","",SUMIFS(VMS_Sales!F:F,VMS_Sales!D:D,A4,VMS_Sales!O:O,$L$2)) -> 90 | C4: =IF(A4="","",ROUND(( SUMIFS(VMS_Sales!F:F,VMS_Sales!D:D,A4,VMS_Sales!O:O,$L$1)+ SUMIFS(VMS_Sales!F:F,VMS_Sales!D:D,A4,VMS_Sales!O:O,$L$2)+ SUMIFS(VMS_Sales!F:F,VMS_Sales!D:D,A4,VMS_Sales!O:O,$L$3) )/3,2)) -> 49.67 | D4: =IF(C4="","",ROUND(C4*1.15,0)) -> 57 | E4: =IFERROR(__xludf.DUMMYFUNCTION("IFERROR(XLOOKUP(A4,FILTER(VMS_Sales!$D:$D,VMS_Sales!$O:$O=$L$2),FILTER(VMS_Sales!$L:$L,VMS_Sales!$O:$O=$L$2),""""),"""")"),7.5) -> 7.5 | F4: =IF(OR(D4="",E4=""),"",ROUND(D4*E4,2)) -> 427.5 | G4: {=IFERROR( SUMIFS( PurchaseLines_Import!$I:$I, PurchaseLines_Import!$C:$C, TEXT(XLOOKUP(A4,Map!$A:$A,Map!$B:$B,""),"0000"), PurchaseLines_Import!$H:$H, $L$1 ), 0)} -> 0 | H4: {=IFERROR( SUMIFS( Inventory_Import!$D:$D, Inventory_Import!$B:$B, TEXT(XLOOKUP(A4,Map!$A:$A,Map!$B:$B,""),"0000") ), 0)} -> 0 | I4: =IF(A4="","",MAX(D4-H4,0)) -> 57 | J4: =IF(OR(I4="",E4=""),"",ROUND(I4*E4,2)) -> 427.5 | N4: =IFERROR(__xludf.DUMMYFUNCTION("""COMPUTED_VALUE"""),"MR Crunch") -> MR Crunch | O4: =IFERROR(__xludf.DUMMYFUNCTION("""COMPUTED_VALUE"""),457.0) -> 457 | P4: =IFERROR(__xludf.DUMMYFUNCTION("""COMPUTED_VALUE"""),355.0) -> 355 | Q4: =IFERROR(__xludf.DUMMYFUNCTION("""COMPUTED_VALUE"""),408.0) -> 408 | R4: =IFERROR(__xludf.DUMMYFUNCTION("""COMPUTED_VALUE"""),3.0) -> 3 | S4: =IFERROR(__xludf.DUMMYFUNCTION("""COMPUTED_VALUE"""),1224.0) -> 1224 | T4: =IFERROR(__xludf.DUMMYFUNCTION("""COMPUTED_VALUE"""),450.0) -> 450 | U4: =IFERROR(__xludf.DUMMYFUNCTION("""COMPUTED_VALUE"""),95.0) -> 95 | V4: =IFERROR(__xludf.DUMMYFUNCTION("""COMPUTED_VALUE"""),313.0) -> 313 | W4: =IFERROR(__xludf.DUMMYFUNCTION("""COMPUTED_VALUE"""),939.0) -> 939
A5: =IFERROR(__xludf.DUMMYFUNCTION("""COMPUTED_VALUE"""),"Schweppes") -> Schweppes | B5: =IF(A5="","",SUMIFS(VMS_Sales!F:F,VMS_Sales!D:D,A5,VMS_Sales!O:O,$L$2)) -> 8 | C5: =IF(A5="","",ROUND(( SUMIFS(VMS_Sales!F:F,VMS_Sales!D:D,A5,VMS_Sales!O:O,$L$1)+ SUMIFS(VMS_Sales!F:F,VMS_Sales!D:D,A5,VMS_Sales!O:O,$L$2)+ SUMIFS(VMS_Sales!F:F,VMS_Sales!D:D,A5,VMS_Sales!O:O,$L$3) )/3,2)) -> 7.67 | D5: =IF(C5="","",ROUND(C5*1.15,0)) -> 9 | E5: =IFERROR(__xludf.DUMMYFUNCTION("IFERROR(XLOOKUP(A5,FILTER(VMS_Sales!$D:$D,VMS_Sales!$O:$O=$L$2),FILTER(VMS_Sales!$L:$L,VMS_Sales!$O:$O=$L$2),""""),"""")"),2.0) -> 2 | F5: =IF(OR(D5="",E5=""),"",ROUND(D5*E5,2)) -> 18 | G5: {=IFERROR( SUMIFS( PurchaseLines_Import!$I:$I, PurchaseLines_Import!$C:$C, TEXT(XLOOKUP(A5,Map!$A:$A,Map!$B:$B,""),"0000"), PurchaseLines_Import!$H:$H, $L$1 ), 0)} -> 0 | H5: {=IFERROR( SUMIFS( Inventory_Import!$D:$D, Inventory_Import!$B:$B, TEXT(XLOOKUP(A5,Map!$A:$A,Map!$B:$B,""),"0000") ), 0)} -> 0 | I5: =IF(A5="","",MAX(D5-H5,0)) -> 9 | J5: =IF(OR(I5="",E5=""),"",ROUND(I5*E5,2)) -> 18 | N5: =IFERROR(__xludf.DUMMYFUNCTION("""COMPUTED_VALUE"""),"Pepsi") -> Pepsi | O5: =IFERROR(__xludf.DUMMYFUNCTION("""COMPUTED_VALUE"""),499.0) -> 499 | P5: =IFERROR(__xludf.DUMMYFUNCTION("""COMPUTED_VALUE"""),279.67) -> 279.67 | Q5: =IFERROR(__xludf.DUMMYFUNCTION("""COMPUTED_VALUE"""),322.0) -> 322 | R5: =IFERROR(__xludf.DUMMYFUNCTION("""COMPUTED_VALUE"""),2.25) -> 2.25 | S5: =IFERROR(__xludf.DUMMYFUNCTION("""COMPUTED_VALUE"""),724.5) -> 724.5 | T5: =IFERROR(__xludf.DUMMYFUNCTION("""COMPUTED_VALUE"""),408.0) -> 408 | U5: =IFERROR(__xludf.DUMMYFUNCTION("""COMPUTED_VALUE"""),-5.0) -> -5 | V5: =IFERROR(__xludf.DUMMYFUNCTION("""COMPUTED_VALUE"""),327.0) -> 327 | W5: =IFERROR(__xludf.DUMMYFUNCTION("""COMPUTED_VALUE"""),735.75) -> 735.75
A6: =IFERROR(__xludf.DUMMYFUNCTION("""COMPUTED_VALUE"""),"Xo Energy") -> Xo Energy | B6: =IF(A6="","",SUMIFS(VMS_Sales!F:F,VMS_Sales!D:D,A6,VMS_Sales!O:O,$L$2)) -> 6 | C6: =IF(A6="","",ROUND(( SUMIFS(VMS_Sales!F:F,VMS_Sales!D:D,A6,VMS_Sales!O:O,$L$1)+ SUMIFS(VMS_Sales!F:F,VMS_Sales!D:D,A6,VMS_Sales!O:O,$L$2)+ SUMIFS(VMS_Sales!F:F,VMS_Sales!D:D,A6,VMS_Sales!O:O,$L$3) )/3,2)) -> 16 | D6: =IF(C6="","",ROUND(C6*1.15,0)) -> 18 | E6: =IFERROR(__xludf.DUMMYFUNCTION("IFERROR(XLOOKUP(A6,FILTER(VMS_Sales!$D:$D,VMS_Sales!$O:$O=$L$2),FILTER(VMS_Sales!$L:$L,VMS_Sales!$O:$O=$L$2),""""),"""")"),3.45) -> 3.45 | F6: =IF(OR(D6="",E6=""),"",ROUND(D6*E6,2)) -> 62.1 | G6: {=IFERROR( SUMIFS( PurchaseLines_Import!$I:$I, PurchaseLines_Import!$C:$C, TEXT(XLOOKUP(A6,Map!$A:$A,Map!$B:$B,""),"0000"), PurchaseLines_Import!$H:$H, $L$1 ), 0)} -> 0 | H6: {=IFERROR( SUMIFS( Inventory_Import!$D:$D, Inventory_Import!$B:$B, TEXT(XLOOKUP(A6,Map!$A:$A,Map!$B:$B,""),"0000") ), 0)} -> 0 | I6: =IF(A6="","",MAX(D6-H6,0)) -> 18 | J6: =IF(OR(I6="",E6=""),"",ROUND(I6*E6,2)) -> 62.1 | N6: =IFERROR(__xludf.DUMMYFUNCTION("""COMPUTED_VALUE"""),"Kinder Bueno") -> Kinder Bueno | O6: =IFERROR(__xludf.DUMMYFUNCTION("""COMPUTED_VALUE"""),151.0) -> 151 | P6: =IFERROR(__xludf.DUMMYFUNCTION("""COMPUTED_VALUE"""),90.0) -> 90 | Q6: =IFERROR(__xludf.DUMMYFUNCTION("""COMPUTED_VALUE"""),104.0) -> 104 | R6: =IFERROR(__xludf.DUMMYFUNCTION("""COMPUTED_VALUE"""),7.0) -> 7 | S6: =IFERROR(__xludf.DUMMYFUNCTION("""COMPUTED_VALUE"""),728.0) -> 728 | T6: =IFERROR(__xludf.DUMMYFUNCTION("""COMPUTED_VALUE"""),205.0) -> 205 | U6: =IFERROR(__xludf.DUMMYFUNCTION("""COMPUTED_VALUE"""),7.0) -> 7 | V6: =IFERROR(__xludf.DUMMYFUNCTION("""COMPUTED_VALUE"""),97.0) -> 97 | W6: =IFERROR(__xludf.DUMMYFUNCTION("""COMPUTED_VALUE"""),679.0) -> 679
A7: =IFERROR(__xludf.DUMMYFUNCTION("""COMPUTED_VALUE"""),"X!R") -> X!R | B7: =IF(A7="","",SUMIFS(VMS_Sales!F:F,VMS_Sales!D:D,A7,VMS_Sales!O:O,$L$2)) -> 740 | C7: =IF(A7="","",ROUND(( SUMIFS(VMS_Sales!F:F,VMS_Sales!D:D,A7,VMS_Sales!O:O,$L$1)+ SUMIFS(VMS_Sales!F:F,VMS_Sales!D:D,A7,VMS_Sales!O:O,$L$2)+ SUMIFS(VMS_Sales!F:F,VMS_Sales!D:D,A7,VMS_Sales!O:O,$L$3) )/3,2)) -> 383 | D7: =IF(C7="","",ROUND(C7*1.15,0)) -> 440 | E7: =IFERROR(__xludf.DUMMYFUNCTION("IFERROR(XLOOKUP(A7,FILTER(VMS_Sales!$D:$D,VMS_Sales!$O:$O=$L$2),FILTER(VMS_Sales!$L:$L,VMS_Sales!$O:$O=$L$2),""""),"""")"),4.29) -> 4.29 | F7: =IF(OR(D7="",E7=""),"",ROUND(D7*E7,2)) -> 1887.6 | G7: {=IFERROR( SUMIFS( PurchaseLines_Import!$I:$I, PurchaseLines_Import!$C:$C, TEXT(XLOOKUP(A7,Map!$A:$A,Map!$B:$B,""),"0000"), PurchaseLines_Import!$H:$H, $L$1 ), 0)} -> 360 | H7: {=IFERROR( SUMIFS( Inventory_Import!$D:$D, Inventory_Import!$B:$B, TEXT(XLOOKUP(A7,Map!$A:$A,Map!$B:$B,""),"0000") ), 0)} -> 59 | I7: =IF(A7="","",MAX(D7-H7,0)) -> 381 | J7: =IF(OR(I7="",E7=""),"",ROUND(I7*E7,2)) -> 1634.49 | N7: =IFERROR(__xludf.DUMMYFUNCTION("""COMPUTED_VALUE"""),"Laviva") -> Laviva | O7: =IFERROR(__xludf.DUMMYFUNCTION("""COMPUTED_VALUE"""),373.0) -> 373 | P7: =IFERROR(__xludf.DUMMYFUNCTION("""COMPUTED_VALUE"""),236.0) -> 236 | Q7: =IFERROR(__xludf.DUMMYFUNCTION("""COMPUTED_VALUE"""),271.0) -> 271 | R7: =IFERROR(__xludf.DUMMYFUNCTION("""COMPUTED_VALUE"""),2.25) -> 2.25 | S7: =IFERROR(__xludf.DUMMYFUNCTION("""COMPUTED_VALUE"""),609.75) -> 609.75 | T7: =IFERROR(__xludf.DUMMYFUNCTION("""COMPUTED_VALUE"""),168.0) -> 168 | U7: =IFERROR(__xludf.DUMMYFUNCTION("""COMPUTED_VALUE"""),7.0) -> 7 | V7: =IFERROR(__xludf.DUMMYFUNCTION("""COMPUTED_VALUE"""),264.0) -> 264 | W7: =IFERROR(__xludf.DUMMYFUNCTION("""COMPUTED_VALUE"""),594.0) -> 594
A8: =IFERROR(__xludf.DUMMYFUNCTION("""COMPUTED_VALUE"""),"Kinder Bueno") -> Kinder Bueno | B8: =IF(A8="","",SUMIFS(VMS_Sales!F:F,VMS_Sales!D:D,A8,VMS_Sales!O:O,$L$2)) -> 151 | C8: =IF(A8="","",ROUND(( SUMIFS(VMS_Sales!F:F,VMS_Sales!D:D,A8,VMS_Sales!O:O,$L$1)+ SUMIFS(VMS_Sales!F:F,VMS_Sales!D:D,A8,VMS_Sales!O:O,$L$2)+ SUMIFS(VMS_Sales!F:F,VMS_Sales!D:D,A8,VMS_Sales!O:O,$L$3) )/3,2)) -> 90 | D8: =IF(C8="","",ROUND(C8*1.15,0)) -> 104 | E8: =IFERROR(__xludf.DUMMYFUNCTION("IFERROR(XLOOKUP(A8,FILTER(VMS_Sales!$D:$D,VMS_Sales!$O:$O=$L$2),FILTER(VMS_Sales!$L:$L,VMS_Sales!$O:$O=$L$2),""""),"""")"),7.0) -> 7 | F8: =IF(OR(D8="",E8=""),"",ROUND(D8*E8,2)) -> 728 | G8: {=IFERROR( SUMIFS( PurchaseLines_Import!$I:$I, PurchaseLines_Import!$C:$C, TEXT(XLOOKUP(A8,Map!$A:$A,Map!$B:$B,""),"0000"), PurchaseLines_Import!$H:$H, $L$1 ), 0)} -> 205 | H8: {=IFERROR( SUMIFS( Inventory_Import!$D:$D, Inventory_Import!$B:$B, TEXT(XLOOKUP(A8,Map!$A:$A,Map!$B:$B,""),"0000") ), 0)} -> 7 | I8: =IF(A8="","",MAX(D8-H8,0)) -> 97 | J8: =IF(OR(I8="",E8=""),"",ROUND(I8*E8,2)) -> 679 | N8: =IFERROR(__xludf.DUMMYFUNCTION("""COMPUTED_VALUE"""),"Turbo strips") -> Turbo strips | O8: =IFERROR(__xludf.DUMMYFUNCTION("""COMPUTED_VALUE"""),120.0) -> 120 | P8: =IFERROR(__xludf.DUMMYFUNCTION("""COMPUTED_VALUE"""),121.0) -> 121 | Q8: =IFERROR(__xludf.DUMMYFUNCTION("""COMPUTED_VALUE"""),139.0) -> 139 | R8: =IFERROR(__xludf.DUMMYFUNCTION("""COMPUTED_VALUE"""),4.08) -> 4.08 | S8: =IFERROR(__xludf.DUMMYFUNCTION("""COMPUTED_VALUE"""),567.12) -> 567.12 | T8: =IFERROR(__xludf.DUMMYFUNCTION("""COMPUTED_VALUE"""),138.0) -> 138 | U8: =IFERROR(__xludf.DUMMYFUNCTION("""COMPUTED_VALUE"""),0.0) -> 0 | V8: =IFERROR(__xludf.DUMMYFUNCTION("""COMPUTED_VALUE"""),139.0) -> 139 | W8: =IFERROR(__xludf.DUMMYFUNCTION("""COMPUTED_VALUE"""),567.12) -> 567.12
A9: =IFERROR(__xludf.DUMMYFUNCTION("""COMPUTED_VALUE"""),"mr bite") -> mr bite | B9: =IF(A9="","",SUMIFS(VMS_Sales!F:F,VMS_Sales!D:D,A9,VMS_Sales!O:O,$L$2)) -> 342 | C9: =IF(A9="","",ROUND(( SUMIFS(VMS_Sales!F:F,VMS_Sales!D:D,A9,VMS_Sales!O:O,$L$1)+ SUMIFS(VMS_Sales!F:F,VMS_Sales!D:D,A9,VMS_Sales!O:O,$L$2)+ SUMIFS(VMS_Sales!F:F,VMS_Sales!D:D,A9,VMS_Sales!O:O,$L$3) )/3,2)) -> 188 | D9: =IF(C9="","",ROUND(C9*1.15,0)) -> 216 | E9: =IFERROR(__xludf.DUMMYFUNCTION("IFERROR(XLOOKUP(A9,FILTER(VMS_Sales!$D:$D,VMS_Sales!$O:$O=$L$2),FILTER(VMS_Sales!$L:$L,VMS_Sales!$O:$O=$L$2),""""),"""")"),1.79) -> 1.79 | F9: =IF(OR(D9="",E9=""),"",ROUND(D9*E9,2)) -> 386.64 | G9: {=IFERROR( SUMIFS( PurchaseLines_Import!$I:$I, PurchaseLines_Import!$C:$C, TEXT(XLOOKUP(A9,Map!$A:$A,Map!$B:$B,""),"0000"), PurchaseLines_Import!$H:$H, $L$1 ), 0)} -> 48 | H9: {=IFERROR( SUMIFS( Inventory_Import!$D:$D, Inventory_Import!$B:$B, TEXT(XLOOKUP(A9,Map!$A:$A,Map!$B:$B,""),"0000") ), 0)} -> 6 | I9: =IF(A9="","",MAX(D9-H9,0)) -> 210 | J9: =IF(OR(I9="",E9=""),"",ROUND(I9*E9,2)) -> 375.9 | N9: =IFERROR(__xludf.DUMMYFUNCTION("""COMPUTED_VALUE"""),"Water") -> Water | O9: =IFERROR(__xludf.DUMMYFUNCTION("""COMPUTED_VALUE"""),2806.0) -> 2806 | P9: =IFERROR(__xludf.DUMMYFUNCTION("""COMPUTED_VALUE"""),1785.67) -> 1785.67 | Q9: =IFERROR(__xludf.DUMMYFUNCTION("""COMPUTED_VALUE"""),2054.0) -> 2054 | R9: =IFERROR(__xludf.DUMMYFUNCTION("""COMPUTED_VALUE"""),0.28) -> 0.28 | S9: =IFERROR(__xludf.DUMMYFUNCTION("""COMPUTED_VALUE"""),575.12) -> 575.12 | T9: =IFERROR(__xludf.DUMMYFUNCTION("""COMPUTED_VALUE"""),2328.0) -> 2328 | U9: =IFERROR(__xludf.DUMMYFUNCTION("""COMPUTED_VALUE"""),84.0) -> 84 | V9: =IFERROR(__xludf.DUMMYFUNCTION("""COMPUTED_VALUE"""),1970.0) -> 1970 | W9: =IFERROR(__xludf.DUMMYFUNCTION("""COMPUTED_VALUE"""),551.6) -> 551.6
A10: =IFERROR(__xludf.DUMMYFUNCTION("""COMPUTED_VALUE"""),"Laviva") -> Laviva | B10: =IF(A10="","",SUMIFS(VMS_Sales!F:F,VMS_Sales!D:D,A10,VMS_Sales!O:O,$L$2)) -> 373 | C10: =IF(A10="","",ROUND(( SUMIFS(VMS_Sales!F:F,VMS_Sales!D:D,A10,VMS_Sales!O:O,$L$1)+ SUMIFS(VMS_Sales!F:F,VMS_Sales!D:D,A10,VMS_Sales!O:O,$L$2)+ SUMIFS(VMS_Sales!F:F,VMS_Sales!D:D,A10,VMS_Sales!O:O,$L$3) )/3,2)) -> 236 | D10: =IF(C10="","",ROUND(C10*1.15,0)) -> 271 | E10: =IFERROR(__xludf.DUMMYFUNCTION("IFERROR(XLOOKUP(A10,FILTER(VMS_Sales!$D:$D,VMS_Sales!$O:$O=$L$2),FILTER(VMS_Sales!$L:$L,VMS_Sales!$O:$O=$L$2),""""),"""")"),2.25) -> 2.25 | F10: =IF(OR(D10="",E10=""),"",ROUND(D10*E10,2)) -> 609.75 | G10: {=IFERROR( SUMIFS( PurchaseLines_Import!$I:$I, PurchaseLines_Import!$C:$C, TEXT(XLOOKUP(A10,Map!$A:$A,Map!$B:$B,""),"0000"), PurchaseLines_Import!$H:$H, $L$1 ), 0)} -> 168 | H10: {=IFERROR( SUMIFS( Inventory_Import!$D:$D, Inventory_Import!$B:$B, TEXT(XLOOKUP(A10,Map!$A:$A,Map!$B:$B,""),"0000") ), 0)} -> 7 | I10: =IF(A10="","",MAX(D10-H10,0)) -> 264 | J10: =IF(OR(I10="",E10=""),"",ROUND(I10*E10,2)) -> 594 | N10: =IFERROR(__xludf.DUMMYFUNCTION("""COMPUTED_VALUE"""),"Doritos green hot") -> Doritos green hot | O10: =IFERROR(__xludf.DUMMYFUNCTION("""COMPUTED_VALUE"""),187.0) -> 187 | P10: =IFERROR(__xludf.DUMMYFUNCTION("""COMPUTED_VALUE"""),191.0) -> 191 | Q10: =IFERROR(__xludf.DUMMYFUNCTION("""COMPUTED_VALUE"""),220.0) -> 220 | R10: =IFERROR(__xludf.DUMMYFUNCTION("""COMPUTED_VALUE"""),2.93) -> 2.93 | S10: =IFERROR(__xludf.DUMMYFUNCTION("""COMPUTED_VALUE"""),644.6) -> 644.6 | T10: =IFERROR(__xludf.DUMMYFUNCTION("""COMPUTED_VALUE"""),0.0) -> 0 | U10: =IFERROR(__xludf.DUMMYFUNCTION("""COMPUTED_VALUE"""),73.0) -> 73 | V10: =IFERROR(__xludf.DUMMYFUNCTION("""COMPUTED_VALUE"""),147.0) -> 147 | W10: =IFERROR(__xludf.DUMMYFUNCTION("""COMPUTED_VALUE"""),430.71) -> 430.71
A11: =IFERROR(__xludf.DUMMYFUNCTION("""COMPUTED_VALUE"""),"Freez") -> Freez | B11: =IF(A11="","",SUMIFS(VMS_Sales!F:F,VMS_Sales!D:D,A11,VMS_Sales!O:O,$L$2)) -> 8 | C11: =IF(A11="","",ROUND(( SUMIFS(VMS_Sales!F:F,VMS_Sales!D:D,A11,VMS_Sales!O:O,$L$1)+ SUMIFS(VMS_Sales!F:F,VMS_Sales!D:D,A11,VMS_Sales!O:O,$L$2)+ SUMIFS(VMS_Sales!F:F,VMS_Sales!D:D,A11,VMS_Sales!O:O,$L$3) )/3,2)) -> 4.67 | D11: =IF(C11="","",ROUND(C11*1.15,0)) -> 5 | E11: =IFERROR(__xludf.DUMMYFUNCTION("IFERROR(XLOOKUP(A11,FILTER(VMS_Sales!$D:$D,VMS_Sales!$O:$O=$L$2),FILTER(VMS_Sales!$L:$L,VMS_Sales!$O:$O=$L$2),""""),"""")"),3.41) -> 3.41 | F11: =IF(OR(D11="",E11=""),"",ROUND(D11*E11,2)) -> 17.05 | G11: {=IFERROR( SUMIFS( PurchaseLines_Import!$I:$I, PurchaseLines_Import!$C:$C, TEXT(XLOOKUP(A11,Map!$A:$A,Map!$B:$B,""),"0000"), PurchaseLines_Import!$H:$H, $L$1 ), 0)} -> 0 | H11: {=IFERROR( SUMIFS( Inventory_Import!$D:$D, Inventory_Import!$B:$B, TEXT(XLOOKUP(A11,Map!$A:$A,Map!$B:$B,""),"0000") ), 0)} -> 0 | I11: =IF(A11="","",MAX(D11-H11,0)) -> 5 | J11: =IF(OR(I11="",E11=""),"",ROUND(I11*E11,2)) -> 17.05 | N11: =IFERROR(__xludf.DUMMYFUNCTION("""COMPUTED_VALUE"""),"Maltesers") -> Maltesers | O11: =IFERROR(__xludf.DUMMYFUNCTION("""COMPUTED_VALUE"""),90.0) -> 90 | P11: =IFERROR(__xludf.DUMMYFUNCTION("""COMPUTED_VALUE"""),49.67) -> 49.67 | Q11: =IFERROR(__xludf.DUMMYFUNCTION("""COMPUTED_VALUE"""),57.0) -> 57 | R11: =IFERROR(__xludf.DUMMYFUNCTION("""COMPUTED_VALUE"""),7.5) -> 7.5 | S11: =IFERROR(__xludf.DUMMYFUNCTION("""COMPUTED_VALUE"""),427.5) -> 427.5 | T11: =IFERROR(__xludf.DUMMYFUNCTION("""COMPUTED_VALUE"""),0.0) -> 0 | U11: =IFERROR(__xludf.DUMMYFUNCTION("""COMPUTED_VALUE"""),0.0) -> 0 | V11: =IFERROR(__xludf.DUMMYFUNCTION("""COMPUTED_VALUE"""),57.0) -> 57 | W11: =IFERROR(__xludf.DUMMYFUNCTION("""COMPUTED_VALUE"""),427.5) -> 427.5
A12: =IFERROR(__xludf.DUMMYFUNCTION("""COMPUTED_VALUE"""),"Twix") -> Twix | B12: =IF(A12="","",SUMIFS(VMS_Sales!F:F,VMS_Sales!D:D,A12,VMS_Sales!O:O,$L$2)) -> 25 | C12: =IF(A12="","",ROUND(( SUMIFS(VMS_Sales!F:F,VMS_Sales!D:D,A12,VMS_Sales!O:O,$L$1)+ SUMIFS(VMS_Sales!F:F,VMS_Sales!D:D,A12,VMS_Sales!O:O,$L$2)+ SUMIFS(VMS_Sales!F:F,VMS_Sales!D:D,A12,VMS_Sales!O:O,$L$3) )/3,2)) -> 17.67 | D12: =IF(C12="","",ROUND(C12*1.15,0)) -> 20 | E12: =IFERROR(__xludf.DUMMYFUNCTION("IFERROR(XLOOKUP(A12,FILTER(VMS_Sales!$D:$D,VMS_Sales!$O:$O=$L$2),FILTER(VMS_Sales!$L:$L,VMS_Sales!$O:$O=$L$2),""""),"""")"),5.0) -> 5 | F12: =IF(OR(D12="",E12=""),"",ROUND(D12*E12,2)) -> 100 | G12: {=IFERROR( SUMIFS( PurchaseLines_Import!$I:$I, PurchaseLines_Import!$C:$C, TEXT(XLOOKUP(A12,Map!$A:$A,Map!$B:$B,""),"0000"), PurchaseLines_Import!$H:$H, $L$1 ), 0)} -> 0 | H12: {=IFERROR( SUMIFS( Inventory_Import!$D:$D, Inventory_Import!$B:$B, TEXT(XLOOKUP(A12,Map!$A:$A,Map!$B:$B,""),"0000") ), 0)} -> 0 | I12: =IF(A12="","",MAX(D12-H12,0)) -> 20 | J12: =IF(OR(I12="",E12=""),"",ROUND(I12*E12,2)) -> 100 | N12: =IFERROR(__xludf.DUMMYFUNCTION("""COMPUTED_VALUE"""),"Mrbeast") -> Mrbeast | O12: =IFERROR(__xludf.DUMMYFUNCTION("""COMPUTED_VALUE"""),173.0) -> 173 | P12: =IFERROR(__xludf.DUMMYFUNCTION("""COMPUTED_VALUE"""),108.67) -> 108.67 | Q12: =IFERROR(__xludf.DUMMYFUNCTION("""COMPUTED_VALUE"""),125.0) -> 125 | R12: =IFERROR(__xludf.DUMMYFUNCTION("""COMPUTED_VALUE"""),3.0) -> 3 | S12: =IFERROR(__xludf.DUMMYFUNCTION("""COMPUTED_VALUE"""),375.0) -> 375 | T12: =IFERROR(__xludf.DUMMYFUNCTION("""COMPUTED_VALUE"""),100.0) -> 100 | U12: =IFERROR(__xludf.DUMMYFUNCTION("""COMPUTED_VALUE"""),-4.0) -> -4 | V12: =IFERROR(__xludf.DUMMYFUNCTION("""COMPUTED_VALUE"""),129.0) -> 129 | W12: =IFERROR(__xludf.DUMMYFUNCTION("""COMPUTED_VALUE"""),387.0) -> 387
A13: =IFERROR(__xludf.DUMMYFUNCTION("""COMPUTED_VALUE"""),"Gardena") -> Gardena | B13: =IF(A13="","",SUMIFS(VMS_Sales!F:F,VMS_Sales!D:D,A13,VMS_Sales!O:O,$L$2)) -> 107 | C13: =IF(A13="","",ROUND(( SUMIFS(VMS_Sales!F:F,VMS_Sales!D:D,A13,VMS_Sales!O:O,$L$1)+ SUMIFS(VMS_Sales!F:F,VMS_Sales!D:D,A13,VMS_Sales!O:O,$L$2)+ SUMIFS(VMS_Sales!F:F,VMS_Sales!D:D,A13,VMS_Sales!O:O,$L$3) )/3,2)) -> 48 | D13: =IF(C13="","",ROUND(C13*1.15,0)) -> 55 | E13: =IFERROR(__xludf.DUMMYFUNCTION("IFERROR(XLOOKUP(A13,FILTER(VMS_Sales!$D:$D,VMS_Sales!$O:$O=$L$2),FILTER(VMS_Sales!$L:$L,VMS_Sales!$O:$O=$L$2),""""),"""")"),5.5) -> 5.5 | F13: =IF(OR(D13="",E13=""),"",ROUND(D13*E13,2)) -> 302.5 | G13: {=IFERROR( SUMIFS( PurchaseLines_Import!$I:$I, PurchaseLines_Import!$C:$C, TEXT(XLOOKUP(A13,Map!$A:$A,Map!$B:$B,""),"0000"), PurchaseLines_Import!$H:$H, $L$1 ), 0)} -> 125 | H13: {=IFERROR( SUMIFS( Inventory_Import!$D:$D, Inventory_Import!$B:$B, TEXT(XLOOKUP(A13,Map!$A:$A,Map!$B:$B,""),"0000") ), 0)} -> 24 | I13: =IF(A13="","",MAX(D13-H13,0)) -> 31 | J13: =IF(OR(I13="",E13=""),"",ROUND(I13*E13,2)) -> 170.5 | N13: =IFERROR(__xludf.DUMMYFUNCTION("""COMPUTED_VALUE"""),"mr bite") -> mr bite | O13: =IFERROR(__xludf.DUMMYFUNCTION("""COMPUTED_VALUE"""),342.0) -> 342 | P13: =IFERROR(__xludf.DUMMYFUNCTION("""COMPUTED_VALUE"""),188.0) -> 188 | Q13: =IFERROR(__xludf.DUMMYFUNCTION("""COMPUTED_VALUE"""),216.0) -> 216 | R13: =IFERROR(__xludf.DUMMYFUNCTION("""COMPUTED_VALUE"""),1.79) -> 1.79 | S13: =IFERROR(__xludf.DUMMYFUNCTION("""COMPUTED_VALUE"""),386.64) -> 386.64 | T13: =IFERROR(__xludf.DUMMYFUNCTION("""COMPUTED_VALUE"""),48.0) -> 48 | U13: =IFERROR(__xludf.DUMMYFUNCTION("""COMPUTED_VALUE"""),6.0) -> 6 | V13: =IFERROR(__xludf.DUMMYFUNCTION("""COMPUTED_VALUE"""),210.0) -> 210 | W13: =IFERROR(__xludf.DUMMYFUNCTION("""COMPUTED_VALUE"""),375.9) -> 375.9
A14: =IFERROR(__xludf.DUMMYFUNCTION("""COMPUTED_VALUE"""),"Snickers") -> Snickers | B14: =IF(A14="","",SUMIFS(VMS_Sales!F:F,VMS_Sales!D:D,A14,VMS_Sales!O:O,$L$2)) -> 64 | C14: =IF(A14="","",ROUND(( SUMIFS(VMS_Sales!F:F,VMS_Sales!D:D,A14,VMS_Sales!O:O,$L$1)+ SUMIFS(VMS_Sales!F:F,VMS_Sales!D:D,A14,VMS_Sales!O:O,$L$2)+ SUMIFS(VMS_Sales!F:F,VMS_Sales!D:D,A14,VMS_Sales!O:O,$L$3) )/3,2)) -> 33 | D14: =IF(C14="","",ROUND(C14*1.15,0)) -> 38 | E14: =IFERROR(__xludf.DUMMYFUNCTION("IFERROR(XLOOKUP(A14,FILTER(VMS_Sales!$D:$D,VMS_Sales!$O:$O=$L$2),FILTER(VMS_Sales!$L:$L,VMS_Sales!$O:$O=$L$2),""""),"""")"),5.2) -> 5.2 | F14: =IF(OR(D14="",E14=""),"",ROUND(D14*E14,2)) -> 197.6 | G14: {=IFERROR( SUMIFS( PurchaseLines_Import!$I:$I, PurchaseLines_Import!$C:$C, TEXT(XLOOKUP(A14,Map!$A:$A,Map!$B:$B,""),"0000"), PurchaseLines_Import!$H:$H, $L$1 ), 0)} -> 0 | H14: {=IFERROR( SUMIFS( Inventory_Import!$D:$D, Inventory_Import!$B:$B, TEXT(XLOOKUP(A14,Map!$A:$A,Map!$B:$B,""),"0000") ), 0)} -> 0 | I14: =IF(A14="","",MAX(D14-H14,0)) -> 38 | J14: =IF(OR(I14="",E14=""),"",ROUND(I14*E14,2)) -> 197.6 | N14: =IFERROR(__xludf.DUMMYFUNCTION("""COMPUTED_VALUE"""),"Haribo") -> Haribo | O14: =IFERROR(__xludf.DUMMYFUNCTION("""COMPUTED_VALUE"""),300.0) -> 300 | P14: =IFERROR(__xludf.DUMMYFUNCTION("""COMPUTED_VALUE"""),163.67) -> 163.67 | Q14: =IFERROR(__xludf.DUMMYFUNCTION("""COMPUTED_VALUE"""),188.0) -> 188 | R14: =IFERROR(__xludf.DUMMYFUNCTION("""COMPUTED_VALUE"""),2.04) -> 2.04 | S14: =IFERROR(__xludf.DUMMYFUNCTION("""COMPUTED_VALUE"""),383.52) -> 383.52 | T14: =IFERROR(__xludf.DUMMYFUNCTION("""COMPUTED_VALUE"""),144.0) -> 144 | U14: =IFERROR(__xludf.DUMMYFUNCTION("""COMPUTED_VALUE"""),21.0) -> 21 | V14: =IFERROR(__xludf.DUMMYFUNCTION("""COMPUTED_VALUE"""),167.0) -> 167 | W14: =IFERROR(__xludf.DUMMYFUNCTION("""COMPUTED_VALUE"""),340.68) -> 340.68
A15: =IFERROR(__xludf.DUMMYFUNCTION("""COMPUTED_VALUE"""),"Pepsi") -> Pepsi | B15: =IF(A15="","",SUMIFS(VMS_Sales!F:F,VMS_Sales!D:D,A15,VMS_Sales!O:O,$L$2)) -> 499 | C15: =IF(A15="","",ROUND(( SUMIFS(VMS_Sales!F:F,VMS_Sales!D:D,A15,VMS_Sales!O:O,$L$1)+ SUMIFS(VMS_Sales!F:F,VMS_Sales!D:D,A15,VMS_Sales!O:O,$L$2)+ SUMIFS(VMS_Sales!F:F,VMS_Sales!D:D,A15,VMS_Sales!O:O,$L$3) )/3,2)) -> 279.67 | D15: =IF(C15="","",ROUND(C15*1.15,0)) -> 322 | E15: =IFERROR(__xludf.DUMMYFUNCTION("IFERROR(XLOOKUP(A15,FILTER(VMS_Sales!$D:$D,VMS_Sales!$O:$O=$L$2),FILTER(VMS_Sales!$L:$L,VMS_Sales!$O:$O=$L$2),""""),"""")"),2.25) -> 2.25 | F15: =IF(OR(D15="",E15=""),"",ROUND(D15*E15,2)) -> 724.5 | G15: {=IFERROR( SUMIFS( PurchaseLines_Import!$I:$I, PurchaseLines_Import!$C:$C, TEXT(XLOOKUP(A15,Map!$A:$A,Map!$B:$B,""),"0000"), PurchaseLines_Import!$H:$H, $L$1 ), 0)} -> 408 | H15: {=IFERROR( SUMIFS( Inventory_Import!$D:$D, Inventory_Import!$B:$B, TEXT(XLOOKUP(A15,Map!$A:$A,Map!$B:$B,""),"0000") ), 0)} -> -5 | I15: =IF(A15="","",MAX(D15-H15,0)) -> 327 | J15: =IF(OR(I15="",E15=""),"",ROUND(I15*E15,2)) -> 735.75 | N15: =IFERROR(__xludf.DUMMYFUNCTION("""COMPUTED_VALUE"""),"Almarai Strawberry") -> Almarai Strawberry | O15: =IFERROR(__xludf.DUMMYFUNCTION("""COMPUTED_VALUE"""),209.0) -> 209 | P15: =IFERROR(__xludf.DUMMYFUNCTION("""COMPUTED_VALUE"""),152.67) -> 152.67 | Q15: =IFERROR(__xludf.DUMMYFUNCTION("""COMPUTED_VALUE"""),176.0) -> 176 | R15: =IFERROR(__xludf.DUMMYFUNCTION("""COMPUTED_VALUE"""),2.29) -> 2.29 | S15: =IFERROR(__xludf.DUMMYFUNCTION("""COMPUTED_VALUE"""),403.04) -> 403.04 | T15: =IFERROR(__xludf.DUMMYFUNCTION("""COMPUTED_VALUE"""),135.0) -> 135 | U15: =IFERROR(__xludf.DUMMYFUNCTION("""COMPUTED_VALUE"""),30.0) -> 30 | V15: =IFERROR(__xludf.DUMMYFUNCTION("""COMPUTED_VALUE"""),146.0) -> 146 | W15: =IFERROR(__xludf.DUMMYFUNCTION("""COMPUTED_VALUE"""),334.34) -> 334.34
A16: =IFERROR(__xludf.DUMMYFUNCTION("""COMPUTED_VALUE"""),"Mars") -> Mars | B16: =IF(A16="","",SUMIFS(VMS_Sales!F:F,VMS_Sales!D:D,A16,VMS_Sales!O:O,$L$2)) -> 38 | C16: =IF(A16="","",ROUND(( SUMIFS(VMS_Sales!F:F,VMS_Sales!D:D,A16,VMS_Sales!O:O,$L$1)+ SUMIFS(VMS_Sales!F:F,VMS_Sales!D:D,A16,VMS_Sales!O:O,$L$2)+ SUMIFS(VMS_Sales!F:F,VMS_Sales!D:D,A16,VMS_Sales!O:O,$L$3) )/3,2)) -> 32 | D16: =IF(C16="","",ROUND(C16*1.15,0)) -> 37 | E16: =IFERROR(__xludf.DUMMYFUNCTION("IFERROR(XLOOKUP(A16,FILTER(VMS_Sales!$D:$D,VMS_Sales!$O:$O=$L$2),FILTER(VMS_Sales!$L:$L,VMS_Sales!$O:$O=$L$2),""""),"""")"),5.5) -> 5.5 | F16: =IF(OR(D16="",E16=""),"",ROUND(D16*E16,2)) -> 203.5 | G16: {=IFERROR( SUMIFS( PurchaseLines_Import!$I:$I, PurchaseLines_Import!$C:$C, TEXT(XLOOKUP(A16,Map!$A:$A,Map!$B:$B,""),"0000"), PurchaseLines_Import!$H:$H, $L$1 ), 0)} -> 0 | H16: {=IFERROR( SUMIFS( Inventory_Import!$D:$D, Inventory_Import!$B:$B, TEXT(XLOOKUP(A16,Map!$A:$A,Map!$B:$B,""),"0000") ), 0)} -> 0 | I16: =IF(A16="","",MAX(D16-H16,0)) -> 37 | J16: =IF(OR(I16="",E16=""),"",ROUND(I16*E16,2)) -> 203.5 | N16: =IFERROR(__xludf.DUMMYFUNCTION("""COMPUTED_VALUE"""),"Doritos nacho") -> Doritos nacho | O16: =IFERROR(__xludf.DUMMYFUNCTION("""COMPUTED_VALUE"""),376.0) -> 376 | P16: =IFERROR(__xludf.DUMMYFUNCTION("""COMPUTED_VALUE"""),175.0) -> 175 | Q16: =IFERROR(__xludf.DUMMYFUNCTION("""COMPUTED_VALUE"""),201.0) -> 201 | R16: =IFERROR(__xludf.DUMMYFUNCTION("""COMPUTED_VALUE"""),2.93) -> 2.93 | S16: =IFERROR(__xludf.DUMMYFUNCTION("""COMPUTED_VALUE"""),588.93) -> 588.93 | T16: =IFERROR(__xludf.DUMMYFUNCTION("""COMPUTED_VALUE"""),165.0) -> 165 | U16: =IFERROR(__xludf.DUMMYFUNCTION("""COMPUTED_VALUE"""),89.0) -> 89 | V16: =IFERROR(__xludf.DUMMYFUNCTION("""COMPUTED_VALUE"""),112.0) -> 112 | W16: =IFERROR(__xludf.DUMMYFUNCTION("""COMPUTED_VALUE"""),328.16) -> 328.16
A17: =IFERROR(__xludf.DUMMYFUNCTION("""COMPUTED_VALUE"""),"Almarai Chocolate") -> Almarai Chocolate | B17: =IF(A17="","",SUMIFS(VMS_Sales!F:F,VMS_Sales!D:D,A17,VMS_Sales!O:O,$L$2)) -> 225 | C17: =IF(A17="","",ROUND(( SUMIFS(VMS_Sales!F:F,VMS_Sales!D:D,A17,VMS_Sales!O:O,$L$1)+ SUMIFS(VMS_Sales!F:F,VMS_Sales!D:D,A17,VMS_Sales!O:O,$L$2)+ SUMIFS(VMS_Sales!F:F,VMS_Sales!D:D,A17,VMS_Sales!O:O,$L$3) )/3,2)) -> 150.33 | D17: =IF(C17="","",ROUND(C17*1.15,0)) -> 173 | E17: =IFERROR(__xludf.DUMMYFUNCTION("IFERROR(XLOOKUP(A17,FILTER(VMS_Sales!$D:$D,VMS_Sales!$O:$O=$L$2),FILTER(VMS_Sales!$L:$L,VMS_Sales!$O:$O=$L$2),""""),"""")"),2.29) -> 2.29 | F17: =IF(OR(D17="",E17=""),"",ROUND(D17*E17,2)) -> 396.17 | G17: {=IFERROR( SUMIFS( PurchaseLines_Import!$I:$I, PurchaseLines_Import!$C:$C, TEXT(XLOOKUP(A17,Map!$A:$A,Map!$B:$B,""),"0000"), PurchaseLines_Import!$H:$H, $L$1 ), 0)} -> 216 | H17: {=IFERROR( SUMIFS( Inventory_Import!$D:$D, Inventory_Import!$B:$B, TEXT(XLOOKUP(A17,Map!$A:$A,Map!$B:$B,""),"0000") ), 0)} -> 39 | I17: =IF(A17="","",MAX(D17-H17,0)) -> 134 | J17: =IF(OR(I17="",E17=""),"",ROUND(I17*E17,2)) -> 306.86 | N17: =IFERROR(__xludf.DUMMYFUNCTION("""COMPUTED_VALUE"""),"Sweeto jelly") -> Sweeto jelly | O17: =IFERROR(__xludf.DUMMYFUNCTION("""COMPUTED_VALUE"""),218.0) -> 218 | P17: =IFERROR(__xludf.DUMMYFUNCTION("""COMPUTED_VALUE"""),72.67) -> 72.67 | Q17: =IFERROR(__xludf.DUMMYFUNCTION("""COMPUTED_VALUE"""),84.0) -> 84 | R17: =IFERROR(__xludf.DUMMYFUNCTION("""COMPUTED_VALUE"""),3.66) -> 3.66 | S17: =IFERROR(__xludf.DUMMYFUNCTION("""COMPUTED_VALUE"""),307.44) -> 307.44 | T17: =IFERROR(__xludf.DUMMYFUNCTION("""COMPUTED_VALUE"""),240.0) -> 240 | U17: =IFERROR(__xludf.DUMMYFUNCTION("""COMPUTED_VALUE"""),0.0) -> 0 | V17: =IFERROR(__xludf.DUMMYFUNCTION("""COMPUTED_VALUE"""),84.0) -> 84 | W17: =IFERROR(__xludf.DUMMYFUNCTION("""COMPUTED_VALUE"""),307.44) -> 307.44
A18: =IFERROR(__xludf.DUMMYFUNCTION("""COMPUTED_VALUE"""),"Corissant Karuzo") -> Corissant Karuzo | B18: =IF(A18="","",SUMIFS(VMS_Sales!F:F,VMS_Sales!D:D,A18,VMS_Sales!O:O,$L$2)) -> 51 | C18: =IF(A18="","",ROUND(( SUMIFS(VMS_Sales!F:F,VMS_Sales!D:D,A18,VMS_Sales!O:O,$L$1)+ SUMIFS(VMS_Sales!F:F,VMS_Sales!D:D,A18,VMS_Sales!O:O,$L$2)+ SUMIFS(VMS_Sales!F:F,VMS_Sales!D:D,A18,VMS_Sales!O:O,$L$3) )/3,2)) -> 33 | D18: =IF(C18="","",ROUND(C18*1.15,0)) -> 38 | E18: =IFERROR(__xludf.DUMMYFUNCTION("IFERROR(XLOOKUP(A18,FILTER(VMS_Sales!$D:$D,VMS_Sales!$O:$O=$L$2),FILTER(VMS_Sales!$L:$L,VMS_Sales!$O:$O=$L$2),""""),"""")"),3.13) -> 3.13 | F18: =IF(OR(D18="",E18=""),"",ROUND(D18*E18,2)) -> 118.94 | G18: {=IFERROR( SUMIFS( PurchaseLines_Import!$I:$I, PurchaseLines_Import!$C:$C, XLOOKUP(A18,Map!$A:$A,Map!$B:$B,""), PurchaseLines_Import!$H:$H, $L$1 ), "")} -> 72 | H18: {=IFERROR( SUMIFS( Inventory_Import!$D:$D, Inventory_Import!$B:$B, TEXT(XLOOKUP(A18,Map!$A:$A,Map!$B:$B,""),"0000") ), 0)} -> 4 | I18: =IF(A18="","",MAX(D18-H18,0)) -> 34 | J18: =IF(OR(I18="",E18=""),"",ROUND(I18*E18,2)) -> 106.42 | N18: =IFERROR(__xludf.DUMMYFUNCTION("""COMPUTED_VALUE"""),"Almarai Chocolate") -> Almarai Chocolate | O18: =IFERROR(__xludf.DUMMYFUNCTION("""COMPUTED_VALUE"""),225.0) -> 225 | P18: =IFERROR(__xludf.DUMMYFUNCTION("""COMPUTED_VALUE"""),150.33) -> 150.33 | Q18: =IFERROR(__xludf.DUMMYFUNCTION("""COMPUTED_VALUE"""),173.0) -> 173 | R18: =IFERROR(__xludf.DUMMYFUNCTION("""COMPUTED_VALUE"""),2.29) -> 2.29 | S18: =IFERROR(__xludf.DUMMYFUNCTION("""COMPUTED_VALUE"""),396.17) -> 396.17 | T18: =IFERROR(__xludf.DUMMYFUNCTION("""COMPUTED_VALUE"""),216.0) -> 216 | U18: =IFERROR(__xludf.DUMMYFUNCTION("""COMPUTED_VALUE"""),39.0) -> 39 | V18: =IFERROR(__xludf.DUMMYFUNCTION("""COMPUTED_VALUE"""),134.0) -> 134 | W18: =IFERROR(__xludf.DUMMYFUNCTION("""COMPUTED_VALUE"""),306.86) -> 306.86
A19: =IFERROR(__xludf.DUMMYFUNCTION("""COMPUTED_VALUE"""),"Kunuz Juice") -> Kunuz Juice | B19: =IF(A19="","",SUMIFS(VMS_Sales!F:F,VMS_Sales!D:D,A19,VMS_Sales!O:O,$L$2)) -> 13 | C19: =IF(A19="","",ROUND(( SUMIFS(VMS_Sales!F:F,VMS_Sales!D:D,A19,VMS_Sales!O:O,$L$1)+ SUMIFS(VMS_Sales!F:F,VMS_Sales!D:D,A19,VMS_Sales!O:O,$L$2)+ SUMIFS(VMS_Sales!F:F,VMS_Sales!D:D,A19,VMS_Sales!O:O,$L$3) )/3,2)) -> 18.33 | D19: =IF(C19="","",ROUND(C19*1.15,0)) -> 21 | E19: =IFERROR(__xludf.DUMMYFUNCTION("IFERROR(XLOOKUP(A19,FILTER(VMS_Sales!$D:$D,VMS_Sales!$O:$O=$L$2),FILTER(VMS_Sales!$L:$L,VMS_Sales!$O:$O=$L$2),""""),"""")"),1.6) -> 1.6 | F19: =IF(OR(D19="",E19=""),"",ROUND(D19*E19,2)) -> 33.6 | G19: {=IFERROR( SUMIFS( PurchaseLines_Import!$I:$I, PurchaseLines_Import!$C:$C, XLOOKUP(A19,Map!$A:$A,Map!$B:$B,""), PurchaseLines_Import!$H:$H, $L$1 ), "")} -> 0 | H19: {=IFERROR( SUMIFS( Inventory_Import!$D:$D, Inventory_Import!$B:$B, TEXT(XLOOKUP(A19,Map!$A:$A,Map!$B:$B,""),"0000") ), 0)} -> 0 | I19: =IF(A19="","",MAX(D19-H19,0)) -> 21 | J19: =IF(OR(I19="",E19=""),"",ROUND(I19*E19,2)) -> 33.6 | N19: =IFERROR(__xludf.DUMMYFUNCTION("""COMPUTED_VALUE"""),"Mirinda") -> Mirinda | O19: =IFERROR(__xludf.DUMMYFUNCTION("""COMPUTED_VALUE"""),220.0) -> 220 | P19: =IFERROR(__xludf.DUMMYFUNCTION("""COMPUTED_VALUE"""),107.33) -> 107.33 | Q19: =IFERROR(__xludf.DUMMYFUNCTION("""COMPUTED_VALUE"""),123.0) -> 123 | R19: =IFERROR(__xludf.DUMMYFUNCTION("""COMPUTED_VALUE"""),2.25) -> 2.25 | S19: =IFERROR(__xludf.DUMMYFUNCTION("""COMPUTED_VALUE"""),276.75) -> 276.75 | T19: =IFERROR(__xludf.DUMMYFUNCTION("""COMPUTED_VALUE"""),24.0) -> 24 | U19: =IFERROR(__xludf.DUMMYFUNCTION("""COMPUTED_VALUE"""),0.0) -> 0 | V19: =IFERROR(__xludf.DUMMYFUNCTION("""COMPUTED_VALUE"""),123.0) -> 123 | W19: =IFERROR(__xludf.DUMMYFUNCTION("""COMPUTED_VALUE"""),276.75) -> 276.75
A20: =IFERROR(__xludf.DUMMYFUNCTION("""COMPUTED_VALUE"""),"Digestive") -> Digestive | B20: =IF(A20="","",SUMIFS(VMS_Sales!F:F,VMS_Sales!D:D,A20,VMS_Sales!O:O,$L$2)) -> 0 | C20: =IF(A20="","",ROUND(( SUMIFS(VMS_Sales!F:F,VMS_Sales!D:D,A20,VMS_Sales!O:O,$L$1)+ SUMIFS(VMS_Sales!F:F,VMS_Sales!D:D,A20,VMS_Sales!O:O,$L$2)+ SUMIFS(VMS_Sales!F:F,VMS_Sales!D:D,A20,VMS_Sales!O:O,$L$3) )/3,2)) -> 9.67 | D20: =IF(C20="","",ROUND(C20*1.15,0)) -> 11 | E20: =IFERROR(__xludf.DUMMYFUNCTION("IFERROR(XLOOKUP(A20,FILTER(VMS_Sales!$D:$D,VMS_Sales!$O:$O=$L$2),FILTER(VMS_Sales!$L:$L,VMS_Sales!$O:$O=$L$2),""""),"""")"),"") | F20: =IF(OR(D20="",E20=""),"",ROUND(D20*E20,2)) | G20: {=IFERROR( SUMIFS( PurchaseLines_Import!$I:$I, PurchaseLines_Import!$C:$C, XLOOKUP(A20,Map!$A:$A,Map!$B:$B,""), PurchaseLines_Import!$H:$H, $L$1 ), "")} -> 0 | H20: {=IFERROR( SUMIFS( Inventory_Import!$D:$D, Inventory_Import!$B:$B, TEXT(XLOOKUP(A20,Map!$A:$A,Map!$B:$B,""),"0000") ), 0)} -> 0 | I20: =IF(A20="","",MAX(D20-H20,0)) -> 11 | J20: =IF(OR(I20="",E20=""),"",ROUND(I20*E20,2)) | N20: =IFERROR(__xludf.DUMMYFUNCTION("""COMPUTED_VALUE"""),"Tiger excellence") -> Tiger excellence | O20: =IFERROR(__xludf.DUMMYFUNCTION("""COMPUTED_VALUE"""),147.0) -> 147 | P20: =IFERROR(__xludf.DUMMYFUNCTION("""COMPUTED_VALUE"""),99.0) -> 99 | Q20: =IFERROR(__xludf.DUMMYFUNCTION("""COMPUTED_VALUE"""),114.0) -> 114 | R20: =IFERROR(__xludf.DUMMYFUNCTION("""COMPUTED_VALUE"""),2.25) -> 2.25 | S20: =IFERROR(__xludf.DUMMYFUNCTION("""COMPUTED_VALUE"""),256.5) -> 256.5 | T20: =IFERROR(__xludf.DUMMYFUNCTION("""COMPUTED_VALUE"""),200.0) -> 200 | U20: =IFERROR(__xludf.DUMMYFUNCTION("""COMPUTED_VALUE"""),0.0) -> 0 | V20: =IFERROR(__xludf.DUMMYFUNCTION("""COMPUTED_VALUE"""),114.0) -> 114 | W20: =IFERROR(__xludf.DUMMYFUNCTION("""COMPUTED_VALUE"""),256.5) -> 256.5
A21: =IFERROR(__xludf.DUMMYFUNCTION("""COMPUTED_VALUE"""),"Lovita cookies") -> Lovita cookies | B21: =IF(A21="","",SUMIFS(VMS_Sales!F:F,VMS_Sales!D:D,A21,VMS_Sales!O:O,$L$2)) -> 25 | C21: =IF(A21="","",ROUND(( SUMIFS(VMS_Sales!F:F,VMS_Sales!D:D,A21,VMS_Sales!O:O,$L$1)+ SUMIFS(VMS_Sales!F:F,VMS_Sales!D:D,A21,VMS_Sales!O:O,$L$2)+ SUMIFS(VMS_Sales!F:F,VMS_Sales!D:D,A21,VMS_Sales!O:O,$L$3) )/3,2)) -> 19.67 | D21: =IF(C21="","",ROUND(C21*1.15,0)) -> 23 | E21: =IFERROR(__xludf.DUMMYFUNCTION("IFERROR(XLOOKUP(A21,FILTER(VMS_Sales!$D:$D,VMS_Sales!$O:$O=$L$2),FILTER(VMS_Sales!$L:$L,VMS_Sales!$O:$O=$L$2),""""),"""")"),5.18) -> 5.18 | F21: =IF(OR(D21="",E21=""),"",ROUND(D21*E21,2)) -> 119.14 | G21: {=IFERROR( SUMIFS( PurchaseLines_Import!$I:$I, PurchaseLines_Import!$C:$C, XLOOKUP(A21,Map!$A:$A,Map!$B:$B,""), PurchaseLines_Import!$H:$H, $L$1 ), "")} -> 34 | H21: {=IFERROR( SUMIFS( Inventory_Import!$D:$D, Inventory_Import!$B:$B, TEXT(XLOOKUP(A21,Map!$A:$A,Map!$B:$B,""),"0000") ), 0)} -> 0 | I21: =IF(A21="","",MAX(D21-H21,0)) -> 23 | J21: =IF(OR(I21="",E21=""),"",ROUND(I21*E21,2)) -> 119.14 | N21: =IFERROR(__xludf.DUMMYFUNCTION("""COMPUTED_VALUE"""),"Shani") -> Shani | O21: =IFERROR(__xludf.DUMMYFUNCTION("""COMPUTED_VALUE"""),159.0) -> 159 | P21: =IFERROR(__xludf.DUMMYFUNCTION("""COMPUTED_VALUE"""),89.67) -> 89.67 | Q21: =IFERROR(__xludf.DUMMYFUNCTION("""COMPUTED_VALUE"""),103.0) -> 103 | R21: =IFERROR(__xludf.DUMMYFUNCTION("""COMPUTED_VALUE"""),2.25) -> 2.25 | S21: =IFERROR(__xludf.DUMMYFUNCTION("""COMPUTED_VALUE"""),231.75) -> 231.75 | T21: =IFERROR(__xludf.DUMMYFUNCTION("""COMPUTED_VALUE"""),0.0) -> 0 | U21: =IFERROR(__xludf.DUMMYFUNCTION("""COMPUTED_VALUE"""),0.0) -> 0 | V21: =IFERROR(__xludf.DUMMYFUNCTION("""COMPUTED_VALUE"""),103.0) -> 103 | W21: =IFERROR(__xludf.DUMMYFUNCTION("""COMPUTED_VALUE"""),231.75) -> 231.75
A22: =IFERROR(__xludf.DUMMYFUNCTION("""COMPUTED_VALUE"""),"Caser Juice") -> Caser Juice | B22: =IF(A22="","",SUMIFS(VMS_Sales!F:F,VMS_Sales!D:D,A22,VMS_Sales!O:O,$L$2)) -> 27 | C22: =IF(A22="","",ROUND(( SUMIFS(VMS_Sales!F:F,VMS_Sales!D:D,A22,VMS_Sales!O:O,$L$1)+ SUMIFS(VMS_Sales!F:F,VMS_Sales!D:D,A22,VMS_Sales!O:O,$L$2)+ SUMIFS(VMS_Sales!F:F,VMS_Sales!D:D,A22,VMS_Sales!O:O,$L$3) )/3,2)) -> 17.67 | D22: =IF(C22="","",ROUND(C22*1.15,0)) -> 20 | E22: =IFERROR(__xludf.DUMMYFUNCTION("IFERROR(XLOOKUP(A22,FILTER(VMS_Sales!$D:$D,VMS_Sales!$O:$O=$L$2),FILTER(VMS_Sales!$L:$L,VMS_Sales!$O:$O=$L$2),""""),"""")"),4.13) -> 4.13 | F22: =IF(OR(D22="",E22=""),"",ROUND(D22*E22,2)) -> 82.6 | G22: {=IFERROR( SUMIFS( PurchaseLines_Import!$I:$I, PurchaseLines_Import!$C:$C, XLOOKUP(A22,Map!$A:$A,Map!$B:$B,""), PurchaseLines_Import!$H:$H, $L$1 ), "")} -> 0 | H22: {=IFERROR( SUMIFS( Inventory_Import!$D:$D, Inventory_Import!$B:$B, TEXT(XLOOKUP(A22,Map!$A:$A,Map!$B:$B,""),"0000") ), 0)} -> 0 | I22: =IF(A22="","",MAX(D22-H22,0)) -> 20 | J22: =IF(OR(I22="",E22=""),"",ROUND(I22*E22,2)) -> 82.6 | N22: =IFERROR(__xludf.DUMMYFUNCTION("""COMPUTED_VALUE"""),"Mars") -> Mars | O22: =IFERROR(__xludf.DUMMYFUNCTION("""COMPUTED_VALUE"""),38.0) -> 38 | P22: =IFERROR(__xludf.DUMMYFUNCTION("""COMPUTED_VALUE"""),32.0) -> 32 | Q22: =IFERROR(__xludf.DUMMYFUNCTION("""COMPUTED_VALUE"""),37.0) -> 37 | R22: =IFERROR(__xludf.DUMMYFUNCTION("""COMPUTED_VALUE"""),5.5) -> 5.5 | S22: =IFERROR(__xludf.DUMMYFUNCTION("""COMPUTED_VALUE"""),203.5) -> 203.5 | T22: =IFERROR(__xludf.DUMMYFUNCTION("""COMPUTED_VALUE"""),0.0) -> 0 | U22: =IFERROR(__xludf.DUMMYFUNCTION("""COMPUTED_VALUE"""),0.0) -> 0 | V22: =IFERROR(__xludf.DUMMYFUNCTION("""COMPUTED_VALUE"""),37.0) -> 37 | W22: =IFERROR(__xludf.DUMMYFUNCTION("""COMPUTED_VALUE"""),203.5) -> 203.5
A23: =IFERROR(__xludf.DUMMYFUNCTION("""COMPUTED_VALUE"""),"MR Crunch") -> MR Crunch | B23: =IF(A23="","",SUMIFS(VMS_Sales!F:F,VMS_Sales!D:D,A23,VMS_Sales!O:O,$L$2)) -> 457 | C23: =IF(A23="","",ROUND(( SUMIFS(VMS_Sales!F:F,VMS_Sales!D:D,A23,VMS_Sales!O:O,$L$1)+ SUMIFS(VMS_Sales!F:F,VMS_Sales!D:D,A23,VMS_Sales!O:O,$L$2)+ SUMIFS(VMS_Sales!F:F,VMS_Sales!D:D,A23,VMS_Sales!O:O,$L$3) )/3,2)) -> 355 | D23: =IF(C23="","",ROUND(C23*1.15,0)) -> 408 | E23: =IFERROR(__xludf.DUMMYFUNCTION("IFERROR(XLOOKUP(A23,FILTER(VMS_Sales!$D:$D,VMS_Sales!$O:$O=$L$2),FILTER(VMS_Sales!$L:$L,VMS_Sales!$O:$O=$L$2),""""),"""")"),3.0) -> 3 | F23: =IF(OR(D23="",E23=""),"",ROUND(D23*E23,2)) -> 1224 | G23: {=IFERROR( SUMIFS( PurchaseLines_Import!$I:$I, PurchaseLines_Import!$C:$C, XLOOKUP(A23,Map!$A:$A,Map!$B:$B,""), PurchaseLines_Import!$H:$H, $L$1 ), "")} -> 450 | H23: {=IFERROR( SUMIFS( Inventory_Import!$D:$D, Inventory_Import!$B:$B, TEXT(XLOOKUP(A23,Map!$A:$A,Map!$B:$B,""),"0000") ), 0)} -> 95 | I23: =IF(A23="","",MAX(D23-H23,0)) -> 313 | J23: =IF(OR(I23="",E23=""),"",ROUND(I23*E23,2)) -> 939 | N23: =IFERROR(__xludf.DUMMYFUNCTION("""COMPUTED_VALUE"""),"Snickers") -> Snickers | O23: =IFERROR(__xludf.DUMMYFUNCTION("""COMPUTED_VALUE"""),64.0) -> 64 | P23: =IFERROR(__xludf.DUMMYFUNCTION("""COMPUTED_VALUE"""),33.0) -> 33 | Q23: =IFERROR(__xludf.DUMMYFUNCTION("""COMPUTED_VALUE"""),38.0) -> 38 | R23: =IFERROR(__xludf.DUMMYFUNCTION("""COMPUTED_VALUE"""),5.2) -> 5.2 | S23: =IFERROR(__xludf.DUMMYFUNCTION("""COMPUTED_VALUE"""),197.6) -> 197.6 | T23: =IFERROR(__xludf.DUMMYFUNCTION("""COMPUTED_VALUE"""),0.0) -> 0 | U23: =IFERROR(__xludf.DUMMYFUNCTION("""COMPUTED_VALUE"""),0.0) -> 0 | V23: =IFERROR(__xludf.DUMMYFUNCTION("""COMPUTED_VALUE"""),38.0) -> 38 | W23: =IFERROR(__xludf.DUMMYFUNCTION("""COMPUTED_VALUE"""),197.6) -> 197.6
A24: =IFERROR(__xludf.DUMMYFUNCTION("""COMPUTED_VALUE"""),"Mirinda") -> Mirinda | B24: =IF(A24="","",SUMIFS(VMS_Sales!F:F,VMS_Sales!D:D,A24,VMS_Sales!O:O,$L$2)) -> 220 | C24: =IF(A24="","",ROUND(( SUMIFS(VMS_Sales!F:F,VMS_Sales!D:D,A24,VMS_Sales!O:O,$L$1)+ SUMIFS(VMS_Sales!F:F,VMS_Sales!D:D,A24,VMS_Sales!O:O,$L$2)+ SUMIFS(VMS_Sales!F:F,VMS_Sales!D:D,A24,VMS_Sales!O:O,$L$3) )/3,2)) -> 107.33 | D24: =IF(C24="","",ROUND(C24*1.15,0)) -> 123 | E24: =IFERROR(__xludf.DUMMYFUNCTION("IFERROR(XLOOKUP(A24,FILTER(VMS_Sales!$D:$D,VMS_Sales!$O:$O=$L$2),FILTER(VMS_Sales!$L:$L,VMS_Sales!$O:$O=$L$2),""""),"""")"),2.25) -> 2.25 | F24: =IF(OR(D24="",E24=""),"",ROUND(D24*E24,2)) -> 276.75 | G24: {=IFERROR( SUMIFS( PurchaseLines_Import!$I:$I, PurchaseLines_Import!$C:$C, XLOOKUP(A24,Map!$A:$A,Map!$B:$B,""), PurchaseLines_Import!$H:$H, $L$1 ), "")} -> 24 | H24: {=IFERROR( SUMIFS( Inventory_Import!$D:$D, Inventory_Import!$B:$B, TEXT(XLOOKUP(A24,Map!$A:$A,Map!$B:$B,""),"0000") ), 0)} -> 0 | I24: =IF(A24="","",MAX(D24-H24,0)) -> 123 | J24: =IF(OR(I24="",E24=""),"",ROUND(I24*E24,2)) -> 276.75 | N24: =IFERROR(__xludf.DUMMYFUNCTION("""COMPUTED_VALUE"""),"Gardena") -> Gardena | O24: =IFERROR(__xludf.DUMMYFUNCTION("""COMPUTED_VALUE"""),107.0) -> 107 | P24: =IFERROR(__xludf.DUMMYFUNCTION("""COMPUTED_VALUE"""),48.0) -> 48 | Q24: =IFERROR(__xludf.DUMMYFUNCTION("""COMPUTED_VALUE"""),55.0) -> 55 | R24: =IFERROR(__xludf.DUMMYFUNCTION("""COMPUTED_VALUE"""),5.5) -> 5.5 | S24: =IFERROR(__xludf.DUMMYFUNCTION("""COMPUTED_VALUE"""),302.5) -> 302.5 | T24: =IFERROR(__xludf.DUMMYFUNCTION("""COMPUTED_VALUE"""),125.0) -> 125 | U24: =IFERROR(__xludf.DUMMYFUNCTION("""COMPUTED_VALUE"""),24.0) -> 24 | V24: =IFERROR(__xludf.DUMMYFUNCTION("""COMPUTED_VALUE"""),31.0) -> 31 | W24: =IFERROR(__xludf.DUMMYFUNCTION("""COMPUTED_VALUE"""),170.5) -> 170.5
A25: =IFERROR(__xludf.DUMMYFUNCTION("""COMPUTED_VALUE"""),"Almarai Strawberry") -> Almarai Strawberry | B25: =IF(A25="","",SUMIFS(VMS_Sales!F:F,VMS_Sales!D:D,A25,VMS_Sales!O:O,$L$2)) -> 209 | C25: =IF(A25="","",ROUND(( SUMIFS(VMS_Sales!F:F,VMS_Sales!D:D,A25,VMS_Sales!O:O,$L$1)+ SUMIFS(VMS_Sales!F:F,VMS_Sales!D:D,A25,VMS_Sales!O:O,$L$2)+ SUMIFS(VMS_Sales!F:F,VMS_Sales!D:D,A25,VMS_Sales!O:O,$L$3) )/3,2)) -> 152.67 | D25: =IF(C25="","",ROUND(C25*1.15,0)) -> 176 | E25: =IFERROR(__xludf.DUMMYFUNCTION("IFERROR(XLOOKUP(A25,FILTER(VMS_Sales!$D:$D,VMS_Sales!$O:$O=$L$2),FILTER(VMS_Sales!$L:$L,VMS_Sales!$O:$O=$L$2),""""),"""")"),2.29) -> 2.29 | F25: =IF(OR(D25="",E25=""),"",ROUND(D25*E25,2)) -> 403.04 | G25: {=IFERROR( SUMIFS( PurchaseLines_Import!$I:$I, PurchaseLines_Import!$C:$C, XLOOKUP(A25,Map!$A:$A,Map!$B:$B,""), PurchaseLines_Import!$H:$H, $L$1 ), "")} -> 135 | H25: {=IFERROR( SUMIFS( Inventory_Import!$D:$D, Inventory_Import!$B:$B, TEXT(XLOOKUP(A25,Map!$A:$A,Map!$B:$B,""),"0000") ), 0)} -> 30 | I25: =IF(A25="","",MAX(D25-H25,0)) -> 146 | J25: =IF(OR(I25="",E25=""),"",ROUND(I25*E25,2)) -> 334.34 | N25: =IFERROR(__xludf.DUMMYFUNCTION("""COMPUTED_VALUE"""),"Doritos red hot") -> Doritos red hot | O25: =IFERROR(__xludf.DUMMYFUNCTION("""COMPUTED_VALUE"""),138.0) -> 138 | P25: =IFERROR(__xludf.DUMMYFUNCTION("""COMPUTED_VALUE"""),46.0) -> 46 | Q25: =IFERROR(__xludf.DUMMYFUNCTION("""COMPUTED_VALUE"""),53.0) -> 53 | R25: =IFERROR(__xludf.DUMMYFUNCTION("""COMPUTED_VALUE"""),2.93) -> 2.93 | S25: =IFERROR(__xludf.DUMMYFUNCTION("""COMPUTED_VALUE"""),155.29) -> 155.29 | T25: =IFERROR(__xludf.DUMMYFUNCTION("""COMPUTED_VALUE"""),150.0) -> 150 | U25: =IFERROR(__xludf.DUMMYFUNCTION("""COMPUTED_VALUE"""),0.0) -> 0 | V25: =IFERROR(__xludf.DUMMYFUNCTION("""COMPUTED_VALUE"""),53.0) -> 53 | W25: =IFERROR(__xludf.DUMMYFUNCTION("""COMPUTED_VALUE"""),155.29) -> 155.29
A26: =IFERROR(__xludf.DUMMYFUNCTION("""COMPUTED_VALUE"""),"Indomie") -> Indomie | B26: =IF(A26="","",SUMIFS(VMS_Sales!F:F,VMS_Sales!D:D,A26,VMS_Sales!O:O,$L$2)) -> 0 | C26: =IF(A26="","",ROUND(( SUMIFS(VMS_Sales!F:F,VMS_Sales!D:D,A26,VMS_Sales!O:O,$L$1)+ SUMIFS(VMS_Sales!F:F,VMS_Sales!D:D,A26,VMS_Sales!O:O,$L$2)+ SUMIFS(VMS_Sales!F:F,VMS_Sales!D:D,A26,VMS_Sales!O:O,$L$3) )/3,2)) -> 0.67 | D26: =IF(C26="","",ROUND(C26*1.15,0)) -> 1 | E26: =IFERROR(__xludf.DUMMYFUNCTION("IFERROR(XLOOKUP(A26,FILTER(VMS_Sales!$D:$D,VMS_Sales!$O:$O=$L$2),FILTER(VMS_Sales!$L:$L,VMS_Sales!$O:$O=$L$2),""""),"""")"),"") | F26: =IF(OR(D26="",E26=""),"",ROUND(D26*E26,2)) | G26: {=IFERROR( SUMIFS( PurchaseLines_Import!$I:$I, PurchaseLines_Import!$C:$C, XLOOKUP(A26,Map!$A:$A,Map!$B:$B,""), PurchaseLines_Import!$H:$H, $L$1 ), "")} -> 0 | H26: {=IFERROR( SUMIFS( Inventory_Import!$D:$D, Inventory_Import!$B:$B, TEXT(XLOOKUP(A26,Map!$A:$A,Map!$B:$B,""),"0000") ), 0)} -> 0 | I26: =IF(A26="","",MAX(D26-H26,0)) -> 1 | J26: =IF(OR(I26="",E26=""),"",ROUND(I26*E26,2)) | N26: =IFERROR(__xludf.DUMMYFUNCTION("""COMPUTED_VALUE"""),"Rayhan suntop") -> Rayhan suntop | O26: =IFERROR(__xludf.DUMMYFUNCTION("""COMPUTED_VALUE"""),261.0) -> 261 | P26: =IFERROR(__xludf.DUMMYFUNCTION("""COMPUTED_VALUE"""),197.0) -> 197 | Q26: =IFERROR(__xludf.DUMMYFUNCTION("""COMPUTED_VALUE"""),227.0) -> 227 | R26: =IFERROR(__xludf.DUMMYFUNCTION("""COMPUTED_VALUE"""),0.68) -> 0.68 | S26: =IFERROR(__xludf.DUMMYFUNCTION("""COMPUTED_VALUE"""),154.36) -> 154.36 | T26: =IFERROR(__xludf.DUMMYFUNCTION("""COMPUTED_VALUE"""),120.0) -> 120 | U26: =IFERROR(__xludf.DUMMYFUNCTION("""COMPUTED_VALUE"""),0.0) -> 0 | V26: =IFERROR(__xludf.DUMMYFUNCTION("""COMPUTED_VALUE"""),227.0) -> 227 | W26: =IFERROR(__xludf.DUMMYFUNCTION("""COMPUTED_VALUE"""),154.36) -> 154.36
A27: =IFERROR(__xludf.DUMMYFUNCTION("""COMPUTED_VALUE"""),"Doritos green hot") -> Doritos green hot | B27: =IF(A27="","",SUMIFS(VMS_Sales!F:F,VMS_Sales!D:D,A27,VMS_Sales!O:O,$L$2)) -> 187 | C27: =IF(A27="","",ROUND(( SUMIFS(VMS_Sales!F:F,VMS_Sales!D:D,A27,VMS_Sales!O:O,$L$1)+ SUMIFS(VMS_Sales!F:F,VMS_Sales!D:D,A27,VMS_Sales!O:O,$L$2)+ SUMIFS(VMS_Sales!F:F,VMS_Sales!D:D,A27,VMS_Sales!O:O,$L$3) )/3,2)) -> 191 | D27: =IF(C27="","",ROUND(C27*1.15,0)) -> 220 | E27: =IFERROR(__xludf.DUMMYFUNCTION("IFERROR(XLOOKUP(A27,FILTER(VMS_Sales!$D:$D,VMS_Sales!$O:$O=$L$2),FILTER(VMS_Sales!$L:$L,VMS_Sales!$O:$O=$L$2),""""),"""")"),2.93) -> 2.93 | F27: =IF(OR(D27="",E27=""),"",ROUND(D27*E27,2)) -> 644.6 | G27: {=IFERROR( SUMIFS( PurchaseLines_Import!$I:$I, PurchaseLines_Import!$C:$C, XLOOKUP(A27,Map!$A:$A,Map!$B:$B,""), PurchaseLines_Import!$H:$H, $L$1 ), "")} -> 0 | H27: {=IFERROR( SUMIFS( Inventory_Import!$D:$D, Inventory_Import!$B:$B, TEXT(XLOOKUP(A27,Map!$A:$A,Map!$B:$B,""),"0000") ), 0)} -> 73 | I27: =IF(A27="","",MAX(D27-H27,0)) -> 147 | J27: =IF(OR(I27="",E27=""),"",ROUND(I27*E27,2)) -> 430.71 | N27: =IFERROR(__xludf.DUMMYFUNCTION("""COMPUTED_VALUE"""),"Toblerone") -> Toblerone | O27: =IFERROR(__xludf.DUMMYFUNCTION("""COMPUTED_VALUE"""),5.0) -> 5 | P27: =IFERROR(__xludf.DUMMYFUNCTION("""COMPUTED_VALUE"""),26.0) -> 26 | Q27: =IFERROR(__xludf.DUMMYFUNCTION("""COMPUTED_VALUE"""),30.0) -> 30 | R27: =IFERROR(__xludf.DUMMYFUNCTION("""COMPUTED_VALUE"""),4.79) -> 4.79 | S27: =IFERROR(__xludf.DUMMYFUNCTION("""COMPUTED_VALUE"""),143.7) -> 143.7 | T27: =IFERROR(__xludf.DUMMYFUNCTION("""COMPUTED_VALUE"""),0.0) -> 0 | U27: =IFERROR(__xludf.DUMMYFUNCTION("""COMPUTED_VALUE"""),0.0) -> 0 | V27: =IFERROR(__xludf.DUMMYFUNCTION("""COMPUTED_VALUE"""),30.0) -> 30 | W27: =IFERROR(__xludf.DUMMYFUNCTION("""COMPUTED_VALUE"""),143.7) -> 143.7
A28: =IFERROR(__xludf.DUMMYFUNCTION("""COMPUTED_VALUE"""),"Doritos nacho") -> Doritos nacho | B28: =IF(A28="","",SUMIFS(VMS_Sales!F:F,VMS_Sales!D:D,A28,VMS_Sales!O:O,$L$2)) -> 376 | C28: =IF(A28="","",ROUND(( SUMIFS(VMS_Sales!F:F,VMS_Sales!D:D,A28,VMS_Sales!O:O,$L$1)+ SUMIFS(VMS_Sales!F:F,VMS_Sales!D:D,A28,VMS_Sales!O:O,$L$2)+ SUMIFS(VMS_Sales!F:F,VMS_Sales!D:D,A28,VMS_Sales!O:O,$L$3) )/3,2)) -> 175 | D28: =IF(C28="","",ROUND(C28*1.15,0)) -> 201 | E28: =IFERROR(__xludf.DUMMYFUNCTION("IFERROR(XLOOKUP(A28,FILTER(VMS_Sales!$D:$D,VMS_Sales!$O:$O=$L$2),FILTER(VMS_Sales!$L:$L,VMS_Sales!$O:$O=$L$2),""""),"""")"),2.93) -> 2.93 | F28: =IF(OR(D28="",E28=""),"",ROUND(D28*E28,2)) -> 588.93 | G28: {=IFERROR( SUMIFS( PurchaseLines_Import!$I:$I, PurchaseLines_Import!$C:$C, XLOOKUP(A28,Map!$A:$A,Map!$B:$B,""), PurchaseLines_Import!$H:$H, $L$1 ), "")} -> 165 | H28: {=IFERROR( SUMIFS( Inventory_Import!$D:$D, Inventory_Import!$B:$B, TEXT(XLOOKUP(A28,Map!$A:$A,Map!$B:$B,""),"0000") ), 0)} -> 89 | I28: =IF(A28="","",MAX(D28-H28,0)) -> 112 | J28: =IF(OR(I28="",E28=""),"",ROUND(I28*E28,2)) -> 328.16 | N28: =IFERROR(__xludf.DUMMYFUNCTION("""COMPUTED_VALUE"""),"Schweppes bullet") -> Schweppes bullet | O28: =IFERROR(__xludf.DUMMYFUNCTION("""COMPUTED_VALUE"""),101.0) -> 101 | P28: =IFERROR(__xludf.DUMMYFUNCTION("""COMPUTED_VALUE"""),63.33) -> 63.33 | Q28: =IFERROR(__xludf.DUMMYFUNCTION("""COMPUTED_VALUE"""),73.0) -> 73 | R28: =IFERROR(__xludf.DUMMYFUNCTION("""COMPUTED_VALUE"""),1.75) -> 1.75 | S28: =IFERROR(__xludf.DUMMYFUNCTION("""COMPUTED_VALUE"""),127.75) -> 127.75 | T28: =IFERROR(__xludf.DUMMYFUNCTION("""COMPUTED_VALUE"""),0.0) -> 0 | U28: =IFERROR(__xludf.DUMMYFUNCTION("""COMPUTED_VALUE"""),0.0) -> 0 | V28: =IFERROR(__xludf.DUMMYFUNCTION("""COMPUTED_VALUE"""),73.0) -> 73 | W28: =IFERROR(__xludf.DUMMYFUNCTION("""COMPUTED_VALUE"""),127.75) -> 127.75
A29: =IFERROR(__xludf.DUMMYFUNCTION("""COMPUTED_VALUE"""),"Barbican") -> Barbican | B29: =IF(A29="","",SUMIFS(VMS_Sales!F:F,VMS_Sales!D:D,A29,VMS_Sales!O:O,$L$2)) -> 15 | C29: =IF(A29="","",ROUND(( SUMIFS(VMS_Sales!F:F,VMS_Sales!D:D,A29,VMS_Sales!O:O,$L$1)+ SUMIFS(VMS_Sales!F:F,VMS_Sales!D:D,A29,VMS_Sales!O:O,$L$2)+ SUMIFS(VMS_Sales!F:F,VMS_Sales!D:D,A29,VMS_Sales!O:O,$L$3) )/3,2)) -> 10.67 | D29: =IF(C29="","",ROUND(C29*1.15,0)) -> 12 | E29: =IFERROR(__xludf.DUMMYFUNCTION("IFERROR(XLOOKUP(A29,FILTER(VMS_Sales!$D:$D,VMS_Sales!$O:$O=$L$2),FILTER(VMS_Sales!$L:$L,VMS_Sales!$O:$O=$L$2),""""),"""")"),3.17) -> 3.17 | F29: =IF(OR(D29="",E29=""),"",ROUND(D29*E29,2)) -> 38.04 | G29: {=IFERROR( SUMIFS( PurchaseLines_Import!$I:$I, PurchaseLines_Import!$C:$C, XLOOKUP(A29,Map!$A:$A,Map!$B:$B,""), PurchaseLines_Import!$H:$H, $L$1 ), "")} -> 0 | H29: {=IFERROR( SUMIFS( Inventory_Import!$D:$D, Inventory_Import!$B:$B, TEXT(XLOOKUP(A29,Map!$A:$A,Map!$B:$B,""),"0000") ), 0)} -> 0 | I29: =IF(A29="","",MAX(D29-H29,0)) -> 12 | J29: =IF(OR(I29="",E29=""),"",ROUND(I29*E29,2)) -> 38.04 | N29: =IFERROR(__xludf.DUMMYFUNCTION("""COMPUTED_VALUE"""),"Chillax chips") -> Chillax chips | O29: =IFERROR(__xludf.DUMMYFUNCTION("""COMPUTED_VALUE"""),36.0) -> 36 | P29: =IFERROR(__xludf.DUMMYFUNCTION("""COMPUTED_VALUE"""),31.0) -> 31 | Q29: =IFERROR(__xludf.DUMMYFUNCTION("""COMPUTED_VALUE"""),36.0) -> 36 | R29: =IFERROR(__xludf.DUMMYFUNCTION("""COMPUTED_VALUE"""),3.5) -> 3.5 | S29: =IFERROR(__xludf.DUMMYFUNCTION("""COMPUTED_VALUE"""),126.0) -> 126 | T29: =IFERROR(__xludf.DUMMYFUNCTION("""COMPUTED_VALUE"""),0.0) -> 0 | U29: =IFERROR(__xludf.DUMMYFUNCTION("""COMPUTED_VALUE"""),0.0) -> 0 | V29: =IFERROR(__xludf.DUMMYFUNCTION("""COMPUTED_VALUE"""),36.0) -> 36 | W29: =IFERROR(__xludf.DUMMYFUNCTION("""COMPUTED_VALUE"""),126.0) -> 126
A30: =IFERROR(__xludf.DUMMYFUNCTION("""COMPUTED_VALUE"""),"Shani") -> Shani | B30: =IF(A30="","",SUMIFS(VMS_Sales!F:F,VMS_Sales!D:D,A30,VMS_Sales!O:O,$L$2)) -> 159 | C30: =IF(A30="","",ROUND(( SUMIFS(VMS_Sales!F:F,VMS_Sales!D:D,A30,VMS_Sales!O:O,$L$1)+ SUMIFS(VMS_Sales!F:F,VMS_Sales!D:D,A30,VMS_Sales!O:O,$L$2)+ SUMIFS(VMS_Sales!F:F,VMS_Sales!D:D,A30,VMS_Sales!O:O,$L$3) )/3,2)) -> 89.67 | D30: =IF(C30="","",ROUND(C30*1.15,0)) -> 103 | E30: =IFERROR(__xludf.DUMMYFUNCTION("IFERROR(XLOOKUP(A30,FILTER(VMS_Sales!$D:$D,VMS_Sales!$O:$O=$L$2),FILTER(VMS_Sales!$L:$L,VMS_Sales!$O:$O=$L$2),""""),"""")"),2.25) -> 2.25 | F30: =IF(OR(D30="",E30=""),"",ROUND(D30*E30,2)) -> 231.75 | G30: {=IFERROR( SUMIFS( PurchaseLines_Import!$I:$I, PurchaseLines_Import!$C:$C, XLOOKUP(A30,Map!$A:$A,Map!$B:$B,""), PurchaseLines_Import!$H:$H, $L$1 ), "")} -> 0 | H30: {=IFERROR( SUMIFS( Inventory_Import!$D:$D, Inventory_Import!$B:$B, TEXT(XLOOKUP(A30,Map!$A:$A,Map!$B:$B,""),"0000") ), 0)} -> 0 | I30: =IF(A30="","",MAX(D30-H30,0)) -> 103 | J30: =IF(OR(I30="",E30=""),"",ROUND(I30*E30,2)) -> 231.75 | N30: =IFERROR(__xludf.DUMMYFUNCTION("""COMPUTED_VALUE"""),"Coach Suntop") -> Coach Suntop | O30: =IFERROR(__xludf.DUMMYFUNCTION("""COMPUTED_VALUE"""),412.0) -> 412 | P30: =IFERROR(__xludf.DUMMYFUNCTION("""COMPUTED_VALUE"""),234.67) -> 234.67 | Q30: =IFERROR(__xludf.DUMMYFUNCTION("""COMPUTED_VALUE"""),270.0) -> 270 | R30: =IFERROR(__xludf.DUMMYFUNCTION("""COMPUTED_VALUE"""),0.45) -> 0.45 | S30: =IFERROR(__xludf.DUMMYFUNCTION("""COMPUTED_VALUE"""),121.5) -> 121.5 | T30: =IFERROR(__xludf.DUMMYFUNCTION("""COMPUTED_VALUE"""),0.0) -> 0 | U30: =IFERROR(__xludf.DUMMYFUNCTION("""COMPUTED_VALUE"""),-1.0) -> -1 | V30: =IFERROR(__xludf.DUMMYFUNCTION("""COMPUTED_VALUE"""),271.0) -> 271 | W30: =IFERROR(__xludf.DUMMYFUNCTION("""COMPUTED_VALUE"""),121.95) -> 121.95
A31: =IFERROR(__xludf.DUMMYFUNCTION("""COMPUTED_VALUE"""),"Toblerone") -> Toblerone | B31: =IF(A31="","",SUMIFS(VMS_Sales!F:F,VMS_Sales!D:D,A31,VMS_Sales!O:O,$L$2)) -> 5 | C31: =IF(A31="","",ROUND(( SUMIFS(VMS_Sales!F:F,VMS_Sales!D:D,A31,VMS_Sales!O:O,$L$1)+ SUMIFS(VMS_Sales!F:F,VMS_Sales!D:D,A31,VMS_Sales!O:O,$L$2)+ SUMIFS(VMS_Sales!F:F,VMS_Sales!D:D,A31,VMS_Sales!O:O,$L$3) )/3,2)) -> 26 | D31: =IF(C31="","",ROUND(C31*1.15,0)) -> 30 | E31: =IFERROR(__xludf.DUMMYFUNCTION("IFERROR(XLOOKUP(A31,FILTER(VMS_Sales!$D:$D,VMS_Sales!$O:$O=$L$2),FILTER(VMS_Sales!$L:$L,VMS_Sales!$O:$O=$L$2),""""),"""")"),4.79) -> 4.79 | F31: =IF(OR(D31="",E31=""),"",ROUND(D31*E31,2)) -> 143.7 | G31: {=IFERROR( SUMIFS( PurchaseLines_Import!$I:$I, PurchaseLines_Import!$C:$C, XLOOKUP(A31,Map!$A:$A,Map!$B:$B,""), PurchaseLines_Import!$H:$H, $L$1 ), "")} -> 0 | H31: {=IFERROR( SUMIFS( Inventory_Import!$D:$D, Inventory_Import!$B:$B, TEXT(XLOOKUP(A31,Map!$A:$A,Map!$B:$B,""),"0000") ), 0)} -> 0 | I31: =IF(A31="","",MAX(D31-H31,0)) -> 30 | J31: =IF(OR(I31="",E31=""),"",ROUND(I31*E31,2)) -> 143.7 | N31: =IFERROR(__xludf.DUMMYFUNCTION("""COMPUTED_VALUE"""),"Lovita cookies") -> Lovita cookies | O31: =IFERROR(__xludf.DUMMYFUNCTION("""COMPUTED_VALUE"""),25.0) -> 25 | P31: =IFERROR(__xludf.DUMMYFUNCTION("""COMPUTED_VALUE"""),19.67) -> 19.67 | Q31: =IFERROR(__xludf.DUMMYFUNCTION("""COMPUTED_VALUE"""),23.0) -> 23 | R31: =IFERROR(__xludf.DUMMYFUNCTION("""COMPUTED_VALUE"""),5.18) -> 5.18 | S31: =IFERROR(__xludf.DUMMYFUNCTION("""COMPUTED_VALUE"""),119.14) -> 119.14 | T31: =IFERROR(__xludf.DUMMYFUNCTION("""COMPUTED_VALUE"""),34.0) -> 34 | U31: =IFERROR(__xludf.DUMMYFUNCTION("""COMPUTED_VALUE"""),0.0) -> 0 | V31: =IFERROR(__xludf.DUMMYFUNCTION("""COMPUTED_VALUE"""),23.0) -> 23 | W31: =IFERROR(__xludf.DUMMYFUNCTION("""COMPUTED_VALUE"""),119.14) -> 119.14
A32: =IFERROR(__xludf.DUMMYFUNCTION("""COMPUTED_VALUE"""),"Rayhan suntop") -> Rayhan suntop | B32: =IF(A32="","",SUMIFS(VMS_Sales!F:F,VMS_Sales!D:D,A32,VMS_Sales!O:O,$L$2)) -> 261 | C32: =IF(A32="","",ROUND(( SUMIFS(VMS_Sales!F:F,VMS_Sales!D:D,A32,VMS_Sales!O:O,$L$1)+ SUMIFS(VMS_Sales!F:F,VMS_Sales!D:D,A32,VMS_Sales!O:O,$L$2)+ SUMIFS(VMS_Sales!F:F,VMS_Sales!D:D,A32,VMS_Sales!O:O,$L$3) )/3,2)) -> 197 | D32: =IF(C32="","",ROUND(C32*1.15,0)) -> 227 | E32: =IFERROR(__xludf.DUMMYFUNCTION("IFERROR(XLOOKUP(A32,FILTER(VMS_Sales!$D:$D,VMS_Sales!$O:$O=$L$2),FILTER(VMS_Sales!$L:$L,VMS_Sales!$O:$O=$L$2),""""),"""")"),0.68) -> 0.68 | F32: =IF(OR(D32="",E32=""),"",ROUND(D32*E32,2)) -> 154.36 | G32: {=IFERROR( SUMIFS( PurchaseLines_Import!$I:$I, PurchaseLines_Import!$C:$C, XLOOKUP(A32,Map!$A:$A,Map!$B:$B,""), PurchaseLines_Import!$H:$H, $L$1 ), "")} -> 120 | H32: {=IFERROR( SUMIFS( Inventory_Import!$D:$D, Inventory_Import!$B:$B, TEXT(XLOOKUP(A32,Map!$A:$A,Map!$B:$B,""),"0000") ), 0)} -> 0 | I32: =IF(A32="","",MAX(D32-H32,0)) -> 227 | J32: =IF(OR(I32="",E32=""),"",ROUND(I32*E32,2)) -> 154.36 | N32: =IFERROR(__xludf.DUMMYFUNCTION("""COMPUTED_VALUE"""),"7up") -> 7up | O32: =IFERROR(__xludf.DUMMYFUNCTION("""COMPUTED_VALUE"""),112.0) -> 112 | P32: =IFERROR(__xludf.DUMMYFUNCTION("""COMPUTED_VALUE"""),44.33) -> 44.33 | Q32: =IFERROR(__xludf.DUMMYFUNCTION("""COMPUTED_VALUE"""),51.0) -> 51 | R32: =IFERROR(__xludf.DUMMYFUNCTION("""COMPUTED_VALUE"""),2.25) -> 2.25 | S32: =IFERROR(__xludf.DUMMYFUNCTION("""COMPUTED_VALUE"""),114.75) -> 114.75 | T32: =IFERROR(__xludf.DUMMYFUNCTION("""COMPUTED_VALUE"""),0.0) -> 0 | U32: =IFERROR(__xludf.DUMMYFUNCTION("""COMPUTED_VALUE"""),0.0) -> 0 | V32: =IFERROR(__xludf.DUMMYFUNCTION("""COMPUTED_VALUE"""),51.0) -> 51 | W32: =IFERROR(__xludf.DUMMYFUNCTION("""COMPUTED_VALUE"""),114.75) -> 114.75
A33: =IFERROR(__xludf.DUMMYFUNCTION("""COMPUTED_VALUE"""),"Tiger excellence") -> Tiger excellence | B33: =IF(A33="","",SUMIFS(VMS_Sales!F:F,VMS_Sales!D:D,A33,VMS_Sales!O:O,$L$2)) -> 147 | C33: =IF(A33="","",ROUND(( SUMIFS(VMS_Sales!F:F,VMS_Sales!D:D,A33,VMS_Sales!O:O,$L$1)+ SUMIFS(VMS_Sales!F:F,VMS_Sales!D:D,A33,VMS_Sales!O:O,$L$2)+ SUMIFS(VMS_Sales!F:F,VMS_Sales!D:D,A33,VMS_Sales!O:O,$L$3) )/3,2)) -> 99 | D33: =IF(C33="","",ROUND(C33*1.15,0)) -> 114 | E33: =IFERROR(__xludf.DUMMYFUNCTION("IFERROR(XLOOKUP(A33,FILTER(VMS_Sales!$D:$D,VMS_Sales!$O:$O=$L$2),FILTER(VMS_Sales!$L:$L,VMS_Sales!$O:$O=$L$2),""""),"""")"),2.25) -> 2.25 | F33: =IF(OR(D33="",E33=""),"",ROUND(D33*E33,2)) -> 256.5 | G33: {=IFERROR( SUMIFS( PurchaseLines_Import!$I:$I, PurchaseLines_Import!$C:$C, XLOOKUP(A33,Map!$A:$A,Map!$B:$B,""), PurchaseLines_Import!$H:$H, $L$1 ), "")} -> 200 | H33: {=IFERROR( SUMIFS( Inventory_Import!$D:$D, Inventory_Import!$B:$B, TEXT(XLOOKUP(A33,Map!$A:$A,Map!$B:$B,""),"0000") ), 0)} -> 0 | I33: =IF(A33="","",MAX(D33-H33,0)) -> 114 | J33: =IF(OR(I33="",E33=""),"",ROUND(I33*E33,2)) -> 256.5 | N33: =IFERROR(__xludf.DUMMYFUNCTION("""COMPUTED_VALUE"""),"Galaxy wafer roll") -> Galaxy wafer roll | O33: =IFERROR(__xludf.DUMMYFUNCTION("""COMPUTED_VALUE"""),277.0) -> 277 | P33: =IFERROR(__xludf.DUMMYFUNCTION("""COMPUTED_VALUE"""),92.33) -> 92.33 | Q33: =IFERROR(__xludf.DUMMYFUNCTION("""COMPUTED_VALUE"""),106.0) -> 106 | R33: =IFERROR(__xludf.DUMMYFUNCTION("""COMPUTED_VALUE"""),1.08) -> 1.08 | S33: =IFERROR(__xludf.DUMMYFUNCTION("""COMPUTED_VALUE"""),114.48) -> 114.48 | T33: =IFERROR(__xludf.DUMMYFUNCTION("""COMPUTED_VALUE"""),240.0) -> 240 | U33: =IFERROR(__xludf.DUMMYFUNCTION("""COMPUTED_VALUE"""),5.0) -> 5 | V33: =IFERROR(__xludf.DUMMYFUNCTION("""COMPUTED_VALUE"""),101.0) -> 101 | W33: =IFERROR(__xludf.DUMMYFUNCTION("""COMPUTED_VALUE"""),109.08) -> 109.08
A34: =IFERROR(__xludf.DUMMYFUNCTION("""COMPUTED_VALUE"""),"Savi stix") -> Savi stix | B34: =IF(A34="","",SUMIFS(VMS_Sales!F:F,VMS_Sales!D:D,A34,VMS_Sales!O:O,$L$2)) -> 31 | C34: =IF(A34="","",ROUND(( SUMIFS(VMS_Sales!F:F,VMS_Sales!D:D,A34,VMS_Sales!O:O,$L$1)+ SUMIFS(VMS_Sales!F:F,VMS_Sales!D:D,A34,VMS_Sales!O:O,$L$2)+ SUMIFS(VMS_Sales!F:F,VMS_Sales!D:D,A34,VMS_Sales!O:O,$L$3) )/3,2)) -> 16 | D34: =IF(C34="","",ROUND(C34*1.15,0)) -> 18 | E34: =IFERROR(__xludf.DUMMYFUNCTION("IFERROR(XLOOKUP(A34,FILTER(VMS_Sales!$D:$D,VMS_Sales!$O:$O=$L$2),FILTER(VMS_Sales!$L:$L,VMS_Sales!$O:$O=$L$2),""""),"""")"),3.6) -> 3.6 | F34: =IF(OR(D34="",E34=""),"",ROUND(D34*E34,2)) -> 64.8 | G34: {=IFERROR( SUMIFS( PurchaseLines_Import!$I:$I, PurchaseLines_Import!$C:$C, XLOOKUP(A34,Map!$A:$A,Map!$B:$B,""), PurchaseLines_Import!$H:$H, $L$1 ), "")} -> 0 | H34: {=IFERROR( SUMIFS( Inventory_Import!$D:$D, Inventory_Import!$B:$B, TEXT(XLOOKUP(A34,Map!$A:$A,Map!$B:$B,""),"0000") ), 0)} -> 0 | I34: =IF(A34="","",MAX(D34-H34,0)) -> 18 | J34: =IF(OR(I34="",E34=""),"",ROUND(I34*E34,2)) -> 64.8 | N34: =IFERROR(__xludf.DUMMYFUNCTION("""COMPUTED_VALUE"""),"Corissant Karuzo") -> Corissant Karuzo | O34: =IFERROR(__xludf.DUMMYFUNCTION("""COMPUTED_VALUE"""),51.0) -> 51 | P34: =IFERROR(__xludf.DUMMYFUNCTION("""COMPUTED_VALUE"""),33.0) -> 33 | Q34: =IFERROR(__xludf.DUMMYFUNCTION("""COMPUTED_VALUE"""),38.0) -> 38 | R34: =IFERROR(__xludf.DUMMYFUNCTION("""COMPUTED_VALUE"""),3.13) -> 3.13 | S34: =IFERROR(__xludf.DUMMYFUNCTION("""COMPUTED_VALUE"""),118.94) -> 118.94 | T34: =IFERROR(__xludf.DUMMYFUNCTION("""COMPUTED_VALUE"""),72.0) -> 72 | U34: =IFERROR(__xludf.DUMMYFUNCTION("""COMPUTED_VALUE"""),4.0) -> 4 | V34: =IFERROR(__xludf.DUMMYFUNCTION("""COMPUTED_VALUE"""),34.0) -> 34 | W34: =IFERROR(__xludf.DUMMYFUNCTION("""COMPUTED_VALUE"""),106.42) -> 106.42
A35: =IFERROR(__xludf.DUMMYFUNCTION("""COMPUTED_VALUE"""),"Lexus") -> Lexus | B35: =IF(A35="","",SUMIFS(VMS_Sales!F:F,VMS_Sales!D:D,A35,VMS_Sales!O:O,$L$2)) -> 0 | C35: =IF(A35="","",ROUND(( SUMIFS(VMS_Sales!F:F,VMS_Sales!D:D,A35,VMS_Sales!O:O,$L$1)+ SUMIFS(VMS_Sales!F:F,VMS_Sales!D:D,A35,VMS_Sales!O:O,$L$2)+ SUMIFS(VMS_Sales!F:F,VMS_Sales!D:D,A35,VMS_Sales!O:O,$L$3) )/3,2)) -> 16 | D35: =IF(C35="","",ROUND(C35*1.15,0)) -> 18 | E35: =IFERROR(__xludf.DUMMYFUNCTION("IFERROR(XLOOKUP(A35,FILTER(VMS_Sales!$D:$D,VMS_Sales!$O:$O=$L$2),FILTER(VMS_Sales!$L:$L,VMS_Sales!$O:$O=$L$2),""""),"""")"),"") | F35: =IF(OR(D35="",E35=""),"",ROUND(D35*E35,2)) | G35: {=IFERROR( SUMIFS( PurchaseLines_Import!$I:$I, PurchaseLines_Import!$C:$C, XLOOKUP(A35,Map!$A:$A,Map!$B:$B,""), PurchaseLines_Import!$H:$H, $L$1 ), "")} -> 0 | H35: {=IFERROR( SUMIFS( Inventory_Import!$D:$D, Inventory_Import!$B:$B, TEXT(XLOOKUP(A35,Map!$A:$A,Map!$B:$B,""),"0000") ), 0)} -> 0 | I35: =IF(A35="","",MAX(D35-H35,0)) -> 18 | J35: =IF(OR(I35="",E35=""),"",ROUND(I35*E35,2)) | N35: =IFERROR(__xludf.DUMMYFUNCTION("""COMPUTED_VALUE"""),"Twix") -> Twix | O35: =IFERROR(__xludf.DUMMYFUNCTION("""COMPUTED_VALUE"""),25.0) -> 25 | P35: =IFERROR(__xludf.DUMMYFUNCTION("""COMPUTED_VALUE"""),17.67) -> 17.67 | Q35: =IFERROR(__xludf.DUMMYFUNCTION("""COMPUTED_VALUE"""),20.0) -> 20 | R35: =IFERROR(__xludf.DUMMYFUNCTION("""COMPUTED_VALUE"""),5.0) -> 5 | S35: =IFERROR(__xludf.DUMMYFUNCTION("""COMPUTED_VALUE"""),100.0) -> 100 | T35: =IFERROR(__xludf.DUMMYFUNCTION("""COMPUTED_VALUE"""),0.0) -> 0 | U35: =IFERROR(__xludf.DUMMYFUNCTION("""COMPUTED_VALUE"""),0.0) -> 0 | V35: =IFERROR(__xludf.DUMMYFUNCTION("""COMPUTED_VALUE"""),20.0) -> 20 | W35: =IFERROR(__xludf.DUMMYFUNCTION("""COMPUTED_VALUE"""),100.0) -> 100
A36: =IFERROR(__xludf.DUMMYFUNCTION("""COMPUTED_VALUE"""),"Kitkat 2 fingers") -> Kitkat 2 fingers | B36: =IF(A36="","",SUMIFS(VMS_Sales!F:F,VMS_Sales!D:D,A36,VMS_Sales!O:O,$L$2)) -> 0 | C36: =IF(A36="","",ROUND(( SUMIFS(VMS_Sales!F:F,VMS_Sales!D:D,A36,VMS_Sales!O:O,$L$1)+ SUMIFS(VMS_Sales!F:F,VMS_Sales!D:D,A36,VMS_Sales!O:O,$L$2)+ SUMIFS(VMS_Sales!F:F,VMS_Sales!D:D,A36,VMS_Sales!O:O,$L$3) )/3,2)) -> 8.33 | D36: =IF(C36="","",ROUND(C36*1.15,0)) -> 10 | E36: =IFERROR(__xludf.DUMMYFUNCTION("IFERROR(XLOOKUP(A36,FILTER(VMS_Sales!$D:$D,VMS_Sales!$O:$O=$L$2),FILTER(VMS_Sales!$L:$L,VMS_Sales!$O:$O=$L$2),""""),"""")"),"") | F36: =IF(OR(D36="",E36=""),"",ROUND(D36*E36,2)) | G36: {=IFERROR( SUMIFS( PurchaseLines_Import!$I:$I, PurchaseLines_Import!$C:$C, XLOOKUP(A36,Map!$A:$A,Map!$B:$B,""), PurchaseLines_Import!$H:$H, $L$1 ), "")} -> 0 | H36: {=IFERROR( SUMIFS( Inventory_Import!$D:$D, Inventory_Import!$B:$B, TEXT(XLOOKUP(A36,Map!$A:$A,Map!$B:$B,""),"0000") ), 0)} -> 0 | I36: =IF(A36="","",MAX(D36-H36,0)) -> 10 | J36: =IF(OR(I36="",E36=""),"",ROUND(I36*E36,2)) | N36: =IFERROR(__xludf.DUMMYFUNCTION("""COMPUTED_VALUE"""),"Caser Juice") -> Caser Juice | O36: =IFERROR(__xludf.DUMMYFUNCTION("""COMPUTED_VALUE"""),27.0) -> 27 | P36: =IFERROR(__xludf.DUMMYFUNCTION("""COMPUTED_VALUE"""),17.67) -> 17.67 | Q36: =IFERROR(__xludf.DUMMYFUNCTION("""COMPUTED_VALUE"""),20.0) -> 20 | R36: =IFERROR(__xludf.DUMMYFUNCTION("""COMPUTED_VALUE"""),4.13) -> 4.13 | S36: =IFERROR(__xludf.DUMMYFUNCTION("""COMPUTED_VALUE"""),82.6) -> 82.6 | T36: =IFERROR(__xludf.DUMMYFUNCTION("""COMPUTED_VALUE"""),0.0) -> 0 | U36: =IFERROR(__xludf.DUMMYFUNCTION("""COMPUTED_VALUE"""),0.0) -> 0 | V36: =IFERROR(__xludf.DUMMYFUNCTION("""COMPUTED_VALUE"""),20.0) -> 20 | W36: =IFERROR(__xludf.DUMMYFUNCTION("""COMPUTED_VALUE"""),82.6) -> 82.6
A37: =IFERROR(__xludf.DUMMYFUNCTION("""COMPUTED_VALUE"""),"Schweppes bullet") -> Schweppes bullet | B37: =IF(A37="","",SUMIFS(VMS_Sales!F:F,VMS_Sales!D:D,A37,VMS_Sales!O:O,$L$2)) -> 101 | C37: =IF(A37="","",ROUND(( SUMIFS(VMS_Sales!F:F,VMS_Sales!D:D,A37,VMS_Sales!O:O,$L$1)+ SUMIFS(VMS_Sales!F:F,VMS_Sales!D:D,A37,VMS_Sales!O:O,$L$2)+ SUMIFS(VMS_Sales!F:F,VMS_Sales!D:D,A37,VMS_Sales!O:O,$L$3) )/3,2)) -> 63.33 | D37: =IF(C37="","",ROUND(C37*1.15,0)) -> 73 | E37: =IFERROR(__xludf.DUMMYFUNCTION("IFERROR(XLOOKUP(A37,FILTER(VMS_Sales!$D:$D,VMS_Sales!$O:$O=$L$2),FILTER(VMS_Sales!$L:$L,VMS_Sales!$O:$O=$L$2),""""),"""")"),1.75) -> 1.75 | F37: =IF(OR(D37="",E37=""),"",ROUND(D37*E37,2)) -> 127.75 | G37: {=IFERROR( SUMIFS( PurchaseLines_Import!$I:$I, PurchaseLines_Import!$C:$C, XLOOKUP(A37,Map!$A:$A,Map!$B:$B,""), PurchaseLines_Import!$H:$H, $L$1 ), "")} -> 0 | H37: {=IFERROR( SUMIFS( Inventory_Import!$D:$D, Inventory_Import!$B:$B, TEXT(XLOOKUP(A37,Map!$A:$A,Map!$B:$B,""),"0000") ), 0)} -> 0 | I37: =IF(A37="","",MAX(D37-H37,0)) -> 73 | J37: =IF(OR(I37="",E37=""),"",ROUND(I37*E37,2)) -> 127.75 | N37: =IFERROR(__xludf.DUMMYFUNCTION("""COMPUTED_VALUE"""),"Skittles") -> Skittles | O37: =IFERROR(__xludf.DUMMYFUNCTION("""COMPUTED_VALUE"""),10.0) -> 10 | P37: =IFERROR(__xludf.DUMMYFUNCTION("""COMPUTED_VALUE"""),11.67) -> 11.67 | Q37: =IFERROR(__xludf.DUMMYFUNCTION("""COMPUTED_VALUE"""),13.0) -> 13 | R37: =IFERROR(__xludf.DUMMYFUNCTION("""COMPUTED_VALUE"""),5.83) -> 5.83 | S37: =IFERROR(__xludf.DUMMYFUNCTION("""COMPUTED_VALUE"""),75.79) -> 75.79 | T37: =IFERROR(__xludf.DUMMYFUNCTION("""COMPUTED_VALUE"""),0.0) -> 0 | U37: =IFERROR(__xludf.DUMMYFUNCTION("""COMPUTED_VALUE"""),0.0) -> 0 | V37: =IFERROR(__xludf.DUMMYFUNCTION("""COMPUTED_VALUE"""),13.0) -> 13 | W37: =IFERROR(__xludf.DUMMYFUNCTION("""COMPUTED_VALUE"""),75.79) -> 75.79
A38: =IFERROR(__xludf.DUMMYFUNCTION("""COMPUTED_VALUE"""),"Tiger *12 tomato") -> Tiger *12 tomato | B38: =IF(A38="","",SUMIFS(VMS_Sales!F:F,VMS_Sales!D:D,A38,VMS_Sales!O:O,$L$2)) -> 0 | C38: =IF(A38="","",ROUND(( SUMIFS(VMS_Sales!F:F,VMS_Sales!D:D,A38,VMS_Sales!O:O,$L$1)+ SUMIFS(VMS_Sales!F:F,VMS_Sales!D:D,A38,VMS_Sales!O:O,$L$2)+ SUMIFS(VMS_Sales!F:F,VMS_Sales!D:D,A38,VMS_Sales!O:O,$L$3) )/3,2)) -> 3.67 | D38: =IF(C38="","",ROUND(C38*1.15,0)) -> 4 | E38: =IFERROR(__xludf.DUMMYFUNCTION("IFERROR(XLOOKUP(A38,FILTER(VMS_Sales!$D:$D,VMS_Sales!$O:$O=$L$2),FILTER(VMS_Sales!$L:$L,VMS_Sales!$O:$O=$L$2),""""),"""")"),"") | F38: =IF(OR(D38="",E38=""),"",ROUND(D38*E38,2)) | G38: {=IFERROR( SUMIFS( PurchaseLines_Import!$I:$I, PurchaseLines_Import!$C:$C, XLOOKUP(A38,Map!$A:$A,Map!$B:$B,""), PurchaseLines_Import!$H:$H, $L$1 ), "")} -> 0 | H38: {=IFERROR( SUMIFS( Inventory_Import!$D:$D, Inventory_Import!$B:$B, TEXT(XLOOKUP(A38,Map!$A:$A,Map!$B:$B,""),"0000") ), 0)} -> 0 | I38: =IF(A38="","",MAX(D38-H38,0)) -> 4 | J38: =IF(OR(I38="",E38=""),"",ROUND(I38*E38,2)) | N38: =IFERROR(__xludf.DUMMYFUNCTION("""COMPUTED_VALUE"""),"Yumi zak") -> Yumi zak | O38: =IFERROR(__xludf.DUMMYFUNCTION("""COMPUTED_VALUE"""),7.0) -> 7 | P38: =IFERROR(__xludf.DUMMYFUNCTION("""COMPUTED_VALUE"""),14.0) -> 14 | Q38: =IFERROR(__xludf.DUMMYFUNCTION("""COMPUTED_VALUE"""),16.0) -> 16 | R38: =IFERROR(__xludf.DUMMYFUNCTION("""COMPUTED_VALUE"""),4.5) -> 4.5 | S38: =IFERROR(__xludf.DUMMYFUNCTION("""COMPUTED_VALUE"""),72.0) -> 72 | T38: =IFERROR(__xludf.DUMMYFUNCTION("""COMPUTED_VALUE"""),0.0) -> 0 | U38: =IFERROR(__xludf.DUMMYFUNCTION("""COMPUTED_VALUE"""),0.0) -> 0 | V38: =IFERROR(__xludf.DUMMYFUNCTION("""COMPUTED_VALUE"""),16.0) -> 16 | W38: =IFERROR(__xludf.DUMMYFUNCTION("""COMPUTED_VALUE"""),72.0) -> 72
A39: =IFERROR(__xludf.DUMMYFUNCTION("""COMPUTED_VALUE"""),"Skittles") -> Skittles | B39: =IF(A39="","",SUMIFS(VMS_Sales!F:F,VMS_Sales!D:D,A39,VMS_Sales!O:O,$L$2)) -> 10 | C39: =IF(A39="","",ROUND(( SUMIFS(VMS_Sales!F:F,VMS_Sales!D:D,A39,VMS_Sales!O:O,$L$1)+ SUMIFS(VMS_Sales!F:F,VMS_Sales!D:D,A39,VMS_Sales!O:O,$L$2)+ SUMIFS(VMS_Sales!F:F,VMS_Sales!D:D,A39,VMS_Sales!O:O,$L$3) )/3,2)) -> 11.67 | D39: =IF(C39="","",ROUND(C39*1.15,0)) -> 13 | E39: =IFERROR(__xludf.DUMMYFUNCTION("IFERROR(XLOOKUP(A39,FILTER(VMS_Sales!$D:$D,VMS_Sales!$O:$O=$L$2),FILTER(VMS_Sales!$L:$L,VMS_Sales!$O:$O=$L$2),""""),"""")"),5.83) -> 5.83 | F39: =IF(OR(D39="",E39=""),"",ROUND(D39*E39,2)) -> 75.79 | G39: {=IFERROR( SUMIFS( PurchaseLines_Import!$I:$I, PurchaseLines_Import!$C:$C, XLOOKUP(A39,Map!$A:$A,Map!$B:$B,""), PurchaseLines_Import!$H:$H, $L$1 ), "")} -> 0 | H39: {=IFERROR( SUMIFS( Inventory_Import!$D:$D, Inventory_Import!$B:$B, TEXT(XLOOKUP(A39,Map!$A:$A,Map!$B:$B,""),"0000") ), 0)} -> 0 | I39: =IF(A39="","",MAX(D39-H39,0)) -> 13 | J39: =IF(OR(I39="",E39=""),"",ROUND(I39*E39,2)) -> 75.79 | N39: =IFERROR(__xludf.DUMMYFUNCTION("""COMPUTED_VALUE"""),"Yumi Zak") -> Yumi Zak | O39: =IFERROR(__xludf.DUMMYFUNCTION("""COMPUTED_VALUE"""),7.0) -> 7 | P39: =IFERROR(__xludf.DUMMYFUNCTION("""COMPUTED_VALUE"""),14.0) -> 14 | Q39: =IFERROR(__xludf.DUMMYFUNCTION("""COMPUTED_VALUE"""),16.0) -> 16 | R39: =IFERROR(__xludf.DUMMYFUNCTION("""COMPUTED_VALUE"""),4.5) -> 4.5 | S39: =IFERROR(__xludf.DUMMYFUNCTION("""COMPUTED_VALUE"""),72.0) -> 72 | T39: =IFERROR(__xludf.DUMMYFUNCTION("""COMPUTED_VALUE"""),0.0) -> 0 | U39: =IFERROR(__xludf.DUMMYFUNCTION("""COMPUTED_VALUE"""),0.0) -> 0 | V39: =IFERROR(__xludf.DUMMYFUNCTION("""COMPUTED_VALUE"""),16.0) -> 16 | W39: =IFERROR(__xludf.DUMMYFUNCTION("""COMPUTED_VALUE"""),72.0) -> 72
A40: =IFERROR(__xludf.DUMMYFUNCTION("""COMPUTED_VALUE"""),"kinza") -> kinza | B40: =IF(A40="","",SUMIFS(VMS_Sales!F:F,VMS_Sales!D:D,A40,VMS_Sales!O:O,$L$2)) -> 7 | C40: =IF(A40="","",ROUND(( SUMIFS(VMS_Sales!F:F,VMS_Sales!D:D,A40,VMS_Sales!O:O,$L$1)+ SUMIFS(VMS_Sales!F:F,VMS_Sales!D:D,A40,VMS_Sales!O:O,$L$2)+ SUMIFS(VMS_Sales!F:F,VMS_Sales!D:D,A40,VMS_Sales!O:O,$L$3) )/3,2)) -> 39 | D40: =IF(C40="","",ROUND(C40*1.15,0)) -> 45 | E40: =IFERROR(__xludf.DUMMYFUNCTION("IFERROR(XLOOKUP(A40,FILTER(VMS_Sales!$D:$D,VMS_Sales!$O:$O=$L$2),FILTER(VMS_Sales!$L:$L,VMS_Sales!$O:$O=$L$2),""""),"""")"),1.54) -> 1.54 | F40: =IF(OR(D40="",E40=""),"",ROUND(D40*E40,2)) -> 69.3 | G40: {=IFERROR( SUMIFS( PurchaseLines_Import!$I:$I, PurchaseLines_Import!$C:$C, XLOOKUP(A40,Map!$A:$A,Map!$B:$B,""), PurchaseLines_Import!$H:$H, $L$1 ), "")} -> 0 | H40: {=IFERROR( SUMIFS( Inventory_Import!$D:$D, Inventory_Import!$B:$B, TEXT(XLOOKUP(A40,Map!$A:$A,Map!$B:$B,""),"0000") ), 0)} -> 0 | I40: =IF(A40="","",MAX(D40-H40,0)) -> 45 | J40: =IF(OR(I40="",E40=""),"",ROUND(I40*E40,2)) -> 69.3 | N40: =IFERROR(__xludf.DUMMYFUNCTION("""COMPUTED_VALUE"""),"kinza") -> kinza | O40: =IFERROR(__xludf.DUMMYFUNCTION("""COMPUTED_VALUE"""),7.0) -> 7 | P40: =IFERROR(__xludf.DUMMYFUNCTION("""COMPUTED_VALUE"""),39.0) -> 39 | Q40: =IFERROR(__xludf.DUMMYFUNCTION("""COMPUTED_VALUE"""),45.0) -> 45 | R40: =IFERROR(__xludf.DUMMYFUNCTION("""COMPUTED_VALUE"""),1.54) -> 1.54 | S40: =IFERROR(__xludf.DUMMYFUNCTION("""COMPUTED_VALUE"""),69.3) -> 69.3 | T40: =IFERROR(__xludf.DUMMYFUNCTION("""COMPUTED_VALUE"""),0.0) -> 0 | U40: =IFERROR(__xludf.DUMMYFUNCTION("""COMPUTED_VALUE"""),0.0) -> 0 | V40: =IFERROR(__xludf.DUMMYFUNCTION("""COMPUTED_VALUE"""),45.0) -> 45 | W40: =IFERROR(__xludf.DUMMYFUNCTION("""COMPUTED_VALUE"""),69.3) -> 69.3
A41: =IFERROR(__xludf.DUMMYFUNCTION("""COMPUTED_VALUE"""),"MrCrunch Normal") -> MrCrunch Normal | B41: =IF(A41="","",SUMIFS(VMS_Sales!F:F,VMS_Sales!D:D,A41,VMS_Sales!O:O,$L$2)) -> 0 | C41: =IF(A41="","",ROUND(( SUMIFS(VMS_Sales!F:F,VMS_Sales!D:D,A41,VMS_Sales!O:O,$L$1)+ SUMIFS(VMS_Sales!F:F,VMS_Sales!D:D,A41,VMS_Sales!O:O,$L$2)+ SUMIFS(VMS_Sales!F:F,VMS_Sales!D:D,A41,VMS_Sales!O:O,$L$3) )/3,2)) -> 1.67 | D41: =IF(C41="","",ROUND(C41*1.15,0)) -> 2 | E41: =IFERROR(__xludf.DUMMYFUNCTION("IFERROR(XLOOKUP(A41,FILTER(VMS_Sales!$D:$D,VMS_Sales!$O:$O=$L$2),FILTER(VMS_Sales!$L:$L,VMS_Sales!$O:$O=$L$2),""""),"""")"),"") | F41: =IF(OR(D41="",E41=""),"",ROUND(D41*E41,2)) | G41: {=IFERROR( SUMIFS( PurchaseLines_Import!$I:$I, PurchaseLines_Import!$C:$C, XLOOKUP(A41,Map!$A:$A,Map!$B:$B,""), PurchaseLines_Import!$H:$H, $L$1 ), "")} -> 0 | H41: {=IFERROR( SUMIFS( Inventory_Import!$D:$D, Inventory_Import!$B:$B, TEXT(XLOOKUP(A41,Map!$A:$A,Map!$B:$B,""),"0000") ), 0)} -> 0 | I41: =IF(A41="","",MAX(D41-H41,0)) -> 2 | J41: =IF(OR(I41="",E41=""),"",ROUND(I41*E41,2)) | N41: =IFERROR(__xludf.DUMMYFUNCTION("""COMPUTED_VALUE"""),"Savi stix") -> Savi stix | O41: =IFERROR(__xludf.DUMMYFUNCTION("""COMPUTED_VALUE"""),31.0) -> 31 | P41: =IFERROR(__xludf.DUMMYFUNCTION("""COMPUTED_VALUE"""),16.0) -> 16 | Q41: =IFERROR(__xludf.DUMMYFUNCTION("""COMPUTED_VALUE"""),18.0) -> 18 | R41: =IFERROR(__xludf.DUMMYFUNCTION("""COMPUTED_VALUE"""),3.6) -> 3.6 | S41: =IFERROR(__xludf.DUMMYFUNCTION("""COMPUTED_VALUE"""),64.8) -> 64.8 | T41: =IFERROR(__xludf.DUMMYFUNCTION("""COMPUTED_VALUE"""),0.0) -> 0 | U41: =IFERROR(__xludf.DUMMYFUNCTION("""COMPUTED_VALUE"""),0.0) -> 0 | V41: =IFERROR(__xludf.DUMMYFUNCTION("""COMPUTED_VALUE"""),18.0) -> 18 | W41: =IFERROR(__xludf.DUMMYFUNCTION("""COMPUTED_VALUE"""),64.8) -> 64.8
A42: =IFERROR(__xludf.DUMMYFUNCTION("""COMPUTED_VALUE"""),"Haribo") -> Haribo | B42: =IF(A42="","",SUMIFS(VMS_Sales!F:F,VMS_Sales!D:D,A42,VMS_Sales!O:O,$L$2)) -> 300 | C42: =IF(A42="","",ROUND(( SUMIFS(VMS_Sales!F:F,VMS_Sales!D:D,A42,VMS_Sales!O:O,$L$1)+ SUMIFS(VMS_Sales!F:F,VMS_Sales!D:D,A42,VMS_Sales!O:O,$L$2)+ SUMIFS(VMS_Sales!F:F,VMS_Sales!D:D,A42,VMS_Sales!O:O,$L$3) )/3,2)) -> 163.67 | D42: =IF(C42="","",ROUND(C42*1.15,0)) -> 188 | E42: =IFERROR(__xludf.DUMMYFUNCTION("IFERROR(XLOOKUP(A42,FILTER(VMS_Sales!$D:$D,VMS_Sales!$O:$O=$L$2),FILTER(VMS_Sales!$L:$L,VMS_Sales!$O:$O=$L$2),""""),"""")"),2.04) -> 2.04 | F42: =IF(OR(D42="",E42=""),"",ROUND(D42*E42,2)) -> 383.52 | G42: {=IFERROR( SUMIFS( PurchaseLines_Import!$I:$I, PurchaseLines_Import!$C:$C, XLOOKUP(A42,Map!$A:$A,Map!$B:$B,""), PurchaseLines_Import!$H:$H, $L$1 ), "")} -> 144 | H42: {=IFERROR( SUMIFS( Inventory_Import!$D:$D, Inventory_Import!$B:$B, TEXT(XLOOKUP(A42,Map!$A:$A,Map!$B:$B,""),"0000") ), 0)} -> 21 | I42: =IF(A42="","",MAX(D42-H42,0)) -> 167 | J42: =IF(OR(I42="",E42=""),"",ROUND(I42*E42,2)) -> 340.68 | N42: =IFERROR(__xludf.DUMMYFUNCTION("""COMPUTED_VALUE"""),"Doritos BBQ") -> Doritos BBQ | O42: =IFERROR(__xludf.DUMMYFUNCTION("""COMPUTED_VALUE"""),57.0) -> 57 | P42: =IFERROR(__xludf.DUMMYFUNCTION("""COMPUTED_VALUE"""),19.0) -> 19 | Q42: =IFERROR(__xludf.DUMMYFUNCTION("""COMPUTED_VALUE"""),22.0) -> 22 | R42: =IFERROR(__xludf.DUMMYFUNCTION("""COMPUTED_VALUE"""),2.93) -> 2.93 | S42: =IFERROR(__xludf.DUMMYFUNCTION("""COMPUTED_VALUE"""),64.46) -> 64.46 | T42: =IFERROR(__xludf.DUMMYFUNCTION("""COMPUTED_VALUE"""),0.0) -> 0 | U42: =IFERROR(__xludf.DUMMYFUNCTION("""COMPUTED_VALUE"""),0.0) -> 0 | V42: =IFERROR(__xludf.DUMMYFUNCTION("""COMPUTED_VALUE"""),22.0) -> 22 | W42: =IFERROR(__xludf.DUMMYFUNCTION("""COMPUTED_VALUE"""),64.46) -> 64.46
A43: =IFERROR(__xludf.DUMMYFUNCTION("""COMPUTED_VALUE"""),"7up") -> 7up | B43: =IF(A43="","",SUMIFS(VMS_Sales!F:F,VMS_Sales!D:D,A43,VMS_Sales!O:O,$L$2)) -> 112 | C43: =IF(A43="","",ROUND(( SUMIFS(VMS_Sales!F:F,VMS_Sales!D:D,A43,VMS_Sales!O:O,$L$1)+ SUMIFS(VMS_Sales!F:F,VMS_Sales!D:D,A43,VMS_Sales!O:O,$L$2)+ SUMIFS(VMS_Sales!F:F,VMS_Sales!D:D,A43,VMS_Sales!O:O,$L$3) )/3,2)) -> 44.33 | D43: =IF(C43="","",ROUND(C43*1.15,0)) -> 51 | E43: =IFERROR(__xludf.DUMMYFUNCTION("IFERROR(XLOOKUP(A43,FILTER(VMS_Sales!$D:$D,VMS_Sales!$O:$O=$L$2),FILTER(VMS_Sales!$L:$L,VMS_Sales!$O:$O=$L$2),""""),"""")"),2.25) -> 2.25 | F43: =IF(OR(D43="",E43=""),"",ROUND(D43*E43,2)) -> 114.75 | G43: {=IFERROR( SUMIFS( PurchaseLines_Import!$I:$I, PurchaseLines_Import!$C:$C, XLOOKUP(A43,Map!$A:$A,Map!$B:$B,""), PurchaseLines_Import!$H:$H, $L$1 ), "")} -> 0 | H43: {=IFERROR( SUMIFS( Inventory_Import!$D:$D, Inventory_Import!$B:$B, TEXT(XLOOKUP(A43,Map!$A:$A,Map!$B:$B,""),"0000") ), 0)} -> 0 | I43: =IF(A43="","",MAX(D43-H43,0)) -> 51 | J43: =IF(OR(I43="",E43=""),"",ROUND(I43*E43,2)) -> 114.75 | N43: =IFERROR(__xludf.DUMMYFUNCTION("""COMPUTED_VALUE"""),"Xo Energy") -> Xo Energy | O43: =IFERROR(__xludf.DUMMYFUNCTION("""COMPUTED_VALUE"""),6.0) -> 6 | P43: =IFERROR(__xludf.DUMMYFUNCTION("""COMPUTED_VALUE"""),16.0) -> 16 | Q43: =IFERROR(__xludf.DUMMYFUNCTION("""COMPUTED_VALUE"""),18.0) -> 18 | R43: =IFERROR(__xludf.DUMMYFUNCTION("""COMPUTED_VALUE"""),3.45) -> 3.45 | S43: =IFERROR(__xludf.DUMMYFUNCTION("""COMPUTED_VALUE"""),62.1) -> 62.1 | T43: =IFERROR(__xludf.DUMMYFUNCTION("""COMPUTED_VALUE"""),0.0) -> 0 | U43: =IFERROR(__xludf.DUMMYFUNCTION("""COMPUTED_VALUE"""),0.0) -> 0 | V43: =IFERROR(__xludf.DUMMYFUNCTION("""COMPUTED_VALUE"""),18.0) -> 18 | W43: =IFERROR(__xludf.DUMMYFUNCTION("""COMPUTED_VALUE"""),62.1) -> 62.1
A44: =IFERROR(__xludf.DUMMYFUNCTION("""COMPUTED_VALUE"""),"Mrbeast") -> Mrbeast | B44: =IF(A44="","",SUMIFS(VMS_Sales!F:F,VMS_Sales!D:D,A44,VMS_Sales!O:O,$L$2)) -> 173 | C44: =IF(A44="","",ROUND(( SUMIFS(VMS_Sales!F:F,VMS_Sales!D:D,A44,VMS_Sales!O:O,$L$1)+ SUMIFS(VMS_Sales!F:F,VMS_Sales!D:D,A44,VMS_Sales!O:O,$L$2)+ SUMIFS(VMS_Sales!F:F,VMS_Sales!D:D,A44,VMS_Sales!O:O,$L$3) )/3,2)) -> 108.67 | D44: =IF(C44="","",ROUND(C44*1.15,0)) -> 125 | E44: =IFERROR(__xludf.DUMMYFUNCTION("IFERROR(XLOOKUP(A44,FILTER(VMS_Sales!$D:$D,VMS_Sales!$O:$O=$L$2),FILTER(VMS_Sales!$L:$L,VMS_Sales!$O:$O=$L$2),""""),"""")"),3.0) -> 3 | F44: =IF(OR(D44="",E44=""),"",ROUND(D44*E44,2)) -> 375 | G44: {=IFERROR( SUMIFS( PurchaseLines_Import!$I:$I, PurchaseLines_Import!$C:$C, XLOOKUP(A44,Map!$A:$A,Map!$B:$B,""), PurchaseLines_Import!$H:$H, $L$1 ), "")} -> 100 | H44: {=IFERROR( SUMIFS( Inventory_Import!$D:$D, Inventory_Import!$B:$B, TEXT(XLOOKUP(A44,Map!$A:$A,Map!$B:$B,""),"0000") ), 0)} -> -4 | I44: =IF(A44="","",MAX(D44-H44,0)) -> 129 | J44: =IF(OR(I44="",E44=""),"",ROUND(I44*E44,2)) -> 387 | N44: =IFERROR(__xludf.DUMMYFUNCTION("""COMPUTED_VALUE"""),"Snickers wafer roll") -> Snickers wafer roll | O44: =IFERROR(__xludf.DUMMYFUNCTION("""COMPUTED_VALUE"""),138.0) -> 138 | P44: =IFERROR(__xludf.DUMMYFUNCTION("""COMPUTED_VALUE"""),46.0) -> 46 | Q44: =IFERROR(__xludf.DUMMYFUNCTION("""COMPUTED_VALUE"""),53.0) -> 53 | R44: =IFERROR(__xludf.DUMMYFUNCTION("""COMPUTED_VALUE"""),1.12) -> 1.12 | S44: =IFERROR(__xludf.DUMMYFUNCTION("""COMPUTED_VALUE"""),59.36) -> 59.36 | T44: =IFERROR(__xludf.DUMMYFUNCTION("""COMPUTED_VALUE"""),336.0) -> 336 | U44: =IFERROR(__xludf.DUMMYFUNCTION("""COMPUTED_VALUE"""),-2.0) -> -2 | V44: =IFERROR(__xludf.DUMMYFUNCTION("""COMPUTED_VALUE"""),55.0) -> 55 | W44: =IFERROR(__xludf.DUMMYFUNCTION("""COMPUTED_VALUE"""),61.6) -> 61.6
A45: =IFERROR(__xludf.DUMMYFUNCTION("""COMPUTED_VALUE"""),"Tiger *12 Cheese") -> Tiger *12 Cheese | B45: =IF(A45="","",SUMIFS(VMS_Sales!F:F,VMS_Sales!D:D,A45,VMS_Sales!O:O,$L$2)) -> 9 | C45: =IF(A45="","",ROUND(( SUMIFS(VMS_Sales!F:F,VMS_Sales!D:D,A45,VMS_Sales!O:O,$L$1)+ SUMIFS(VMS_Sales!F:F,VMS_Sales!D:D,A45,VMS_Sales!O:O,$L$2)+ SUMIFS(VMS_Sales!F:F,VMS_Sales!D:D,A45,VMS_Sales!O:O,$L$3) )/3,2)) -> 6 | D45: =IF(C45="","",ROUND(C45*1.15,0)) -> 7 | E45: =IFERROR(__xludf.DUMMYFUNCTION("IFERROR(XLOOKUP(A45,FILTER(VMS_Sales!$D:$D,VMS_Sales!$O:$O=$L$2),FILTER(VMS_Sales!$L:$L,VMS_Sales!$O:$O=$L$2),""""),"""")"),3.5) -> 3.5 | F45: =IF(OR(D45="",E45=""),"",ROUND(D45*E45,2)) -> 24.5 | G45: {=IFERROR( SUMIFS( PurchaseLines_Import!$I:$I, PurchaseLines_Import!$C:$C, XLOOKUP(A45,Map!$A:$A,Map!$B:$B,""), PurchaseLines_Import!$H:$H, $L$1 ), "")} -> 0 | H45: {=IFERROR( SUMIFS( Inventory_Import!$D:$D, Inventory_Import!$B:$B, TEXT(XLOOKUP(A45,Map!$A:$A,Map!$B:$B,""),"0000") ), 0)} -> 0 | I45: =IF(A45="","",MAX(D45-H45,0)) -> 7 | J45: =IF(OR(I45="",E45=""),"",ROUND(I45*E45,2)) -> 24.5 | N45: =IFERROR(__xludf.DUMMYFUNCTION("""COMPUTED_VALUE"""),"Mr Cruch veggy's") -> Mr Cruch veggy's | O45: =IFERROR(__xludf.DUMMYFUNCTION("""COMPUTED_VALUE"""),32.0) -> 32 | P45: =IFERROR(__xludf.DUMMYFUNCTION("""COMPUTED_VALUE"""),21.67) -> 21.67 | Q45: =IFERROR(__xludf.DUMMYFUNCTION("""COMPUTED_VALUE"""),25.0) -> 25 | R45: =IFERROR(__xludf.DUMMYFUNCTION("""COMPUTED_VALUE"""),2.44) -> 2.44 | S45: =IFERROR(__xludf.DUMMYFUNCTION("""COMPUTED_VALUE"""),61.0) -> 61 | T45: =IFERROR(__xludf.DUMMYFUNCTION("""COMPUTED_VALUE"""),0.0) -> 0 | U45: =IFERROR(__xludf.DUMMYFUNCTION("""COMPUTED_VALUE"""),0.0) -> 0 | V45: =IFERROR(__xludf.DUMMYFUNCTION("""COMPUTED_VALUE"""),25.0) -> 25 | W45: =IFERROR(__xludf.DUMMYFUNCTION("""COMPUTED_VALUE"""),61.0) -> 61
A46: =IFERROR(__xludf.DUMMYFUNCTION("""COMPUTED_VALUE"""),"Tiger *12 kebab") -> Tiger *12 kebab | B46: =IF(A46="","",SUMIFS(VMS_Sales!F:F,VMS_Sales!D:D,A46,VMS_Sales!O:O,$L$2)) -> 0 | C46: =IF(A46="","",ROUND(( SUMIFS(VMS_Sales!F:F,VMS_Sales!D:D,A46,VMS_Sales!O:O,$L$1)+ SUMIFS(VMS_Sales!F:F,VMS_Sales!D:D,A46,VMS_Sales!O:O,$L$2)+ SUMIFS(VMS_Sales!F:F,VMS_Sales!D:D,A46,VMS_Sales!O:O,$L$3) )/3,2)) -> 2.33 | D46: =IF(C46="","",ROUND(C46*1.15,0)) -> 3 | E46: =IFERROR(__xludf.DUMMYFUNCTION("IFERROR(XLOOKUP(A46,FILTER(VMS_Sales!$D:$D,VMS_Sales!$O:$O=$L$2),FILTER(VMS_Sales!$L:$L,VMS_Sales!$O:$O=$L$2),""""),"""")"),"") | F46: =IF(OR(D46="",E46=""),"",ROUND(D46*E46,2)) | G46: {=IFERROR( SUMIFS( PurchaseLines_Import!$I:$I, PurchaseLines_Import!$C:$C, XLOOKUP(A46,Map!$A:$A,Map!$B:$B,""), PurchaseLines_Import!$H:$H, $L$1 ), "")} -> 0 | H46: {=IFERROR( SUMIFS( Inventory_Import!$D:$D, Inventory_Import!$B:$B, TEXT(XLOOKUP(A46,Map!$A:$A,Map!$B:$B,""),"0000") ), 0)} -> 0 | I46: =IF(A46="","",MAX(D46-H46,0)) -> 3 | J46: =IF(OR(I46="",E46=""),"",ROUND(I46*E46,2)) | N46: =IFERROR(__xludf.DUMMYFUNCTION("""COMPUTED_VALUE"""),"Bounty wafer roll") -> Bounty wafer roll | O46: =IFERROR(__xludf.DUMMYFUNCTION("""COMPUTED_VALUE"""),126.0) -> 126 | P46: =IFERROR(__xludf.DUMMYFUNCTION("""COMPUTED_VALUE"""),42.0) -> 42 | Q46: =IFERROR(__xludf.DUMMYFUNCTION("""COMPUTED_VALUE"""),48.0) -> 48 | R46: =IFERROR(__xludf.DUMMYFUNCTION("""COMPUTED_VALUE"""),1.08) -> 1.08 | S46: =IFERROR(__xludf.DUMMYFUNCTION("""COMPUTED_VALUE"""),51.84) -> 51.84 | T46: =IFERROR(__xludf.DUMMYFUNCTION("""COMPUTED_VALUE"""),0.0) -> 0 | U46: =IFERROR(__xludf.DUMMYFUNCTION("""COMPUTED_VALUE"""),0.0) -> 0 | V46: =IFERROR(__xludf.DUMMYFUNCTION("""COMPUTED_VALUE"""),48.0) -> 48 | W46: =IFERROR(__xludf.DUMMYFUNCTION("""COMPUTED_VALUE"""),51.84) -> 51.84
A47: =IFERROR(__xludf.DUMMYFUNCTION("""COMPUTED_VALUE"""),"Tiger 12 chili and lemon") -> Tiger 12 chili and lemon | B47: =IF(A47="","",SUMIFS(VMS_Sales!F:F,VMS_Sales!D:D,A47,VMS_Sales!O:O,$L$2)) -> 4 | C47: =IF(A47="","",ROUND(( SUMIFS(VMS_Sales!F:F,VMS_Sales!D:D,A47,VMS_Sales!O:O,$L$1)+ SUMIFS(VMS_Sales!F:F,VMS_Sales!D:D,A47,VMS_Sales!O:O,$L$2)+ SUMIFS(VMS_Sales!F:F,VMS_Sales!D:D,A47,VMS_Sales!O:O,$L$3) )/3,2)) -> 6.33 | D47: =IF(C47="","",ROUND(C47*1.15,0)) -> 7 | E47: =IFERROR(__xludf.DUMMYFUNCTION("IFERROR(XLOOKUP(A47,FILTER(VMS_Sales!$D:$D,VMS_Sales!$O:$O=$L$2),FILTER(VMS_Sales!$L:$L,VMS_Sales!$O:$O=$L$2),""""),"""")"),3.5) -> 3.5 | F47: =IF(OR(D47="",E47=""),"",ROUND(D47*E47,2)) -> 24.5 | G47: {=IFERROR( SUMIFS( PurchaseLines_Import!$I:$I, PurchaseLines_Import!$C:$C, XLOOKUP(A47,Map!$A:$A,Map!$B:$B,""), PurchaseLines_Import!$H:$H, $L$1 ), "")} -> 0 | H47: {=IFERROR( SUMIFS( Inventory_Import!$D:$D, Inventory_Import!$B:$B, TEXT(XLOOKUP(A47,Map!$A:$A,Map!$B:$B,""),"0000") ), 0)} -> 0 | I47: =IF(A47="","",MAX(D47-H47,0)) -> 7 | J47: =IF(OR(I47="",E47=""),"",ROUND(I47*E47,2)) -> 24.5 | N47: =IFERROR(__xludf.DUMMYFUNCTION("""COMPUTED_VALUE"""),"Haribo 80g") -> Haribo 80g | O47: =IFERROR(__xludf.DUMMYFUNCTION("""COMPUTED_VALUE"""),12.0) -> 12 | P47: =IFERROR(__xludf.DUMMYFUNCTION("""COMPUTED_VALUE"""),5.33) -> 5.33 | Q47: =IFERROR(__xludf.DUMMYFUNCTION("""COMPUTED_VALUE"""),6.0) -> 6 | R47: =IFERROR(__xludf.DUMMYFUNCTION("""COMPUTED_VALUE"""),7.2) -> 7.2 | S47: =IFERROR(__xludf.DUMMYFUNCTION("""COMPUTED_VALUE"""),43.2) -> 43.2 | T47: =IFERROR(__xludf.DUMMYFUNCTION("""COMPUTED_VALUE"""),0.0) -> 0 | U47: =IFERROR(__xludf.DUMMYFUNCTION("""COMPUTED_VALUE"""),0.0) -> 0 | V47: =IFERROR(__xludf.DUMMYFUNCTION("""COMPUTED_VALUE"""),6.0) -> 6 | W47: =IFERROR(__xludf.DUMMYFUNCTION("""COMPUTED_VALUE"""),43.2) -> 43.2
A48: =IFERROR(__xludf.DUMMYFUNCTION("""COMPUTED_VALUE"""),"Tiger 12 sweet chili") -> Tiger 12 sweet chili | B48: =IF(A48="","",SUMIFS(VMS_Sales!F:F,VMS_Sales!D:D,A48,VMS_Sales!O:O,$L$2)) -> 0 | C48: =IF(A48="","",ROUND(( SUMIFS(VMS_Sales!F:F,VMS_Sales!D:D,A48,VMS_Sales!O:O,$L$1)+ SUMIFS(VMS_Sales!F:F,VMS_Sales!D:D,A48,VMS_Sales!O:O,$L$2)+ SUMIFS(VMS_Sales!F:F,VMS_Sales!D:D,A48,VMS_Sales!O:O,$L$3) )/3,2)) -> 3 | D48: =IF(C48="","",ROUND(C48*1.15,0)) -> 3 | E48: =IFERROR(__xludf.DUMMYFUNCTION("IFERROR(XLOOKUP(A48,FILTER(VMS_Sales!$D:$D,VMS_Sales!$O:$O=$L$2),FILTER(VMS_Sales!$L:$L,VMS_Sales!$O:$O=$L$2),""""),"""")"),"") | F48: =IF(OR(D48="",E48=""),"",ROUND(D48*E48,2)) | G48: {=IFERROR( SUMIFS( PurchaseLines_Import!$I:$I, PurchaseLines_Import!$C:$C, XLOOKUP(A48,Map!$A:$A,Map!$B:$B,""), PurchaseLines_Import!$H:$H, $L$1 ), "")} -> 0 | H48: {=IFERROR( SUMIFS( Inventory_Import!$D:$D, Inventory_Import!$B:$B, TEXT(XLOOKUP(A48,Map!$A:$A,Map!$B:$B,""),"0000") ), 0)} -> 0 | I48: =IF(A48="","",MAX(D48-H48,0)) -> 3 | J48: =IF(OR(I48="",E48=""),"",ROUND(I48*E48,2)) | N48: =IFERROR(__xludf.DUMMYFUNCTION("""COMPUTED_VALUE"""),"Yupi") -> Yupi | O48: =IFERROR(__xludf.DUMMYFUNCTION("""COMPUTED_VALUE"""),38.0) -> 38 | P48: =IFERROR(__xludf.DUMMYFUNCTION("""COMPUTED_VALUE"""),20.67) -> 20.67 | Q48: =IFERROR(__xludf.DUMMYFUNCTION("""COMPUTED_VALUE"""),24.0) -> 24 | R48: =IFERROR(__xludf.DUMMYFUNCTION("""COMPUTED_VALUE"""),1.79) -> 1.79 | S48: =IFERROR(__xludf.DUMMYFUNCTION("""COMPUTED_VALUE"""),42.96) -> 42.96 | T48: =IFERROR(__xludf.DUMMYFUNCTION("""COMPUTED_VALUE"""),0.0) -> 0 | U48: =IFERROR(__xludf.DUMMYFUNCTION("""COMPUTED_VALUE"""),0.0) -> 0 | V48: =IFERROR(__xludf.DUMMYFUNCTION("""COMPUTED_VALUE"""),24.0) -> 24 | W48: =IFERROR(__xludf.DUMMYFUNCTION("""COMPUTED_VALUE"""),42.96) -> 42.96
A49: =IFERROR(__xludf.DUMMYFUNCTION("""COMPUTED_VALUE"""),"Mr Cruch veggy's") -> Mr Cruch veggy's | B49: =IF(A49="","",SUMIFS(VMS_Sales!F:F,VMS_Sales!D:D,A49,VMS_Sales!O:O,$L$2)) -> 32 | C49: =IF(A49="","",ROUND(( SUMIFS(VMS_Sales!F:F,VMS_Sales!D:D,A49,VMS_Sales!O:O,$L$1)+ SUMIFS(VMS_Sales!F:F,VMS_Sales!D:D,A49,VMS_Sales!O:O,$L$2)+ SUMIFS(VMS_Sales!F:F,VMS_Sales!D:D,A49,VMS_Sales!O:O,$L$3) )/3,2)) -> 21.67 | D49: =IF(C49="","",ROUND(C49*1.15,0)) -> 25 | E49: =IFERROR(__xludf.DUMMYFUNCTION("IFERROR(XLOOKUP(A49,FILTER(VMS_Sales!$D:$D,VMS_Sales!$O:$O=$L$2),FILTER(VMS_Sales!$L:$L,VMS_Sales!$O:$O=$L$2),""""),"""")"),2.44) -> 2.44 | F49: =IF(OR(D49="",E49=""),"",ROUND(D49*E49,2)) -> 61 | G49: {=IFERROR( SUMIFS( PurchaseLines_Import!$I:$I, PurchaseLines_Import!$C:$C, XLOOKUP(A49,Map!$A:$A,Map!$B:$B,""), PurchaseLines_Import!$H:$H, $L$1 ), "")} -> 0 | H49: {=IFERROR( SUMIFS( Inventory_Import!$D:$D, Inventory_Import!$B:$B, TEXT(XLOOKUP(A49,Map!$A:$A,Map!$B:$B,""),"0000") ), 0)} -> 0 | I49: =IF(A49="","",MAX(D49-H49,0)) -> 25 | J49: =IF(OR(I49="",E49=""),"",ROUND(I49*E49,2)) -> 61 | N49: =IFERROR(__xludf.DUMMYFUNCTION("""COMPUTED_VALUE"""),"Dallas juice") -> Dallas juice | O49: =IFERROR(__xludf.DUMMYFUNCTION("""COMPUTED_VALUE"""),41.0) -> 41 | P49: =IFERROR(__xludf.DUMMYFUNCTION("""COMPUTED_VALUE"""),41.0) -> 41 | Q49: =IFERROR(__xludf.DUMMYFUNCTION("""COMPUTED_VALUE"""),47.0) -> 47 | R49: =IFERROR(__xludf.DUMMYFUNCTION("""COMPUTED_VALUE"""),0.91) -> 0.91 | S49: =IFERROR(__xludf.DUMMYFUNCTION("""COMPUTED_VALUE"""),42.77) -> 42.77 | T49: =IFERROR(__xludf.DUMMYFUNCTION("""COMPUTED_VALUE"""),0.0) -> 0 | U49: =IFERROR(__xludf.DUMMYFUNCTION("""COMPUTED_VALUE"""),0.0) -> 0 | V49: =IFERROR(__xludf.DUMMYFUNCTION("""COMPUTED_VALUE"""),47.0) -> 47 | W49: =IFERROR(__xludf.DUMMYFUNCTION("""COMPUTED_VALUE"""),42.77) -> 42.77
A50: =IFERROR(__xludf.DUMMYFUNCTION("""COMPUTED_VALUE"""),"Buldak") -> Buldak | B50: =IF(A50="","",SUMIFS(VMS_Sales!F:F,VMS_Sales!D:D,A50,VMS_Sales!O:O,$L$2)) -> 0 | C50: =IF(A50="","",ROUND(( SUMIFS(VMS_Sales!F:F,VMS_Sales!D:D,A50,VMS_Sales!O:O,$L$1)+ SUMIFS(VMS_Sales!F:F,VMS_Sales!D:D,A50,VMS_Sales!O:O,$L$2)+ SUMIFS(VMS_Sales!F:F,VMS_Sales!D:D,A50,VMS_Sales!O:O,$L$3) )/3,2)) -> 1.67 | D50: =IF(C50="","",ROUND(C50*1.15,0)) -> 2 | E50: =IFERROR(__xludf.DUMMYFUNCTION("IFERROR(XLOOKUP(A50,FILTER(VMS_Sales!$D:$D,VMS_Sales!$O:$O=$L$2),FILTER(VMS_Sales!$L:$L,VMS_Sales!$O:$O=$L$2),""""),"""")"),"") | F50: =IF(OR(D50="",E50=""),"",ROUND(D50*E50,2)) | G50: {=IFERROR( SUMIFS( PurchaseLines_Import!$I:$I, PurchaseLines_Import!$C:$C, XLOOKUP(A50,Map!$A:$A,Map!$B:$B,""), PurchaseLines_Import!$H:$H, $L$1 ), "")} -> 0 | H50: {=IFERROR( SUMIFS( Inventory_Import!$D:$D, Inventory_Import!$B:$B, TEXT(XLOOKUP(A50,Map!$A:$A,Map!$B:$B,""),"0000") ), 0)} -> 0 | I50: =IF(A50="","",MAX(D50-H50,0)) -> 2 | J50: =IF(OR(I50="",E50=""),"",ROUND(I50*E50,2)) | N50: =IFERROR(__xludf.DUMMYFUNCTION("""COMPUTED_VALUE"""),"Twix wafer roll") -> Twix wafer roll | O50: =IFERROR(__xludf.DUMMYFUNCTION("""COMPUTED_VALUE"""),189.0) -> 189 | P50: =IFERROR(__xludf.DUMMYFUNCTION("""COMPUTED_VALUE"""),63.0) -> 63 | Q50: =IFERROR(__xludf.DUMMYFUNCTION("""COMPUTED_VALUE"""),72.0) -> 72 | R50: =IFERROR(__xludf.DUMMYFUNCTION("""COMPUTED_VALUE"""),1.08) -> 1.08 | S50: =IFERROR(__xludf.DUMMYFUNCTION("""COMPUTED_VALUE"""),77.76) -> 77.76 | T50: =IFERROR(__xludf.DUMMYFUNCTION("""COMPUTED_VALUE"""),240.0) -> 240 | U50: =IFERROR(__xludf.DUMMYFUNCTION("""COMPUTED_VALUE"""),34.0) -> 34 | V50: =IFERROR(__xludf.DUMMYFUNCTION("""COMPUTED_VALUE"""),38.0) -> 38 | W50: =IFERROR(__xludf.DUMMYFUNCTION("""COMPUTED_VALUE"""),41.04) -> 41.04
A51: =IFERROR(__xludf.DUMMYFUNCTION("""COMPUTED_VALUE"""),"Tiger *16 kebab") -> Tiger *16 kebab | B51: =IF(A51="","",SUMIFS(VMS_Sales!F:F,VMS_Sales!D:D,A51,VMS_Sales!O:O,$L$2)) -> 0 | C51: =IF(A51="","",ROUND(( SUMIFS(VMS_Sales!F:F,VMS_Sales!D:D,A51,VMS_Sales!O:O,$L$1)+ SUMIFS(VMS_Sales!F:F,VMS_Sales!D:D,A51,VMS_Sales!O:O,$L$2)+ SUMIFS(VMS_Sales!F:F,VMS_Sales!D:D,A51,VMS_Sales!O:O,$L$3) )/3,2)) -> 0.67 | D51: =IF(C51="","",ROUND(C51*1.15,0)) -> 1 | E51: =IFERROR(__xludf.DUMMYFUNCTION("IFERROR(XLOOKUP(A51,FILTER(VMS_Sales!$D:$D,VMS_Sales!$O:$O=$L$2),FILTER(VMS_Sales!$L:$L,VMS_Sales!$O:$O=$L$2),""""),"""")"),"") | F51: =IF(OR(D51="",E51=""),"",ROUND(D51*E51,2)) | G51: {=IFERROR( SUMIFS( PurchaseLines_Import!$I:$I, PurchaseLines_Import!$C:$C, XLOOKUP(A51,Map!$A:$A,Map!$B:$B,""), PurchaseLines_Import!$H:$H, $L$1 ), "")} -> 0 | H51: {=IFERROR( SUMIFS( Inventory_Import!$D:$D, Inventory_Import!$B:$B, TEXT(XLOOKUP(A51,Map!$A:$A,Map!$B:$B,""),"0000") ), 0)} -> 0 | I51: =IF(A51="","",MAX(D51-H51,0)) -> 1 | J51: =IF(OR(I51="",E51=""),"",ROUND(I51*E51,2)) | N51: =IFERROR(__xludf.DUMMYFUNCTION("""COMPUTED_VALUE"""),"BeBeto marshmello") -> BeBeto marshmello | O51: =IFERROR(__xludf.DUMMYFUNCTION("""COMPUTED_VALUE"""),51.0) -> 51 | P51: =IFERROR(__xludf.DUMMYFUNCTION("""COMPUTED_VALUE"""),17.0) -> 17 | Q51: =IFERROR(__xludf.DUMMYFUNCTION("""COMPUTED_VALUE"""),20.0) -> 20 | R51: =IFERROR(__xludf.DUMMYFUNCTION("""COMPUTED_VALUE"""),1.91) -> 1.91 | S51: =IFERROR(__xludf.DUMMYFUNCTION("""COMPUTED_VALUE"""),38.2) -> 38.2 | T51: =IFERROR(__xludf.DUMMYFUNCTION("""COMPUTED_VALUE"""),0.0) -> 0 | U51: =IFERROR(__xludf.DUMMYFUNCTION("""COMPUTED_VALUE"""),0.0) -> 0 | V51: =IFERROR(__xludf.DUMMYFUNCTION("""COMPUTED_VALUE"""),20.0) -> 20 | W51: =IFERROR(__xludf.DUMMYFUNCTION("""COMPUTED_VALUE"""),38.2) -> 38.2
A52: =IFERROR(__xludf.DUMMYFUNCTION("""COMPUTED_VALUE"""),"Haribo bears") -> Haribo bears | B52: =IF(A52="","",SUMIFS(VMS_Sales!F:F,VMS_Sales!D:D,A52,VMS_Sales!O:O,$L$2)) -> 5 | C52: =IF(A52="","",ROUND(( SUMIFS(VMS_Sales!F:F,VMS_Sales!D:D,A52,VMS_Sales!O:O,$L$1)+ SUMIFS(VMS_Sales!F:F,VMS_Sales!D:D,A52,VMS_Sales!O:O,$L$2)+ SUMIFS(VMS_Sales!F:F,VMS_Sales!D:D,A52,VMS_Sales!O:O,$L$3) )/3,2)) -> 20.67 | D52: =IF(C52="","",ROUND(C52*1.15,0)) -> 24 | E52: =IFERROR(__xludf.DUMMYFUNCTION("IFERROR(XLOOKUP(A52,FILTER(VMS_Sales!$D:$D,VMS_Sales!$O:$O=$L$2),FILTER(VMS_Sales!$L:$L,VMS_Sales!$O:$O=$L$2),""""),"""")"),1.37) -> 1.37 | F52: =IF(OR(D52="",E52=""),"",ROUND(D52*E52,2)) -> 32.88 | G52: {=IFERROR( SUMIFS( PurchaseLines_Import!$I:$I, PurchaseLines_Import!$C:$C, XLOOKUP(A52,Map!$A:$A,Map!$B:$B,""), PurchaseLines_Import!$H:$H, $L$1 ), "")} -> 0 | H52: {=IFERROR( SUMIFS( Inventory_Import!$D:$D, Inventory_Import!$B:$B, TEXT(XLOOKUP(A52,Map!$A:$A,Map!$B:$B,""),"0000") ), 0)} -> 0 | I52: =IF(A52="","",MAX(D52-H52,0)) -> 24 | J52: =IF(OR(I52="",E52=""),"",ROUND(I52*E52,2)) -> 32.88 | N52: =IFERROR(__xludf.DUMMYFUNCTION("""COMPUTED_VALUE"""),"Barbican") -> Barbican | O52: =IFERROR(__xludf.DUMMYFUNCTION("""COMPUTED_VALUE"""),15.0) -> 15 | P52: =IFERROR(__xludf.DUMMYFUNCTION("""COMPUTED_VALUE"""),10.67) -> 10.67 | Q52: =IFERROR(__xludf.DUMMYFUNCTION("""COMPUTED_VALUE"""),12.0) -> 12 | R52: =IFERROR(__xludf.DUMMYFUNCTION("""COMPUTED_VALUE"""),3.17) -> 3.17 | S52: =IFERROR(__xludf.DUMMYFUNCTION("""COMPUTED_VALUE"""),38.04) -> 38.04 | T52: =IFERROR(__xludf.DUMMYFUNCTION("""COMPUTED_VALUE"""),0.0) -> 0 | U52: =IFERROR(__xludf.DUMMYFUNCTION("""COMPUTED_VALUE"""),0.0) -> 0 | V52: =IFERROR(__xludf.DUMMYFUNCTION("""COMPUTED_VALUE"""),12.0) -> 12 | W52: =IFERROR(__xludf.DUMMYFUNCTION("""COMPUTED_VALUE"""),38.04) -> 38.04
A53: =IFERROR(__xludf.DUMMYFUNCTION("""COMPUTED_VALUE"""),"Turbo strips") -> Turbo strips | B53: =IF(A53="","",SUMIFS(VMS_Sales!F:F,VMS_Sales!D:D,A53,VMS_Sales!O:O,$L$2)) -> 120 | C53: =IF(A53="","",ROUND(( SUMIFS(VMS_Sales!F:F,VMS_Sales!D:D,A53,VMS_Sales!O:O,$L$1)+ SUMIFS(VMS_Sales!F:F,VMS_Sales!D:D,A53,VMS_Sales!O:O,$L$2)+ SUMIFS(VMS_Sales!F:F,VMS_Sales!D:D,A53,VMS_Sales!O:O,$L$3) )/3,2)) -> 121 | D53: =IF(C53="","",ROUND(C53*1.15,0)) -> 139 | E53: =IFERROR(__xludf.DUMMYFUNCTION("IFERROR(XLOOKUP(A53,FILTER(VMS_Sales!$D:$D,VMS_Sales!$O:$O=$L$2),FILTER(VMS_Sales!$L:$L,VMS_Sales!$O:$O=$L$2),""""),"""")"),4.08) -> 4.08 | F53: =IF(OR(D53="",E53=""),"",ROUND(D53*E53,2)) -> 567.12 | G53: {=IFERROR( SUMIFS( PurchaseLines_Import!$I:$I, PurchaseLines_Import!$C:$C, XLOOKUP(A53,Map!$A:$A,Map!$B:$B,""), PurchaseLines_Import!$H:$H, $L$1 ), "")} -> 138 | H53: {=IFERROR( SUMIFS( Inventory_Import!$D:$D, Inventory_Import!$B:$B, TEXT(XLOOKUP(A53,Map!$A:$A,Map!$B:$B,""),"0000") ), 0)} -> 0 | I53: =IF(A53="","",MAX(D53-H53,0)) -> 139 | J53: =IF(OR(I53="",E53=""),"",ROUND(I53*E53,2)) -> 567.12 | N53: =IFERROR(__xludf.DUMMYFUNCTION("""COMPUTED_VALUE"""),"Kunuz Juice") -> Kunuz Juice | O53: =IFERROR(__xludf.DUMMYFUNCTION("""COMPUTED_VALUE"""),13.0) -> 13 | P53: =IFERROR(__xludf.DUMMYFUNCTION("""COMPUTED_VALUE"""),18.33) -> 18.33 | Q53: =IFERROR(__xludf.DUMMYFUNCTION("""COMPUTED_VALUE"""),21.0) -> 21 | R53: =IFERROR(__xludf.DUMMYFUNCTION("""COMPUTED_VALUE"""),1.6) -> 1.6 | S53: =IFERROR(__xludf.DUMMYFUNCTION("""COMPUTED_VALUE"""),33.6) -> 33.6 | T53: =IFERROR(__xludf.DUMMYFUNCTION("""COMPUTED_VALUE"""),0.0) -> 0 | U53: =IFERROR(__xludf.DUMMYFUNCTION("""COMPUTED_VALUE"""),0.0) -> 0 | V53: =IFERROR(__xludf.DUMMYFUNCTION("""COMPUTED_VALUE"""),21.0) -> 21 | W53: =IFERROR(__xludf.DUMMYFUNCTION("""COMPUTED_VALUE"""),33.6) -> 33.6
A54: =IFERROR(__xludf.DUMMYFUNCTION("""COMPUTED_VALUE"""),"Chotso") -> Chotso | B54: =IF(A54="","",SUMIFS(VMS_Sales!F:F,VMS_Sales!D:D,A54,VMS_Sales!O:O,$L$2)) -> 0 | C54: =IF(A54="","",ROUND(( SUMIFS(VMS_Sales!F:F,VMS_Sales!D:D,A54,VMS_Sales!O:O,$L$1)+ SUMIFS(VMS_Sales!F:F,VMS_Sales!D:D,A54,VMS_Sales!O:O,$L$2)+ SUMIFS(VMS_Sales!F:F,VMS_Sales!D:D,A54,VMS_Sales!O:O,$L$3) )/3,2)) -> 0.33 | D54: =IF(C54="","",ROUND(C54*1.15,0)) -> 0 | E54: =IFERROR(__xludf.DUMMYFUNCTION("IFERROR(XLOOKUP(A54,FILTER(VMS_Sales!$D:$D,VMS_Sales!$O:$O=$L$2),FILTER(VMS_Sales!$L:$L,VMS_Sales!$O:$O=$L$2),""""),"""")"),"") | F54: =IF(OR(D54="",E54=""),"",ROUND(D54*E54,2)) | G54: {=IFERROR( SUMIFS( PurchaseLines_Import!$I:$I, PurchaseLines_Import!$C:$C, XLOOKUP(A54,Map!$A:$A,Map!$B:$B,""), PurchaseLines_Import!$H:$H, $L$1 ), "")} -> 0 | H54: {=IFERROR( SUMIFS( Inventory_Import!$D:$D, Inventory_Import!$B:$B, TEXT(XLOOKUP(A54,Map!$A:$A,Map!$B:$B,""),"0000") ), 0)} -> 0 | I54: =IF(A54="","",MAX(D54-H54,0)) -> 0 | J54: =IF(OR(I54="",E54=""),"",ROUND(I54*E54,2)) | N54: =IFERROR(__xludf.DUMMYFUNCTION("""COMPUTED_VALUE"""),"Haribo bears") -> Haribo bears | O54: =IFERROR(__xludf.DUMMYFUNCTION("""COMPUTED_VALUE"""),5.0) -> 5 | P54: =IFERROR(__xludf.DUMMYFUNCTION("""COMPUTED_VALUE"""),20.67) -> 20.67 | Q54: =IFERROR(__xludf.DUMMYFUNCTION("""COMPUTED_VALUE"""),24.0) -> 24 | R54: =IFERROR(__xludf.DUMMYFUNCTION("""COMPUTED_VALUE"""),1.37) -> 1.37 | S54: =IFERROR(__xludf.DUMMYFUNCTION("""COMPUTED_VALUE"""),32.88) -> 32.88 | T54: =IFERROR(__xludf.DUMMYFUNCTION("""COMPUTED_VALUE"""),0.0) -> 0 | U54: =IFERROR(__xludf.DUMMYFUNCTION("""COMPUTED_VALUE"""),0.0) -> 0 | V54: =IFERROR(__xludf.DUMMYFUNCTION("""COMPUTED_VALUE"""),24.0) -> 24 | W54: =IFERROR(__xludf.DUMMYFUNCTION("""COMPUTED_VALUE"""),32.88) -> 32.88
A55: =IFERROR(__xludf.DUMMYFUNCTION("""COMPUTED_VALUE"""),"Coach Suntop") -> Coach Suntop | B55: =IF(A55="","",SUMIFS(VMS_Sales!F:F,VMS_Sales!D:D,A55,VMS_Sales!O:O,$L$2)) -> 412 | C55: =IF(A55="","",ROUND(( SUMIFS(VMS_Sales!F:F,VMS_Sales!D:D,A55,VMS_Sales!O:O,$L$1)+ SUMIFS(VMS_Sales!F:F,VMS_Sales!D:D,A55,VMS_Sales!O:O,$L$2)+ SUMIFS(VMS_Sales!F:F,VMS_Sales!D:D,A55,VMS_Sales!O:O,$L$3) )/3,2)) -> 234.67 | D55: =IF(C55="","",ROUND(C55*1.15,0)) -> 270 | E55: =IFERROR(__xludf.DUMMYFUNCTION("IFERROR(XLOOKUP(A55,FILTER(VMS_Sales!$D:$D,VMS_Sales!$O:$O=$L$2),FILTER(VMS_Sales!$L:$L,VMS_Sales!$O:$O=$L$2),""""),"""")"),0.45) -> 0.45 | F55: =IF(OR(D55="",E55=""),"",ROUND(D55*E55,2)) -> 121.5 | G55: {=IFERROR( SUMIFS( PurchaseLines_Import!$I:$I, PurchaseLines_Import!$C:$C, XLOOKUP(A55,Map!$A:$A,Map!$B:$B,""), PurchaseLines_Import!$H:$H, $L$1 ), "")} -> 0 | H55: {=IFERROR( SUMIFS( Inventory_Import!$D:$D, Inventory_Import!$B:$B, TEXT(XLOOKUP(A55,Map!$A:$A,Map!$B:$B,""),"0000") ), 0)} -> -1 | I55: =IF(A55="","",MAX(D55-H55,0)) -> 271 | J55: =IF(OR(I55="",E55=""),"",ROUND(I55*E55,2)) -> 121.95 | N55: =IFERROR(__xludf.DUMMYFUNCTION("""COMPUTED_VALUE"""),"Takis") -> Takis | O55: =IFERROR(__xludf.DUMMYFUNCTION("""COMPUTED_VALUE"""),1.0) -> 1 | P55: =IFERROR(__xludf.DUMMYFUNCTION("""COMPUTED_VALUE"""),1.33) -> 1.33 | Q55: =IFERROR(__xludf.DUMMYFUNCTION("""COMPUTED_VALUE"""),2.0) -> 2 | R55: =IFERROR(__xludf.DUMMYFUNCTION("""COMPUTED_VALUE"""),15.0) -> 15 | S55: =IFERROR(__xludf.DUMMYFUNCTION("""COMPUTED_VALUE"""),30.0) -> 30 | T55: =IFERROR(__xludf.DUMMYFUNCTION("""COMPUTED_VALUE"""),0.0) -> 0 | U55: =IFERROR(__xludf.DUMMYFUNCTION("""COMPUTED_VALUE"""),0.0) -> 0 | V55: =IFERROR(__xludf.DUMMYFUNCTION("""COMPUTED_VALUE"""),2.0) -> 2 | W55: =IFERROR(__xludf.DUMMYFUNCTION("""COMPUTED_VALUE"""),30.0) -> 30
A56: =IFERROR(__xludf.DUMMYFUNCTION("""COMPUTED_VALUE"""),"Twix single") -> Twix single | B56: =IF(A56="","",SUMIFS(VMS_Sales!F:F,VMS_Sales!D:D,A56,VMS_Sales!O:O,$L$2)) -> 1 | C56: =IF(A56="","",ROUND(( SUMIFS(VMS_Sales!F:F,VMS_Sales!D:D,A56,VMS_Sales!O:O,$L$1)+ SUMIFS(VMS_Sales!F:F,VMS_Sales!D:D,A56,VMS_Sales!O:O,$L$2)+ SUMIFS(VMS_Sales!F:F,VMS_Sales!D:D,A56,VMS_Sales!O:O,$L$3) )/3,2)) -> 9.33 | D56: =IF(C56="","",ROUND(C56*1.15,0)) -> 11 | E56: =IFERROR(__xludf.DUMMYFUNCTION("IFERROR(XLOOKUP(A56,FILTER(VMS_Sales!$D:$D,VMS_Sales!$O:$O=$L$2),FILTER(VMS_Sales!$L:$L,VMS_Sales!$O:$O=$L$2),""""),"""")"),2.35) -> 2.35 | F56: =IF(OR(D56="",E56=""),"",ROUND(D56*E56,2)) -> 25.85 | G56: {=IFERROR( SUMIFS( PurchaseLines_Import!$I:$I, PurchaseLines_Import!$C:$C, XLOOKUP(A56,Map!$A:$A,Map!$B:$B,""), PurchaseLines_Import!$H:$H, $L$1 ), "")} -> 0 | H56: {=IFERROR( SUMIFS( Inventory_Import!$D:$D, Inventory_Import!$B:$B, TEXT(XLOOKUP(A56,Map!$A:$A,Map!$B:$B,""),"0000") ), 0)} -> 0 | I56: =IF(A56="","",MAX(D56-H56,0)) -> 11 | J56: =IF(OR(I56="",E56=""),"",ROUND(I56*E56,2)) -> 25.85 | N56: =IFERROR(__xludf.DUMMYFUNCTION("""COMPUTED_VALUE"""),"vitrac") -> vitrac | O56: =IFERROR(__xludf.DUMMYFUNCTION("""COMPUTED_VALUE"""),44.0) -> 44 | P56: =IFERROR(__xludf.DUMMYFUNCTION("""COMPUTED_VALUE"""),14.67) -> 14.67 | Q56: =IFERROR(__xludf.DUMMYFUNCTION("""COMPUTED_VALUE"""),17.0) -> 17 | R56: =IFERROR(__xludf.DUMMYFUNCTION("""COMPUTED_VALUE"""),1.6) -> 1.6 | S56: =IFERROR(__xludf.DUMMYFUNCTION("""COMPUTED_VALUE"""),27.2) -> 27.2 | T56: =IFERROR(__xludf.DUMMYFUNCTION("""COMPUTED_VALUE"""),0.0) -> 0 | U56: =IFERROR(__xludf.DUMMYFUNCTION("""COMPUTED_VALUE"""),0.0) -> 0 | V56: =IFERROR(__xludf.DUMMYFUNCTION("""COMPUTED_VALUE"""),17.0) -> 17 | W56: =IFERROR(__xludf.DUMMYFUNCTION("""COMPUTED_VALUE"""),27.2) -> 27.2
A57: =IFERROR(__xludf.DUMMYFUNCTION("""COMPUTED_VALUE"""),"Yupi") -> Yupi | B57: =IF(A57="","",SUMIFS(VMS_Sales!F:F,VMS_Sales!D:D,A57,VMS_Sales!O:O,$L$2)) -> 38 | C57: =IF(A57="","",ROUND(( SUMIFS(VMS_Sales!F:F,VMS_Sales!D:D,A57,VMS_Sales!O:O,$L$1)+ SUMIFS(VMS_Sales!F:F,VMS_Sales!D:D,A57,VMS_Sales!O:O,$L$2)+ SUMIFS(VMS_Sales!F:F,VMS_Sales!D:D,A57,VMS_Sales!O:O,$L$3) )/3,2)) -> 20.67 | D57: =IF(C57="","",ROUND(C57*1.15,0)) -> 24 | E57: =IFERROR(__xludf.DUMMYFUNCTION("IFERROR(XLOOKUP(A57,FILTER(VMS_Sales!$D:$D,VMS_Sales!$O:$O=$L$2),FILTER(VMS_Sales!$L:$L,VMS_Sales!$O:$O=$L$2),""""),"""")"),1.79) -> 1.79 | F57: =IF(OR(D57="",E57=""),"",ROUND(D57*E57,2)) -> 42.96 | G57: {=IFERROR( SUMIFS( PurchaseLines_Import!$I:$I, PurchaseLines_Import!$C:$C, XLOOKUP(A57,Map!$A:$A,Map!$B:$B,""), PurchaseLines_Import!$H:$H, $L$1 ), "")} -> 0 | H57: {=IFERROR( SUMIFS( Inventory_Import!$D:$D, Inventory_Import!$B:$B, TEXT(XLOOKUP(A57,Map!$A:$A,Map!$B:$B,""),"0000") ), 0)} -> 0 | I57: =IF(A57="","",MAX(D57-H57,0)) -> 24 | J57: =IF(OR(I57="",E57=""),"",ROUND(I57*E57,2)) -> 42.96 | N57: =IFERROR(__xludf.DUMMYFUNCTION("""COMPUTED_VALUE"""),"Twix single") -> Twix single | O57: =IFERROR(__xludf.DUMMYFUNCTION("""COMPUTED_VALUE"""),1.0) -> 1 | P57: =IFERROR(__xludf.DUMMYFUNCTION("""COMPUTED_VALUE"""),9.33) -> 9.33 | Q57: =IFERROR(__xludf.DUMMYFUNCTION("""COMPUTED_VALUE"""),11.0) -> 11 | R57: =IFERROR(__xludf.DUMMYFUNCTION("""COMPUTED_VALUE"""),2.35) -> 2.35 | S57: =IFERROR(__xludf.DUMMYFUNCTION("""COMPUTED_VALUE"""),25.85) -> 25.85 | T57: =IFERROR(__xludf.DUMMYFUNCTION("""COMPUTED_VALUE"""),0.0) -> 0 | U57: =IFERROR(__xludf.DUMMYFUNCTION("""COMPUTED_VALUE"""),0.0) -> 0 | V57: =IFERROR(__xludf.DUMMYFUNCTION("""COMPUTED_VALUE"""),11.0) -> 11 | W57: =IFERROR(__xludf.DUMMYFUNCTION("""COMPUTED_VALUE"""),25.85) -> 25.85
A58: =IFERROR(__xludf.DUMMYFUNCTION("""COMPUTED_VALUE"""),"Haribo 80g") -> Haribo 80g | B58: =IF(A58="","",SUMIFS(VMS_Sales!F:F,VMS_Sales!D:D,A58,VMS_Sales!O:O,$L$2)) -> 12 | C58: =IF(A58="","",ROUND(( SUMIFS(VMS_Sales!F:F,VMS_Sales!D:D,A58,VMS_Sales!O:O,$L$1)+ SUMIFS(VMS_Sales!F:F,VMS_Sales!D:D,A58,VMS_Sales!O:O,$L$2)+ SUMIFS(VMS_Sales!F:F,VMS_Sales!D:D,A58,VMS_Sales!O:O,$L$3) )/3,2)) -> 5.33 | D58: =IF(C58="","",ROUND(C58*1.15,0)) -> 6 | E58: =IFERROR(__xludf.DUMMYFUNCTION("IFERROR(XLOOKUP(A58,FILTER(VMS_Sales!$D:$D,VMS_Sales!$O:$O=$L$2),FILTER(VMS_Sales!$L:$L,VMS_Sales!$O:$O=$L$2),""""),"""")"),7.2) -> 7.2 | F58: =IF(OR(D58="",E58=""),"",ROUND(D58*E58,2)) -> 43.2 | G58: {=IFERROR( SUMIFS( PurchaseLines_Import!$I:$I, PurchaseLines_Import!$C:$C, XLOOKUP(A58,Map!$A:$A,Map!$B:$B,""), PurchaseLines_Import!$H:$H, $L$1 ), "")} -> 0 | H58: {=IFERROR( SUMIFS( Inventory_Import!$D:$D, Inventory_Import!$B:$B, TEXT(XLOOKUP(A58,Map!$A:$A,Map!$B:$B,""),"0000") ), 0)} -> 0 | I58: =IF(A58="","",MAX(D58-H58,0)) -> 6 | J58: =IF(OR(I58="",E58=""),"",ROUND(I58*E58,2)) -> 43.2 | N58: =IFERROR(__xludf.DUMMYFUNCTION("""COMPUTED_VALUE"""),"Tiger *12 Cheese") -> Tiger *12 Cheese | O58: =IFERROR(__xludf.DUMMYFUNCTION("""COMPUTED_VALUE"""),9.0) -> 9 | P58: =IFERROR(__xludf.DUMMYFUNCTION("""COMPUTED_VALUE"""),6.0) -> 6 | Q58: =IFERROR(__xludf.DUMMYFUNCTION("""COMPUTED_VALUE"""),7.0) -> 7 | R58: =IFERROR(__xludf.DUMMYFUNCTION("""COMPUTED_VALUE"""),3.5) -> 3.5 | S58: =IFERROR(__xludf.DUMMYFUNCTION("""COMPUTED_VALUE"""),24.5) -> 24.5 | T58: =IFERROR(__xludf.DUMMYFUNCTION("""COMPUTED_VALUE"""),0.0) -> 0 | U58: =IFERROR(__xludf.DUMMYFUNCTION("""COMPUTED_VALUE"""),0.0) -> 0 | V58: =IFERROR(__xludf.DUMMYFUNCTION("""COMPUTED_VALUE"""),7.0) -> 7 | W58: =IFERROR(__xludf.DUMMYFUNCTION("""COMPUTED_VALUE"""),24.5) -> 24.5
A59: =IFERROR(__xludf.DUMMYFUNCTION("""COMPUTED_VALUE"""),"sunTop") -> sunTop | B59: =IF(A59="","",SUMIFS(VMS_Sales!F:F,VMS_Sales!D:D,A59,VMS_Sales!O:O,$L$2)) -> 0 | C59: =IF(A59="","",ROUND(( SUMIFS(VMS_Sales!F:F,VMS_Sales!D:D,A59,VMS_Sales!O:O,$L$1)+ SUMIFS(VMS_Sales!F:F,VMS_Sales!D:D,A59,VMS_Sales!O:O,$L$2)+ SUMIFS(VMS_Sales!F:F,VMS_Sales!D:D,A59,VMS_Sales!O:O,$L$3) )/3,2)) -> 7 | D59: =IF(C59="","",ROUND(C59*1.15,0)) -> 8 | E59: =IFERROR(__xludf.DUMMYFUNCTION("IFERROR(XLOOKUP(A59,FILTER(VMS_Sales!$D:$D,VMS_Sales!$O:$O=$L$2),FILTER(VMS_Sales!$L:$L,VMS_Sales!$O:$O=$L$2),""""),"""")"),"") | F59: =IF(OR(D59="",E59=""),"",ROUND(D59*E59,2)) | G59: {=IFERROR( SUMIFS( PurchaseLines_Import!$I:$I, PurchaseLines_Import!$C:$C, XLOOKUP(A59,Map!$A:$A,Map!$B:$B,""), PurchaseLines_Import!$H:$H, $L$1 ), "")} -> 0 | H59: {=IFERROR( SUMIFS( Inventory_Import!$D:$D, Inventory_Import!$B:$B, TEXT(XLOOKUP(A59,Map!$A:$A,Map!$B:$B,""),"0000") ), 0)} -> 2 | I59: =IF(A59="","",MAX(D59-H59,0)) -> 6 | J59: =IF(OR(I59="",E59=""),"",ROUND(I59*E59,2)) | N59: =IFERROR(__xludf.DUMMYFUNCTION("""COMPUTED_VALUE"""),"Tiger 12 chili and lemon") -> Tiger 12 chili and lemon | O59: =IFERROR(__xludf.DUMMYFUNCTION("""COMPUTED_VALUE"""),4.0) -> 4 | P59: =IFERROR(__xludf.DUMMYFUNCTION("""COMPUTED_VALUE"""),6.33) -> 6.33 | Q59: =IFERROR(__xludf.DUMMYFUNCTION("""COMPUTED_VALUE"""),7.0) -> 7 | R59: =IFERROR(__xludf.DUMMYFUNCTION("""COMPUTED_VALUE"""),3.5) -> 3.5 | S59: =IFERROR(__xludf.DUMMYFUNCTION("""COMPUTED_VALUE"""),24.5) -> 24.5 | T59: =IFERROR(__xludf.DUMMYFUNCTION("""COMPUTED_VALUE"""),0.0) -> 0 | U59: =IFERROR(__xludf.DUMMYFUNCTION("""COMPUTED_VALUE"""),0.0) -> 0 | V59: =IFERROR(__xludf.DUMMYFUNCTION("""COMPUTED_VALUE"""),7.0) -> 7 | W59: =IFERROR(__xludf.DUMMYFUNCTION("""COMPUTED_VALUE"""),24.5) -> 24.5
A60: =IFERROR(__xludf.DUMMYFUNCTION("""COMPUTED_VALUE"""),"Prime") -> Prime | B60: =IF(A60="","",SUMIFS(VMS_Sales!F:F,VMS_Sales!D:D,A60,VMS_Sales!O:O,$L$2)) -> 0 | C60: =IF(A60="","",ROUND(( SUMIFS(VMS_Sales!F:F,VMS_Sales!D:D,A60,VMS_Sales!O:O,$L$1)+ SUMIFS(VMS_Sales!F:F,VMS_Sales!D:D,A60,VMS_Sales!O:O,$L$2)+ SUMIFS(VMS_Sales!F:F,VMS_Sales!D:D,A60,VMS_Sales!O:O,$L$3) )/3,2)) -> 1 | D60: =IF(C60="","",ROUND(C60*1.15,0)) -> 1 | E60: =IFERROR(__xludf.DUMMYFUNCTION("IFERROR(XLOOKUP(A60,FILTER(VMS_Sales!$D:$D,VMS_Sales!$O:$O=$L$2),FILTER(VMS_Sales!$L:$L,VMS_Sales!$O:$O=$L$2),""""),"""")"),"") | F60: =IF(OR(D60="",E60=""),"",ROUND(D60*E60,2)) | G60: {=IFERROR( SUMIFS( PurchaseLines_Import!$I:$I, PurchaseLines_Import!$C:$C, XLOOKUP(A60,Map!$A:$A,Map!$B:$B,""), PurchaseLines_Import!$H:$H, $L$1 ), "")} -> 0 | H60: {=IFERROR( SUMIFS( Inventory_Import!$D:$D, Inventory_Import!$B:$B, TEXT(XLOOKUP(A60,Map!$A:$A,Map!$B:$B,""),"0000") ), 0)} -> 0 | I60: =IF(A60="","",MAX(D60-H60,0)) -> 1 | J60: =IF(OR(I60="",E60=""),"",ROUND(I60*E60,2)) | N60: =IFERROR(__xludf.DUMMYFUNCTION("""COMPUTED_VALUE"""),"Shada up") -> Shada up | O60: =IFERROR(__xludf.DUMMYFUNCTION("""COMPUTED_VALUE"""),5.0) -> 5 | P60: =IFERROR(__xludf.DUMMYFUNCTION("""COMPUTED_VALUE"""),14.0) -> 14 | Q60: =IFERROR(__xludf.DUMMYFUNCTION("""COMPUTED_VALUE"""),16.0) -> 16 | R60: =IFERROR(__xludf.DUMMYFUNCTION("""COMPUTED_VALUE"""),1.41) -> 1.41 | S60: =IFERROR(__xludf.DUMMYFUNCTION("""COMPUTED_VALUE"""),22.56) -> 22.56 | T60: =IFERROR(__xludf.DUMMYFUNCTION("""COMPUTED_VALUE"""),0.0) -> 0 | U60: =IFERROR(__xludf.DUMMYFUNCTION("""COMPUTED_VALUE"""),0.0) -> 0 | V60: =IFERROR(__xludf.DUMMYFUNCTION("""COMPUTED_VALUE"""),16.0) -> 16 | W60: =IFERROR(__xludf.DUMMYFUNCTION("""COMPUTED_VALUE"""),22.56) -> 22.56
A61: =IFERROR(__xludf.DUMMYFUNCTION("""COMPUTED_VALUE"""),"Dallas juice") -> Dallas juice | B61: =IF(A61="","",SUMIFS(VMS_Sales!F:F,VMS_Sales!D:D,A61,VMS_Sales!O:O,$L$2)) -> 41 | C61: =IF(A61="","",ROUND(( SUMIFS(VMS_Sales!F:F,VMS_Sales!D:D,A61,VMS_Sales!O:O,$L$1)+ SUMIFS(VMS_Sales!F:F,VMS_Sales!D:D,A61,VMS_Sales!O:O,$L$2)+ SUMIFS(VMS_Sales!F:F,VMS_Sales!D:D,A61,VMS_Sales!O:O,$L$3) )/3,2)) -> 41 | D61: =IF(C61="","",ROUND(C61*1.15,0)) -> 47 | E61: =IFERROR(__xludf.DUMMYFUNCTION("IFERROR(XLOOKUP(A61,FILTER(VMS_Sales!$D:$D,VMS_Sales!$O:$O=$L$2),FILTER(VMS_Sales!$L:$L,VMS_Sales!$O:$O=$L$2),""""),"""")"),0.91) -> 0.91 | F61: =IF(OR(D61="",E61=""),"",ROUND(D61*E61,2)) -> 42.77 | G61: {=IFERROR( SUMIFS( PurchaseLines_Import!$I:$I, PurchaseLines_Import!$C:$C, XLOOKUP(A61,Map!$A:$A,Map!$B:$B,""), PurchaseLines_Import!$H:$H, $L$1 ), "")} -> 0 | H61: {=IFERROR( SUMIFS( Inventory_Import!$D:$D, Inventory_Import!$B:$B, TEXT(XLOOKUP(A61,Map!$A:$A,Map!$B:$B,""),"0000") ), 0)} -> 0 | I61: =IF(A61="","",MAX(D61-H61,0)) -> 47 | J61: =IF(OR(I61="",E61=""),"",ROUND(I61*E61,2)) -> 42.77 | N61: =IFERROR(__xludf.DUMMYFUNCTION("""COMPUTED_VALUE"""),"Lavazza") -> Lavazza | O61: =IFERROR(__xludf.DUMMYFUNCTION("""COMPUTED_VALUE"""),6.0) -> 6 | P61: =IFERROR(__xludf.DUMMYFUNCTION("""COMPUTED_VALUE"""),4.33) -> 4.33 | Q61: =IFERROR(__xludf.DUMMYFUNCTION("""COMPUTED_VALUE"""),5.0) -> 5 | R61: =IFERROR(__xludf.DUMMYFUNCTION("""COMPUTED_VALUE"""),4.5) -> 4.5 | S61: =IFERROR(__xludf.DUMMYFUNCTION("""COMPUTED_VALUE"""),22.5) -> 22.5 | T61: =IFERROR(__xludf.DUMMYFUNCTION("""COMPUTED_VALUE"""),0.0) -> 0 | U61: =IFERROR(__xludf.DUMMYFUNCTION("""COMPUTED_VALUE"""),0.0) -> 0 | V61: =IFERROR(__xludf.DUMMYFUNCTION("""COMPUTED_VALUE"""),5.0) -> 5 | W61: =IFERROR(__xludf.DUMMYFUNCTION("""COMPUTED_VALUE"""),22.5) -> 22.5
A62: =IFERROR(__xludf.DUMMYFUNCTION("""COMPUTED_VALUE"""),"Mulino Cookis") -> Mulino Cookis | B62: =IF(A62="","",SUMIFS(VMS_Sales!F:F,VMS_Sales!D:D,A62,VMS_Sales!O:O,$L$2)) -> 0 | C62: =IF(A62="","",ROUND(( SUMIFS(VMS_Sales!F:F,VMS_Sales!D:D,A62,VMS_Sales!O:O,$L$1)+ SUMIFS(VMS_Sales!F:F,VMS_Sales!D:D,A62,VMS_Sales!O:O,$L$2)+ SUMIFS(VMS_Sales!F:F,VMS_Sales!D:D,A62,VMS_Sales!O:O,$L$3) )/3,2)) -> 0.67 | D62: =IF(C62="","",ROUND(C62*1.15,0)) -> 1 | E62: =IFERROR(__xludf.DUMMYFUNCTION("IFERROR(XLOOKUP(A62,FILTER(VMS_Sales!$D:$D,VMS_Sales!$O:$O=$L$2),FILTER(VMS_Sales!$L:$L,VMS_Sales!$O:$O=$L$2),""""),"""")"),"") | F62: =IF(OR(D62="",E62=""),"",ROUND(D62*E62,2)) | G62: {=IFERROR( SUMIFS( PurchaseLines_Import!$I:$I, PurchaseLines_Import!$C:$C, XLOOKUP(A62,Map!$A:$A,Map!$B:$B,""), PurchaseLines_Import!$H:$H, $L$1 ), "")} -> 0 | H62: {=IFERROR( SUMIFS( Inventory_Import!$D:$D, Inventory_Import!$B:$B, TEXT(XLOOKUP(A62,Map!$A:$A,Map!$B:$B,""),"0000") ), 0)} -> 0 | I62: =IF(A62="","",MAX(D62-H62,0)) -> 1 | J62: =IF(OR(I62="",E62=""),"",ROUND(I62*E62,2)) | N62: =IFERROR(__xludf.DUMMYFUNCTION("""COMPUTED_VALUE"""),"Schweppes") -> Schweppes | O62: =IFERROR(__xludf.DUMMYFUNCTION("""COMPUTED_VALUE"""),8.0) -> 8 | P62: =IFERROR(__xludf.DUMMYFUNCTION("""COMPUTED_VALUE"""),7.67) -> 7.67 | Q62: =IFERROR(__xludf.DUMMYFUNCTION("""COMPUTED_VALUE"""),9.0) -> 9 | R62: =IFERROR(__xludf.DUMMYFUNCTION("""COMPUTED_VALUE"""),2.0) -> 2 | S62: =IFERROR(__xludf.DUMMYFUNCTION("""COMPUTED_VALUE"""),18.0) -> 18 | T62: =IFERROR(__xludf.DUMMYFUNCTION("""COMPUTED_VALUE"""),0.0) -> 0 | U62: =IFERROR(__xludf.DUMMYFUNCTION("""COMPUTED_VALUE"""),0.0) -> 0 | V62: =IFERROR(__xludf.DUMMYFUNCTION("""COMPUTED_VALUE"""),9.0) -> 9 | W62: =IFERROR(__xludf.DUMMYFUNCTION("""COMPUTED_VALUE"""),18.0) -> 18
A63: =IFERROR(__xludf.DUMMYFUNCTION("""COMPUTED_VALUE"""),"Doritos real") -> Doritos real | B63: =IF(A63="","",SUMIFS(VMS_Sales!F:F,VMS_Sales!D:D,A63,VMS_Sales!O:O,$L$2)) -> 0 | C63: =IF(A63="","",ROUND(( SUMIFS(VMS_Sales!F:F,VMS_Sales!D:D,A63,VMS_Sales!O:O,$L$1)+ SUMIFS(VMS_Sales!F:F,VMS_Sales!D:D,A63,VMS_Sales!O:O,$L$2)+ SUMIFS(VMS_Sales!F:F,VMS_Sales!D:D,A63,VMS_Sales!O:O,$L$3) )/3,2)) -> 8.33 | D63: =IF(C63="","",ROUND(C63*1.15,0)) -> 10 | E63: =IFERROR(__xludf.DUMMYFUNCTION("IFERROR(XLOOKUP(A63,FILTER(VMS_Sales!$D:$D,VMS_Sales!$O:$O=$L$2),FILTER(VMS_Sales!$L:$L,VMS_Sales!$O:$O=$L$2),""""),"""")"),"") | F63: =IF(OR(D63="",E63=""),"",ROUND(D63*E63,2)) | G63: {=IFERROR( SUMIFS( PurchaseLines_Import!$I:$I, PurchaseLines_Import!$C:$C, XLOOKUP(A63,Map!$A:$A,Map!$B:$B,""), PurchaseLines_Import!$H:$H, $L$1 ), "")} -> 0 | H63: {=IFERROR( SUMIFS( Inventory_Import!$D:$D, Inventory_Import!$B:$B, TEXT(XLOOKUP(A63,Map!$A:$A,Map!$B:$B,""),"0000") ), 0)} -> 0 | I63: =IF(A63="","",MAX(D63-H63,0)) -> 10 | J63: =IF(OR(I63="",E63=""),"",ROUND(I63*E63,2)) | N63: =IFERROR(__xludf.DUMMYFUNCTION("""COMPUTED_VALUE"""),"brownies moulin") -> brownies moulin | O63: =IFERROR(__xludf.DUMMYFUNCTION("""COMPUTED_VALUE"""),19.0) -> 19 | P63: =IFERROR(__xludf.DUMMYFUNCTION("""COMPUTED_VALUE"""),8.67) -> 8.67 | Q63: =IFERROR(__xludf.DUMMYFUNCTION("""COMPUTED_VALUE"""),10.0) -> 10 | R63: =IFERROR(__xludf.DUMMYFUNCTION("""COMPUTED_VALUE"""),1.8) -> 1.8 | S63: =IFERROR(__xludf.DUMMYFUNCTION("""COMPUTED_VALUE"""),18.0) -> 18 | T63: =IFERROR(__xludf.DUMMYFUNCTION("""COMPUTED_VALUE"""),0.0) -> 0 | U63: =IFERROR(__xludf.DUMMYFUNCTION("""COMPUTED_VALUE"""),0.0) -> 0 | V63: =IFERROR(__xludf.DUMMYFUNCTION("""COMPUTED_VALUE"""),10.0) -> 10 | W63: =IFERROR(__xludf.DUMMYFUNCTION("""COMPUTED_VALUE"""),18.0) -> 18
A64: =IFERROR(__xludf.DUMMYFUNCTION("""COMPUTED_VALUE"""),"brownies moulin") -> brownies moulin | B64: =IF(A64="","",SUMIFS(VMS_Sales!F:F,VMS_Sales!D:D,A64,VMS_Sales!O:O,$L$2)) -> 19 | C64: =IF(A64="","",ROUND(( SUMIFS(VMS_Sales!F:F,VMS_Sales!D:D,A64,VMS_Sales!O:O,$L$1)+ SUMIFS(VMS_Sales!F:F,VMS_Sales!D:D,A64,VMS_Sales!O:O,$L$2)+ SUMIFS(VMS_Sales!F:F,VMS_Sales!D:D,A64,VMS_Sales!O:O,$L$3) )/3,2)) -> 8.67 | D64: =IF(C64="","",ROUND(C64*1.15,0)) -> 10 | E64: =IFERROR(__xludf.DUMMYFUNCTION("IFERROR(XLOOKUP(A64,FILTER(VMS_Sales!$D:$D,VMS_Sales!$O:$O=$L$2),FILTER(VMS_Sales!$L:$L,VMS_Sales!$O:$O=$L$2),""""),"""")"),1.8) -> 1.8 | F64: =IF(OR(D64="",E64=""),"",ROUND(D64*E64,2)) -> 18 | G64: {=IFERROR( SUMIFS( PurchaseLines_Import!$I:$I, PurchaseLines_Import!$C:$C, XLOOKUP(A64,Map!$A:$A,Map!$B:$B,""), PurchaseLines_Import!$H:$H, $L$1 ), "")} -> 0 | H64: {=IFERROR( SUMIFS( Inventory_Import!$D:$D, Inventory_Import!$B:$B, TEXT(XLOOKUP(A64,Map!$A:$A,Map!$B:$B,""),"0000") ), 0)} -> 0 | I64: =IF(A64="","",MAX(D64-H64,0)) -> 10 | J64: =IF(OR(I64="",E64=""),"",ROUND(I64*E64,2)) -> 18 | N64: =IFERROR(__xludf.DUMMYFUNCTION("""COMPUTED_VALUE"""),"wafe'up") -> wafe'up | O64: =IFERROR(__xludf.DUMMYFUNCTION("""COMPUTED_VALUE"""),22.0) -> 22 | P64: =IFERROR(__xludf.DUMMYFUNCTION("""COMPUTED_VALUE"""),7.33) -> 7.33 | Q64: =IFERROR(__xludf.DUMMYFUNCTION("""COMPUTED_VALUE"""),8.0) -> 8 | R64: =IFERROR(__xludf.DUMMYFUNCTION("""COMPUTED_VALUE"""),2.25) -> 2.25 | S64: =IFERROR(__xludf.DUMMYFUNCTION("""COMPUTED_VALUE"""),18.0) -> 18 | T64: =IFERROR(__xludf.DUMMYFUNCTION("""COMPUTED_VALUE"""),0.0) -> 0 | U64: =IFERROR(__xludf.DUMMYFUNCTION("""COMPUTED_VALUE"""),0.0) -> 0 | V64: =IFERROR(__xludf.DUMMYFUNCTION("""COMPUTED_VALUE"""),8.0) -> 8 | W64: =IFERROR(__xludf.DUMMYFUNCTION("""COMPUTED_VALUE"""),18.0) -> 18
A65: =IFERROR(__xludf.DUMMYFUNCTION("""COMPUTED_VALUE"""),"Chico") -> Chico | B65: =IF(A65="","",SUMIFS(VMS_Sales!F:F,VMS_Sales!D:D,A65,VMS_Sales!O:O,$L$2)) -> 0 | C65: =IF(A65="","",ROUND(( SUMIFS(VMS_Sales!F:F,VMS_Sales!D:D,A65,VMS_Sales!O:O,$L$1)+ SUMIFS(VMS_Sales!F:F,VMS_Sales!D:D,A65,VMS_Sales!O:O,$L$2)+ SUMIFS(VMS_Sales!F:F,VMS_Sales!D:D,A65,VMS_Sales!O:O,$L$3) )/3,2)) -> 6.67 | D65: =IF(C65="","",ROUND(C65*1.15,0)) -> 8 | E65: =IFERROR(__xludf.DUMMYFUNCTION("IFERROR(XLOOKUP(A65,FILTER(VMS_Sales!$D:$D,VMS_Sales!$O:$O=$L$2),FILTER(VMS_Sales!$L:$L,VMS_Sales!$O:$O=$L$2),""""),"""")"),"") | F65: =IF(OR(D65="",E65=""),"",ROUND(D65*E65,2)) | G65: {=IFERROR( SUMIFS( PurchaseLines_Import!$I:$I, PurchaseLines_Import!$C:$C, XLOOKUP(A65,Map!$A:$A,Map!$B:$B,""), PurchaseLines_Import!$H:$H, $L$1 ), "")} -> 0 | H65: {=IFERROR( SUMIFS( Inventory_Import!$D:$D, Inventory_Import!$B:$B, TEXT(XLOOKUP(A65,Map!$A:$A,Map!$B:$B,""),"0000") ), 0)} -> 0 | I65: =IF(A65="","",MAX(D65-H65,0)) -> 8 | J65: =IF(OR(I65="",E65=""),"",ROUND(I65*E65,2)) | N65: =IFERROR(__xludf.DUMMYFUNCTION("""COMPUTED_VALUE"""),"Freez") -> Freez | O65: =IFERROR(__xludf.DUMMYFUNCTION("""COMPUTED_VALUE"""),8.0) -> 8 | P65: =IFERROR(__xludf.DUMMYFUNCTION("""COMPUTED_VALUE"""),4.67) -> 4.67 | Q65: =IFERROR(__xludf.DUMMYFUNCTION("""COMPUTED_VALUE"""),5.0) -> 5 | R65: =IFERROR(__xludf.DUMMYFUNCTION("""COMPUTED_VALUE"""),3.41) -> 3.41 | S65: =IFERROR(__xludf.DUMMYFUNCTION("""COMPUTED_VALUE"""),17.05) -> 17.05 | T65: =IFERROR(__xludf.DUMMYFUNCTION("""COMPUTED_VALUE"""),0.0) -> 0 | U65: =IFERROR(__xludf.DUMMYFUNCTION("""COMPUTED_VALUE"""),0.0) -> 0 | V65: =IFERROR(__xludf.DUMMYFUNCTION("""COMPUTED_VALUE"""),5.0) -> 5 | W65: =IFERROR(__xludf.DUMMYFUNCTION("""COMPUTED_VALUE"""),17.05) -> 17.05
A66: =IFERROR(__xludf.DUMMYFUNCTION("""COMPUTED_VALUE"""),"vita go") -> vita go | B66: =IF(A66="","",SUMIFS(VMS_Sales!F:F,VMS_Sales!D:D,A66,VMS_Sales!O:O,$L$2)) -> 0 | C66: =IF(A66="","",ROUND(( SUMIFS(VMS_Sales!F:F,VMS_Sales!D:D,A66,VMS_Sales!O:O,$L$1)+ SUMIFS(VMS_Sales!F:F,VMS_Sales!D:D,A66,VMS_Sales!O:O,$L$2)+ SUMIFS(VMS_Sales!F:F,VMS_Sales!D:D,A66,VMS_Sales!O:O,$L$3) )/3,2)) -> 12.33 | D66: =IF(C66="","",ROUND(C66*1.15,0)) -> 14 | E66: =IFERROR(__xludf.DUMMYFUNCTION("IFERROR(XLOOKUP(A66,FILTER(VMS_Sales!$D:$D,VMS_Sales!$O:$O=$L$2),FILTER(VMS_Sales!$L:$L,VMS_Sales!$O:$O=$L$2),""""),"""")"),"") | F66: =IF(OR(D66="",E66=""),"",ROUND(D66*E66,2)) | G66: {=IFERROR( SUMIFS( PurchaseLines_Import!$I:$I, PurchaseLines_Import!$C:$C, XLOOKUP(A66,Map!$A:$A,Map!$B:$B,""), PurchaseLines_Import!$H:$H, $L$1 ), "")} -> 0 | H66: {=IFERROR( SUMIFS( Inventory_Import!$D:$D, Inventory_Import!$B:$B, TEXT(XLOOKUP(A66,Map!$A:$A,Map!$B:$B,""),"0000") ), 0)} -> 0 | I66: =IF(A66="","",MAX(D66-H66,0)) -> 14 | J66: =IF(OR(I66="",E66=""),"",ROUND(I66*E66,2)) | N66: =IFERROR(__xludf.DUMMYFUNCTION("""COMPUTED_VALUE"""),"Balls") -> Balls | O66: =IFERROR(__xludf.DUMMYFUNCTION("""COMPUTED_VALUE"""),100.0) -> 100 | P66: =IFERROR(__xludf.DUMMYFUNCTION("""COMPUTED_VALUE"""),33.33) -> 33.33 | Q66: =IFERROR(__xludf.DUMMYFUNCTION("""COMPUTED_VALUE"""),38.0) -> 38 | R66: =IFERROR(__xludf.DUMMYFUNCTION("""COMPUTED_VALUE"""),0.4) -> 0.4 | S66: =IFERROR(__xludf.DUMMYFUNCTION("""COMPUTED_VALUE"""),15.2) -> 15.2 | T66: =IFERROR(__xludf.DUMMYFUNCTION("""COMPUTED_VALUE"""),0.0) -> 0 | U66: =IFERROR(__xludf.DUMMYFUNCTION("""COMPUTED_VALUE"""),0.0) -> 0 | V66: =IFERROR(__xludf.DUMMYFUNCTION("""COMPUTED_VALUE"""),38.0) -> 38 | W66: =IFERROR(__xludf.DUMMYFUNCTION("""COMPUTED_VALUE"""),15.2) -> 15.2
A67: =IFERROR(__xludf.DUMMYFUNCTION("""COMPUTED_VALUE"""),"Goftime") -> Goftime | B67: =IF(A67="","",SUMIFS(VMS_Sales!F:F,VMS_Sales!D:D,A67,VMS_Sales!O:O,$L$2)) -> 0 | C67: =IF(A67="","",ROUND(( SUMIFS(VMS_Sales!F:F,VMS_Sales!D:D,A67,VMS_Sales!O:O,$L$1)+ SUMIFS(VMS_Sales!F:F,VMS_Sales!D:D,A67,VMS_Sales!O:O,$L$2)+ SUMIFS(VMS_Sales!F:F,VMS_Sales!D:D,A67,VMS_Sales!O:O,$L$3) )/3,2)) -> 5.33 | D67: =IF(C67="","",ROUND(C67*1.15,0)) -> 6 | E67: =IFERROR(__xludf.DUMMYFUNCTION("IFERROR(XLOOKUP(A67,FILTER(VMS_Sales!$D:$D,VMS_Sales!$O:$O=$L$2),FILTER(VMS_Sales!$L:$L,VMS_Sales!$O:$O=$L$2),""""),"""")"),"") | F67: =IF(OR(D67="",E67=""),"",ROUND(D67*E67,2)) | G67: {=IFERROR( SUMIFS( PurchaseLines_Import!$I:$I, PurchaseLines_Import!$C:$C, XLOOKUP(A67,Map!$A:$A,Map!$B:$B,""), PurchaseLines_Import!$H:$H, $L$1 ), "")} -> 0 | H67: {=IFERROR( SUMIFS( Inventory_Import!$D:$D, Inventory_Import!$B:$B, TEXT(XLOOKUP(A67,Map!$A:$A,Map!$B:$B,""),"0000") ), 0)} -> 0 | I67: =IF(A67="","",MAX(D67-H67,0)) -> 6 | J67: =IF(OR(I67="",E67=""),"",ROUND(I67*E67,2)) | N67: =IFERROR(__xludf.DUMMYFUNCTION("""COMPUTED_VALUE"""),"Almarai Banana") -> Almarai Banana | O67: =IFERROR(__xludf.DUMMYFUNCTION("""COMPUTED_VALUE"""),2.0) -> 2 | P67: =IFERROR(__xludf.DUMMYFUNCTION("""COMPUTED_VALUE"""),4.0) -> 4 | Q67: =IFERROR(__xludf.DUMMYFUNCTION("""COMPUTED_VALUE"""),5.0) -> 5 | R67: =IFERROR(__xludf.DUMMYFUNCTION("""COMPUTED_VALUE"""),2.29) -> 2.29 | S67: =IFERROR(__xludf.DUMMYFUNCTION("""COMPUTED_VALUE"""),11.45) -> 11.45 | T67: =IFERROR(__xludf.DUMMYFUNCTION("""COMPUTED_VALUE"""),0.0) -> 0 | U67: =IFERROR(__xludf.DUMMYFUNCTION("""COMPUTED_VALUE"""),0.0) -> 0 | V67: =IFERROR(__xludf.DUMMYFUNCTION("""COMPUTED_VALUE"""),5.0) -> 5 | W67: =IFERROR(__xludf.DUMMYFUNCTION("""COMPUTED_VALUE"""),11.45) -> 11.45
A68: =IFERROR(__xludf.DUMMYFUNCTION("""COMPUTED_VALUE"""),"Waffi") -> Waffi | B68: =IF(A68="","",SUMIFS(VMS_Sales!F:F,VMS_Sales!D:D,A68,VMS_Sales!O:O,$L$2)) -> 0 | C68: =IF(A68="","",ROUND(( SUMIFS(VMS_Sales!F:F,VMS_Sales!D:D,A68,VMS_Sales!O:O,$L$1)+ SUMIFS(VMS_Sales!F:F,VMS_Sales!D:D,A68,VMS_Sales!O:O,$L$2)+ SUMIFS(VMS_Sales!F:F,VMS_Sales!D:D,A68,VMS_Sales!O:O,$L$3) )/3,2)) -> 2.33 | D68: =IF(C68="","",ROUND(C68*1.15,0)) -> 3 | E68: =IFERROR(__xludf.DUMMYFUNCTION("IFERROR(XLOOKUP(A68,FILTER(VMS_Sales!$D:$D,VMS_Sales!$O:$O=$L$2),FILTER(VMS_Sales!$L:$L,VMS_Sales!$O:$O=$L$2),""""),"""")"),"") | F68: =IF(OR(D68="",E68=""),"",ROUND(D68*E68,2)) | G68: {=IFERROR( SUMIFS( PurchaseLines_Import!$I:$I, PurchaseLines_Import!$C:$C, XLOOKUP(A68,Map!$A:$A,Map!$B:$B,""), PurchaseLines_Import!$H:$H, $L$1 ), "")} -> 0 | H68: {=IFERROR( SUMIFS( Inventory_Import!$D:$D, Inventory_Import!$B:$B, TEXT(XLOOKUP(A68,Map!$A:$A,Map!$B:$B,""),"0000") ), 0)} -> 0 | I68: =IF(A68="","",MAX(D68-H68,0)) -> 3 | J68: =IF(OR(I68="",E68=""),"",ROUND(I68*E68,2)) | N68: =IFERROR(__xludf.DUMMYFUNCTION("""COMPUTED_VALUE"""),"Prime Ex") -> Prime Ex | O68: =IFERROR(__xludf.DUMMYFUNCTION("""COMPUTED_VALUE"""),3.0) -> 3 | P68: =IFERROR(__xludf.DUMMYFUNCTION("""COMPUTED_VALUE"""),1.0) -> 1 | Q68: =IFERROR(__xludf.DUMMYFUNCTION("""COMPUTED_VALUE"""),1.0) -> 1 | R68: =IFERROR(__xludf.DUMMYFUNCTION("""COMPUTED_VALUE"""),9.0) -> 9 | S68: =IFERROR(__xludf.DUMMYFUNCTION("""COMPUTED_VALUE"""),9.0) -> 9 | T68: =IFERROR(__xludf.DUMMYFUNCTION("""COMPUTED_VALUE"""),0.0) -> 0 | U68: =IFERROR(__xludf.DUMMYFUNCTION("""COMPUTED_VALUE"""),0.0) -> 0 | V68: =IFERROR(__xludf.DUMMYFUNCTION("""COMPUTED_VALUE"""),1.0) -> 1 | W68: =IFERROR(__xludf.DUMMYFUNCTION("""COMPUTED_VALUE"""),9.0) -> 9
A69: =IFERROR(__xludf.DUMMYFUNCTION("""COMPUTED_VALUE"""),"Shada up") -> Shada up | B69: =IF(A69="","",SUMIFS(VMS_Sales!F:F,VMS_Sales!D:D,A69,VMS_Sales!O:O,$L$2)) -> 5 | C69: =IF(A69="","",ROUND(( SUMIFS(VMS_Sales!F:F,VMS_Sales!D:D,A69,VMS_Sales!O:O,$L$1)+ SUMIFS(VMS_Sales!F:F,VMS_Sales!D:D,A69,VMS_Sales!O:O,$L$2)+ SUMIFS(VMS_Sales!F:F,VMS_Sales!D:D,A69,VMS_Sales!O:O,$L$3) )/3,2)) -> 14 | D69: =IF(C69="","",ROUND(C69*1.15,0)) -> 16 | E69: =IFERROR(__xludf.DUMMYFUNCTION("IFERROR(XLOOKUP(A69,FILTER(VMS_Sales!$D:$D,VMS_Sales!$O:$O=$L$2),FILTER(VMS_Sales!$L:$L,VMS_Sales!$O:$O=$L$2),""""),"""")"),1.41) -> 1.41 | F69: =IF(OR(D69="",E69=""),"",ROUND(D69*E69,2)) -> 22.56 | G69: {=IFERROR( SUMIFS( PurchaseLines_Import!$I:$I, PurchaseLines_Import!$C:$C, XLOOKUP(A69,Map!$A:$A,Map!$B:$B,""), PurchaseLines_Import!$H:$H, $L$1 ), "")} -> 0 | H69: {=IFERROR( SUMIFS( Inventory_Import!$D:$D, Inventory_Import!$B:$B, TEXT(XLOOKUP(A69,Map!$A:$A,Map!$B:$B,""),"0000") ), 0)} -> 0 | I69: =IF(A69="","",MAX(D69-H69,0)) -> 16 | J69: =IF(OR(I69="",E69=""),"",ROUND(I69*E69,2)) -> 22.56 | N69: =IFERROR(__xludf.DUMMYFUNCTION("""COMPUTED_VALUE"""),"mr.bite strike") -> mr.bite strike | O69: =IFERROR(__xludf.DUMMYFUNCTION("""COMPUTED_VALUE"""),1.0) -> 1 | P69: =IFERROR(__xludf.DUMMYFUNCTION("""COMPUTED_VALUE"""),3.33) -> 3.33 | Q69: =IFERROR(__xludf.DUMMYFUNCTION("""COMPUTED_VALUE"""),4.0) -> 4 | R69: =IFERROR(__xludf.DUMMYFUNCTION("""COMPUTED_VALUE"""),1.87) -> 1.87 | S69: =IFERROR(__xludf.DUMMYFUNCTION("""COMPUTED_VALUE"""),7.48) -> 7.48 | T69: =IFERROR(__xludf.DUMMYFUNCTION("""COMPUTED_VALUE"""),0.0) -> 0 | U69: =IFERROR(__xludf.DUMMYFUNCTION("""COMPUTED_VALUE"""),0.0) -> 0 | V69: =IFERROR(__xludf.DUMMYFUNCTION("""COMPUTED_VALUE"""),4.0) -> 4 | W69: =IFERROR(__xludf.DUMMYFUNCTION("""COMPUTED_VALUE"""),7.48) -> 7.48
A70: =IFERROR(__xludf.DUMMYFUNCTION("""COMPUTED_VALUE"""),"Be happy kids") -> Be happy kids | B70: =IF(A70="","",SUMIFS(VMS_Sales!F:F,VMS_Sales!D:D,A70,VMS_Sales!O:O,$L$2)) -> 0 | C70: =IF(A70="","",ROUND(( SUMIFS(VMS_Sales!F:F,VMS_Sales!D:D,A70,VMS_Sales!O:O,$L$1)+ SUMIFS(VMS_Sales!F:F,VMS_Sales!D:D,A70,VMS_Sales!O:O,$L$2)+ SUMIFS(VMS_Sales!F:F,VMS_Sales!D:D,A70,VMS_Sales!O:O,$L$3) )/3,2)) -> 2.67 | D70: =IF(C70="","",ROUND(C70*1.15,0)) -> 3 | E70: =IFERROR(__xludf.DUMMYFUNCTION("IFERROR(XLOOKUP(A70,FILTER(VMS_Sales!$D:$D,VMS_Sales!$O:$O=$L$2),FILTER(VMS_Sales!$L:$L,VMS_Sales!$O:$O=$L$2),""""),"""")"),"") | F70: =IF(OR(D70="",E70=""),"",ROUND(D70*E70,2)) | G70: {=IFERROR( SUMIFS( PurchaseLines_Import!$I:$I, PurchaseLines_Import!$C:$C, XLOOKUP(A70,Map!$A:$A,Map!$B:$B,""), PurchaseLines_Import!$H:$H, $L$1 ), "")} -> 0 | H70: {=IFERROR( SUMIFS( Inventory_Import!$D:$D, Inventory_Import!$B:$B, TEXT(XLOOKUP(A70,Map!$A:$A,Map!$B:$B,""),"0000") ), 0)} -> 0 | I70: =IF(A70="","",MAX(D70-H70,0)) -> 3 | J70: =IF(OR(I70="",E70=""),"",ROUND(I70*E70,2)) | N70: =IFERROR(__xludf.DUMMYFUNCTION("""COMPUTED_VALUE"""),"未设置") -> 未设置 | O70: =IFERROR(__xludf.DUMMYFUNCTION("""COMPUTED_VALUE"""),57.0) -> 57 | P70: =IFERROR(__xludf.DUMMYFUNCTION("""COMPUTED_VALUE"""),48.0) -> 48 | Q70: =IFERROR(__xludf.DUMMYFUNCTION("""COMPUTED_VALUE"""),55.0) -> 55 | R70: =IFERROR(__xludf.DUMMYFUNCTION("""COMPUTED_VALUE"""),0.0) -> 0 | S70: =IFERROR(__xludf.DUMMYFUNCTION("""COMPUTED_VALUE"""),0.0) -> 0 | T70: =IFERROR(__xludf.DUMMYFUNCTION("""COMPUTED_VALUE"""),0.0) -> 0 | U70: =IFERROR(__xludf.DUMMYFUNCTION("""COMPUTED_VALUE"""),0.0) -> 0 | V70: =IFERROR(__xludf.DUMMYFUNCTION("""COMPUTED_VALUE"""),55.0) -> 55 | W70: =IFERROR(__xludf.DUMMYFUNCTION("""COMPUTED_VALUE"""),0.0) -> 0
A71: =IFERROR(__xludf.DUMMYFUNCTION("""COMPUTED_VALUE"""),"Wafer Laviva") -> Wafer Laviva | B71: =IF(A71="","",SUMIFS(VMS_Sales!F:F,VMS_Sales!D:D,A71,VMS_Sales!O:O,$L$2)) -> 0 | C71: =IF(A71="","",ROUND(( SUMIFS(VMS_Sales!F:F,VMS_Sales!D:D,A71,VMS_Sales!O:O,$L$1)+ SUMIFS(VMS_Sales!F:F,VMS_Sales!D:D,A71,VMS_Sales!O:O,$L$2)+ SUMIFS(VMS_Sales!F:F,VMS_Sales!D:D,A71,VMS_Sales!O:O,$L$3) )/3,2)) -> 1 | D71: =IF(C71="","",ROUND(C71*1.15,0)) -> 1 | E71: =IFERROR(__xludf.DUMMYFUNCTION("IFERROR(XLOOKUP(A71,FILTER(VMS_Sales!$D:$D,VMS_Sales!$O:$O=$L$2),FILTER(VMS_Sales!$L:$L,VMS_Sales!$O:$O=$L$2),""""),"""")"),"") | F71: =IF(OR(D71="",E71=""),"",ROUND(D71*E71,2)) | G71: {=IFERROR( SUMIFS( PurchaseLines_Import!$I:$I, PurchaseLines_Import!$C:$C, XLOOKUP(A71,Map!$A:$A,Map!$B:$B,""), PurchaseLines_Import!$H:$H, $L$1 ), "")} -> 0 | H71: {=IFERROR( SUMIFS( Inventory_Import!$D:$D, Inventory_Import!$B:$B, TEXT(XLOOKUP(A71,Map!$A:$A,Map!$B:$B,""),"0000") ), 0)} -> 0 | I71: =IF(A71="","",MAX(D71-H71,0)) -> 1 | J71: =IF(OR(I71="",E71=""),"",ROUND(I71*E71,2)) | N71: =IFERROR(__xludf.DUMMYFUNCTION("""COMPUTED_VALUE"""),"kinder delice") -> kinder delice | O71: =IFERROR(__xludf.DUMMYFUNCTION("""COMPUTED_VALUE"""),6.0) -> 6 | P71: =IFERROR(__xludf.DUMMYFUNCTION("""COMPUTED_VALUE"""),2.0) -> 2 | Q71: =IFERROR(__xludf.DUMMYFUNCTION("""COMPUTED_VALUE"""),2.0) -> 2 | R71: =IFERROR(__xludf.DUMMYFUNCTION("""COMPUTED_VALUE"""),2.4) -> 2.4 | S71: =IFERROR(__xludf.DUMMYFUNCTION("""COMPUTED_VALUE"""),4.8) -> 4.8 | T71: =IFERROR(__xludf.DUMMYFUNCTION("""COMPUTED_VALUE"""),50.0) -> 50 | U71: =IFERROR(__xludf.DUMMYFUNCTION("""COMPUTED_VALUE"""),5.0) -> 5 | V71: =IFERROR(__xludf.DUMMYFUNCTION("""COMPUTED_VALUE"""),0.0) -> 0 | W71: =IFERROR(__xludf.DUMMYFUNCTION("""COMPUTED_VALUE"""),0.0) -> 0
A72: =IFERROR(__xludf.DUMMYFUNCTION("""COMPUTED_VALUE"""),"Chillax chips") -> Chillax chips | B72: =IF(A72="","",SUMIFS(VMS_Sales!F:F,VMS_Sales!D:D,A72,VMS_Sales!O:O,$L$2)) -> 36 | C72: =IF(A72="","",ROUND(( SUMIFS(VMS_Sales!F:F,VMS_Sales!D:D,A72,VMS_Sales!O:O,$L$1)+ SUMIFS(VMS_Sales!F:F,VMS_Sales!D:D,A72,VMS_Sales!O:O,$L$2)+ SUMIFS(VMS_Sales!F:F,VMS_Sales!D:D,A72,VMS_Sales!O:O,$L$3) )/3,2)) -> 31 | D72: =IF(C72="","",ROUND(C72*1.15,0)) -> 36 | E72: =IFERROR(__xludf.DUMMYFUNCTION("IFERROR(XLOOKUP(A72,FILTER(VMS_Sales!$D:$D,VMS_Sales!$O:$O=$L$2),FILTER(VMS_Sales!$L:$L,VMS_Sales!$O:$O=$L$2),""""),"""")"),3.5) -> 3.5 | F72: =IF(OR(D72="",E72=""),"",ROUND(D72*E72,2)) -> 126 | G72: {=IFERROR( SUMIFS( PurchaseLines_Import!$I:$I, PurchaseLines_Import!$C:$C, XLOOKUP(A72,Map!$A:$A,Map!$B:$B,""), PurchaseLines_Import!$H:$H, $L$1 ), "")} -> 0 | H72: {=IFERROR( SUMIFS( Inventory_Import!$D:$D, Inventory_Import!$B:$B, TEXT(XLOOKUP(A72,Map!$A:$A,Map!$B:$B,""),"0000") ), 0)} -> 0 | I72: =IF(A72="","",MAX(D72-H72,0)) -> 36 | J72: =IF(OR(I72="",E72=""),"",ROUND(I72*E72,2)) -> 126 | N72: =IFERROR(__xludf.DUMMYFUNCTION("""COMPUTED_VALUE"""),"Digestive") -> Digestive | O72: =IFERROR(__xludf.DUMMYFUNCTION("""COMPUTED_VALUE"""),0.0) -> 0 | P72: =IFERROR(__xludf.DUMMYFUNCTION("""COMPUTED_VALUE"""),9.67) -> 9.67 | Q72: =IFERROR(__xludf.DUMMYFUNCTION("""COMPUTED_VALUE"""),11.0) -> 11 | T72: =IFERROR(__xludf.DUMMYFUNCTION("""COMPUTED_VALUE"""),0.0) -> 0 | U72: =IFERROR(__xludf.DUMMYFUNCTION("""COMPUTED_VALUE"""),0.0) -> 0 | V72: =IFERROR(__xludf.DUMMYFUNCTION("""COMPUTED_VALUE"""),11.0) -> 11
A73: =IFERROR(__xludf.DUMMYFUNCTION("""COMPUTED_VALUE"""),"mr.bite strike") -> mr.bite strike | B73: =IF(A73="","",SUMIFS(VMS_Sales!F:F,VMS_Sales!D:D,A73,VMS_Sales!O:O,$L$2)) -> 1 | C73: =IF(A73="","",ROUND(( SUMIFS(VMS_Sales!F:F,VMS_Sales!D:D,A73,VMS_Sales!O:O,$L$1)+ SUMIFS(VMS_Sales!F:F,VMS_Sales!D:D,A73,VMS_Sales!O:O,$L$2)+ SUMIFS(VMS_Sales!F:F,VMS_Sales!D:D,A73,VMS_Sales!O:O,$L$3) )/3,2)) -> 3.33 | D73: =IF(C73="","",ROUND(C73*1.15,0)) -> 4 | E73: =IFERROR(__xludf.DUMMYFUNCTION("IFERROR(XLOOKUP(A73,FILTER(VMS_Sales!$D:$D,VMS_Sales!$O:$O=$L$2),FILTER(VMS_Sales!$L:$L,VMS_Sales!$O:$O=$L$2),""""),"""")"),1.87) -> 1.87 | F73: =IF(OR(D73="",E73=""),"",ROUND(D73*E73,2)) -> 7.48 | G73: {=IFERROR( SUMIFS( PurchaseLines_Import!$I:$I, PurchaseLines_Import!$C:$C, XLOOKUP(A73,Map!$A:$A,Map!$B:$B,""), PurchaseLines_Import!$H:$H, $L$1 ), "")} -> 0 | H73: {=IFERROR( SUMIFS( Inventory_Import!$D:$D, Inventory_Import!$B:$B, TEXT(XLOOKUP(A73,Map!$A:$A,Map!$B:$B,""),"0000") ), 0)} -> 0 | I73: =IF(A73="","",MAX(D73-H73,0)) -> 4 | J73: =IF(OR(I73="",E73=""),"",ROUND(I73*E73,2)) -> 7.48 | N73: =IFERROR(__xludf.DUMMYFUNCTION("""COMPUTED_VALUE"""),"Indomie") -> Indomie | O73: =IFERROR(__xludf.DUMMYFUNCTION("""COMPUTED_VALUE"""),0.0) -> 0 | P73: =IFERROR(__xludf.DUMMYFUNCTION("""COMPUTED_VALUE"""),0.67) -> 0.67 | Q73: =IFERROR(__xludf.DUMMYFUNCTION("""COMPUTED_VALUE"""),1.0) -> 1 | T73: =IFERROR(__xludf.DUMMYFUNCTION("""COMPUTED_VALUE"""),0.0) -> 0 | U73: =IFERROR(__xludf.DUMMYFUNCTION("""COMPUTED_VALUE"""),0.0) -> 0 | V73: =IFERROR(__xludf.DUMMYFUNCTION("""COMPUTED_VALUE"""),1.0) -> 1
A74: =IFERROR(__xludf.DUMMYFUNCTION("""COMPUTED_VALUE"""),"Lavazza") -> Lavazza | B74: =IF(A74="","",SUMIFS(VMS_Sales!F:F,VMS_Sales!D:D,A74,VMS_Sales!O:O,$L$2)) -> 6 | C74: =IF(A74="","",ROUND(( SUMIFS(VMS_Sales!F:F,VMS_Sales!D:D,A74,VMS_Sales!O:O,$L$1)+ SUMIFS(VMS_Sales!F:F,VMS_Sales!D:D,A74,VMS_Sales!O:O,$L$2)+ SUMIFS(VMS_Sales!F:F,VMS_Sales!D:D,A74,VMS_Sales!O:O,$L$3) )/3,2)) -> 4.33 | D74: =IF(C74="","",ROUND(C74*1.15,0)) -> 5 | E74: =IFERROR(__xludf.DUMMYFUNCTION("IFERROR(XLOOKUP(A74,FILTER(VMS_Sales!$D:$D,VMS_Sales!$O:$O=$L$2),FILTER(VMS_Sales!$L:$L,VMS_Sales!$O:$O=$L$2),""""),"""")"),4.5) -> 4.5 | F74: =IF(OR(D74="",E74=""),"",ROUND(D74*E74,2)) -> 22.5 | G74: {=IFERROR( SUMIFS( PurchaseLines_Import!$I:$I, PurchaseLines_Import!$C:$C, XLOOKUP(A74,Map!$A:$A,Map!$B:$B,""), PurchaseLines_Import!$H:$H, $L$1 ), "")} -> 0 | H74: {=IFERROR( SUMIFS( Inventory_Import!$D:$D, Inventory_Import!$B:$B, TEXT(XLOOKUP(A74,Map!$A:$A,Map!$B:$B,""),"0000") ), 0)} -> 0 | I74: =IF(A74="","",MAX(D74-H74,0)) -> 5 | J74: =IF(OR(I74="",E74=""),"",ROUND(I74*E74,2)) -> 22.5 | N74: =IFERROR(__xludf.DUMMYFUNCTION("""COMPUTED_VALUE"""),"Lexus") -> Lexus | O74: =IFERROR(__xludf.DUMMYFUNCTION("""COMPUTED_VALUE"""),0.0) -> 0 | P74: =IFERROR(__xludf.DUMMYFUNCTION("""COMPUTED_VALUE"""),16.0) -> 16 | Q74: =IFERROR(__xludf.DUMMYFUNCTION("""COMPUTED_VALUE"""),18.0) -> 18 | T74: =IFERROR(__xludf.DUMMYFUNCTION("""COMPUTED_VALUE"""),0.0) -> 0 | U74: =IFERROR(__xludf.DUMMYFUNCTION("""COMPUTED_VALUE"""),0.0) -> 0 | V74: =IFERROR(__xludf.DUMMYFUNCTION("""COMPUTED_VALUE"""),18.0) -> 18
A75: =IFERROR(__xludf.DUMMYFUNCTION("""COMPUTED_VALUE"""),"Yumi zak") -> Yumi zak | B75: =IF(A75="","",SUMIFS(VMS_Sales!F:F,VMS_Sales!D:D,A75,VMS_Sales!O:O,$L$2)) -> 7 | C75: =IF(A75="","",ROUND(( SUMIFS(VMS_Sales!F:F,VMS_Sales!D:D,A75,VMS_Sales!O:O,$L$1)+ SUMIFS(VMS_Sales!F:F,VMS_Sales!D:D,A75,VMS_Sales!O:O,$L$2)+ SUMIFS(VMS_Sales!F:F,VMS_Sales!D:D,A75,VMS_Sales!O:O,$L$3) )/3,2)) -> 14 | D75: =IF(C75="","",ROUND(C75*1.15,0)) -> 16 | E75: =IFERROR(__xludf.DUMMYFUNCTION("IFERROR(XLOOKUP(A75,FILTER(VMS_Sales!$D:$D,VMS_Sales!$O:$O=$L$2),FILTER(VMS_Sales!$L:$L,VMS_Sales!$O:$O=$L$2),""""),"""")"),4.5) -> 4.5 | F75: =IF(OR(D75="",E75=""),"",ROUND(D75*E75,2)) -> 72 | G75: {=IFERROR( SUMIFS( PurchaseLines_Import!$I:$I, PurchaseLines_Import!$C:$C, XLOOKUP(A75,Map!$A:$A,Map!$B:$B,""), PurchaseLines_Import!$H:$H, $L$1 ), "")} -> 0 | H75: {=IFERROR( SUMIFS( Inventory_Import!$D:$D, Inventory_Import!$B:$B, TEXT(XLOOKUP(A75,Map!$A:$A,Map!$B:$B,""),"0000") ), 0)} -> 0 | I75: =IF(A75="","",MAX(D75-H75,0)) -> 16 | J75: =IF(OR(I75="",E75=""),"",ROUND(I75*E75,2)) -> 72 | N75: =IFERROR(__xludf.DUMMYFUNCTION("""COMPUTED_VALUE"""),"Kitkat 2 fingers") -> Kitkat 2 fingers | O75: =IFERROR(__xludf.DUMMYFUNCTION("""COMPUTED_VALUE"""),0.0) -> 0 | P75: =IFERROR(__xludf.DUMMYFUNCTION("""COMPUTED_VALUE"""),8.33) -> 8.33 | Q75: =IFERROR(__xludf.DUMMYFUNCTION("""COMPUTED_VALUE"""),10.0) -> 10 | T75: =IFERROR(__xludf.DUMMYFUNCTION("""COMPUTED_VALUE"""),0.0) -> 0 | U75: =IFERROR(__xludf.DUMMYFUNCTION("""COMPUTED_VALUE"""),0.0) -> 0 | V75: =IFERROR(__xludf.DUMMYFUNCTION("""COMPUTED_VALUE"""),10.0) -> 10
A76: =IFERROR(__xludf.DUMMYFUNCTION("""COMPUTED_VALUE"""),"未设置") -> 未设置 | B76: =IF(A76="","",SUMIFS(VMS_Sales!F:F,VMS_Sales!D:D,A76,VMS_Sales!O:O,$L$2)) -> 57 | C76: =IF(A76="","",ROUND(( SUMIFS(VMS_Sales!F:F,VMS_Sales!D:D,A76,VMS_Sales!O:O,$L$1)+ SUMIFS(VMS_Sales!F:F,VMS_Sales!D:D,A76,VMS_Sales!O:O,$L$2)+ SUMIFS(VMS_Sales!F:F,VMS_Sales!D:D,A76,VMS_Sales!O:O,$L$3) )/3,2)) -> 48 | D76: =IF(C76="","",ROUND(C76*1.15,0)) -> 55 | E76: =IFERROR(__xludf.DUMMYFUNCTION("IFERROR(XLOOKUP(A76,FILTER(VMS_Sales!$D:$D,VMS_Sales!$O:$O=$L$2),FILTER(VMS_Sales!$L:$L,VMS_Sales!$O:$O=$L$2),""""),"""")"),0.0) -> 0 | F76: =IF(OR(D76="",E76=""),"",ROUND(D76*E76,2)) -> 0 | G76: {=IFERROR( SUMIFS( PurchaseLines_Import!$I:$I, PurchaseLines_Import!$C:$C, XLOOKUP(A76,Map!$A:$A,Map!$B:$B,""), PurchaseLines_Import!$H:$H, $L$1 ), "")} -> 0 | H76: {=IFERROR( SUMIFS( Inventory_Import!$D:$D, Inventory_Import!$B:$B, TEXT(XLOOKUP(A76,Map!$A:$A,Map!$B:$B,""),"0000") ), 0)} -> 0 | I76: =IF(A76="","",MAX(D76-H76,0)) -> 55 | J76: =IF(OR(I76="",E76=""),"",ROUND(I76*E76,2)) -> 0 | N76: =IFERROR(__xludf.DUMMYFUNCTION("""COMPUTED_VALUE"""),"Tiger *12 tomato") -> Tiger *12 tomato | O76: =IFERROR(__xludf.DUMMYFUNCTION("""COMPUTED_VALUE"""),0.0) -> 0 | P76: =IFERROR(__xludf.DUMMYFUNCTION("""COMPUTED_VALUE"""),3.67) -> 3.67 | Q76: =IFERROR(__xludf.DUMMYFUNCTION("""COMPUTED_VALUE"""),4.0) -> 4 | T76: =IFERROR(__xludf.DUMMYFUNCTION("""COMPUTED_VALUE"""),0.0) -> 0 | U76: =IFERROR(__xludf.DUMMYFUNCTION("""COMPUTED_VALUE"""),0.0) -> 0 | V76: =IFERROR(__xludf.DUMMYFUNCTION("""COMPUTED_VALUE"""),4.0) -> 4
A77: =IFERROR(__xludf.DUMMYFUNCTION("""COMPUTED_VALUE"""),"Takis") -> Takis | B77: =IF(A77="","",SUMIFS(VMS_Sales!F:F,VMS_Sales!D:D,A77,VMS_Sales!O:O,$L$2)) -> 1 | C77: =IF(A77="","",ROUND(( SUMIFS(VMS_Sales!F:F,VMS_Sales!D:D,A77,VMS_Sales!O:O,$L$1)+ SUMIFS(VMS_Sales!F:F,VMS_Sales!D:D,A77,VMS_Sales!O:O,$L$2)+ SUMIFS(VMS_Sales!F:F,VMS_Sales!D:D,A77,VMS_Sales!O:O,$L$3) )/3,2)) -> 1.33 | D77: =IF(C77="","",ROUND(C77*1.15,0)) -> 2 | E77: =IFERROR(__xludf.DUMMYFUNCTION("IFERROR(XLOOKUP(A77,FILTER(VMS_Sales!$D:$D,VMS_Sales!$O:$O=$L$2),FILTER(VMS_Sales!$L:$L,VMS_Sales!$O:$O=$L$2),""""),"""")"),15.0) -> 15 | F77: =IF(OR(D77="",E77=""),"",ROUND(D77*E77,2)) -> 30 | G77: {=IFERROR( SUMIFS( PurchaseLines_Import!$I:$I, PurchaseLines_Import!$C:$C, XLOOKUP(A77,Map!$A:$A,Map!$B:$B,""), PurchaseLines_Import!$H:$H, $L$1 ), "")} -> 0 | H77: {=IFERROR( SUMIFS( Inventory_Import!$D:$D, Inventory_Import!$B:$B, TEXT(XLOOKUP(A77,Map!$A:$A,Map!$B:$B,""),"0000") ), 0)} -> 0 | I77: =IF(A77="","",MAX(D77-H77,0)) -> 2 | J77: =IF(OR(I77="",E77=""),"",ROUND(I77*E77,2)) -> 30 | N77: =IFERROR(__xludf.DUMMYFUNCTION("""COMPUTED_VALUE"""),"MrCrunch Normal") -> MrCrunch Normal | O77: =IFERROR(__xludf.DUMMYFUNCTION("""COMPUTED_VALUE"""),0.0) -> 0 | P77: =IFERROR(__xludf.DUMMYFUNCTION("""COMPUTED_VALUE"""),1.67) -> 1.67 | Q77: =IFERROR(__xludf.DUMMYFUNCTION("""COMPUTED_VALUE"""),2.0) -> 2 | T77: =IFERROR(__xludf.DUMMYFUNCTION("""COMPUTED_VALUE"""),0.0) -> 0 | U77: =IFERROR(__xludf.DUMMYFUNCTION("""COMPUTED_VALUE"""),0.0) -> 0 | V77: =IFERROR(__xludf.DUMMYFUNCTION("""COMPUTED_VALUE"""),2.0) -> 2
A78: =IFERROR(__xludf.DUMMYFUNCTION("""COMPUTED_VALUE"""),"m&m") -> m&m | B78: =IF(A78="","",SUMIFS(VMS_Sales!F:F,VMS_Sales!D:D,A78,VMS_Sales!O:O,$L$2)) -> 0 | C78: =IF(A78="","",ROUND(( SUMIFS(VMS_Sales!F:F,VMS_Sales!D:D,A78,VMS_Sales!O:O,$L$1)+ SUMIFS(VMS_Sales!F:F,VMS_Sales!D:D,A78,VMS_Sales!O:O,$L$2)+ SUMIFS(VMS_Sales!F:F,VMS_Sales!D:D,A78,VMS_Sales!O:O,$L$3) )/3,2)) -> 1 | D78: =IF(C78="","",ROUND(C78*1.15,0)) -> 1 | E78: =IFERROR(__xludf.DUMMYFUNCTION("IFERROR(XLOOKUP(A78,FILTER(VMS_Sales!$D:$D,VMS_Sales!$O:$O=$L$2),FILTER(VMS_Sales!$L:$L,VMS_Sales!$O:$O=$L$2),""""),"""")"),"") | F78: =IF(OR(D78="",E78=""),"",ROUND(D78*E78,2)) | G78: {=IFERROR( SUMIFS( PurchaseLines_Import!$I:$I, PurchaseLines_Import!$C:$C, XLOOKUP(A78,Map!$A:$A,Map!$B:$B,""), PurchaseLines_Import!$H:$H, $L$1 ), "")} -> 0 | H78: {=IFERROR( SUMIFS( Inventory_Import!$D:$D, Inventory_Import!$B:$B, TEXT(XLOOKUP(A78,Map!$A:$A,Map!$B:$B,""),"0000") ), 0)} -> 0 | I78: =IF(A78="","",MAX(D78-H78,0)) -> 1 | J78: =IF(OR(I78="",E78=""),"",ROUND(I78*E78,2)) | N78: =IFERROR(__xludf.DUMMYFUNCTION("""COMPUTED_VALUE"""),"Tiger *12 kebab") -> Tiger *12 kebab | O78: =IFERROR(__xludf.DUMMYFUNCTION("""COMPUTED_VALUE"""),0.0) -> 0 | P78: =IFERROR(__xludf.DUMMYFUNCTION("""COMPUTED_VALUE"""),2.33) -> 2.33 | Q78: =IFERROR(__xludf.DUMMYFUNCTION("""COMPUTED_VALUE"""),3.0) -> 3 | T78: =IFERROR(__xludf.DUMMYFUNCTION("""COMPUTED_VALUE"""),0.0) -> 0 | U78: =IFERROR(__xludf.DUMMYFUNCTION("""COMPUTED_VALUE"""),0.0) -> 0 | V78: =IFERROR(__xludf.DUMMYFUNCTION("""COMPUTED_VALUE"""),3.0) -> 3
A79: =IFERROR(__xludf.DUMMYFUNCTION("""COMPUTED_VALUE"""),"L suntop") -> L suntop | B79: =IF(A79="","",SUMIFS(VMS_Sales!F:F,VMS_Sales!D:D,A79,VMS_Sales!O:O,$L$2)) -> 0 | C79: =IF(A79="","",ROUND(( SUMIFS(VMS_Sales!F:F,VMS_Sales!D:D,A79,VMS_Sales!O:O,$L$1)+ SUMIFS(VMS_Sales!F:F,VMS_Sales!D:D,A79,VMS_Sales!O:O,$L$2)+ SUMIFS(VMS_Sales!F:F,VMS_Sales!D:D,A79,VMS_Sales!O:O,$L$3) )/3,2)) -> 2.67 | D79: =IF(C79="","",ROUND(C79*1.15,0)) -> 3 | E79: =IFERROR(__xludf.DUMMYFUNCTION("IFERROR(XLOOKUP(A79,FILTER(VMS_Sales!$D:$D,VMS_Sales!$O:$O=$L$2),FILTER(VMS_Sales!$L:$L,VMS_Sales!$O:$O=$L$2),""""),"""")"),"") | F79: =IF(OR(D79="",E79=""),"",ROUND(D79*E79,2)) | G79: {=IFERROR( SUMIFS( PurchaseLines_Import!$I:$I, PurchaseLines_Import!$C:$C, XLOOKUP(A79,Map!$A:$A,Map!$B:$B,""), PurchaseLines_Import!$H:$H, $L$1 ), "")} -> 0 | H79: {=IFERROR( SUMIFS( Inventory_Import!$D:$D, Inventory_Import!$B:$B, TEXT(XLOOKUP(A79,Map!$A:$A,Map!$B:$B,""),"0000") ), 0)} -> 0 | I79: =IF(A79="","",MAX(D79-H79,0)) -> 3 | J79: =IF(OR(I79="",E79=""),"",ROUND(I79*E79,2)) | N79: =IFERROR(__xludf.DUMMYFUNCTION("""COMPUTED_VALUE"""),"Tiger 12 sweet chili") -> Tiger 12 sweet chili | O79: =IFERROR(__xludf.DUMMYFUNCTION("""COMPUTED_VALUE"""),0.0) -> 0 | P79: =IFERROR(__xludf.DUMMYFUNCTION("""COMPUTED_VALUE"""),3.0) -> 3 | Q79: =IFERROR(__xludf.DUMMYFUNCTION("""COMPUTED_VALUE"""),3.0) -> 3 | T79: =IFERROR(__xludf.DUMMYFUNCTION("""COMPUTED_VALUE"""),0.0) -> 0 | U79: =IFERROR(__xludf.DUMMYFUNCTION("""COMPUTED_VALUE"""),0.0) -> 0 | V79: =IFERROR(__xludf.DUMMYFUNCTION("""COMPUTED_VALUE"""),3.0) -> 3
A80: =IFERROR(__xludf.DUMMYFUNCTION("""COMPUTED_VALUE"""),"EXO") -> EXO | B80: =IF(A80="","",SUMIFS(VMS_Sales!F:F,VMS_Sales!D:D,A80,VMS_Sales!O:O,$L$2)) -> 0 | C80: =IF(A80="","",ROUND(( SUMIFS(VMS_Sales!F:F,VMS_Sales!D:D,A80,VMS_Sales!O:O,$L$1)+ SUMIFS(VMS_Sales!F:F,VMS_Sales!D:D,A80,VMS_Sales!O:O,$L$2)+ SUMIFS(VMS_Sales!F:F,VMS_Sales!D:D,A80,VMS_Sales!O:O,$L$3) )/3,2)) -> 2 | D80: =IF(C80="","",ROUND(C80*1.15,0)) -> 2 | E80: =IFERROR(__xludf.DUMMYFUNCTION("IFERROR(XLOOKUP(A80,FILTER(VMS_Sales!$D:$D,VMS_Sales!$O:$O=$L$2),FILTER(VMS_Sales!$L:$L,VMS_Sales!$O:$O=$L$2),""""),"""")"),"") | F80: =IF(OR(D80="",E80=""),"",ROUND(D80*E80,2)) | G80: {=IFERROR( SUMIFS( PurchaseLines_Import!$I:$I, PurchaseLines_Import!$C:$C, XLOOKUP(A80,Map!$A:$A,Map!$B:$B,""), PurchaseLines_Import!$H:$H, $L$1 ), "")} -> 0 | H80: {=IFERROR( SUMIFS( Inventory_Import!$D:$D, Inventory_Import!$B:$B, TEXT(XLOOKUP(A80,Map!$A:$A,Map!$B:$B,""),"0000") ), 0)} -> 0 | I80: =IF(A80="","",MAX(D80-H80,0)) -> 2 | J80: =IF(OR(I80="",E80=""),"",ROUND(I80*E80,2)) | N80: =IFERROR(__xludf.DUMMYFUNCTION("""COMPUTED_VALUE"""),"Buldak") -> Buldak | O80: =IFERROR(__xludf.DUMMYFUNCTION("""COMPUTED_VALUE"""),0.0) -> 0 | P80: =IFERROR(__xludf.DUMMYFUNCTION("""COMPUTED_VALUE"""),1.67) -> 1.67 | Q80: =IFERROR(__xludf.DUMMYFUNCTION("""COMPUTED_VALUE"""),2.0) -> 2 | T80: =IFERROR(__xludf.DUMMYFUNCTION("""COMPUTED_VALUE"""),0.0) -> 0 | U80: =IFERROR(__xludf.DUMMYFUNCTION("""COMPUTED_VALUE"""),0.0) -> 0 | V80: =IFERROR(__xludf.DUMMYFUNCTION("""COMPUTED_VALUE"""),2.0) -> 2
A81: =IFERROR(__xludf.DUMMYFUNCTION("""COMPUTED_VALUE"""),"Almarai Banana") -> Almarai Banana | B81: =IF(A81="","",SUMIFS(VMS_Sales!F:F,VMS_Sales!D:D,A81,VMS_Sales!O:O,$L$2)) -> 2 | C81: =IF(A81="","",ROUND(( SUMIFS(VMS_Sales!F:F,VMS_Sales!D:D,A81,VMS_Sales!O:O,$L$1)+ SUMIFS(VMS_Sales!F:F,VMS_Sales!D:D,A81,VMS_Sales!O:O,$L$2)+ SUMIFS(VMS_Sales!F:F,VMS_Sales!D:D,A81,VMS_Sales!O:O,$L$3) )/3,2)) -> 4 | D81: =IF(C81="","",ROUND(C81*1.15,0)) -> 5 | E81: =IFERROR(__xludf.DUMMYFUNCTION("IFERROR(XLOOKUP(A81,FILTER(VMS_Sales!$D:$D,VMS_Sales!$O:$O=$L$2),FILTER(VMS_Sales!$L:$L,VMS_Sales!$O:$O=$L$2),""""),"""")"),2.29) -> 2.29 | F81: =IF(OR(D81="",E81=""),"",ROUND(D81*E81,2)) -> 11.45 | G81: {=IFERROR( SUMIFS( PurchaseLines_Import!$I:$I, PurchaseLines_Import!$C:$C, XLOOKUP(A81,Map!$A:$A,Map!$B:$B,""), PurchaseLines_Import!$H:$H, $L$1 ), "")} -> 0 | H81: {=IFERROR( SUMIFS( Inventory_Import!$D:$D, Inventory_Import!$B:$B, TEXT(XLOOKUP(A81,Map!$A:$A,Map!$B:$B,""),"0000") ), 0)} -> 0 | I81: =IF(A81="","",MAX(D81-H81,0)) -> 5 | J81: =IF(OR(I81="",E81=""),"",ROUND(I81*E81,2)) -> 11.45 | N81: =IFERROR(__xludf.DUMMYFUNCTION("""COMPUTED_VALUE"""),"Tiger *16 kebab") -> Tiger *16 kebab | O81: =IFERROR(__xludf.DUMMYFUNCTION("""COMPUTED_VALUE"""),0.0) -> 0 | P81: =IFERROR(__xludf.DUMMYFUNCTION("""COMPUTED_VALUE"""),0.67) -> 0.67 | Q81: =IFERROR(__xludf.DUMMYFUNCTION("""COMPUTED_VALUE"""),1.0) -> 1 | T81: =IFERROR(__xludf.DUMMYFUNCTION("""COMPUTED_VALUE"""),0.0) -> 0 | U81: =IFERROR(__xludf.DUMMYFUNCTION("""COMPUTED_VALUE"""),0.0) -> 0 | V81: =IFERROR(__xludf.DUMMYFUNCTION("""COMPUTED_VALUE"""),1.0) -> 1
A82: =IFERROR(__xludf.DUMMYFUNCTION("""COMPUTED_VALUE"""),"Activ chips") -> Activ chips | B82: =IF(A82="","",SUMIFS(VMS_Sales!F:F,VMS_Sales!D:D,A82,VMS_Sales!O:O,$L$2)) -> 0 | C82: =IF(A82="","",ROUND(( SUMIFS(VMS_Sales!F:F,VMS_Sales!D:D,A82,VMS_Sales!O:O,$L$1)+ SUMIFS(VMS_Sales!F:F,VMS_Sales!D:D,A82,VMS_Sales!O:O,$L$2)+ SUMIFS(VMS_Sales!F:F,VMS_Sales!D:D,A82,VMS_Sales!O:O,$L$3) )/3,2)) -> 4 | D82: =IF(C82="","",ROUND(C82*1.15,0)) -> 5 | E82: =IFERROR(__xludf.DUMMYFUNCTION("IFERROR(XLOOKUP(A82,FILTER(VMS_Sales!$D:$D,VMS_Sales!$O:$O=$L$2),FILTER(VMS_Sales!$L:$L,VMS_Sales!$O:$O=$L$2),""""),"""")"),"") | F82: =IF(OR(D82="",E82=""),"",ROUND(D82*E82,2)) | G82: {=IFERROR( SUMIFS( PurchaseLines_Import!$I:$I, PurchaseLines_Import!$C:$C, XLOOKUP(A82,Map!$A:$A,Map!$B:$B,""), PurchaseLines_Import!$H:$H, $L$1 ), "")} -> 0 | H82: {=IFERROR( SUMIFS( Inventory_Import!$D:$D, Inventory_Import!$B:$B, TEXT(XLOOKUP(A82,Map!$A:$A,Map!$B:$B,""),"0000") ), 0)} -> 0 | I82: =IF(A82="","",MAX(D82-H82,0)) -> 5 | J82: =IF(OR(I82="",E82=""),"",ROUND(I82*E82,2)) | N82: =IFERROR(__xludf.DUMMYFUNCTION("""COMPUTED_VALUE"""),"sunTop") -> sunTop | O82: =IFERROR(__xludf.DUMMYFUNCTION("""COMPUTED_VALUE"""),0.0) -> 0 | P82: =IFERROR(__xludf.DUMMYFUNCTION("""COMPUTED_VALUE"""),7.0) -> 7 | Q82: =IFERROR(__xludf.DUMMYFUNCTION("""COMPUTED_VALUE"""),8.0) -> 8 | T82: =IFERROR(__xludf.DUMMYFUNCTION("""COMPUTED_VALUE"""),0.0) -> 0 | U82: =IFERROR(__xludf.DUMMYFUNCTION("""COMPUTED_VALUE"""),2.0) -> 2 | V82: =IFERROR(__xludf.DUMMYFUNCTION("""COMPUTED_VALUE"""),6.0) -> 6
A83: =IFERROR(__xludf.DUMMYFUNCTION("""COMPUTED_VALUE"""),"Yumi Zak") -> Yumi Zak | B83: =IF(A83="","",SUMIFS(VMS_Sales!F:F,VMS_Sales!D:D,A83,VMS_Sales!O:O,$L$2)) -> 7 | C83: =IF(A83="","",ROUND(( SUMIFS(VMS_Sales!F:F,VMS_Sales!D:D,A83,VMS_Sales!O:O,$L$1)+ SUMIFS(VMS_Sales!F:F,VMS_Sales!D:D,A83,VMS_Sales!O:O,$L$2)+ SUMIFS(VMS_Sales!F:F,VMS_Sales!D:D,A83,VMS_Sales!O:O,$L$3) )/3,2)) -> 14 | D83: =IF(C83="","",ROUND(C83*1.15,0)) -> 16 | E83: =IFERROR(__xludf.DUMMYFUNCTION("IFERROR(XLOOKUP(A83,FILTER(VMS_Sales!$D:$D,VMS_Sales!$O:$O=$L$2),FILTER(VMS_Sales!$L:$L,VMS_Sales!$O:$O=$L$2),""""),"""")"),4.5) -> 4.5 | F83: =IF(OR(D83="",E83=""),"",ROUND(D83*E83,2)) -> 72 | G83: {=IFERROR( SUMIFS( PurchaseLines_Import!$I:$I, PurchaseLines_Import!$C:$C, XLOOKUP(A83,Map!$A:$A,Map!$B:$B,""), PurchaseLines_Import!$H:$H, $L$1 ), "")} -> 0 | H83: {=IFERROR( SUMIFS( Inventory_Import!$D:$D, Inventory_Import!$B:$B, TEXT(XLOOKUP(A83,Map!$A:$A,Map!$B:$B,""),"0000") ), 0)} -> 0 | I83: =IF(A83="","",MAX(D83-H83,0)) -> 16 | J83: =IF(OR(I83="",E83=""),"",ROUND(I83*E83,2)) -> 72 | N83: =IFERROR(__xludf.DUMMYFUNCTION("""COMPUTED_VALUE"""),"Prime") -> Prime | O83: =IFERROR(__xludf.DUMMYFUNCTION("""COMPUTED_VALUE"""),0.0) -> 0 | P83: =IFERROR(__xludf.DUMMYFUNCTION("""COMPUTED_VALUE"""),1.0) -> 1 | Q83: =IFERROR(__xludf.DUMMYFUNCTION("""COMPUTED_VALUE"""),1.0) -> 1 | T83: =IFERROR(__xludf.DUMMYFUNCTION("""COMPUTED_VALUE"""),0.0) -> 0 | U83: =IFERROR(__xludf.DUMMYFUNCTION("""COMPUTED_VALUE"""),0.0) -> 0 | V83: =IFERROR(__xludf.DUMMYFUNCTION("""COMPUTED_VALUE"""),1.0) -> 1
A84: =IFERROR(__xludf.DUMMYFUNCTION("""COMPUTED_VALUE"""),"wafe'up") -> wafe'up | B84: =IF(A84="","",SUMIFS(VMS_Sales!F:F,VMS_Sales!D:D,A84,VMS_Sales!O:O,$L$2)) -> 22 | C84: =IF(A84="","",ROUND(( SUMIFS(VMS_Sales!F:F,VMS_Sales!D:D,A84,VMS_Sales!O:O,$L$1)+ SUMIFS(VMS_Sales!F:F,VMS_Sales!D:D,A84,VMS_Sales!O:O,$L$2)+ SUMIFS(VMS_Sales!F:F,VMS_Sales!D:D,A84,VMS_Sales!O:O,$L$3) )/3,2)) -> 7.33 | D84: =IF(C84="","",ROUND(C84*1.15,0)) -> 8 | E84: =IFERROR(__xludf.DUMMYFUNCTION("IFERROR(XLOOKUP(A84,FILTER(VMS_Sales!$D:$D,VMS_Sales!$O:$O=$L$2),FILTER(VMS_Sales!$L:$L,VMS_Sales!$O:$O=$L$2),""""),"""")"),2.25) -> 2.25 | F84: =IF(OR(D84="",E84=""),"",ROUND(D84*E84,2)) -> 18 | G84: {=IFERROR( SUMIFS( PurchaseLines_Import!$I:$I, PurchaseLines_Import!$C:$C, XLOOKUP(A84,Map!$A:$A,Map!$B:$B,""), PurchaseLines_Import!$H:$H, $L$1 ), "")} -> 0 | H84: {=IFERROR( SUMIFS( Inventory_Import!$D:$D, Inventory_Import!$B:$B, TEXT(XLOOKUP(A84,Map!$A:$A,Map!$B:$B,""),"0000") ), 0)} -> 0 | I84: =IF(A84="","",MAX(D84-H84,0)) -> 8 | J84: =IF(OR(I84="",E84=""),"",ROUND(I84*E84,2)) -> 18 | N84: =IFERROR(__xludf.DUMMYFUNCTION("""COMPUTED_VALUE"""),"Mulino Cookis") -> Mulino Cookis | O84: =IFERROR(__xludf.DUMMYFUNCTION("""COMPUTED_VALUE"""),0.0) -> 0 | P84: =IFERROR(__xludf.DUMMYFUNCTION("""COMPUTED_VALUE"""),0.67) -> 0.67 | Q84: =IFERROR(__xludf.DUMMYFUNCTION("""COMPUTED_VALUE"""),1.0) -> 1 | T84: =IFERROR(__xludf.DUMMYFUNCTION("""COMPUTED_VALUE"""),0.0) -> 0 | U84: =IFERROR(__xludf.DUMMYFUNCTION("""COMPUTED_VALUE"""),0.0) -> 0 | V84: =IFERROR(__xludf.DUMMYFUNCTION("""COMPUTED_VALUE"""),1.0) -> 1
A85: =IFERROR(__xludf.DUMMYFUNCTION("""COMPUTED_VALUE"""),"vitrac") -> vitrac | B85: =IF(A85="","",SUMIFS(VMS_Sales!F:F,VMS_Sales!D:D,A85,VMS_Sales!O:O,$L$2)) -> 44 | C85: =IF(A85="","",ROUND(( SUMIFS(VMS_Sales!F:F,VMS_Sales!D:D,A85,VMS_Sales!O:O,$L$1)+ SUMIFS(VMS_Sales!F:F,VMS_Sales!D:D,A85,VMS_Sales!O:O,$L$2)+ SUMIFS(VMS_Sales!F:F,VMS_Sales!D:D,A85,VMS_Sales!O:O,$L$3) )/3,2)) -> 14.67 | D85: =IF(C85="","",ROUND(C85*1.15,0)) -> 17 | E85: =IFERROR(__xludf.DUMMYFUNCTION("IFERROR(XLOOKUP(A85,FILTER(VMS_Sales!$D:$D,VMS_Sales!$O:$O=$L$2),FILTER(VMS_Sales!$L:$L,VMS_Sales!$O:$O=$L$2),""""),"""")"),1.6) -> 1.6 | F85: =IF(OR(D85="",E85=""),"",ROUND(D85*E85,2)) -> 27.2 | G85: {=IFERROR( SUMIFS( PurchaseLines_Import!$I:$I, PurchaseLines_Import!$C:$C, XLOOKUP(A85,Map!$A:$A,Map!$B:$B,""), PurchaseLines_Import!$H:$H, $L$1 ), "")} -> 0 | H85: {=IFERROR( SUMIFS( Inventory_Import!$D:$D, Inventory_Import!$B:$B, TEXT(XLOOKUP(A85,Map!$A:$A,Map!$B:$B,""),"0000") ), 0)} -> 0 | I85: =IF(A85="","",MAX(D85-H85,0)) -> 17 | J85: =IF(OR(I85="",E85=""),"",ROUND(I85*E85,2)) -> 27.2 | N85: =IFERROR(__xludf.DUMMYFUNCTION("""COMPUTED_VALUE"""),"Doritos real") -> Doritos real | O85: =IFERROR(__xludf.DUMMYFUNCTION("""COMPUTED_VALUE"""),0.0) -> 0 | P85: =IFERROR(__xludf.DUMMYFUNCTION("""COMPUTED_VALUE"""),8.33) -> 8.33 | Q85: =IFERROR(__xludf.DUMMYFUNCTION("""COMPUTED_VALUE"""),10.0) -> 10 | T85: =IFERROR(__xludf.DUMMYFUNCTION("""COMPUTED_VALUE"""),0.0) -> 0 | U85: =IFERROR(__xludf.DUMMYFUNCTION("""COMPUTED_VALUE"""),0.0) -> 0 | V85: =IFERROR(__xludf.DUMMYFUNCTION("""COMPUTED_VALUE"""),10.0) -> 10
A86: =IFERROR(__xludf.DUMMYFUNCTION("""COMPUTED_VALUE"""),"Doritos red hot") -> Doritos red hot | B86: =IF(A86="","",SUMIFS(VMS_Sales!F:F,VMS_Sales!D:D,A86,VMS_Sales!O:O,$L$2)) -> 138 | C86: =IF(A86="","",ROUND(( SUMIFS(VMS_Sales!F:F,VMS_Sales!D:D,A86,VMS_Sales!O:O,$L$1)+ SUMIFS(VMS_Sales!F:F,VMS_Sales!D:D,A86,VMS_Sales!O:O,$L$2)+ SUMIFS(VMS_Sales!F:F,VMS_Sales!D:D,A86,VMS_Sales!O:O,$L$3) )/3,2)) -> 46 | D86: =IF(C86="","",ROUND(C86*1.15,0)) -> 53 | E86: =IFERROR(__xludf.DUMMYFUNCTION("IFERROR(XLOOKUP(A86,FILTER(VMS_Sales!$D:$D,VMS_Sales!$O:$O=$L$2),FILTER(VMS_Sales!$L:$L,VMS_Sales!$O:$O=$L$2),""""),"""")"),2.93) -> 2.93 | F86: =IF(OR(D86="",E86=""),"",ROUND(D86*E86,2)) -> 155.29 | G86: {=IFERROR( SUMIFS( PurchaseLines_Import!$I:$I, PurchaseLines_Import!$C:$C, XLOOKUP(A86,Map!$A:$A,Map!$B:$B,""), PurchaseLines_Import!$H:$H, $L$1 ), "")} -> 150 | H86: {=IFERROR( SUMIFS( Inventory_Import!$D:$D, Inventory_Import!$B:$B, TEXT(XLOOKUP(A86,Map!$A:$A,Map!$B:$B,""),"0000") ), 0)} -> 0 | I86: =IF(A86="","",MAX(D86-H86,0)) -> 53 | J86: =IF(OR(I86="",E86=""),"",ROUND(I86*E86,2)) -> 155.29 | N86: =IFERROR(__xludf.DUMMYFUNCTION("""COMPUTED_VALUE"""),"Chico") -> Chico | O86: =IFERROR(__xludf.DUMMYFUNCTION("""COMPUTED_VALUE"""),0.0) -> 0 | P86: =IFERROR(__xludf.DUMMYFUNCTION("""COMPUTED_VALUE"""),6.67) -> 6.67 | Q86: =IFERROR(__xludf.DUMMYFUNCTION("""COMPUTED_VALUE"""),8.0) -> 8 | T86: =IFERROR(__xludf.DUMMYFUNCTION("""COMPUTED_VALUE"""),0.0) -> 0 | U86: =IFERROR(__xludf.DUMMYFUNCTION("""COMPUTED_VALUE"""),0.0) -> 0 | V86: =IFERROR(__xludf.DUMMYFUNCTION("""COMPUTED_VALUE"""),8.0) -> 8
